Workbook
Name ageOfRetirement: Assumptions!$B$14
Name annualBudget: Assumptions!$B$71
Name assetReturn: Assumptions!$B$10
Name assetsSaveShare: Assumptions!$B$48
Name benefitRound: Assumptions!$B$74
Name CASH_SAVINGS_SHARE: Assumptions!$B$51
Name CI_COST: Assumptions!$B$35
Name CI_YEARS: Assumptions!$B$34
Name coverPremRoundStep: Assumptions!$B$67
Name coverSliderPremFloor: Assumptions!$B$68
Name CPF_employee: CPF!$B$25
Name CPF_income: CPF!$B$8
Name CPF_on: CPF!$B$22
Name CPF_rate: CPF!$B$24
Name CPF_takeHome: CPF!$B$26
Name CpfCountrySwitch: CPF!$I$6:$J$14
Name cpfRate_over70: CPF!$B$16
Name cpfRate_to55: CPF!$B$12
Name cpfRate_to60: CPF!$B$13
Name cpfRate_to65: CPF!$B$14
Name cpfRate_to70: CPF!$B$15
Name criMedicalPlaceholder: Assumptions!$B$77
Name currentYear: Assumptions!$B$16
Name EDU_TOTAL_COST: Assumptions!$B$39
Name eduYearsDefault: Assumptions!$B$40
Name endAge: Assumptions!$B$17
Name FREE_BUDGET_SHARE: Assumptions!$B$64
Name funeralLump: Assumptions!$B$76
Name FX_cash: FX!$B$21
Name FX_expenseMonthly: FX!$B$20
Name FX_incomeMonthly: FX!$B$19
Name FX_investments: FX!$B$22
Name FX_liabilities: FX!$B$25
Name FX_lifeSum: FX!$B$26
Name FX_mortgage: FX!$B$24
Name FX_property: FX!$B$23
Name FX_usdPerLocal: FX!$B$16
Name FxTable: FX!$I$6:$J$14
Name gfr: Assumptions!$B$73
Name HOSP_MONTHS: Assumptions!$B$38
Name huNumSims: Assumptions!$B$75
Name IncomeBands: Assumptions!$E$6:$G$13
Name incomeGrowthRate: Assumptions!$B$8
Name inflationRate: Assumptions!$B$5
Name interestRate: Assumptions!$B$6
Name investmentReturn: Assumptions!$B$9
Name INVESTMENTS_SHARE: Assumptions!$B$52
Name liabilityRatio: Assumptions!$B$50
Name lifeExpectancyDefault: Assumptions!$B$15
Name lifePremiumRate: Assumptions!$B$59
Name lifeRoundUnit: Assumptions!$B$60
Name lifestyleFrugal: Assumptions!$B$28
Name lifestyleOnlyTheBest: Assumptions!$B$30
Name lifestyleStressFree: Assumptions!$B$29
Name lifeSupportMax: Assumptions!$B$32
Name lifeSupportMin: Assumptions!$B$31
Name lifeSupportPivotAge: Assumptions!$B$33
Name loanRate: Assumptions!$B$7
Name lumpRoundStep: Assumptions!$B$65
Name monthlyRoundStep: Assumptions!$B$66

Sheet Overview
A1: FinPlan360 calculation components — live code, September 2026
A2: Yellow = type here. Orange = override (leave blank to keep the calculated value). Pick the persona on the Selected persona tab; every later tab follows that id. Gold = persona input, blue = LLM, orange = user / Money-page override, green = calculated, purple = assumptions. FX converts local amounts to USD. Validation applies USD-only rules. CPF is its own tab and is on only when the country switch says so (Singapore on, others off). HappiU and Scenario Visualizer are mapped here but scored / projected in HU and SV.
A3: Component | B3: Owner | C3: Reads | D3: Writes | E3: How it calculates (code) | F3: Code | G3: Tab | H3: HTTP / UI
A4: CPF | B4: GP pipeline (Singapore only) | C4: country, residency, age, incomeMonthly. Country switch on the CPF tab. | D4: employee CPF, take-home. 0 / income when CPF is off. | E4: On only when the country table (or orange override) is TRUE. Singapore Citizen/PR: employee CPF = floor(min(gross, OW_CEILING) × age-band rate). Foreigner → 0. Any other country → off, take-home = gross. src/cpf.py. | F4: src/cpf.py | G4: CPF | H4: Inside POST /v1/predict (take-home)
A5: People Like You | B5: GP pipeline | C5: age / DOB, occupation, gender, dependents, residency. CPF box for take-home. Does not read Assumptions. | D5: incomeMonthly, expenseMonthly, cash, investments, property, mortgage, one Life Protection policy, lifeExpectancy, isSmoker. | E5: LLM proposes gross monthly income and lifestyle flags. Income is clamped to the Singapore occupation band. Employee CPF = floor(min(gross, 8000) × age-band rate); 0 if Foreigner. expenseMonthly = round(take-home × min(67.5% + 5pp × dependents, 90%), 2). Liquid assets = max(0, surplus × 12 × 0.5 × (age − 21)), then cash 15% / investments 85%. If the model says they own a home: property from income band, mortgage = round(property × 55%). Assumed life cover = max(mortgage rounded up to S$100k, 5 × annual income if dependents > 0); premium = round(sum × 0.31%). PLU liabilities (= assets × 0.7) is not the mortgage. If this step fails, predict returns 503. | F5: src/pipeline/people_like_you.py, src/cpf.py, src/predict.py _apply_plu | G5: People Like You | H5: POST /v1/predict (first of three)
A6: Need Profiler | B6: GP pipeline | C6: Age, gender, dependents, occupation, smoker, income, expense, liquid assets, PLU liabilities, hospital/ward/lifestyle/sports, car/home/travel flags. Existing cover is hard-coded 0. No Assumptions. No LLM. | D6: needs[].enabled, needs[].priority, needs[].weightageScore. Four UNIFIED types on: two protection + two growth (retirement always one of the growth pair). | E6: Twelve AI labels are scored as Σ (factor_weight × option_weight), rounded to 2 dp, then min–max scaled 0–10. Income / expense / assets / liabilities buckets convert SGD × 0.75 to a USD table. Car ownership, home ownership, travel, and existing life / CI cover have factor weights but no matching weight_options, so they add 0. select_unified_top ignores top_n (app.py still passes 4). If has_property, N_PRP replaces N_SAV in the second growth slot. priority = 5 if scaled score > 7 else 3. Personal accident / motor / travel / farewell are scored and dropped. Orange Enable? columns let you force a need on or off. | F6: src/pipeline/need_profiler.py, src/pipeline/prompts/Need_profiler.json, src/app.py top_n=4 | G6: Need Profiler | H6: POST /v1/predict
A7: Need Calculator | B7: GP pipeline | C7: Money attributes, enabled needs, goal-card sliders (lifestyle, retAge, targetYear, incomeReplaceMonthly, dependYears, bequest, monthlyContribution, tagged existing), Assumptions rates, Need parameters. | D7: For every UNIFIED type: needAmount, have, gap. Copies ageOfRetirement from the retirement row. | E7: realReturn = max(0, (1 + investmentReturn) / (1 + inflationRate) − 1). N_RET = PV of (today’s annual spend × lifestyle, grown at inflation to retirement) as an ordinary annuity for lifeExpectancy − retAge. N_INC = bequest + mortgage + ordinary annuity of annual spend over supportYears = min(max(10, 50 − age), 25). N_CRI / N_TPD = annuity-due of replacement income for 3 / 5 years + S$200,000. N_HOS = income × 6. N_EDU = 75,000 × (1 + inflation)^(targetYear − thisYear). N_SAV / N_PRP = stored needAmount if > 0, else 1× / 5× annual income. Protection have = policy sum (life is seeded by PLU). Wealth have = tagged investments only, grown at realReturn; cash is never allocated. Amounts are computed for all eight types even when a need is off. Orange Enable? and slider columns are the goal-card inputs. | F7: src/pipeline/need_calculator.py evaluate_session, src/pipeline/goal_math.py, src/hu_payload.py need_existing / apply_investment_pot | G7: Need Calculator | H7: POST /v1/predict and POST /v1/needs
A8: Goal cards | B8: GP UI | C8: Last calculator row (have, gap, stored sliders). | D8: Slider fields on the need; then POST /v1/needs (debounced). Does not recompute amounts in the browser. | E8: fillNeedEdit reads stored fields. patchNeedInputs writes lifestyle / retAge / targetYear / existing / … onto the session. Retirement stays on. The Score/Plan cap of four needs is UI-only (needEdit.capEnabledNeeds); this workbook lets you switch any need. | F8: frontend/src/lib/needEdit.ts | G8: Need Calculator (slider columns) | H8: Score and Plan screens
A9: Plan Calculator | B9: GP UI | C9: Enabled needs with gap > 0, take-home surplus, Assumptions inflationRate / investmentReturn / ageOfRetirement. | D9: planSum + planPrem (protection), planMth + planLump (wealth), investMth / investLump totals, plansOff. | E9: Suggested = enabled AND gap > 0. Default planSum = round(gap). planPrem = round((sum × 0.00078) / 10) × 10. Wealth horizon = years to retirement, or targetYear − this year. Lump / monthly caps = the amount that alone grows to the gap at realReturn (round up to S$1,000 / S$50). Default monthly = round((max(0, take-home − expense) × 12 − all protection premiums) × 50% / 12 / n_wealth / 50) × 50, then min(share, cap). Default lump = 0. Orange Include? columns are plansOff. | F9: frontend/src/lib/planProducts.ts, frontend/src/lib/local.ts seedProducts | G9: Plan Calculator | H9: Plan screen (not an HTTP engine)
A10: Budget Calculator | B10: GP UI | C10: take-home, expenseMonthly, investments, included planPrem / planMth / planLump. Not the economic rates. | D10: Nothing on the session. Plan-screen affordability only. | E10: available = max(0, takeHomeMonthly − expenseMonthly). free = round(available × 0.5). monthly = round(wealth contributions + protection premiums / 12). monthlyOver = monthly − free. lumpOver = wealth lumps − investments. Separate from the HappiU envelope (annualBudget 1500). | F10: planAfford in frontend/src/lib/planProducts.ts; availableBudget in types.ts | G10: Budget Calculator | H10: Plan screen
A11: FX | B11: Workbook only (not an HTTP engine) | C11: Personas currency + effective session money fields from People Like You. | D11: USD per 1 local, and each money field in USD. Validation reads these; engines stay local. | E11: Lookup ISO code in the FX rate table (USD per 1 local unit). USD = local × rate. Example: 5,000 SGD × 0.74 = 3,700 USD; 5,000 VND × 0.000038 = 0.19 USD. Edit the rate table on this tab. People Like You still stores local currency. | F11: Workbook FX tab (no src module — validation helper) | G11: FX | H11: Not in the live pipeline
A12: HappiU | B12: HU, via GP | C12: Whole session. Assumptions rates, CPF (inside HU), riskProfile, plan fields when set. Need amounts already stored. | D12: preHappiU, postHappiU. GP does not run the Monte Carlo. | E12: GP maps the session (src/hu_payload.py). Salary is gross incomeMonthly. N_HOS is renamed N_HSP. If retirement is off, GP still sends a synthetic N_RET = expense × 12 × (lifeExpectancy − retAge). Before a plan: benefitAmount = needAmount rounded to S$50,000, budget 200. With a plan: planSum / planPrem. This workbook does not score HappiU. | F12: src/hu_payload.py → POST /v1/score → HU | G12: Assumptions (envelope only) | H12: POST /v1/score
A13: Scenario Visualizer | B13: SV, via GP | C13: Session after Plan, all six rates, ageOfRetirement, endAge, stress chips. CPF inside SV. | D13: Year-by-year wealth path. GP does not run the year step. | E13: preWealth = session without the plan; postWealth = plus included planMth / planLump / planSum / planPrem. svNumSims defaults to 20. Investment contribution = max(0, take-home − expenseMonthly) once a year. This workbook does not project the path. | F13: src/sv_payload.py → POST /v1/project → SV | G13: Assumptions (stress catalogue) | H13: POST /v1/project
A14: Journey order (one session, each step adds attributes)
A15: Shared inputs (Assumptions · CPF · Need parameters · Risk · Stress events) → About you → CPF (on for Singapore only) → People Like You (or the customer edits the same money fields) → Need Profiler → Need Calculator → HappiU (no plan) → Plan Calculator → Budget Calculator → Scenario Visualizer → HappiU (with plan). Workbook-only: FX (local → USD) then Validation (USD rules).
A17: UNIFIED types in code order: N_INC, N_CRI, N_TPD, N_HOS (protection) · N_RET, N_EDU, N_SAV, N_PRP (wealth). Goal-card sliders live on the Need Calculator tab. See Discrepancies for every place the markdown still disagrees with the code.

Sheet Selected persona
A1: Selected persona — pick one id here. Every calculation tab follows this cell.
A2: Selected persona | B2: P02 | C2: =IFERROR(INDEX(Personas!B$3:B$52,MATCH($B$2,Personas!$A$3:$A$52,0)),"") -> Wei Ling Tan | D2: This is the only picker. CPF, People Like You, Need Profiler, Need Calculator, Plan, Budget, FX, and Validation follow this cell. | F2: A · INPUT DATA
A3: Attribute | B3: Value | C3: Kind | D3: Source / formula | F3: B · LLM PREDICTED DATA
A4: A · ABOUT YOU — from the Personas row (edit there) | F4: C · DETERMINISTICALLY CALCULATED
A5: name | B5: =IFERROR(INDEX(Personas!B$3:B$52,MATCH($B$2,Personas!$A$3:$A$52,0)),"") -> Wei Ling Tan | C5: A · input | D5: Personas B. | F5: D · ASSUMPTIONS / SHARED DATA
A6: age | B6: =IFERROR(INDEX(Personas!C$3:C$52,MATCH($B$2,Personas!$A$3:$A$52,0)),"") -> 27 | C6: A · input | D6: Personas C. | F6: E · USER / FRONTEND OVERRIDE
A7: gender | B7: =IFERROR(INDEX(Personas!D$3:D$52,MATCH($B$2,Personas!$A$3:$A$52,0)),"") -> Male | C7: A · input | D7: Personas D.
A8: residency | B8: =IFERROR(INDEX(Personas!E$3:E$52,MATCH($B$2,Personas!$A$3:$A$52,0)),"") -> PR | C8: A · input | D8: Personas E.
A9: country | B9: =IFERROR(INDEX(Personas!F$3:F$52,MATCH($B$2,Personas!$A$3:$A$52,0)),"") -> Singapore | C9: A · input | D9: Personas F. CPF on/off uses this.
A10: occupation | B10: =IFERROR(INDEX(Personas!G$3:G$52,MATCH($B$2,Personas!$A$3:$A$52,0)),"") -> Teacher | C10: A · input | D10: Personas G. Income clamp band.
A11: dependents | B11: =IFERROR(INDEX(Personas!H$3:H$52,MATCH($B$2,Personas!$A$3:$A$52,0)),"") -> 0 | C11: A · input | D11: Personas H.
A12: maritalStatus | B12: =IFERROR(INDEX(Personas!I$3:I$52,MATCH($B$2,Personas!$A$3:$A$52,0)),"") -> 0 | C12: A · input | D12: Personas I. Blank = infer on People Like You.
A13: what this row varies | B13: =IFERROR(INDEX(Personas!AD$3:AD$52,MATCH($B$2,Personas!$A$3:$A$52,0)),"") -> Teacher; age 27; PR; 0 dep; rent; non-smoker | C13: A · input | D13: Personas AD. Why this persona exists.
A15: B · LLM PREDICTED — from the Personas row (edit there)
A16: incomeMonthly (LLM) | B16: =IFERROR(INDEX(Personas!J$3:J$52,MATCH($B$2,Personas!$A$3:$A$52,0)),"") -> 6020 | C16: B · LLM predicted | D16: Personas J. Before clamp and CPF.
A17: currency | B17: =IFERROR(INDEX(Personas!K$3:K$52,MATCH($B$2,Personas!$A$3:$A$52,0)),"") -> SGD | C17: B · LLM predicted | D17: Personas K. FX looks this up.
A18: risk ability | B18: =IFERROR(INDEX(Personas!L$3:L$52,MATCH($B$2,Personas!$A$3:$A$52,0)),"") -> moderate | C18: B · LLM predicted | D18: Personas L.
A19: price sensitivity | B19: =IFERROR(INDEX(Personas!M$3:M$52,MATCH($B$2,Personas!$A$3:$A$52,0)),"") -> medium | C19: B · LLM predicted | D19: Personas M.
A20: owns property | B20: =IFERROR(INDEX(Personas!N$3:N$52,MATCH($B$2,Personas!$A$3:$A$52,0)),"") -> FALSE | C20: B · LLM predicted | D20: Personas N.
A21: owns car | B21: =IFERROR(INDEX(Personas!O$3:O$52,MATCH($B$2,Personas!$A$3:$A$52,0)),"") -> TRUE | C21: B · LLM predicted | D21: Personas O.
A22: is smoker | B22: =IFERROR(INDEX(Personas!U$3:U$52,MATCH($B$2,Personas!$A$3:$A$52,0)),"") -> FALSE | C22: B · LLM predicted | D22: Personas U.
A23: life expectancy | B23: =IFERROR(INDEX(Personas!V$3:V$52,MATCH($B$2,Personas!$A$3:$A$52,0)),"") -> 81 | C23: B · LLM predicted | D23: Personas V.
A24: retirement lifestyle | B24: =IFERROR(INDEX(Personas!T$3:T$52,MATCH($B$2,Personas!$A$3:$A$52,0)),"") -> Comfortable | C24: B · LLM predicted | D24: Personas T.
A26: C · EFFECTIVE SESSION — after CPF, People Like You, and Money-page overrides
A27: CPF on | B27: =CPF_on -> TRUE | C27: C · calculated | D27: From the CPF tab.
A28: incomeMonthly | B28: =PLU_incomeMonthly -> 6020 | C28: C · calculated | D28: Clamped LLM income.
A29: take-home | B29: =PLU_takeHome -> 4816 | C29: C · calculated | D29: Gross minus employee CPF when CPF is on.
A30: expenseMonthly | B30: =PLU_expenseMonthly -> 3250.8 | C30: C · calculated | D30: Override if Personas W is set.
A31: cash | B31: =PLU_cash -> 8452 | C31: C · calculated | D31: Cash & Savings.
A32: investments | B32: =PLU_investments -> 47895 | C32: C · calculated
A33: property | B33: =PLU_property -> 0 | C33: C · calculated | D33: 0 if renter.
A34: mortgage | B34: =PLU_mortgage -> 0 | C34: C · calculated
A35: PLU liabilities | B35: =PLU_liabilities -> 39443.04 | C35: C · calculated | D35: Not the mortgage.
A36: life sum assured | B36: =PLU_lifeSum -> 0 | C36: C · calculated

Sheet Personas
A1: A · INPUT DATA — About you (typed / session) | J1: B · LLM PREDICTED DATA — 13 fields from people_like_you_all_fields.json | W1: E · USER / FRONTEND OVERRIDE — Money page (blank = keep People Like You calculated) | AD1: notes | AF1: A · INPUT DATA
A2: id | B2: name | C2: age | D2: gender | E2: residency | F2: country | G2: occupation | H2: dependents | I2: maritalStatus (blank = infer) | J2: income | K2: currency | L2: risk_ability | M2: price_sensitivity | N2: property | O2: car | P2: ward_type | Q2: hospitalization_type | R2: travelling | S2: sports | T2: retirement_lifestyle | U2: is_smoker | V2: life_expectancy | W2: expenseMonthly | X2: cash (Cash & Savings) | Y2: investments | Z2: property value | AA2: mortgage (loans) | AB2: PLU liabilities | AC2: life sum assured | AD2: What this row varies | AF2: B · LLM PREDICTED DATA
A3: P01 | B3: Aisha Rahman | C3: 22 | D3: Female | E3: Citizen | F3: Singapore | G3: Nurse | H3: 0 | J3: 4200 | K3: SGD | L3: conservative | M3: high | N3: FALSE | O3: FALSE | P3: Ward | Q3: Public | R3: FALSE | S3: Yoga | T3: Basic | U3: FALSE | V3: 86 | W3: 2268 | X3: 983 | Y3: 5569 | Z3: 0 | AA3: 0 | AB3: 4586.4 | AC3: 0 | AD3: Nurse; age 22; Citizen; 0 dep; rent; non-smoker | AF3: C · DETERMINISTICALLY CALCULATED
A4: P02 | B4: Wei Ling Tan | C4: 27 | D4: Male | E4: PR | F4: Singapore | G4: Teacher | H4: 0 | J4: 6020 | K4: SGD | L4: moderate | M4: medium | N4: FALSE | O4: TRUE | P4: Double | Q4: Private | R4: TRUE | S4: Running | T4: Comfortable | U4: FALSE | V4: 81 | W4: 3250.8 | X4: 8452 | Y4: 47895 | Z4: 0 | AA4: 0 | AB4: 39443.04 | AC4: 0 | AD4: Teacher; age 27; PR; 0 dep; rent; non-smoker | AF4: D · ASSUMPTIONS / SHARED DATA
A5: P03 | B5: Daniel Koh | C5: 34 | D5: Female | E5: Citizen | F5: Singapore | G5: Accountant | H5: 1 | J5: 7140 | K5: SGD | L5: moderate | M5: medium | N5: TRUE | O5: TRUE | P5: Single | Q5: Private | R5: TRUE | S5: Swimming | T5: Comfortable | U5: FALSE | V5: 88 | W5: 4141.2 | X5: 18378 | Y5: 104144 | Z5: 350000 | AA5: 192500 | AB5: 85765.68 | AC5: 428400 | AD5: Accountant; age 34; Citizen; 1 dep; home; non-smoker | AF5: E · USER / FRONTEND OVERRIDE
A6: P04 | B6: Priya Nair | C6: 41 | D6: Male | E6: Citizen | F6: Singapore | G6: Marketing Manager | H6: 2 | J6: 4550 | K6: SGD | L6: conservative | M6: high | N6: TRUE | O6: TRUE | P6: Ward | Q6: Public | R6: FALSE | S6: I dont do sports | T6: frugal | U6: TRUE | V6: 78 | W6: 2821 | X6: 14742 | Y6: 83538 | Z6: 350000 | AA6: 192500 | AB6: 68796 | AC6: 273000 | AD6: Marketing Manager; age 41; Citizen; 2 dep; home; smoker
A7: P05 | B7: Marcus Lim | C7: 47 | D7: Female | E7: Foreigner | F7: Singapore | G7: Software Engineer | H7: 2 | J7: 5000 | K7: SGD | L7: aggressive | M7: high | N7: TRUE | O7: FALSE | P7: A | Q7: Private | R7: TRUE | S7: Adventurous Sports | T7: only the best | U7: FALSE | V7: 90 | W7: 3875 | X7: 26325 | Y7: 149175 | Z7: 350000 | AA7: 192500 | AB7: 122850 | AC7: 300000 | AD7: Software Engineer; age 47; Foreigner; 2 dep; home; non-smoker
A8: P06 | B8: Hannah Wong | C8: 32 | D8: Male | E8: Citizen | F8: Singapore | G8: Doctor | H8: 1 | J8: 13910 | K8: SGD | L8: moderate | M8: medium | N8: TRUE | O8: TRUE | P8: B | Q8: Public | R8: TRUE | S8: Life style activities | T8: stress-free | U8: FALSE | V8: 83 | W8: 8924.75 | X8: 33514 | Y8: 189913 | Z8: 650000 | AA8: 357500 | AB8: 156398.55 | AC8: 834600 | AD8: Doctor; age 32; Citizen; 1 dep; home; non-smoker
A9: P07 | B9: Julian Chee | C9: 54 | D9: Female | E9: PR | F9: Singapore | G9: Investment Banker | H9: 0 | J9: 5525 | K9: SGD | L9: conservative | M9: high | N9: TRUE | O9: TRUE | P9: Single | Q9: Private | R9: FALSE | S9: Walking | T9: Basic | U9: FALSE | V9: 89 | W9: 2983.5 | X9: 42664 | Y9: 241763 | Z9: 350000 | AA9: 192500 | AB9: 199098.9 | AC9: 200000 | AD9: Investment Banker; age 54; PR; 0 dep; home; non-smoker
A10: P08 | B10: Mei Fen Ong | C10: 60 | D10: Male | E10: Citizen | F10: Singapore | G10: CEO | H10: 3 | J10: 5975 | K10: SGD | L10: conservative | M10: high | N10: TRUE | O10: TRUE | P10: Ward | Q10: Public | R10: FALSE | S10: I dont do sports | T10: frugal | U10: TRUE | V10: 76 | W10: 4042.5 | X10: 30098 | Y10: 170557 | Z10: 350000 | AA10: 192500 | AB10: 140458.5 | AC10: 358500 | AD10: CEO; age 60; Citizen; 3 dep; home; smoker
A11: P09 | B11: Hafiz Abdullah | C11: 25 | D11: Female | E11: Citizen | F11: Singapore | G11: Baker | H11: 0 | J11: 3350 | K11: SGD | L11: moderate | M11: high | N11: FALSE | O11: FALSE | P11: Ward | Q11: Public | R11: TRUE | S11: HIIT | T11: Comfortable | U11: FALSE | V11: 87 | W11: 1809 | X11: 3136 | Y11: 17768 | Z11: 0 | AA11: 0 | AB11: 14632.8 | AC11: 0 | AD11: Baker; age 25; Citizen; 0 dep; rent; non-smoker
A12: P10 | B12: Siti Hassan | C12: 37 | D12: Male | E12: Foreigner | F12: Singapore | G12: Driver | H12: 2 | J12: 4250 | K12: SGD | L12: aggressive | M12: high | N12: FALSE | O12: TRUE | P12: Double | Q12: Private | R12: TRUE | S12: Football | T12: Luxurious | U12: FALSE | V12: 80 | W12: 3293.75 | X12: 13770 | Y12: 78030 | Z12: 0 | AA12: 0 | AB12: 64260 | AC12: 255000 | AD12: Driver; age 37; Foreigner; 2 dep; rent; non-smoker
A13: P11 | B13: Aisha Ng | C13: 51 | D13: Female | E13: Citizen | F13: Singapore | G13: Nurse | H13: 1 | J13: 7140 | K13: SGD | L13: moderate | M13: medium | N13: TRUE | O13: TRUE | P13: A | Q13: Private | R13: TRUE | S13: Pilates | T13: only the best | U13: FALSE | V13: 91 | W13: 4141.2 | X13: 42412 | Y13: 240332 | Z13: 350000 | AA13: 192500 | AB13: 197920.8 | AC13: 428400 | AD13: Nurse; age 51; Citizen; 1 dep; home; non-smoker
A14: P12 | B14: Wei Ling Chua | C14: 66 | D14: Male | E14: Citizen | F14: Singapore | G14: Teacher | H14: 0 | J14: 9800 | K14: SGD | L14: conservative | M14: medium | N14: TRUE | O14: FALSE | P14: Ward | Q14: Public | R14: FALSE | S14: I dont do sports | T14: Basic | U14: FALSE | V14: 85 | W14: 6210 | X14: 121095 | Y14: 686205 | Z14: 350000 | AA14: 192500 | AB14: 565110 | AC14: 200000 | AD14: Teacher; age 66; Citizen; 0 dep; home; non-smoker
A15: P13 | B15: Daniel Lee | C15: 30 | D15: Female | E15: PR | F15: Singapore | G15: Accountant | H15: 1 | J15: 6580 | K15: SGD | L15: moderate | M15: medium | N15: FALSE | O15: TRUE | P15: Double | Q15: Public | R15: FALSE | S15: Running | T15: Comfortable | U15: TRUE | V15: 79 | W15: 3816.4 | X15: 11726 | Y15: 66445 | Z15: 0 | AA15: 0 | AB15: 54719.28 | AC15: 394800 | AD15: Accountant; age 30; PR; 1 dep; rent; smoker
A16: P14 | B16: Priya Goh | C16: 44 | D16: Male | E16: Citizen | F16: Singapore | G16: Marketing Manager | H16: 4 | J16: 4775 | K16: SGD | L16: aggressive | M16: high | N16: TRUE | O16: TRUE | P16: Single | Q16: Private | R16: TRUE | S16: Golf | T16: Luxurious | U16: FALSE | V16: 84 | W16: 3342.5 | X16: 9884 | Y16: 56011 | Z16: 350000 | AA16: 192500 | AB16: 46126.5 | AC16: 286500 | AD16: Marketing Manager; age 44; Citizen; 4 dep; home; non-smoker
A17: P15 | B17: Marcus Teo | C17: 57 | D17: Female | E17: Citizen | F17: Singapore | G17: Software Engineer | H17: 2 | J17: 5750 | K17: SGD | L17: conservative | M17: high | N17: TRUE | O17: TRUE | P17: B | Q17: Private | R17: FALSE | S17: Life style activities | T17: stress-free | U17: FALSE | V17: 92 | W17: 3654.12 | X17: 34373 | Y17: 194778 | Z17: 350000 | AA17: 192500 | AB17: 160405.06 | AC17: 345000 | AD17: Software Engineer; age 57; Citizen; 2 dep; home; non-smoker
... A52: P50 | B52: Siti Lim | C52: 47 | D52: Female | E52: Foreigner | F52: Singapore | G52: Driver | H52: 2 | J52: 5000 | K52: SGD | L52: aggressive | M52: high | N52: TRUE | O52: FALSE | P52: A | Q52: Private | R52: TRUE | S52: Adventurous Sports | T52: only the best | U52: FALSE | V52: 90 | W52: 3875 | X52: 26325 | Y52: 149175 | Z52: 350000 | AA52: 192500 | AB52: 122850 | AC52: 300000 | AD52: Driver; age 47; Foreigner; 2 dep; home; non-smoker

Sheet CPF
A1: CPF — selected persona. Singapore employee ordinary-wage CPF (src/cpf.py). Off for every other country.
A2: Selected persona | B2: =SelectedPersona -> P02 | C2: =IFERROR(INDEX(Personas!B$3:B$52,MATCH($B$2,Personas!$A$3:$A$52,0)),"") -> Wei Ling Tan | D2: Follows the dropdown on the Selected persona tab. | F2: A · INPUT DATA
A3: Attribute | B3: Value | C3: Kind | D3: Source / formula | F3: B · LLM PREDICTED DATA
A4: A · INPUT DATA — from the selected Personas row | F4: C · DETERMINISTICALLY CALCULATED | I4: D · COUNTRY SWITCH — CPF on? (edit)
A5: country | B5: =IFERROR(INDEX(Personas!F$3:F$52,MATCH($B$2,Personas!$A$3:$A$52,0)),"") -> Singapore | C5: A · input | D5: Personas F. Looks up the country switch. | F5: D · ASSUMPTIONS / SHARED DATA | I5: country | J5: CPF on? | K5: note
A6: residency | B6: =IFERROR(INDEX(Personas!E$3:E$52,MATCH($B$2,Personas!$A$3:$A$52,0)),"") -> PR | C6: A · input | D6: Personas E. When CPF is on, Foreigner → rate 0. | F6: E · USER / FRONTEND OVERRIDE | I6: Singapore | J6: TRUE | K6: src/cpf.py applies. Citizen / PR contribute; Foreigner rate 0.
A7: age | B7: =IFERROR(INDEX(Personas!C$3:C$52,MATCH($B$2,Personas!$A$3:$A$52,0)),"") -> 27 | C7: A · input | D7: Personas C. Age-band rate when CPF is on. | I7: Vietnam | J7: FALSE | K7: No CPF. Take-home = gross.
A8: incomeMonthly | B8: =IFERROR(INDEX(Personas!J$3:J$52,MATCH($B$2,Personas!$A$3:$A$52,0)),"") -> 6020 | C8: A · input | D8: Personas J (LLM or user overwrite). | I8: Malaysia | J8: FALSE | K8: No CPF. Take-home = gross.
I9: Thailand | J9: FALSE | K9: No CPF. Take-home = gross.
A10: D · ASSUMPTIONS — src/cpf.py (used only when CPF is on) | I10: Philippines | J10: FALSE | K10: No CPF. Take-home = gross.
A11: OW_CEILING | B11: 8000 | C11: D · assumption / shared | D11: Ordinary-wage ceiling. Employee CPF is on min(gross, this). | I11: Australia | J11: FALSE | K11: No CPF. Take-home = gross.
A12: cpfRate_to55 | B12: 0.2 | C12: D · assumption / shared | D12: Employee rate age ≤ 55. | I12: Germany | J12: FALSE | K12: No CPF. Take-home = gross.
A13: cpfRate_to60 | B13: 0.18 | C13: D · assumption / shared | D13: Age 56–60. | I13: Hong Kong | J13: FALSE | K13: No CPF. Take-home = gross.
A14: cpfRate_to65 | B14: 0.125 | C14: D · assumption / shared | D14: Age 61–65. | I14: United States | J14: FALSE | K14: No CPF. Take-home = gross.
A15: cpfRate_to70 | B15: 0.075 | C15: D · assumption / shared | D15: Age 66–70.
A16: cpfRate_over70 | B16: 0.05 | C16: D · assumption / shared | D16: Age > 70.
A18: E · OVERRIDE — blank = country switch. TRUE / FALSE forces CPF on or off
A19: CPF on? (override) | C19: E · user / frontend override | D19: TRUE / FALSE / blank. Blank uses the country table.
A21: C · DETERMINISTICALLY CALCULATED — src/cpf.py when on; identity when off
A22: CPF on (effective) | B22: =IF(B19="",IFERROR(VLOOKUP(B5,CpfCountrySwitch,2,FALSE),FALSE),B19) -> TRUE | C22: C · calculated | D22: Country table, unless the orange override is set.
A23: Singapore age-band rate | B23: =IF(LOWER(B6)="foreigner",0,IF(B7<=55,cpfRate_to55,IF(B7<=60,cpfRate_to60,IF(B7<=65,cpfRate_to65,IF(B7<=70,cpfRate_to70,cpfRate_over70))))) -> 0.2 | C23: C · calculated | D23: employee_cpf_rate. Ignored when CPF is off.
A24: CPF rate used | B24: =IF(B22=TRUE,B23,0) -> 0.2 | C24: C · calculated | D24: 0 when CPF is off for this country.
A25: employee CPF | B25: =IF(OR(B22<>TRUE,B8<=0,B24<=0),0,FLOOR(MIN(B8,OW_CEILING)*B24,1)) -> 1204 | C25: C · calculated | D25: floor(min(gross, ceiling) × rate). 0 if CPF off.
A26: take-home | B26: =IF(B8<=0,0,ROUND(MAX(0,B8-B25),2)) -> 4816 | C26: C · calculated | D26: Gross minus employee CPF. Equals income when CPF is off.

Sheet People Like You
A1: People Like You — selected persona. Spend, assets, home, life cover. Take-home comes from the CPF tab.
A2: Selected persona | B2: =SelectedPersona -> P02 | C2: =IFERROR(INDEX(Personas!B$3:B$52,MATCH($B$2,Personas!$A$3:$A$52,0)),"") -> Wei Ling Tan | D2: Follows the dropdown on the Selected persona tab. | F2: A · INPUT DATA
A3: Attribute | B3: Value | C3: Kind | D3: Source / formula | F3: B · LLM PREDICTED DATA
A4: A · INPUT DATA — About you from the selected Personas row | F4: C · DETERMINISTICALLY CALCULATED
A5: age | B5: =IFERROR(INDEX(Personas!C$3:C$52,MATCH($B$2,Personas!$A$3:$A$52,0)),"") -> 27 | C5: A · input | D5: Personas C. Working years = age − 21. | F5: D · ASSUMPTIONS / SHARED DATA
A6: gender | B6: =IFERROR(INDEX(Personas!D$3:D$52,MATCH($B$2,Personas!$A$3:$A$52,0)),"") -> Male | C6: A · input | D6: Personas D. Not used by this component. | F6: E · USER / FRONTEND OVERRIDE
A7: residency | B7: =IFERROR(INDEX(Personas!E$3:E$52,MATCH($B$2,Personas!$A$3:$A$52,0)),"") -> PR | C7: A · input | D7: Personas E. Passed to the CPF tab (Foreigner → 0 when CPF is on).
A8: country | B8: =IFERROR(INDEX(Personas!F$3:F$52,MATCH($B$2,Personas!$A$3:$A$52,0)),"") -> Singapore | C8: A · input | D8: Personas F. CPF on/off is decided on the CPF tab.
A9: occupation | B9: =IFERROR(INDEX(Personas!G$3:G$52,MATCH($B$2,Personas!$A$3:$A$52,0)),"") -> Teacher | C9: A · input | D9: Personas G. Looks up income_anchors.json Singapore band.
A10: dependents | B10: =IFERROR(INDEX(Personas!H$3:H$52,MATCH($B$2,Personas!$A$3:$A$52,0)),"") -> 0 | C10: A · input | D10: Personas H. Spend-share +5 pp each; 5× income life cover if > 0.
A11: maritalStatus (typed) | B11: =IFERROR(INDEX(Personas!I$3:I$52,MATCH($B$2,Personas!$A$3:$A$52,0)),"") -> 0 | C11: A · input | D11: Personas I. Blank → infer below.
A13: B · LLM PREDICTED DATA — fields this component reads from Personas
A14: income (LLM gross monthly) | B14: =IFERROR(INDEX(Personas!J$3:J$52,MATCH($B$2,Personas!$A$3:$A$52,0)),"") -> 6020 | C14: B · LLM predicted | D14: Personas J. people_like_you_all_fields.json income.
A15: currency | B15: =IFERROR(INDEX(Personas!K$3:K$52,MATCH($B$2,Personas!$A$3:$A$52,0)),"") -> SGD | C15: B · LLM predicted | D15: Personas K. SGD in this workbook.
A16: property (owns home) | B16: =IFERROR(INDEX(Personas!N$3:N$52,MATCH($B$2,Personas!$A$3:$A$52,0)),"") -> FALSE | C16: B · LLM predicted | D16: Personas N. seed_property_value if TRUE.
A17: life_expectancy (raw) | B17: =IFERROR(INDEX(Personas!V$3:V$52,MATCH($B$2,Personas!$A$3:$A$52,0)),"") -> 81 | C17: B · LLM predicted | D17: Personas V. Used only when 70–120; else default 85.
A19: D · ASSUMPTIONS / SHARED DATA — named cells on Assumptions (CPF is on the CPF tab)
A20: spendShareBase | B20: =spendShareBase -> 0.675 | C20: D · assumption / shared | D20: 67.5% of take-home.
A21: spendSharePerDependant | B21: =spendSharePerDependant -> 0.05 | C21: D · assumption / shared | D21: +5 pp per dependant.
A22: spendShareCap | B22: =spendShareCap -> 0.9 | C22: D · assumption / shared | D22: 90% cap.
A23: assetsSaveShare | B23: =assetsSaveShare -> 0.5 | C23: D · assumption / shared | D23: 50% of annual surplus saved.
A24: workStartAge | B24: =workStartAge -> 21 | C24: D · assumption / shared | D24: 21. Working years = max(0, age − 21).
A25: CASH_SAVINGS_SHARE | B25: =CASH_SAVINGS_SHARE -> 0.15 | C25: D · assumption / shared | D25: src/predict.py 15% (not the 45% in some docs).
A26: INVESTMENTS_SHARE | B26: =INVESTMENTS_SHARE -> 0.85 | C26: D · assumption / shared | D26: src/predict.py 85%.
A27: liabilityRatio | B27: =liabilityRatio -> 0.7 | C27: D · assumption / shared | D27: PLU liabilities = liquid assets × 0.7 (not the mortgage).
A28: propertyLow | B28: =propertyLow -> 350000 | C28: D · assumption / shared | D28: seed_property_value: income < 10,000 → S$350,000.
A29: propertyMid | B29: =propertyMid -> 650000 | C29: D · assumption / shared | D29: income 10,000–20,000 → S$650,000.
A30: propertyHigh | B30: =propertyHigh -> 850000 | C30: D · assumption / shared | D30: income > 20,000 → S$850,000.
A31: propertyIncomeLow | B31: =propertyIncomeLow -> 10000 | C31: D · assumption / shared | D31: 10,000. Below this → propertyLow.
A32: propertyIncomeHigh | B32: =propertyIncomeHigh -> 20000 | C32: D · assumption / shared | D32: 20,000. Above this → propertyHigh.
A33: PROPERTY_LTV | B33: =PROPERTY_LTV -> 0.55 | C33: D · assumption / shared | D33: Mortgage = round(property × 55%).
A34: lifePremiumRate | B34: =lifePremiumRate -> 0.0031 | C34: D · assumption / shared | D34: 0.31% of sum assured.
A35: lifeRoundUnit | B35: =lifeRoundUnit -> 100000 | C35: D · assumption / shared | D35: Mortgage cover rounded to nearest S$100,000.
A36: lifeExpectancyDefault | B36: =lifeExpectancyDefault -> 85 | C36: D · assumption / shared | D36: 85 when raw LE is outside 70–120.
A38: C · DETERMINISTICALLY CALCULATED — _apply_plu. Take-home is read from the CPF tab.
A39: band min | B39: =IFERROR(INDEX(Assumptions!$F$6:$F$13,MATCH(B9,Assumptions!$E$6:$E$13,0)),"") -> 5600 | C39: C · calculated | D39: income_anchors.json Singapore min for occupation.
A40: band max | B40: =IFERROR(INDEX(Assumptions!$G$6:$G$13,MATCH(B9,Assumptions!$E$6:$E$13,0)),"") -> 9800 | C40: C · calculated | D40: income_anchors.json Singapore max.
A41: incomeMonthly (clamped) | B41: =IF(OR(B39="",B14=0),B14,MIN(MAX(B14,B39),B40)) -> 6020 | C41: C · calculated | D41: Clamp LLM income into the occupation band. 0 stays 0.
A42: CPF on (from CPF tab) | B42: =CPF_on -> TRUE | C42: A · input | D42: Country switch or orange override on the CPF tab.
A43: CPF rate | B43: =CPF_rate -> 0.2 | C43: C · calculated | D43: 0 when CPF is off for this country.
A44: employee CPF | B44: =CPF_employee -> 1204 | C44: C · calculated | D44: 0 when CPF is off.
A45: take-home | B45: =CPF_takeHome -> 4816 | C45: C · calculated | D45: Gross minus employee CPF. Equals income when CPF is off.
A46: spend share | B46: =MIN(spendShareBase+spendSharePerDependant*MAX(0,B10),spendShareCap) -> 0.675 | C46: C · calculated | D46: min(67.5% + 5pp × dependents, 90%).
A47: expenseMonthly | B47: =IF(B45<=0,0,ROUND(B45*B46,2)) -> 3250.8 | C47: C · calculated | D47: expenses_from_gross / spend of take-home.
A48: surplus / mo | B48: =B45-B47 -> 1565.2 | C48: C · calculated | D48: take-home − expense.
A49: working years | B49: =MAX(0,B5-workStartAge) -> 6 | C49: C · calculated | D49: max(0, age − 21).
A50: liquid assets | B50: =IF(AND(B14>0,B47>0,B5>workStartAge),MAX(0,B48*12*assetsSaveShare*B49),0) -> 56347.2 | C50: C · calculated | D50: surplus × 12 × 0.5 × working years.
A51: PLU liabilities | B51: =B50*liabilityRatio -> 39443.04 | C51: C · calculated | D51: liquid × 0.7. Not the mortgage.
A52: cash (15%) | B52: =ROUND(B50*CASH_SAVINGS_SHARE,0) -> 8452 | C52: C · calculated | D52: CASH_SAVINGS_SHARE.
A53: investments (85%) | B53: =ROUND(B50*INVESTMENTS_SHARE,0) -> 47895 | C53: C · calculated | D53: INVESTMENTS_SHARE.
A54: property | B54: =IF(B16=FALSE,0,IF(B14<propertyIncomeLow,propertyLow,IF(B14<=propertyIncomeHigh,propertyMid,propertyHigh))) -> 0 | C54: C · calculated | D54: seed_property_value.
A55: mortgage | B55: =IF(B54=0,0,ROUND(B54*PROPERTY_LTV,0)) -> 0 | C55: C · calculated | D55: round(property × 55%).
A56: life sum assured | B56: =MAX(IF(B54>0,INT((B55+lifeRoundUnit/2)/lifeRoundUnit)*lifeRoundUnit,0),IF(B10>0,ROUND(B14*12*5,0),0)) -> 0 | C56: C · calculated | D56: _assumed_life_policy: max(mortgage rounded to 100k, 5 × annual income if dependents).
A57: life premium | B57: =IF(B56<=0,0,MAX(0,ROUND(B56*lifePremiumRate,0))) -> 0 | C57: C · calculated | D57: round(sum × 0.31%).
A58: lifeExpectancy used | B58: =IF(AND(B17>=70,B17<=120),B17,lifeExpectancyDefault) -> 81 | C58: C · calculated | D58: Session LE when 70–120, else 85.
A59: marital (inferred) | B59: =IF(IFERROR(INDEX(Personas!I$3:I$52,MATCH($B$2,Personas!$A$3:$A$52,0)),"")<>"",LOWER(IFERROR(INDEX(Personas!I$3:I$52,MATCH($B$2,Personas!$A$3:$A$52,0)),"")),IF(B5<30,"single","married")) -> single | C59: C · calculated | D59: Typed maritalStatus, else age < 30 → single.
A61: E · USER / FRONTEND OVERRIDE — Personas W–AC (Money page). Blank keeps the green calculated value.
A62: override expenseMonthly | B62: =IFERROR(INDEX(Personas!W$3:W$52,MATCH($B$2,Personas!$A$3:$A$52,0)),"") -> 3250.8 | C62: E · user / frontend override | D62: Money page spend. Frontend MIN_EXPENSE_MONTHLY = 100 SGD.
A63: override cash | B63: =IFERROR(INDEX(Personas!X$3:X$52,MATCH($B$2,Personas!$A$3:$A$52,0)),"") -> 8452 | C63: E · user / frontend override | D63: Cash & Savings. Provenance key cash / savings.
A64: override investments | B64: =IFERROR(INDEX(Personas!Y$3:Y$52,MATCH($B$2,Personas!$A$3:$A$52,0)),"") -> 47895 | C64: E · user / frontend override | D64: Investments.
A65: override property value | B65: =IFERROR(INDEX(Personas!Z$3:Z$52,MATCH($B$2,Personas!$A$3:$A$52,0)),"") -> 0 | C65: E · user / frontend override | D65: Home value. Distinct from owns-home flag N.
A66: override mortgage | B66: =IFERROR(INDEX(Personas!AA$3:AA$52,MATCH($B$2,Personas!$A$3:$A$52,0)),"") -> 0 | C66: E · user / frontend override | D66: Money page loans.
A67: override PLU liabilities | B67: =IFERROR(INDEX(Personas!AB$3:AB$52,MATCH($B$2,Personas!$A$3:$A$52,0)),"") -> 39443.04 | C67: E · user / frontend override | D67: Need Profiler TotalLiabilities. Not the mortgage.
A68: override life sum assured | B68: =IFERROR(INDEX(Personas!AC$3:AC$52,MATCH($B$2,Personas!$A$3:$A$52,0)),"") -> 0 | C68: E · user / frontend override | D68: Existing Life Protection cover.
A70: C · EFFECTIVE SESSION — override if set, else calculated. Downstream and Validation read these.
A71: incomeMonthly | B71: =B14 -> 6020 | C71: C · calculated | D71: Personas J (LLM or user). The clamp row above is what /predict would force.
A72: expenseMonthly | B72: =IF(IFERROR(INDEX(Personas!W$3:W$52,MATCH($B$2,Personas!$A$3:$A$52,0)),"")="",B47,IFERROR(INDEX(Personas!W$3:W$52,MATCH($B$2,Personas!$A$3:$A$52,0)),"")) -> 3250.8 | C72: C · calculated
A73: take-home | B73: =B45 -> 4816 | C73: C · calculated | D73: From Personas J and CPF.
A74: surplus / mo | B74: =B73-B72 -> 1565.2 | C74: C · calculated
A75: cash | B75: =IF(IFERROR(INDEX(Personas!X$3:X$52,MATCH($B$2,Personas!$A$3:$A$52,0)),"")="",B52,IFERROR(INDEX(Personas!X$3:X$52,MATCH($B$2,Personas!$A$3:$A$52,0)),"")) -> 8452 | C75: C · calculated
A76: investments | B76: =IF(IFERROR(INDEX(Personas!Y$3:Y$52,MATCH($B$2,Personas!$A$3:$A$52,0)),"")="",B53,IFERROR(INDEX(Personas!Y$3:Y$52,MATCH($B$2,Personas!$A$3:$A$52,0)),"")) -> 47895 | C76: C · calculated
A77: liquid assets | B77: =B75+B76 -> 56347 | C77: C · calculated | D77: cash + investments.
A78: property | B78: =IF(IFERROR(INDEX(Personas!Z$3:Z$52,MATCH($B$2,Personas!$A$3:$A$52,0)),"")="",B54,IFERROR(INDEX(Personas!Z$3:Z$52,MATCH($B$2,Personas!$A$3:$A$52,0)),"")) -> 0 | C78: C · calculated
A79: mortgage | B79: =IF(IFERROR(INDEX(Personas!AA$3:AA$52,MATCH($B$2,Personas!$A$3:$A$52,0)),"")="",B55,IFERROR(INDEX(Personas!AA$3:AA$52,MATCH($B$2,Personas!$A$3:$A$52,0)),"")) -> 0 | C79: C · calculated
A80: PLU liabilities | B80: =IF(IFERROR(INDEX(Personas!AB$3:AB$52,MATCH($B$2,Personas!$A$3:$A$52,0)),"")="",B51,IFERROR(INDEX(Personas!AB$3:AB$52,MATCH($B$2,Personas!$A$3:$A$52,0)),"")) -> 39443.04 | C80: C · calculated
A81: life sum assured | B81: =IF(IFERROR(INDEX(Personas!AC$3:AC$52,MATCH($B$2,Personas!$A$3:$A$52,0)),"")="",B56,IFERROR(INDEX(Personas!AC$3:AC$52,MATCH($B$2,Personas!$A$3:$A$52,0)),"")) -> 0 | C81: C · calculated
A82: life premium | B82: =IF(B81<=0,0,MAX(0,ROUND(B81*lifePremiumRate,0))) -> 0 | C82: C · calculated | D82: Recomputed from effective sum.
A83: currency | B83: =IFERROR(INDEX(Personas!K$3:K$52,MATCH($B$2,Personas!$A$3:$A$52,0)),"") -> SGD | C83: B · LLM predicted | D83: Personas K. FX converts with this ISO code.

Sheet Need Profiler
A1: Need Profiler — selected persona. Weighted scores → two protection + two growth. Orange Enable? overrides.
A2: Selected persona | B2: =SelectedPersona -> P02 | C2: =IFERROR(INDEX(Personas!B$3:B$52,MATCH($B$2,Personas!$A$3:$A$52,0)),"") -> Wei Ling Tan | D2: Follows the dropdown on the Selected persona tab. | F2: A · INPUT DATA
A3: Attribute | B3: Value | C3: Kind | D3: Source / formula | F3: B · LLM PREDICTED DATA
A4: A · INPUT DATA — from selected Personas + People Like You results | F4: C · DETERMINISTICALLY CALCULATED
A5: age | B5: =IFERROR(INDEX(Personas!C$3:C$52,MATCH($B$2,Personas!$A$3:$A$52,0)),"") -> 27 | C5: A · input | D5: Personas C. Bucket <21 / ≤30 / ≤40 / else. | F5: D · ASSUMPTIONS / SHARED DATA
A6: gender | B6: =IFERROR(INDEX(Personas!D$3:D$52,MATCH($B$2,Personas!$A$3:$A$52,0)),"") -> Male | C6: A · input | D6: Personas D. male=3, female=2. | F6: E · USER / FRONTEND OVERRIDE
A7: dependents | B7: =IFERROR(INDEX(Personas!H$3:H$52,MATCH($B$2,Personas!$A$3:$A$52,0)),"") -> 0 | C7: A · input | D7: Personas H. 0 / 1 / ≥2 → 0 / 2 / 4.
A8: occupation | B8: =IFERROR(INDEX(Personas!G$3:G$52,MATCH($B$2,Personas!$A$3:$A$52,0)),"") -> Teacher | C8: A · input | D8: Personas G. Self-employed tokens → 2, else 1.
A9: incomeMonthly (from PLU) | B9: =PLU_incomeMonthly -> 6020 | C9: A · input | D9: People Like You calculated income, used as profiler Income.
A10: expenseMonthly (from PLU) | B10: =PLU_expenseMonthly -> 3250.8 | C10: A · input | D10: People Like You calculated spend.
A11: liquid assets (from PLU) | B11: =PLU_cash+PLU_investments -> 56347 | C11: A · input | D11: cash + investments.
A12: PLU liabilities (from PLU) | B12: =PLU_liabilities -> 39443.04 | C12: A · input | D12: Not the mortgage.
A14: B · LLM PREDICTED DATA — lifestyle flags this component reads
A15: is_smoker | B15: =IFERROR(INDEX(Personas!U$3:U$52,MATCH($B$2,Personas!$A$3:$A$52,0)),"") -> FALSE | C15: B · LLM predicted | D15: Personas U. TRUE→3, else 1 (JSON has no Smoking options).
A16: hospitalization_type | B16: =IFERROR(INDEX(Personas!Q$3:Q$52,MATCH($B$2,Personas!$A$3:$A$52,0)),"") -> Private | C16: B · LLM predicted | D16: Personas Q. private=4, public=2.
A17: ward_type | B17: =IFERROR(INDEX(Personas!P$3:P$52,MATCH($B$2,Personas!$A$3:$A$52,0)),"") -> Double | C17: B · LLM predicted | D17: Personas P. A=3, B=2. Single/Double/Ward score 0.
A18: retirement_lifestyle | B18: =IFERROR(INDEX(Personas!T$3:T$52,MATCH($B$2,Personas!$A$3:$A$52,0)),"") -> Comfortable | C18: B · LLM predicted | D18: Personas T. frugal / stress-free / only the best.
A19: sports | B19: =IFERROR(INDEX(Personas!S$3:S$52,MATCH($B$2,Personas!$A$3:$A$52,0)),"") -> Running | C19: B · LLM predicted | D19: Personas S. Adventurous / I dont do sports / Life style.
A20: property (owns home) | B20: =IFERROR(INDEX(Personas!N$3:N$52,MATCH($B$2,Personas!$A$3:$A$52,0)),"") -> FALSE | C20: B · LLM predicted | D20: Personas N. Swaps N_SAV ↔ N_PRP in the second growth slot.
A22: D · ASSUMPTIONS / SHARED DATA — used by this component
A23: Existing hospital cover | B23: 0 | C23: D · assumption / shared | D23: build_profiler_profile hard-codes Existing*Coverage = False → option weight 1.
A24: Existing disability cover | B24: 0 | C24: D · assumption / shared | D24: Same. Stored as 0 here; option weight of False is 1.
A25: SGD → USD factor | B25: 0.75 | C25: D · assumption / shared | D25: Income / expense / assets / liabilities: value × 0.75 then hardcoded USD buckets.
A26: Selection rule | B26: 2 prot + N_RET + 1 growth | C26: D · assumption / shared | D26: select_unified_top ignores top_n. If owns home, N_PRP replaces N_SAV.
A27: Profiler weight matrix | B27: Assumptions!B90:M104 | C27: D · assumption / shared | D27: Need_profiler.json needs_factor_weights. SUMPRODUCT with option weights.
A29: C · DETERMINISTICALLY CALCULATED — SGD×0.75 helpers, then 15 option weights
A30: usd Income | B30: =PLU_incomeMonthly*0.75 -> 4515 | C30: C · calculated | D30: People Like You incomeMonthly × 0.75. No LET (Excel #NAME? on LET).
A31: usd Expense | B31: =PLU_expenseMonthly*0.75 -> 2438.1 | C31: C · calculated | D31: People Like You expenseMonthly × 0.75.
A32: usd Assets | B32: =(PLU_cash+PLU_investments)*0.75 -> 42260.25 | C32: C · calculated | D32: cash + investments × 0.75.
A33: usd Liab | B33: =PLU_liabilities*0.75 -> 29582.28 | C33: C · calculated | D33: PLU liabilities × 0.75.
A34: ow Age | B34: =IF(B5<21,1,IF(B5<=30,2,IF(B5<=40,3,4))) -> 2 | C34: C · calculated | D34: _get_option_weight Date of Birth.
A35: ow Gender | B35: =IF(LOWER(B6)="male",3,IF(LOWER(B6)="female",2,0)) -> 3 | C35: C · calculated | D35: male=3, female=2.
A36: ow Deps | B36: =IF(B7=0,0,IF(B7=1,2,4)) -> 0 | C36: C · calculated | D36: 0 / 1 / else.
A37: ow Occ | B37: =IF(OR(ISNUMBER(SEARCH("self",B8)),ISNUMBER(SEARCH("entrepreneur",B8)),ISNUMBER(SEARCH("own business",B8)),ISNUMBER(SEARCH("freelance",B8))),2,1) -> 1 | C37: C · calculated | D37: Self-employed tokens.
A38: ow Smoke | B38: =IF(B15=TRUE,3,1) -> 1 | C38: C · calculated | D38: No Smoking options in JSON.
A39: ow Income | B39: =IF(B30<108,4,IF(B30<243,3,IF(B30<1081,2,IF(B30<2703,1,0)))) -> 0 | C39: C · calculated | D39: Hardcoded USD buckets after × 0.75.
A40: ow Expense | B40: =IF(B31<68,4,IF(B31<135,3,IF(B31<541,2,IF(B31<1351,1,0)))) -> 0 | C40: C · calculated | D40: Same bucket pattern.
A41: ow Assets | B41: =IF(B32<541,4,IF(B32<1351,3,IF(B32<5405,2,IF(B32<27027,1,0)))) -> 0 | C41: C · calculated | D41: cash + investments.
A42: ow Liab | B42: =IF(B33<270,4,IF(B33<541,3,IF(B33<1351,2,IF(B33<5405,1,0)))) -> 0 | C42: C · calculated | D42: PLU liabilities.
A43: ow HospExist | B43: 1 | C43: C · calculated | D43: Existing hospital coverage always False → 1.
A44: ow DisExist | B44: 1 | C44: C · calculated | D44: Existing disability coverage always False → 1.
A45: ow HospType | B45: =IF(LOWER(B16)="private",4,IF(LOWER(B16)="public",2,0)) -> 4 | C45: C · calculated | D45: Hospital Type.
A46: ow Ward | B46: =IF(UPPER(B17)="A",3,IF(UPPER(B17)="B",2,0)) -> 0 | C46: C · calculated | D46: Ward Type.
A47: ow Lifestyle | B47: =IF(LOWER(B18)="frugal",1,IF(OR(LOWER(B18)="stress-free",LOWER(B18)="stress free"),2,IF(LOWER(B18)="only the best",4,0))) -> 0 | C47: C · calculated | D47: Basic/Comfortable/Luxurious score 0.
A48: ow Sports | B48: =IF(ISNUMBER(SEARCH("adventurous",B19)),4,IF(ISNUMBER(SEARCH("dont do sports",B19)),0,IF(ISNUMBER(SEARCH("life style",B19)),1,0))) -> 0 | C48: C · calculated | D48: Free-text sports.
A50: C · RESULTS — raw Σ (factor × option), then min–max scale 0–10
A51: raw Life Protection | B51: =ROUND(SUMPRODUCT($B$34:$B$48,Assumptions!B$90:B$104),2) -> 19 | C51: C · calculated | D51: Need_profiler.json column Life Protection.
A52: raw Critical Illness | B52: =ROUND(SUMPRODUCT($B$34:$B$48,Assumptions!C$90:C$104),2) -> 23 | C52: C · calculated | D52: Need_profiler.json column Critical Illness.
A53: raw Disability | B53: =ROUND(SUMPRODUCT($B$34:$B$48,Assumptions!D$90:D$104),2) -> 14 | C53: C · calculated | D53: Need_profiler.json column Disability.
A54: raw Retirement | B54: =ROUND(SUMPRODUCT($B$34:$B$48,Assumptions!E$90:E$104),2) -> 16 | C54: C · calculated | D54: Need_profiler.json column Retirement.
A55: raw Education | B55: =ROUND(SUMPRODUCT($B$34:$B$48,Assumptions!F$90:F$104),2) -> 0 | C55: C · calculated | D55: Need_profiler.json column Education.
A56: raw Hospitalization | B56: =ROUND(SUMPRODUCT($B$34:$B$48,Assumptions!G$90:G$104),2) -> 22 | C56: C · calculated | D56: Need_profiler.json column Hospitalization.
A57: raw General Savings | B57: =ROUND(SUMPRODUCT($B$34:$B$48,Assumptions!H$90:H$104),2) -> 15 | C57: C · calculated | D57: Need_profiler.json column General Savings.
A58: raw Farewell | B58: =ROUND(SUMPRODUCT($B$34:$B$48,Assumptions!I$90:I$104),2) -> 14 | C58: C · calculated | D58: Need_profiler.json column Farewell.
A59: raw Personal Accident | B59: =ROUND(SUMPRODUCT($B$34:$B$48,Assumptions!J$90:J$104),2) -> 0 | C59: C · calculated | D59: Need_profiler.json column Personal Accident.
A60: raw Car Protection | B60: =ROUND(SUMPRODUCT($B$34:$B$48,Assumptions!K$90:K$104),2) -> 19 | C60: C · calculated | D60: Need_profiler.json column Car Protection.
A61: raw Home Protection | B61: =ROUND(SUMPRODUCT($B$34:$B$48,Assumptions!L$90:L$104),2) -> 13 | C61: C · calculated | D61: Need_profiler.json column Home Protection.
A62: raw Travel Protection | B62: =ROUND(SUMPRODUCT($B$34:$B$48,Assumptions!M$90:M$104),2) -> 18 | C62: C · calculated | D62: Need_profiler.json column Travel Protection.
A63: min raw | B63: =MIN(B51:B62) -> 0 | C63: C · calculated | D63: scale_scores min.
A64: max raw | B64: =MAX(B51:B62) -> 23 | C64: C · calculated | D64: If max=min, divisor is forced to 1 so every scaled value is 0.
A65: scaled Life Protection | B65: =ROUND(((B51-B63)/IF(B64>B63,B64-B63,1))*10,1) -> 8.3 | C65: C · calculated | D65: 0–10, 1 decimal.
A66: scaled Critical Illness | B66: =ROUND(((B52-B63)/IF(B64>B63,B64-B63,1))*10,1) -> 10 | C66: C · calculated | D66: 0–10, 1 decimal.
A67: scaled Disability | B67: =ROUND(((B53-B63)/IF(B64>B63,B64-B63,1))*10,1) -> 6.1 | C67: C · calculated | D67: 0–10, 1 decimal.
A68: scaled Retirement | B68: =ROUND(((B54-B63)/IF(B64>B63,B64-B63,1))*10,1) -> 7 | C68: C · calculated | D68: 0–10, 1 decimal.
A69: scaled Education | B69: =ROUND(((B55-B63)/IF(B64>B63,B64-B63,1))*10,1) -> 0 | C69: C · calculated | D69: 0–10, 1 decimal.
A70: scaled Hospitalization | B70: =ROUND(((B56-B63)/IF(B64>B63,B64-B63,1))*10,1) -> 9.6 | C70: C · calculated | D70: 0–10, 1 decimal.
A71: scaled General Savings | B71: =ROUND(((B57-B63)/IF(B64>B63,B64-B63,1))*10,1) -> 6.5 | C71: C · calculated | D71: 0–10, 1 decimal.
A72: scaled Farewell | B72: =ROUND(((B58-B63)/IF(B64>B63,B64-B63,1))*10,1) -> 6.1 | C72: C · calculated | D72: 0–10, 1 decimal.
A73: scaled Personal Accident | B73: =ROUND(((B59-B63)/IF(B64>B63,B64-B63,1))*10,1) -> 0 | C73: C · calculated | D73: 0–10, 1 decimal.
A74: scaled Car Protection | B74: =ROUND(((B60-B63)/IF(B64>B63,B64-B63,1))*10,1) -> 8.3 | C74: C · calculated | D74: 0–10, 1 decimal.
A75: scaled Home Protection | B75: =ROUND(((B61-B63)/IF(B64>B63,B64-B63,1))*10,1) -> 5.7 | C75: C · calculated | D75: 0–10, 1 decimal.
A76: scaled Travel Protection | B76: =ROUND(((B62-B63)/IF(B64>B63,B64-B63,1))*10,1) -> 7.8 | C76: C · calculated | D76: 0–10, 1 decimal.
A78: tb N_INC | B78: =B65+0.004 -> 8.304 | C78: C · calculated | D78: Tie-break: Life Protection first in AI label order.
A79: tb N_CRI | B79: =B66+0.003 -> 10.003 | C79: C · calculated | D79: Critical Illness second.
A80: tb N_TPD | B80: =B67+0.002 -> 6.102 | C80: C · calculated | D80: Disability third.
A81: tb N_HOS | B81: =B70+0.001 -> 9.601 | C81: C · calculated | D81: Hospitalization last.
A82: prot1 | B82: =IF(B78=MAX(B78,B79,B80,B81),"N_INC",IF(B79=MAX(B78,B79,B80,B81),"N_CRI",IF(B80=MAX(B78,B79,B80,B81),"N_TPD","N_HOS"))) -> N_CRI | C82: C · calculated | D82: Highest protection score after the 0.00x order bonus.
A83: tb2 N_INC | B83: =IF(B82="N_INC",-1,B65+0.004) -> 8.304 | C83: C · calculated | D83: Winner of prot1 is excluded.
A84: tb2 N_CRI | B84: =IF(B82="N_CRI",-1,B66+0.003) -> -1 | C84: C · calculated
A85: tb2 N_TPD | B85: =IF(B82="N_TPD",-1,B67+0.002) -> 6.102 | C85: C · calculated
A86: tb2 N_HOS | B86: =IF(B82="N_HOS",-1,B70+0.001) -> 9.601 | C86: C · calculated
A87: prot2 | B87: =IF(B83=MAX(B83,B84,B85,B86),"N_INC",IF(B84=MAX(B83,B84,B85,B86),"N_CRI",IF(B85=MAX(B83,B84,B85,B86),"N_TPD","N_HOS"))) -> N_HOS | C87: C · calculated | D87: Second protection.
A88: tb N_EDU | B88: =B69+0.003 -> 0.003 | C88: C · calculated | D88: Education first among remaining growth.
A89: tb N_SAV | B89: =B71+0.002 -> 6.502 | C89: C · calculated | D89: General Savings second.
A90: tb N_PRP | B90: =B75+0.001 -> 5.701 | C90: C · calculated | D90: Home Protection last.
A91: grow2 raw | B91: =IF(B88=MAX(B88,B89,B90),"N_EDU",IF(B89=MAX(B88,B89,B90),"N_SAV","N_PRP")) -> N_SAV | C91: C · calculated | D91: Before the home-ownership swap.
A92: grow2 | B92: =IF(AND(B20=TRUE,B91="N_SAV"),"N_PRP",IF(AND(B20=FALSE,B91="N_PRP"),"N_SAV",B91)) -> N_SAV | C92: C · calculated | D92: Second growth after forced N_RET. Home ownership swaps SAV/PRP.
A94: C · RESULTS — eight UNIFIED flags. Orange Enable? = TRUE / FALSE / blank
A95: type | B95: calc on | C95: Enable? | D95: on (effective) | E95: priority
A96: N_INC | B96: =OR($B$82="N_INC",$B$87="N_INC") -> FALSE | D96: =IF(C96="",B96,C96) -> FALSE | E96: =IF(B65>7,5,3) -> 5
A97: N_CRI | B97: =OR($B$82="N_CRI",$B$87="N_CRI") -> TRUE | D97: =IF(C97="",B97,C97) -> TRUE | E97: =IF(B66>7,5,3) -> 5
A98: N_TPD | B98: =OR($B$82="N_TPD",$B$87="N_TPD") -> FALSE | D98: =IF(C98="",B98,C98) -> FALSE | E98: =IF(B67>7,5,3) -> 3
A99: N_HOS | B99: =OR($B$82="N_HOS",$B$87="N_HOS") -> TRUE | D99: =IF(C99="",B99,C99) -> TRUE | E99: =IF(B70>7,5,3) -> 5
A100: N_RET | B100: TRUE | D100: =IF(C100="",B100,C100) -> TRUE | E100: =IF(B68>7,5,3) -> 3
A101: N_EDU | B101: =$B$92="N_EDU" -> FALSE | D101: =IF(C101="",B101,C101) -> FALSE | E101: =IF(B69>7,5,3) -> 3
A102: N_SAV | B102: =$B$92="N_SAV" -> TRUE | D102: =IF(C102="",B102,C102) -> TRUE | E102: =IF(B71>7,5,3) -> 3
A103: N_PRP | B103: =$B$92="N_PRP" -> FALSE | D103: =IF(C103="",B103,C103) -> FALSE | E103: =IF(B75>7,5,3) -> 3

Sheet Need Calculator
A1: Need Calculator — selected persona. evaluate_session / goal_math.py. Orange cells are goal-card sliders.
A2: Selected persona | B2: =SelectedPersona -> P02 | C2: =IFERROR(INDEX(Personas!B$3:B$52,MATCH($B$2,Personas!$A$3:$A$52,0)),"") -> Wei Ling Tan | D2: Follows the dropdown on the Selected persona tab. | F2: A · INPUT DATA
A3: Attribute | B3: Value | C3: Kind | D3: Source / formula | F3: B · LLM PREDICTED DATA
A4: A · INPUT DATA — from Personas, People Like You, and Need Profiler | F4: C · DETERMINISTICALLY CALCULATED
A5: age | B5: =IFERROR(INDEX(Personas!C$3:C$52,MATCH($B$2,Personas!$A$3:$A$52,0)),"") -> 27 | C5: A · input | D5: Personas C. | F5: D · ASSUMPTIONS / SHARED DATA
A6: incomeMonthly (from PLU) | B6: =PLU_incomeMonthly -> 6020 | C6: A · input | D6: Clamped gross monthly. | F6: E · USER / FRONTEND OVERRIDE
A7: expenseMonthly (from PLU) | B7: =PLU_expenseMonthly -> 3250.8 | C7: A · input | D7: Annual spend = this × 12.
A8: mortgage (from PLU) | B8: =PLU_mortgage -> 0 | C8: A · input | D8: Added to N_INC amount.
A9: life sum (from PLU) | B9: =PLU_lifeSum -> 0 | C9: A · input | D9: N_INC have.
A10: investments (from PLU) | B10: =PLU_investments -> 47895 | C10: A · input | D10: Tagged wealth pot only. Cash is never allocated.
A11: lifeExpectancy used (from PLU) | B11: =PLU_leUsed -> 81 | C11: A · input | D11: yearsInRet = max(0, LE − retAge).
A13: O · GOAL-CARD SLIDERS / OVERRIDES — orange. Blank years keep the age rule
A14: lifestyle (1/2/3) | B14: 2 | C14: E · user / frontend override | D14: 1=frugal, 2=stress-free, 3=only the best. Default 2.
A15: retAge | B15: =ageOfRetirement -> 65 | C15: E · user / frontend override | D15: Default from Assumptions (65).
A16: targetYear | B16: =currentYear+eduYearsDefault -> 2036 | C16: E · user / frontend override | D16: Education horizon year.
A17: bequest | B17: 0 | C17: E · user / frontend override | D17: Added to N_INC amount.
A18: dependYears (blank = age rule) | C18: E · user / frontend override | D18: Blank or ≤0 → supportYears.
A19: incomeReplace (blank = income) | C19: E · user / frontend override | D19: Blank → incomeMonthly for CI / TPD.
A20: N_SAV stored | B20: 0 | C20: E · user / frontend override | D20: If > 0, this is N_SAV amount; else 1× annual income.
A21: N_PRP stored | B21: 0 | C21: E · user / frontend override | D21: If > 0, this is N_PRP amount; else 5× annual income.
A22: tag N_RET | B22: 0 | C22: E · user / frontend override | D22: Investments tagged to retirement, then grown at realReturn.
A23: tag N_EDU | B23: 0 | C23: E · user / frontend override | D23: apply_investment_pot walk order: RET, EDU, SAV, PRP.
A24: tag N_SAV | B24: 0 | C24: E · user / frontend override | D24: Takes from remaining investments after RET and EDU.
A25: tag N_PRP | B25: 0 | C25: E · user / frontend override | D25: Last in the walk.
A27: D · ASSUMPTIONS / SHARED DATA — rates and need parameters
A28: inflationRate | B28: =inflationRate -> 0.023 | C28: D · assumption / shared | D28: Grows retirement spend to retAge; grows EDU cost.
A29: investmentReturn | B29: =investmentReturn -> 0.042 | C29: D · assumption / shared | D29: Used to form realReturn.
A30: realReturn | B30: =realReturn -> 0.018572825 | C30: D · assumption / shared | D30: max(0, (1+i)/(1+π) − 1). Discount rate.
A31: lifestyleFrugal | B31: =lifestyleFrugal -> 0.75 | C31: D · assumption / shared | D31: N_RET spend multiple when lifestyle=1.
A32: lifestyleStressFree | B32: =lifestyleStressFree -> 1 | C32: D · assumption / shared | D32: Default lifestyle=2.
A33: lifestyleOnlyTheBest | B33: =lifestyleOnlyTheBest -> 1.25 | C33: D · assumption / shared | D33: lifestyle=3.
A34: lifeSupportMin / Max / Pivot | B34: =lifeSupportMin -> 10 | C34: D · assumption / shared | D34: supportYears = min(max(10, 50 − age), 25).
A35: CI_YEARS / CI_COST | B35: =CI_YEARS -> 3 | C35: D · assumption / shared | D35: 3 years annuity-due + S$200,000.
A36: TPD_YEARS / TPD_COST | B36: =TPD_YEARS -> 5 | C36: D · assumption / shared | D36: 5 years annuity-due + S$200,000.
A37: HOSP_MONTHS | B37: =HOSP_MONTHS -> 6 | C37: D · assumption / shared | D37: N_HOS = income × 6.
A38: EDU_TOTAL_COST | B38: =EDU_TOTAL_COST -> 75000 | C38: D · assumption / shared | D38: 75,000 grown at inflation.
A39: savIncomeMultiple | B39: =savIncomeMultiple -> 1 | C39: D · assumption / shared | D39: 1 × annual income if stored is 0.
A40: prpIncomeMultiple | B40: =prpIncomeMultiple -> 5 | C40: D · assumption / shared | D40: 5 × annual income if stored is 0.
A41: currentYear / ageOfRetirement | B41: =currentYear -> 2026 | C41: D · assumption / shared | D41: 2026 / 65 in this workbook.
A43: C · DETERMINISTICALLY CALCULATED — horizons
A44: supportYears | B44: =MIN(MAX(lifeSupportMin,lifeSupportPivotAge-B5),lifeSupportMax) -> 23 | C44: C · calculated | D44: life_support_years(age).
A45: yearsToRet | B45: =MAX(0,B15-B5) -> 38 | C45: C · calculated | D45: years_to_retirement.
A46: yearsInRet | B46: =MAX(0,PLU_leUsed-B15) -> 16 | C46: C · calculated | D46: years_in_retirement(retAge, session LE).
A47: eduYears | B47: =MAX(0,B16-currentYear) -> 10 | C47: C · calculated | D47: max(0, targetYear − thisYear).
A49: C · RESULTS — amount / have / gap for every UNIFIED type (even when off)
A50: type | B50: needAmount | C50: have | D50: gap | E50: Enable? | F50: on (effective)
A51: N_INC | B51: =MAX(0,ROUND(B17+PLU_mortgage+IF(OR((IF(OR(B18="",B18<=0),B44,B18))<=0,(PLU_expenseMonthly*12)<=0),0,IF(ABS(realReturn)<0.000000000001,(PLU_expenseMonthly*12)*(IF(OR(B18="",B18<=0),B44,B18)),(PLU_expenseMonthly*12)*(1-(1+realReturn)^(-(IF(OR(B18="",B18<=0),B44,B18))))/(realReturn))),0)) -> 724812 | C51: =ROUND(PLU_lifeSum,0) -> 0 | D51: =MAX(0,B51-C51) -> 724812 | F51: =IF(E51="",NP_on_N_INC,E51) -> FALSE | G51: bequest + mortgage + PV of annual spend over dependYears.
A52: N_CRI | B52: =MAX(0,ROUND(IF(OR((CI_YEARS)<=0,((IF(B19="",PLU_incomeMonthly,B19))*12)<=0),0,IF(ABS(realReturn)<0.000000000001,((IF(B19="",PLU_incomeMonthly,B19))*12)*(CI_YEARS),((IF(B19="",PLU_incomeMonthly,B19))*12)*(1-(1/((1+realReturn)))^(CI_YEARS))/(1-(1/((1+realReturn))))))+CI_COST,0)) -> 412792 | C52: =0 -> 0 | D52: =MAX(0,B52-C52) -> 412792 | F52: =IF(E52="",NP_on_N_CRI,E52) -> TRUE | G52: Annuity-due of replacement income for CI_YEARS + CI_COST.
A53: N_TPD | B53: =MAX(0,ROUND(IF(OR((TPD_YEARS)<=0,((IF(B19="",PLU_incomeMonthly,B19))*12)<=0),0,IF(ABS(realReturn)<0.000000000001,((IF(B19="",PLU_incomeMonthly,B19))*12)*(TPD_YEARS),((IF(B19="",PLU_incomeMonthly,B19))*12)*(1-(1/((1+realReturn)))^(TPD_YEARS))/(1-(1/((1+realReturn))))))+TPD_COST,0)) -> 548266 | C53: =0 -> 0 | D53: =MAX(0,B53-C53) -> 548266 | F53: =IF(E53="",NP_on_N_TPD,E53) -> FALSE | G53: Annuity-due of replacement income for TPD_YEARS + TPD_COST.
A54: N_HOS | B54: =MAX(0,ROUND(PLU_incomeMonthly*HOSP_MONTHS,0)) -> 36120 | C54: =0 -> 0 | D54: =MAX(0,B54-C54) -> 36120 | F54: =IF(E54="",NP_on_N_HOS,E54) -> TRUE | G54: incomeMonthly × HOSP_MONTHS.
A55: N_RET | B55: =MAX(0,ROUND(IF(OR((B46)<=0,(IF((B45)<=0,MAX(0,PLU_expenseMonthly*12*(IF(B14=1,lifestyleFrugal,IF(B14=3,lifestyleOnlyTheBest,lifestyleStressFree)))),(PLU_expenseMonthly*12*(IF(B14=1,lifestyleFrugal,IF(B14=3,lifestyleOnlyTheBest,lifestyleStressFree))))*(1+inflationRate)^(B45)))<=0),0,IF(ABS(realReturn)<0.000000000001,(IF((B45)<=0,MAX(0,PLU_expenseMonthly*12*(IF(B14=1,lifestyleFrugal,IF(B14=3,lifestyleOnlyTheBest,lifestyleStressFree)))),(PLU_expenseMonthly*12*(IF(B14=1,lifestyleFrugal,IF(B14=3,lifestyleOnlyTheBest,lifestyleStressFree))))*(1+inflationRate)^(B45)))*(B46),(IF((B45)<=0,MAX(0,PLU_expenseMonthly*12*(IF(B14=1,lifestyleFrugal,IF(B14=3,lifestyleOnlyTheBest,lifestyleStressFree)))),(PLU_expenseMonthly*12*(IF(B14=1,lifestyleFrugal,IF(B14=3,lifestyleOnlyTheBest,lifestyleStressFree))))*(1+inflationRate)^(B45)))*(1-(1+realReturn)^(-(B46)))/(realReturn))),0)) -> 1271143 | C55: =ROUND(IF((B45)<=0,MAX(0,MIN(MAX(0,B22),MAX(0,PLU_investments))),(MIN(MAX(0,B22),MAX(0,PLU_investments)))*(1+realReturn)^(B45)),0) -> 0 | D55: =MAX(0,B55-C55) -> 1271143 | F55: =IF(E55="",NP_on_N_RET,E55) -> TRUE | G55: PV of inflated lifestyle spend over yearsInRet.
A56: N_EDU | B56: =MAX(0,ROUND(EDU_TOTAL_COST*(1+inflationRate)^B47,0)) -> 94149 | C56: =ROUND(IF((B47)<=0,MAX(0,MIN(MAX(0,B23),MAX(0,PLU_investments-MIN(MAX(0,B22),MAX(0,PLU_investments))))),(MIN(MAX(0,B23),MAX(0,PLU_investments-MIN(MAX(0,B22),MAX(0,PLU_investments)))))*(1+realReturn)^(B47)),0) -> 0 | D56: =MAX(0,B56-C56) -> 94149 | F56: =IF(E56="",NP_on_N_EDU,E56) -> FALSE | G56: 75,000 × (1+inflation)^eduYears.
A57: N_SAV | B57: =IF(B20>0,ROUND(B20,0),ROUND(PLU_incomeMonthly*12*savIncomeMultiple,0)) -> 72240 | C57: =ROUND(IF((B47)<=0,MAX(0,MIN(MAX(0,B24),MAX(0,MAX(0,PLU_investments-MIN(MAX(0,B22),MAX(0,PLU_investments)))-MIN(MAX(0,B23),MAX(0,PLU_investments-MIN(MAX(0,B22),MAX(0,PLU_investments))))))),(MIN(MAX(0,B24),MAX(0,MAX(0,PLU_investments-MIN(MAX(0,B22),MAX(0,PLU_investments)))-MIN(MAX(0,B23),MAX(0,PLU_investments-MIN(MAX(0,B22),MAX(0,PLU_investments)))))))*(1+realReturn)^(B47)),0) -> 0 | D57: =MAX(0,B57-C57) -> 72240 | F57: =IF(E57="",NP_on_N_SAV,E57) -> TRUE | G57: Stored or 1× annual income.
A58: N_PRP | B58: =IF(B21>0,ROUND(B21,0),ROUND(PLU_incomeMonthly*12*prpIncomeMultiple,0)) -> 361200 | C58: =ROUND(IF((B47)<=0,MAX(0,MIN(MAX(0,B25),MAX(0,MAX(0,MAX(0,PLU_investments-MIN(MAX(0,B22),MAX(0,PLU_investments)))-MIN(MAX(0,B23),MAX(0,PLU_investments-MIN(MAX(0,B22),MAX(0,PLU_investments)))))-MIN(MAX(0,B24),MAX(0,MAX(0,PLU_investments-MIN(MAX(0,B22),MAX(0,PLU_investments)))-MIN(MAX(0,B23),MAX(0,PLU_investments-MIN(MAX(0,B22),MAX(0,PLU_investments))))))))),(MIN(MAX(0,B25),MAX(0,MAX(0,MAX(0,PLU_investments-MIN(MAX(0,B22),MAX(0,PLU_investments)))-MIN(MAX(0,B23),MAX(0,PLU_investments-MIN(MAX(0,B22),MAX(0,PLU_investments)))))-MIN(MAX(0,B24),MAX(0,MAX(0,PLU_investments-MIN(MAX(0,B22),MAX(0,PLU_investments)))-MIN(MAX(0,B23),MAX(0,PLU_investments-MIN(MAX(0,B22),MAX(0,PLU_investments)))))))))*(1+realReturn)^(B47)),0) -> 0 | D58: =MAX(0,B58-C58) -> 361200 | F58: =IF(E58="",NP_on_N_PRP,E58) -> FALSE | G58: Stored or 5× annual income.

Sheet Plan Calculator
A1: Plan Calculator — selected persona. seedProducts / planProducts.ts. Suggested = enabled AND gap > 0.
A2: Selected persona | B2: =SelectedPersona -> P02 | C2: =IFERROR(INDEX(Personas!B$3:B$52,MATCH($B$2,Personas!$A$3:$A$52,0)),"") -> Wei Ling Tan | D2: Follows the dropdown on the Selected persona tab. | F2: A · INPUT DATA
A3: Attribute | B3: Value | C3: Kind | D3: Source / formula | F3: B · LLM PREDICTED DATA
A4: A · INPUT DATA — from People Like You and Need Calculator | F4: C · DETERMINISTICALLY CALCULATED
A5: take-home (from PLU) | B5: =PLU_takeHome -> 4816 | C5: A · input | D5: Surplus uses take-home, not gross income. | F5: D · ASSUMPTIONS / SHARED DATA
A6: expenseMonthly (from PLU) | B6: =PLU_expenseMonthly -> 3250.8 | C6: A · input | D6: types.ts availableBudget. | F6: E · USER / FRONTEND OVERRIDE
A7: N_INC on (from Need Calculator) | B7: =NC_on_N_INC -> FALSE | C7: A · input | D7: Effective enable after Need Calculator override.
A8: N_INC gap (from Need Calculator) | B8: =NC_gap_N_INC -> 724812 | C8: A · input | D8: remaining_gap.
A9: N_CRI on (from Need Calculator) | B9: =NC_on_N_CRI -> TRUE | C9: A · input | D9: Effective enable after Need Calculator override.
A10: N_CRI gap (from Need Calculator) | B10: =NC_gap_N_CRI -> 412792 | C10: A · input | D10: remaining_gap.
A11: N_TPD on (from Need Calculator) | B11: =NC_on_N_TPD -> FALSE | C11: A · input | D11: Effective enable after Need Calculator override.
A12: N_TPD gap (from Need Calculator) | B12: =NC_gap_N_TPD -> 548266 | C12: A · input | D12: remaining_gap.
A13: N_HOS on (from Need Calculator) | B13: =NC_on_N_HOS -> TRUE | C13: A · input | D13: Effective enable after Need Calculator override.
A14: N_HOS gap (from Need Calculator) | B14: =NC_gap_N_HOS -> 36120 | C14: A · input | D14: remaining_gap.
A15: N_RET on (from Need Calculator) | B15: =NC_on_N_RET -> TRUE | C15: A · input | D15: Effective enable after Need Calculator override.
A16: N_RET gap (from Need Calculator) | B16: =NC_gap_N_RET -> 1271143 | C16: A · input | D16: remaining_gap.
A17: N_EDU on (from Need Calculator) | B17: =NC_on_N_EDU -> FALSE | C17: A · input | D17: Effective enable after Need Calculator override.
A18: N_EDU gap (from Need Calculator) | B18: =NC_gap_N_EDU -> 94149 | C18: A · input | D18: remaining_gap.
A19: N_SAV on (from Need Calculator) | B19: =NC_on_N_SAV -> TRUE | C19: A · input | D19: Effective enable after Need Calculator override.
A20: N_SAV gap (from Need Calculator) | B20: =NC_gap_N_SAV -> 72240 | C20: A · input | D20: remaining_gap.
A21: N_PRP on (from Need Calculator) | B21: =NC_on_N_PRP -> FALSE | C21: A · input | D21: Effective enable after Need Calculator override.
A22: N_PRP gap (from Need Calculator) | B22: =NC_gap_N_PRP -> 361200 | C22: A · input | D22: remaining_gap.
A23: yearsToRet (from Need Calculator) | B23: =NC_yearsToRet -> 38 | C23: A · input | D23: Retirement contribution horizon.
A24: eduYears (from Need Calculator) | B24: =NC_eduYears -> 10 | C24: A · input | D24: EDU / SAV / PRP contribution horizon.
A26: D · ASSUMPTIONS / SHARED DATA
A27: protectionPremiumRate | B27: =protectionPremiumRate -> 0.00078 | C27: D · assumption / shared | D27: Indicative premium = sum × this rate, rounded.
A28: FREE_BUDGET_SHARE | B28: =FREE_BUDGET_SHARE -> 0.5 | C28: D · assumption / shared | D28: Half of leftover surplus split across wealth needs.
A29: monthlyRoundStep | B29: =monthlyRoundStep -> 50 | C29: D · assumption / shared | D29: Contributions rounded to S$50.
A30: coverPremRoundStep | B30: =coverPremRoundStep -> 10 | C30: D · assumption / shared | D30: Premium rounded to nearest step.
A31: realReturn | B31: =realReturn -> 0.018572825 | C31: D · assumption / shared | D31: annualPmtToHitFv for the wealth cap.
A33: C · DETERMINISTICALLY CALCULATED — suggested flags and protection sizing
A34: sug N_INC | B34: =AND(NC_on_N_INC,NC_gap_N_INC>0) -> FALSE | C34: C · calculated | D34: enabled AND gap > 0.
A35: sug N_CRI | B35: =AND(NC_on_N_CRI,NC_gap_N_CRI>0) -> TRUE | C35: C · calculated | D35: enabled AND gap > 0.
A36: sug N_TPD | B36: =AND(NC_on_N_TPD,NC_gap_N_TPD>0) -> FALSE | C36: C · calculated | D36: enabled AND gap > 0.
A37: sug N_HOS | B37: =AND(NC_on_N_HOS,NC_gap_N_HOS>0) -> TRUE | C37: C · calculated | D37: enabled AND gap > 0.
A38: sug N_RET | B38: =AND(NC_on_N_RET,NC_gap_N_RET>0) -> TRUE | C38: C · calculated | D38: enabled AND gap > 0.
A39: sug N_EDU | B39: =AND(NC_on_N_EDU,NC_gap_N_EDU>0) -> FALSE | C39: C · calculated | D39: enabled AND gap > 0.
A40: sug N_SAV | B40: =AND(NC_on_N_SAV,NC_gap_N_SAV>0) -> TRUE | C40: C · calculated | D40: enabled AND gap > 0.
A41: sug N_PRP | B41: =AND(NC_on_N_PRP,NC_gap_N_PRP>0) -> FALSE | C41: C · calculated | D41: enabled AND gap > 0.
A42: n wealth suggested | B42: =(B38*1)+(B39*1)+(B40*1)+(B41*1) -> 2 | C42: C · calculated | D42: Count of suggested wealth needs.
A43: planSum N_INC | B43: =IF(B34,MAX(0,ROUND(NC_gap_N_INC,0)),0) -> 0 | C43: C · calculated | D43: Suggested protection sum = gap.
A44: planPrem N_INC | B44: =IF(B43<=0,0,MAX(0,ROUND((B43*protectionPremiumRate)/coverPremRoundStep,0)*coverPremRoundStep)) -> 0 | C44: C · calculated | D44: coverPremiumFor(sum). Indicative, not half of slider max.
A45: planSum N_CRI | B45: =IF(B35,MAX(0,ROUND(NC_gap_N_CRI,0)),0) -> 412792 | C45: C · calculated | D45: Suggested protection sum = gap.
A46: planPrem N_CRI | B46: =IF(B45<=0,0,MAX(0,ROUND((B45*protectionPremiumRate)/coverPremRoundStep,0)*coverPremRoundStep)) -> 320 | C46: C · calculated | D46: coverPremiumFor(sum). Indicative, not half of slider max.
A47: planSum N_TPD | B47: =IF(B36,MAX(0,ROUND(NC_gap_N_TPD,0)),0) -> 0 | C47: C · calculated | D47: Suggested protection sum = gap.
A48: planPrem N_TPD | B48: =IF(B47<=0,0,MAX(0,ROUND((B47*protectionPremiumRate)/coverPremRoundStep,0)*coverPremRoundStep)) -> 0 | C48: C · calculated | D48: coverPremiumFor(sum). Indicative, not half of slider max.
A49: planSum N_HOS | B49: =IF(B37,MAX(0,ROUND(NC_gap_N_HOS,0)),0) -> 36120 | C49: C · calculated | D49: Suggested protection sum = gap.
A50: planPrem N_HOS | B50: =IF(B49<=0,0,MAX(0,ROUND((B49*protectionPremiumRate)/coverPremRoundStep,0)*coverPremRoundStep)) -> 30 | C50: C · calculated | D50: coverPremiumFor(sum). Indicative, not half of slider max.
A51: prot prem / yr | B51: =B44+B46+B48+B50 -> 350 | C51: C · calculated | D51: Sum of suggested protection premiums (before Include?).
A52: default wealth mth share | B52: =IF(B42=0,0,MAX(0,ROUND((MAX(0,(PLU_takeHome-PLU_expenseMonthly)*12-B51)*FREE_BUDGET_SHARE)/12/B42/monthlyRoundStep,0)*monthlyRoundStep)) -> 400 | C52: C · calculated | D52: Leftover surplus × 50% / 12 / n wealth, rounded to S$50.
A53: cap mth N_RET | B53: =IF((IF(OR((NC_gap_N_RET)<=0,(NC_yearsToRet)<=0),0,IF(ABS(realReturn)<0.000000000001,(NC_gap_N_RET)/(NC_yearsToRet),(NC_gap_N_RET)*realReturn/((1+realReturn)^(NC_yearsToRet)-1))))<=0,0,ROUNDUP((IF(OR((NC_gap_N_RET)<=0,(NC_yearsToRet)<=0),0,IF(ABS(realReturn)<0.000000000001,(NC_gap_N_RET)/(NC_yearsToRet),(NC_gap_N_RET)*realReturn/((1+realReturn)^(NC_yearsToRet)-1))))/12/monthlyRoundStep,0)*monthlyRoundStep) -> 1950 | C53: C · calculated | D53: annualPmtToHitFv / 12, rounded up to S$50.
A54: planMth N_RET | B54: =IF(B38,MIN(B52,B53),0) -> 400 | C54: C · calculated | D54: min(default share, cap).
A55: planLump N_RET | B55: 0 | C55: C · calculated | D55: Default lump is 0.
A56: cap mth N_EDU | B56: =IF((IF(OR((NC_gap_N_EDU)<=0,(NC_eduYears)<=0),0,IF(ABS(realReturn)<0.000000000001,(NC_gap_N_EDU)/(NC_eduYears),(NC_gap_N_EDU)*realReturn/((1+realReturn)^(NC_eduYears)-1))))<=0,0,ROUNDUP((IF(OR((NC_gap_N_EDU)<=0,(NC_eduYears)<=0),0,IF(ABS(realReturn)<0.000000000001,(NC_gap_N_EDU)/(NC_eduYears),(NC_gap_N_EDU)*realReturn/((1+realReturn)^(NC_eduYears)-1))))/12/monthlyRoundStep,0)*monthlyRoundStep) -> 750 | C56: C · calculated | D56: annualPmtToHitFv / 12, rounded up to S$50.
A57: planMth N_EDU | B57: =IF(B39,MIN(B52,B56),0) -> 0 | C57: C · calculated | D57: min(default share, cap).
A58: planLump N_EDU | B58: 0 | C58: C · calculated | D58: Default lump is 0.
A59: cap mth N_SAV | B59: =IF((IF(OR((NC_gap_N_SAV)<=0,(NC_eduYears)<=0),0,IF(ABS(realReturn)<0.000000000001,(NC_gap_N_SAV)/(NC_eduYears),(NC_gap_N_SAV)*realReturn/((1+realReturn)^(NC_eduYears)-1))))<=0,0,ROUNDUP((IF(OR((NC_gap_N_SAV)<=0,(NC_eduYears)<=0),0,IF(ABS(realReturn)<0.000000000001,(NC_gap_N_SAV)/(NC_eduYears),(NC_gap_N_SAV)*realReturn/((1+realReturn)^(NC_eduYears)-1))))/12/monthlyRoundStep,0)*monthlyRoundStep) -> 600 | C59: C · calculated | D59: annualPmtToHitFv / 12, rounded up to S$50.
A60: planMth N_SAV | B60: =IF(B40,MIN(B52,B59),0) -> 400 | C60: C · calculated | D60: min(default share, cap).
A61: planLump N_SAV | B61: 0 | C61: C · calculated | D61: Default lump is 0.
A62: cap mth N_PRP | B62: =IF((IF(OR((NC_gap_N_PRP)<=0,(NC_eduYears)<=0),0,IF(ABS(realReturn)<0.000000000001,(NC_gap_N_PRP)/(NC_eduYears),(NC_gap_N_PRP)*realReturn/((1+realReturn)^(NC_eduYears)-1))))<=0,0,ROUNDUP((IF(OR((NC_gap_N_PRP)<=0,(NC_eduYears)<=0),0,IF(ABS(realReturn)<0.000000000001,(NC_gap_N_PRP)/(NC_eduYears),(NC_gap_N_PRP)*realReturn/((1+realReturn)^(NC_eduYears)-1))))/12/monthlyRoundStep,0)*monthlyRoundStep) -> 2800 | C62: C · calculated | D62: annualPmtToHitFv / 12, rounded up to S$50.
A63: planMth N_PRP | B63: =IF(B41,MIN(B52,B62),0) -> 0 | C63: C · calculated | D63: min(default share, cap).
A64: planLump N_PRP | B64: 0 | C64: C · calculated | D64: Default lump is 0.
A66: C · RESULTS — Include? blank keeps the suggested product
A67: type | B67: suggested | C67: Include? | D67: included
A68: N_INC | B68: =B34 -> FALSE | D68: =AND(B68,IF(C68="",TRUE,C68)) -> FALSE
A69: N_CRI | B69: =B35 -> TRUE | D69: =AND(B69,IF(C69="",TRUE,C69)) -> TRUE
A70: N_TPD | B70: =B36 -> FALSE | D70: =AND(B70,IF(C70="",TRUE,C70)) -> FALSE
A71: N_HOS | B71: =B37 -> TRUE | D71: =AND(B71,IF(C71="",TRUE,C71)) -> TRUE
A72: N_RET | B72: =B38 -> TRUE | D72: =AND(B72,IF(C72="",TRUE,C72)) -> TRUE
A73: N_EDU | B73: =B39 -> FALSE | D73: =AND(B73,IF(C73="",TRUE,C73)) -> FALSE
A74: N_SAV | B74: =B40 -> TRUE | D74: =AND(B74,IF(C74="",TRUE,C74)) -> TRUE
A75: N_PRP | B75: =B41 -> FALSE | D75: =AND(B75,IF(C75="",TRUE,C75)) -> FALSE
A77: investMth | B77: =(D72*B54)+(D73*B57)+(D74*B60)+(D75*B63) -> 800 | C77: C · calculated | D77: Sum of included wealth monthly contributions.
A78: investLump | B78: =(D72*B55)+(D73*B58)+(D74*B61)+(D75*B64) -> 0 | C78: C · calculated | D78: Sum of included wealth lumps (default 0).

Sheet Budget Calculator
A1: Budget Calculator — selected persona. planAfford. Surplus is take-home minus expense.
A2: Selected persona | B2: =SelectedPersona -> P02 | C2: =IFERROR(INDEX(Personas!B$3:B$52,MATCH($B$2,Personas!$A$3:$A$52,0)),"") -> Wei Ling Tan | D2: Follows the dropdown on the Selected persona tab. | F2: A · INPUT DATA
A3: Attribute | B3: Value | C3: Kind | D3: Source / formula | F3: B · LLM PREDICTED DATA
A4: A · INPUT DATA — from People Like You and Plan Calculator | F4: C · DETERMINISTICALLY CALCULATED
A5: take-home (from PLU) | B5: =PLU_takeHome -> 4816 | C5: A · input | D5: types.ts availableBudget uses take-home. | F5: D · ASSUMPTIONS / SHARED DATA
A6: expenseMonthly (from PLU) | B6: =PLU_expenseMonthly -> 3250.8 | C6: A · input | D6: Not gross income. | F6: E · USER / FRONTEND OVERRIDE
A7: investments (from PLU) | B7: =PLU_investments -> 47895 | C7: A · input | D7: Cap for lumps.
A8: included N_INC premium | B8: =IF(PLAN_included_N_INC,PLAN_prem_N_INC,0) -> 0 | C8: A · input | D8: Only included protection.
A9: included N_CRI premium | B9: =IF(PLAN_included_N_CRI,PLAN_prem_N_CRI,0) -> 320 | C9: A · input
A10: included N_TPD premium | B10: =IF(PLAN_included_N_TPD,PLAN_prem_N_TPD,0) -> 0 | C10: A · input
A11: included N_HOS premium | B11: =IF(PLAN_included_N_HOS,PLAN_prem_N_HOS,0) -> 30 | C11: A · input
A12: investMth (from Plan) | B12: =PLAN_investMth -> 800 | C12: A · input | D12: Included wealth contributions.
A13: investLump (from Plan) | B13: =PLAN_investLump -> 0 | C13: A · input | D13: Included wealth lumps.
A15: D · ASSUMPTIONS / SHARED DATA
A16: FREE_BUDGET_SHARE | B16: =FREE_BUDGET_SHARE -> 0.5 | C16: D · assumption / shared | D16: Half of monthly surplus is the free budget.
A18: C · DETERMINISTICALLY CALCULATED — planAfford
A19: available | B19: =MAX(0,PLU_takeHome-PLU_expenseMonthly) -> 1565.2 | C19: C · calculated | D19: max(0, take-home − expense).
A20: free (50%) | B20: =ROUND(B19*FREE_BUDGET_SHARE,0) -> 783 | C20: C · calculated | D20: available × 50%, rounded.
A21: included prot prem / yr | B21: =IF(PLAN_included_N_INC,PLAN_prem_N_INC,0)+IF(PLAN_included_N_CRI,PLAN_prem_N_CRI,0)+IF(PLAN_included_N_TPD,PLAN_prem_N_TPD,0)+IF(PLAN_included_N_HOS,PLAN_prem_N_HOS,0) -> 350 | C21: C · calculated | D21: Sum of included protection premiums.
A22: premMth (display) | B22: =ROUND(B21/12,0) -> 29 | C22: C · calculated | D22: Annual premiums / 12.
A23: contribMth | B23: =PLAN_investMth -> 800 | C23: C · calculated | D23: Same as investMth.
A24: monthly | B24: =ROUND(PLAN_investMth+B21/12,0) -> 829 | C24: C · calculated | D24: contrib + prem/12.
A25: monthlyOver | B25: =B24-B20 -> 46 | C25: C · calculated | D25: > 0 means the plan exceeds the free budget.
A26: lumps | B26: =PLAN_investLump -> 0 | C26: C · calculated | D26: Included lumps.
A27: lumpOver | B27: =B26-PLU_investments -> -47895 | C27: C · calculated | D27: > 0 means lumps exceed current investments.

Sheet FX
A1: FX — selected persona. Convert local currency to USD. Validation reads these amounts.
A2: Selected persona | B2: =SelectedPersona -> P02 | C2: =IFERROR(INDEX(Personas!B$3:B$52,MATCH($B$2,Personas!$A$3:$A$52,0)),"") -> Wei Ling Tan | D2: Follows the dropdown on the Selected persona tab. | F2: A · INPUT DATA
A3: Attribute | B3: Value | C3: Kind | D3: Source / formula | F3: B · LLM PREDICTED DATA
A4: A · INPUT DATA — currency and effective session (local) | F4: C · DETERMINISTICALLY CALCULATED | I4: D · RATE TABLE — USD per 1 local unit (edit)
A5: currency | B5: =PLU_currency -> SGD | C5: A · input | D5: Personas K via People Like You. Lookup key for the rate table. | F5: D · ASSUMPTIONS / SHARED DATA | I5: currency | J5: USD per 1 unit | K5: note
A6: incomeMonthly (local) | B6: =PLU_incomeMonthly -> 6020 | C6: A · input | D6: Effective session. | F6: E · USER / FRONTEND OVERRIDE | I6: USD | J6: 1 | K6: Identity. 5,000 USD = 5,000 USD.
A7: expenseMonthly (local) | B7: =PLU_expenseMonthly -> 3250.8 | C7: A · input | I7: SGD | J7: 0.74 | K7: 5,000 SGD × 0.74 = 3,700 USD.
A8: cash (local) | B8: =PLU_cash -> 8452 | C8: A · input | I8: VND | J8: 3.8e-05 | K8: 5,000 VND × 0.000038 = 0.19 USD.
A9: investments (local) | B9: =PLU_investments -> 47895 | C9: A · input | I9: MYR | J9: 0.225
A10: property (local) | B10: =PLU_property -> 0 | C10: A · input | I10: THB | J10: 0.029
A11: mortgage (local) | B11: =PLU_mortgage -> 0 | C11: A · input | I11: PHP | J11: 0.0175
A12: PLU liabilities (local) | B12: =PLU_liabilities -> 39443.04 | C12: A · input | I12: AUD | J12: 0.66
A13: life sum assured (local) | B13: =PLU_lifeSum -> 0 | C13: A · input | I13: EUR | J13: 1.09
I14: HKD | J14: 0.128
A15: D · ASSUMPTIONS — rate from the table on the right
A16: USD per 1 local | B16: =IFERROR(VLOOKUP(PLU_currency,FxTable,2,FALSE),"") -> 0.74 | C16: D · assumption / shared | D16: Blank if Personas currency is not a row in the rate table.
A18: C · DETERMINISTICALLY CALCULATED — local × USD per 1
A19: incomeMonthly USD | B19: =IF($B$16="","",B6*$B$16) -> 4454.8 | C19: C · calculated | D19: 5,000 SGD → 3,700. 5,000 VND → 0.19.
A20: expenseMonthly USD | B20: =IF($B$16="","",B7*$B$16) -> 2405.592 | C20: C · calculated
A21: cash USD | B21: =IF($B$16="","",B8*$B$16) -> 6254.48 | C21: C · calculated
A22: investments USD | B22: =IF($B$16="","",B9*$B$16) -> 35442.3 | C22: C · calculated
A23: property USD | B23: =IF($B$16="","",B10*$B$16) -> 0 | C23: C · calculated
A24: mortgage USD | B24: =IF($B$16="","",B11*$B$16) -> 0 | C24: C · calculated
A25: PLU liabilities USD | B25: =IF($B$16="","",B12*$B$16) -> 29187.85 | C25: C · calculated
A26: life sum assured USD | B26: =IF($B$16="","",B13*$B$16) -> 0 | C26: C · calculated

Sheet Validation
A1: Validation — USD-only min / max on the selected persona. Conversion lives on the FX tab. People Like You still stores local currency.
A2: Example: 5,000 SGD → FX 3,700 USD (pass). 5,000 VND → FX 0.19 USD (fail min income). Change Personas currency to VND and keep income 5,000 to see the fail. Yellow cells are editable.
A4: USD validation rules (edit these)
A5: field | B5: min USD | C5: max USD | D5: source / why | E5: fail if
A6: incomeMonthly | B6: 200 | C6: 100000 | D6: InsApi rejects below ~USD 1,000. Workbook floor 200 so a junior US wage still passes; 5,000 VND does not. | E6: USD < min or > max
A7: expenseMonthly | B7: 80 | C7: 80000 | D7: Frontend MIN_EXPENSE_MONTHLY = 100 SGD ≈ 74 USD. Floor 80 USD. | E7: USD < min or > max
A8: cash | B8: 0 | C8: 20000000 | D8: Cash & Savings stock, not a monthly flow. | E8: USD < 0 or > max
A9: investments | B9: 0 | C9: 20000000 | D9: Investment stock. | E9: USD < 0 or > max
A10: property | B10: 0 | C10: 50000000 | D10: Home value. 0 is valid (renter). | E10: USD < 0 or > max
A11: mortgage | B11: 0 | C11: 50000000 | D11: Loans. Also fail if USD mortgage > USD property when property > 0. | E11: USD < 0, > max, or > property
A12: PLU liabilities | B12: 0 | C12: 20000000 | D12: Profiler TotalLiabilities (liquid × 0.7 unless overridden). | E12: USD < 0 or > max
A13: life sum assured | B13: 0 | C13: 20000000 | D13: Existing life cover. 0 is valid. | E13: USD < 0 or > max
A15: Selected persona — pass / fail against USD rules
A16: Selected persona | B16: =SelectedPersona -> P02 | C16: =IFERROR(INDEX(Personas!B$3:B$52,MATCH($B$16,Personas!$A$3:$A$52,0)),"") -> Wei Ling Tan | D16: =IFERROR(INDEX(Personas!F$3:F$52,MATCH($B$16,Personas!$A$3:$A$52,0)),"")&" / "&PLU_currency -> Singapore / SGD | E16: Follows the Selected persona tab. Change the id there.
A17: USD per 1 local | B17: =FX_usdPerLocal -> 0.74 | C17: Pointer to the FX tab. Edit rates there, not here.
A19: field | B19: local (effective) | C19: USD (from FX) | D19: min USD | E19: max USD | F19: status | G19: detail
A20: incomeMonthly | B20: =PLU_incomeMonthly -> 6020 | C20: =FX_incomeMonthly -> 4454.8 | D20: =B6 -> 200 | E20: =C6 -> 100000 | F20: =IF(FX_usdPerLocal="","no FX",IF(OR(C20<D20,C20>E20),"FAIL","OK")) -> OK | G20: =IF(FX_usdPerLocal="","Set Personas currency to a row on the FX tab.",IF(C20<D20,"below min USD",IF(C20>E20,"above max USD","inside USD band"))) -> inside USD band
A21: expenseMonthly | B21: =PLU_expenseMonthly -> 3250.8 | C21: =FX_expenseMonthly -> 2405.592 | D21: =B7 -> 80 | E21: =C7 -> 80000 | F21: =IF(FX_usdPerLocal="","no FX",IF(OR(C21<D21,C21>E21),"FAIL","OK")) -> OK | G21: =IF(FX_usdPerLocal="","Set Personas currency to a row on the FX tab.",IF(C21<D21,"below min USD",IF(C21>E21,"above max USD","inside USD band"))) -> inside USD band
A22: cash | B22: =PLU_cash -> 8452 | C22: =FX_cash -> 6254.48 | D22: =B8 -> 0 | E22: =C8 -> 20000000 | F22: =IF(FX_usdPerLocal="","no FX",IF(OR(C22<D22,C22>E22),"FAIL","OK")) -> OK | G22: =IF(FX_usdPerLocal="","Set Personas currency to a row on the FX tab.",IF(C22<D22,"below min USD",IF(C22>E22,"above max USD","inside USD band"))) -> inside USD band
A23: investments | B23: =PLU_investments -> 47895 | C23: =FX_investments -> 35442.3 | D23: =B9 -> 0 | E23: =C9 -> 20000000 | F23: =IF(FX_usdPerLocal="","no FX",IF(OR(C23<D23,C23>E23),"FAIL","OK")) -> OK | G23: =IF(FX_usdPerLocal="","Set Personas currency to a row on the FX tab.",IF(C23<D23,"below min USD",IF(C23>E23,"above max USD","inside USD band"))) -> inside USD band
A24: property | B24: =PLU_property -> 0 | C24: =FX_property -> 0 | D24: =B10 -> 0 | E24: =C10 -> 50000000 | F24: =IF(FX_usdPerLocal="","no FX",IF(OR(C24<D24,C24>E24),"FAIL","OK")) -> OK | G24: =IF(FX_usdPerLocal="","Set Personas currency to a row on the FX tab.",IF(C24<D24,"below min USD",IF(C24>E24,"above max USD","inside USD band"))) -> inside USD band
A25: mortgage | B25: =PLU_mortgage -> 0 | C25: =FX_mortgage -> 0 | D25: =B11 -> 0 | E25: =C11 -> 50000000 | F25: =IF(FX_usdPerLocal="","no FX",IF(OR(C25<D25,C25>E25,AND(C25>C24,C24>0)),"FAIL","OK")) -> OK | G25: =IF(FX_usdPerLocal="","Set Personas currency to a row on the FX tab.",IF(AND(C25>C24,C24>0),"mortgage USD > property USD",IF(C25<D25,"below min USD",IF(C25>E25,"above max USD","inside USD band")))) -> inside USD band
A26: PLU liabilities | B26: =PLU_liabilities -> 39443.04 | C26: =FX_liabilities -> 29187.85 | D26: =B12 -> 0 | E26: =C12 -> 20000000 | F26: =IF(FX_usdPerLocal="","no FX",IF(OR(C26<D26,C26>E26),"FAIL","OK")) -> OK | G26: =IF(FX_usdPerLocal="","Set Personas currency to a row on the FX tab.",IF(C26<D26,"below min USD",IF(C26>E26,"above max USD","inside USD band"))) -> inside USD band
A27: life sum assured | B27: =PLU_lifeSum -> 0 | C27: =FX_lifeSum -> 0 | D27: =B13 -> 0 | E27: =C13 -> 20000000 | F27: =IF(FX_usdPerLocal="","no FX",IF(OR(C27<D27,C27>E27),"FAIL","OK")) -> OK | G27: =IF(FX_usdPerLocal="","Set Personas currency to a row on the FX tab.",IF(C27<D27,"below min USD",IF(C27>E27,"above max USD","inside USD band"))) -> inside USD band
A29: Overall | B29: =IF(COUNTIF(F20:F27,"FAIL")>0,"FAIL",IF(COUNTIF(F20:F27,"no FX")>0,"no FX","OK")) -> OK

Sheet Assumptions
A1: Assumptions and shared data — values the live code actually reads
A2: Yellow cells are editable. Every other tab reads these named cells. HappiU and Scenario Visualizer still run in HU / SV; this sheet only stores what GP sends them.
A4: Economic rates (src/session_rates.py DEFAULTS / ASSUME_DEFAULTS) | E4: Singapore occupation income bands (income_anchors.json) | I4: Docs that disagree with these cells are listed on the Discrepancies tab. Code wins. Cash/investments is 15%/85% (predict.py), not 45%/55%.
A5: inflationRate | B5: 0.023 | E5: occupation | F5: min | G5: max
A6: interestRate | B6: 0.012 | E6: Teacher | F6: 5600 | G6: 9800 | H6: Teacher / educator
A7: loanRate | B7: 0.035 | E7: Software Engineer | F7: 7500 | G7: 18000 | H7: Software engineer
A8: incomeGrowthRate | B8: 0.028 | E8: Investment Banker | F8: 11200 | G8: 28000 | H8: Investment banker / finance director
A9: investmentReturn | B9: 0.042 | E9: Marketing Manager | F9: 7000 | G9: 14000 | H9: Marketing manager
A10: assetReturn | B10: 0.03 | E10: Doctor | F10: 10400 | G10: 26000 | H10: Doctor / physician
A11: realReturn (derived) | B11: =MAX(0,(1+investmentReturn)/(1+inflationRate)-1) -> 0.018572825 | C11: Need Calculator and Plan Calculator discount at this rate | E11: Nurse | F11: 4200 | G11: 8400 | H11: Nurse
E12: Accountant | F12: 5600 | G12: 11200 | H12: Accountant
A13: Life-cycle | E13: CEO | F13: 16800 | G13: 42000 | H13: CEO / managing director of a typical firm
A14: ageOfRetirement | B14: 65
A15: lifeExpectancyDefault | B15: 85
A16: currentYear | B16: 2026
A17: endAge (chart horizon) | B17: 85
A19: CPF rates and formulas live on the CPF tab (country on / off)
E20: Stress events (frontend/src/lib/stressEvents.ts) — Scenario Visualizer only
E21: id | F21: label | G21: default size | H21: default year | I21: what SV applies
E22: crash | F22: Market crash | G22: 35% | H22: year 8 | I22: Haircut on invested assets
E23: ccy | F23: Currency shock | G23: 14% | H23: year 6 | I23: Haircut on liquid assets at 2/3 of slider
E24: infl | F24: Inflation shock | G24: +3 pp | H24: years 4–9 | I24: Session inflationRate plus extra
E25: inc | F25: Impact on income | G25: −20% | H25: years 5–10 | I25: Salary reduced for that span
E26: death | F26: Death | G26: S$20,000 | H26: year 17 | I26: One-time cost; salary → 0
A27: Need parameters (src/pipeline/goal_math.py) | E27: ci | F27: Critical illness | G27: S$150,000 | H27: year 12 | I27: One-time medical cost
A28: lifestyleFrugal | B28: 0.75 | E28: tpd | F28: Total & permanent disability | G28: S$200,000 | H28: year 15 | I28: One-time medical cost
A29: lifestyleStressFree | B29: 1 | E29: pa | F29: Personal accident | G29: S$80,000 | H29: year 10 | I29: One-time medical cost
A30: lifestyleOnlyTheBest | B30: 1.25 | E30: hosp | F30: Hospitalisation | G30: S$120,000 | H30: year 9 | I30: One-time hospital bill
A31: lifeSupportMin | B31: 10 | E31: care | F31: Long-term care years | G31: S$90,000 / yr | H31: years 30–35 | I31: Extra annual spend
A32: lifeSupportMax | B32: 25 | E32: wed | F32: Wedding / marriage | G32: S$60,000 | H32: year 5 | I32: One-time cost
A33: lifeSupportPivotAge | B33: 50 | E33: baby | F33: Newborn | G33: S$35,000 | H33: year 3 | I33: One-time cost
A34: CI_YEARS | B34: 3 | E34: exp | F34: Impact on expenses | G34: +15% | H34: years 6–12 | I34: Living spend raised
A35: CI_COST | B35: 200000
A36: TPD_YEARS | B36: 5
A37: TPD_COST | B37: 200000
A38: HOSP_MONTHS | B38: 6
A39: EDU_TOTAL_COST | B39: 75000
A40: eduYearsDefault | B40: 10
A41: savIncomeMultiple | B41: 1
A42: prpIncomeMultiple | B42: 5
A44: Household seeding (src/predict.py spend / assets; CPF is on the CPF tab)
A45: spendShareBase | B45: 0.675
A46: spendSharePerDependant | B46: 0.05
A47: spendShareCap | B47: 0.9
A48: assetsSaveShare | B48: 0.5
A49: workStartAge | B49: 21
A50: liabilityRatio (PLU only; not the mortgage) | B50: 0.7
A51: CASH_SAVINGS_SHARE | B51: 0.15
A52: INVESTMENTS_SHARE | B52: 0.85
A53: propertyLow | B53: 350000
A54: propertyMid | B54: 650000
A55: propertyHigh | B55: 850000
A56: propertyIncomeLow | B56: 10000
... A60: lifeRoundUnit | B60: 100000
A62: Plan and budget (frontend/src/lib/planProducts.ts)
A63: protectionPremiumRate | B63: 0.00078
A64: FREE_BUDGET_SHARE | B64: 0.5
A65: lumpRoundStep | B65: 1000
A66: monthlyRoundStep | B66: 50
A67: coverPremRoundStep | B67: 10
A68: coverSliderPremFloor | B68: 200
A70: HappiU budget envelope (src/hu_payload.py) — not Budget Calculator
A71: annualBudget | B71: 1500
A72: placeholderNeedBudget | B72: 200
A73: gfr | B73: 0.05
A74: benefitRound | B74: 50000
A75: huNumSims | B75: 200
A76: funeralLump | B76: 10000
A77: criMedicalPlaceholder | B77: 62400
A79: Risk → investmentReturn seed (frontend/src/lib/riskCapacity.ts)
A80: suggestBand1 | B80: 0.03
A81: suggestBand2 | B81: 0.035
A82: suggestBand3 | B82: 0.042
A83: suggestBand4 | B83: 0.05
A84: suggestBand5 | B84: 0.055
A85: defaultRiskTolerance | B85: 3
A88: Need Profiler factor weights (Need_profiler.json needs_factor_weights)
A89: factor \ need | B89: Life Protection | C89: Critical Illness | D89: Disability | E89: Retirement | F89: Education | G89: Hospitalization | H89: General Savings | I89: Farewell | J89: Personal Accident | K89: Car Protection | L89: Home Protection | M89: Travel Protection
A90: Date of Birth | B90: 0 | C90: 0 | D90: 0 | E90: 2 | F90: 0 | G90: 0 | H90: 0 | I90: 2 | J90: 0 | K90: 1 | L90: 1 | M90: 0
A91: Gender | B91: 0 | C91: 0 | D91: 0 | E91: 2 | F91: 0 | G91: 0 | H91: 2 | I91: 1 | J91: 0 | K91: 2 | L91: 1 | M91: 2
A92: Dependants | B92: 4 | C92: 1 | D92: 0 | E92: 1 | F92: 0 | G92: 0 | H92: 3 | I92: 1 | J92: 0 | K92: 2 | L92: 2 | M92: 2
A93: Occupation | B93: 1 | C93: 1 | D93: 0 | E93: 1 | F93: 0 | G93: 0 | H93: 1 | I93: 2 | J93: 0 | K93: 1 | L93: 2 | M93: 2
A94: Smoking | B94: 4 | C94: 4 | D94: 2 | E94: 1 | F94: 0 | G94: 3 | H94: 0 | I94: 1 | J94: 0 | K94: 2 | L94: 2 | M94: 2
A95: Income | B95: 4 | C95: 1 | D95: 2 | E95: 1 | F95: 0 | G95: 3 | H95: 1 | I95: 2 | J95: 0 | K95: 2 | L95: 2 | M95: 2
A96: Expense | B96: 4 | C96: 2 | D96: 2 | E96: 1 | F96: 0 | G96: 3 | H96: 3 | I96: 2 | J96: 0 | K96: 2 | L96: 1 | M96: 1
A97: Assets | B97: 4 | C97: 1 | D97: 2 | E97: 1 | F97: 0 | G97: 3 | H97: 2 | I97: 1 | J97: 0 | K97: 2 | L97: 1 | M97: 1
A98: Liabilities | B98: 3 | C98: 1 | D98: 2 | E98: 1 | F98: 0 | G98: 3 | H98: 2 | I98: 1 | J98: 0 | K98: 1 | L98: 2 | M98: 1
A99: Hospitalization | B99: 3 | C99: 3 | D99: 0 | E99: 0 | F99: 0 | G99: 4 | H99: 0 | I99: 0 | J99: 0 | K99: 0 | L99: 0 | M99: 0
A100: Disability | B100: 3 | C100: 3 | D100: 4 | E100: 0 | F100: 0 | G100: 3 | H100: 0 | I100: 0 | J100: 0 | K100: 0 | L100: 0 | M100: 0
A101: Hospital Type | B101: 2 | C101: 3 | D101: 2 | E101: 1 | F101: 0 | G101: 3 | H101: 2 | I101: 1 | J101: 0 | K101: 2 | L101: 1 | M101: 2
... A104: Sports | B104: 1 | C104: 0 | D104: 2 | E104: 0 | F104: 0 | G104: 1 | H104: 0 | I104: 0 | J104: 0 | K104: 0 | L104: 0 | M104: 2

Sheet Discrepancies
A1: Code vs documentation — this workbook follows the code
A2: Found while transcribing formulas. If a formula file and Calculations.md disagree, the formula file is supposed to win; when both disagree with the live module, the module wins and is what the Excel formulas implement.
A3: # | B3: Component | C3: Docs say | D3: Code does | E3: Workbook uses | F3: Where
A4: 1 | B4: People Like You | C4: cash / investments split 45% / 55% (Calculations.md §3, People-like-you.md `_apply_plu` table). | D4: CASH_SAVINGS_SHARE = 0.15, INVESTMENTS_SHARE = 0.85 in src/predict.py. tests/test_predict.py asserts 0.15. | E4: 15% / 85% | F4: src/predict.py:14-15; People-like-you.md:63; Calculations.md:255
A5: 2 | B5: Need Profiler | C5: GP sends topN: 5 and walks the ranked UNIFIED list until 5 types are on (Need-profiler.md, Architecture.md, People-like-you-and-needs.md). | D5: app.py calls run_need_profiler(top_n=4). select_unified_top ignores top_n and always returns 2 protection + 2 growth (retirement forced). DEFAULT_TOP_N = 4. | E5: Four needs: two protection + N_RET + one other growth. | F5: src/app.py:218; src/pipeline/need_profiler.py:22-71
A6: 3 | B6: Need Profiler fallback | C6: If the profiler is down: enable N_INC and N_RET, plus N_EDU when dependents > 0 (Need-profiler.md, Calculations.md §5). | D6: app.py default_on = {N_INC, N_CRI, N_RET, N_PRP or N_SAV}; if dependents: {N_INC, N_CRI, N_RET, N_EDU}. | E6: Live path only (not the down fallback). See app.py if you simulate a 503. | F6: src/app.py:224-232; Need-profiler.md:29
A7: 4 | B7: Need Calculator N_RET | C7: needAmount = annualSpend × (1+realReturn)^T × a(realReturn, n) (Need-calculator.md). | D7: pv_annuity(fv(annual, inflationRate, T), realReturn, n). Spend is grown at inflation, then discounted at real return. | E7: Code: grow at inflationRate, PV at realReturn. | F7: src/pipeline/need_calculator.py:143-148; Need-calculator.md:45
A8: 5 | B8: Need Calculator years in retirement | C8: n = 85 − retAge (Need-calculator.md). | D8: years_in_retirement(retAge, session_life_expectancy). Uses People Like You lifeExpectancy when 70–120, else 85. | E8: Session life expectancy (People Like You lifeExpectancy used). | F8: src/pipeline/goal_math.py:120-133; Need-calculator.md:21,39
A9: 6 | B9: Need Calculator sample | C9: Age 42, income 6,800, spend 4,000, mortgage 200,000: N_INC 634,401 (Need-calculator.md). | D9: evaluate_session on those inputs gives N_INC 634,401 (supportYears at 42 is 10). | E9: Live evaluate_session number. | F9: Need-calculator.md:55; src/pipeline/need_calculator.py
A10: 7 | B10: Plan Calculator surplus | C10: annual_surplus = max(0, (income − expense) × 12) (Plan-calculator.md). Budget available = max(0, income − expense) (Budget-calculator.md, Calculations.md §9). | D10: availableBudget = takeHomeMonthly − expenseMonthly (types.ts). defaultWealthMth and planAfford use that. | E10: Take-home minus expense. | F10: frontend/src/lib/types.ts:452-454; Plan-calculator.md:40; Budget-calculator.md:10
A11: 8 | B11: Plan Calculator default premium | C11: default premium = round((slider_max / 2) / 10) × 10 where slider_max = max(indicative × 2, 200). | D11: seedCoverDefaults / refreshUntouchedCover set planPrem = coverPremiumFor(sum) = the indicative itself. | E11: Indicative premium, not half of the slider max. | F11: frontend/src/lib/local.ts:178-180; planProducts.ts:232-234; Plan-calculator.md:16-17
A12: 9 | B12: Plan Calculator premiums subtracted | C12: left = annual_surplus − life_premium (Plan-calculator.md). | D12: left = surplus − protectionPremAnnual (every included protection premium, not only life). | E12: All included protection premiums. | F12: frontend/src/lib/planProducts.ts:321-326; Plan-calculator.md:41
A13: 10 | B13: Need Profiler × People Like You enums | C13: Not documented as a break. Profiler Lifestyle options are frugal / stress-free / only the best; Ward is A / B. | D13: PLU prompt asks retirement_lifestyle: Basic | Comfortable | Luxurious and ward_type: Single | Double | Ward. String match is case-insensitive but hyphen-sensitive. Basic/Comfortable/Luxurious and Single/Double/Ward score 0. Sports is free text; only “Adventurous Sports”, “Life style activities”, and “I dont do sports” match. | E13: Exact string match, so most LLM lifestyle / ward / sports flags add 0. Personas mix matching and PLU strings so you can see both. | F13: people_like_you_all_fields.json:79-80; Need_profiler.json Lifestyle / Ward / Sports; need_profiler.py:229-231
A14: 11 | B14: Need Profiler existing cover / ownership | C14: Reads liquid assets and the person (Calculations.md §5). Does not say existing policies are ignored. | D14: build_profiler_profile hard-codes Existing*Coverage = 0. Car / home / travel have factor weights but no weight_options, so option_weight is 0. Existing Life / CI look up “Life Protection” / “Critical Illness”, which are not in weight_options. | E14: Existing cover 0. Ownership flags stored but do not change the score. | F14: src/pipeline/onboarding.py:154-157; need_profiler.py:128-129
... A17: 14 | B17: HappiU N_CRI years | C17: Need parameters: CI is 3 years + S$200,000. HappiU.md says payload medicalCost S$62,400. | D17: Need Calculator uses CI_YEARS = 3. hu_payload._calc_entry writes numYearsIncomeNeeded = 5 and medicalCost = 62400 for N_CRI. Those two figures are not the Need parameters. | E17: Need Calculator uses 3 years + 200,000. HappiU payload extras are not recalculated here. | F17: src/hu_payload.py:189-196; goal_math.py:32-33; HappiU.md:37-38

Sheet Code check
A1: Values computed by importing the GP modules at workbook build time. After Excel recalculates, pick that id on People Like You and compare the single-persona results. This sheet is a snapshot — it does not follow yellow-cell edits.
A2: id | B2: incomeMonthly | C2: expenseMonthly | D2: cash | E2: investments | F2: property | G2: mortgage | H2: life sum | I2: on N_INC | J2: on N_CRI | K2: on N_TPD | L2: on N_HOS | M2: on N_RET | N2: on N_EDU | O2: on N_SAV | P2: on N_PRP | Q2: N_INC amount | R2: N_RET amount
A3: P01 | B3: 4200 | C3: 2268 | D3: 983 | E3: 5569 | F3: 0 | G3: 0 | H3: 0 | I3: TRUE | J3: FALSE | K3: FALSE | L3: TRUE | M3: TRUE | N3: FALSE | O3: TRUE | P3: FALSE | Q3: 540361 | R3: 1248751
A4: P02 | B4: 6020 | C4: 3250.8 | D4: 8452 | E4: 47895 | F4: 0 | G4: 0 | H4: 0 | I4: FALSE | J4: TRUE | K4: FALSE | L4: TRUE | M4: TRUE | N4: FALSE | O4: TRUE | P4: FALSE | Q4: 724812 | R4: 1271143
A5: P03 | B5: 7140 | C5: 4141.2 | D5: 18378 | E5: 104144 | F5: 350000 | G5: 192500 | H5: 428400 | I5: TRUE | J5: TRUE | K5: FALSE | L5: FALSE | M5: TRUE | N5: FALSE | O5: FALSE | P5: TRUE | Q5: 874927 | R5: 1868554
A6: P04 | B6: 4550 | C6: 2821 | D6: 14742 | E6: 83538 | F6: 350000 | G6: 192500 | H6: 273000 | I6: TRUE | J6: TRUE | K6: FALSE | L6: FALSE | M6: TRUE | N6: FALSE | O6: FALSE | P6: TRUE | Q6: 498862 | R6: 669310
A7: P05 | B7: 5000 | C7: 3875 | D7: 26325 | E7: 149175 | F7: 350000 | G7: 192500 | H7: 300000 | I7: TRUE | J7: TRUE | K7: FALSE | L7: FALSE | M7: TRUE | N7: FALSE | O7: FALSE | P7: TRUE | Q7: 613326 | R7: 1390191
A8: P06 | B8: 13910 | C8: 8924.75 | D8: 33514 | E8: 189913 | F8: 650000 | G8: 357500 | H8: 834600 | I8: TRUE | J8: TRUE | K8: FALSE | L8: FALSE | M8: TRUE | N8: FALSE | O8: FALSE | P8: TRUE | Q8: 1983433 | R8: 3443487
A9: P07 | B9: 5525 | C9: 2983.5 | D9: 42664 | E9: 241763 | F9: 350000 | G9: 192500 | H9: 200000 | I9: FALSE | J9: TRUE | K9: FALSE | L9: TRUE | M9: TRUE | N9: FALSE | O9: FALSE | P9: TRUE | Q9: 516509 | R9: 883827
A10: P08 | B10: 5975 | C10: 4042.5 | D10: 30098 | E10: 170557 | F10: 350000 | G10: 192500 | H10: 358500 | I10: TRUE | J10: TRUE | K10: FALSE | L10: FALSE | M10: TRUE | N10: FALSE | O10: FALSE | P10: TRUE | Q10: 631517 | R10: 536272
A11: P09 | B11: 3350 | C11: 1809 | D11: 3136 | E11: 17768 | F11: 0 | G11: 0 | H11: 0 | I11: TRUE | J11: FALSE | K11: FALSE | L11: TRUE | M11: TRUE | N11: FALSE | O11: TRUE | P11: FALSE | Q11: 431003 | R11: 966306
A12: P10 | B12: 4250 | C12: 3293.75 | D12: 13770 | E12: 78030 | F12: 0 | G12: 0 | H12: 255000 | I12: TRUE | J12: TRUE | K12: FALSE | L12: FALSE | M12: TRUE | N12: FALSE | O12: TRUE | P12: FALSE | Q12: 452793 | R12: 970322
A13: P11 | B13: 7140 | C13: 4141.2 | D13: 42412 | E13: 240332 | F13: 350000 | G13: 192500 | H13: 428400 | I13: FALSE | J13: TRUE | K13: FALSE | L13: TRUE | M13: TRUE | N13: FALSE | O13: FALSE | P13: TRUE | Q13: 642236 | R13: 1398863
A14: P12 | B14: 9800 | C14: 6210 | D14: 121095 | E14: 686205 | F14: 350000 | G14: 192500 | H14: 200000 | I14: FALSE | J14: TRUE | K14: FALSE | L14: TRUE | M14: TRUE | N14: FALSE | O14: FALSE | P14: TRUE | Q14: 866908 | R14: 1235459
... A52: P50 | B52: 5000 | C52: 3875 | D52: 26325 | E52: 149175 | F52: 350000 | G52: 192500 | H52: 300000 | I52: TRUE | J52: TRUE | K52: FALSE | L52: FALSE | M52: TRUE | N52: FALSE | O52: FALSE | P52: TRUE | Q52: 613326 | R52: 1390191
