Workbook
Name inflationRate: Assumptions!$B$5
Name systemCurrency: Assumptions!$B$22
Name fxMode: Assumptions!$B$23
Name priceLevelOn: Assumptions!$B$24
Name interestRate: Assumptions!$B$6
Name loanRate: Assumptions!$B$7
Name incomeGrowthRate: Assumptions!$B$8
Name investmentReturn: Assumptions!$B$9
Name assetReturn: Assumptions!$B$10
Name realReturn: Assumptions!$B$11
Name ageOfRetirement: Assumptions!$B$14
Name lifeExpectancyDefault: Assumptions!$B$15
Name currentYear: Assumptions!$B$16
Name endAge: Assumptions!$B$17
Name RET_LIFESTYLE_FRUGAL: Assumptions!$B$28
Name RET_LIFESTYLE_STRESSFREE: Assumptions!$B$29
Name RET_LIFESTYLE_ONLYTHEBEST: Assumptions!$B$30
Name INC_SUPPORT_MIN: Assumptions!$B$31
Name INC_SUPPORT_MAX: Assumptions!$B$32
Name INC_SUPPORT_PIVOT_AGE: Assumptions!$B$33
Name CRI_YEARS: Assumptions!$B$34
Name CRI_COST: Assumptions!$B$35
Name TPD_YEARS: Assumptions!$B$36
Name TPD_COST: Assumptions!$B$37
Name HOS_MONTHS: Assumptions!$B$38
Name EDU_COST: Assumptions!$B$39
Name EDU_YEARS_DEFAULT: Assumptions!$B$40
Name SAV_INCOME_MULT: Assumptions!$B$41
Name PRP_INCOME_MULT: Assumptions!$B$42
Name PAC_YEARS: Assumptions!$B$43
Name PAC_COST: Assumptions!$B$44
Name LON_AGE: Assumptions!$B$45
Name spendShareBase: Assumptions!$B$47
Name spendSharePerDependant: Assumptions!$B$48
Name spendShareCap: Assumptions!$B$49
Name assetsSaveShare: Assumptions!$B$50
Name workStartAge: Assumptions!$B$51
Name liabilityRatio: Assumptions!$B$52
Name CASH_SAVINGS_SHARE: Assumptions!$B$53
Name INVESTMENTS_SHARE: Assumptions!$B$54
Name propertyLow: Assumptions!$B$55
Name propertyMid: Assumptions!$B$56
Name propertyHigh: Assumptions!$B$57
Name propertyIncomeLow: Assumptions!$B$58
Name propertyIncomeHigh: Assumptions!$B$59
Name PROPERTY_LTV: Assumptions!$B$60
Name lifePremiumRate: Assumptions!$B$61
Name lifeRoundUnit: Assumptions!$B$62
Name protectionPremiumRate: Assumptions!$B$65
Name FREE_BUDGET_SHARE: Assumptions!$B$66
Name lumpRoundStep: Assumptions!$B$67
Name monthlyRoundStep: Assumptions!$B$68
Name coverPremRoundStep: Assumptions!$B$69
Name coverSliderPremFloor: Assumptions!$B$70
Name annualBudget: Assumptions!$B$73
Name placeholderNeedBudget: Assumptions!$B$74
Name gfr: Assumptions!$B$75
Name benefitRound: Assumptions!$B$76
Name huNumSims: Assumptions!$B$77
Name CRI_MEDICAL_HU: Assumptions!$B$79

Sheet Overview
A1: FinPlan360 calculation components — live code, September 2026
A2: Yellow = type here. Orange = override (leave blank to keep the calculated value). Pick the persona on the Selected persona tab; every later tab follows that id. Gold = persona input, blue = LLM, orange = user / Money-page override, green = calculated, purple = assumptions. FX converts local amounts to USD. Validation applies USD-only rules. CPF is its own tab and is on only when the country switch says so (Singapore on, others off). HappiU and Scenario Visualizer are mapped here but scored / projected in HU and SV.
A3: Component | B3: Owner | C3: Reads | D3: Writes | E3: How it calculates (code) | F3: Code | G3: Tab | H3: HTTP / UI
A4: CPF | B4: GP pipeline (Singapore only) | C4: country, residency, age, incomeMonthly. Country switch on the CPF tab. | D4: employee CPF, take-home. 0 / income when CPF is off. | E4: On only when the country table (or orange override) is TRUE. Singapore Citizen/PR: employee CPF = floor(min(gross, OW_CEILING) × age-band rate). Foreigner → 0. Any other country → off, take-home = gross. src/cpf.py. | F4: src/cpf.py | G4: CPF | H4: Inside POST /v1/predict (take-home)
A5: People Like You | B5: GP pipeline | C5: age / DOB, occupation, gender, dependents, residency. CPF box for take-home. Does not read Assumptions. | D5: incomeMonthly, expenseMonthly, cash, investments, property, mortgage, one Life Protection policy, lifeExpectancy, isSmoker. | E5: LLM proposes gross monthly income and lifestyle flags. Income is clamped to the Singapore occupation band. Employee CPF = floor(min(gross, 8000) × age-band rate); 0 if Foreigner. expenseMonthly = round(take-home × min(67.5% + 5pp × dependents, 90%), 2). Liquid assets = max(0, surplus × 12 × 0.5 × (age − 21)), then cash 15% / investments 85%. If the model says they own a home: property from income band, mortgage = round(property × 55%). Assumed life cover = max(mortgage rounded up to S$100k, 5 × annual income if dependents > 0); premium = round(sum × 0.31%). PLU liabilities (= assets × 0.7) is not the mortgage. If this step fails, predict returns 503. | F5: src/pipeline/people_like_you.py, src/cpf.py, src/predict.py _apply_plu | G5: People Like You | H5: POST /v1/predict (first of three)
A6: Need Profiler | B6: GP pipeline | C6: Age, gender, dependents, occupation, smoker, income, expense, liquid assets, PLU liabilities, hospital/ward/lifestyle/sports, car/home/travel flags. Existing cover is hard-coded 0. No Assumptions. No LLM. | D6: needs[].enabled, needs[].priority, needs[].weightageScore. Four UNIFIED types on: two protection + two growth (retirement always one of the growth pair). | E6: Twelve AI labels are scored as Σ (factor_weight × option_weight), rounded to 2 dp, then min–max scaled 0–10. Income / expense / assets / liabilities convert local × FX to USD, then retuned USD bands. Car ownership, home ownership, travel, and existing life / CI cover have factor weights but no matching weight_options, so they add 0. select_unified_top ignores top_n (app.py still passes 4). If has_property, N_PRP replaces N_SAV in the second growth slot. priority = 5 if scaled score > 7 else 3. Personal accident / motor / travel / farewell are scored and dropped. Orange Enable? columns let you force a need on or off. | F6: src/pipeline/need_profiler.py, src/pipeline/prompts/Need_profiler.json, src/app.py top_n=4 | G6: Need Profiler | H6: POST /v1/predict
A7: Need Calculator | B7: GP pipeline | C7: Money attributes, enabled needs, goal-card sliders (lifestyle, retAge, targetYear, incomeReplaceMonthly, dependYears, bequest, monthlyContribution, tagged existing), Assumptions rates, Need parameters. | D7: For every UNIFIED type: needAmount, have, gap. Copies ageOfRetirement from the retirement row. | E7: realReturn = max(0, (1 + investmentReturn) / (1 + inflationRate) − 1). N_RET = annualSpend × (1+realReturn)^T × a(realReturn, n), n = min(LE,99) − retAge. N_INC = bequest + mortgage + ordinary annuity of annual spend over supportYears = min(max(10, 50 − age), 25). N_CRI / N_TPD = annuity-due of replacement income for 3 / 5 years + S$200,000. N_HOS = income × 6. N_EDU = 75,000 × (1 + inflation)^(targetYear − thisYear). N_SAV / N_PRP = stored needAmount if > 0, else 1× / 5× annual income. Protection have = policy sum (life is seeded by PLU). Wealth have = tagged investments only, grown at realReturn; cash is never allocated. Amounts are computed for all eight types even when a need is off. Orange Enable? and slider columns are the goal-card inputs. | F7: src/pipeline/need_calculator.py evaluate_session, src/pipeline/goal_math.py, src/hu_payload.py need_existing / apply_investment_pot | G7: Need Calculator | H7: POST /v1/predict and POST /v1/needs
A8: Goal cards | B8: GP UI | C8: Last calculator row (have, gap, stored sliders). | D8: Slider fields on the need; then POST /v1/needs (debounced). Does not recompute amounts in the browser. | E8: fillNeedEdit reads stored fields. patchNeedInputs writes lifestyle / retAge / targetYear / existing / … onto the session. Retirement stays on. The Score/Plan cap of four needs is UI-only (needEdit.capEnabledNeeds); this workbook lets you switch any need. | F8: frontend/src/lib/needEdit.ts | G8: Need Calculator (slider columns) | H8: Score and Plan screens
A9: Plan Calculator | B9: GP UI | C9: Enabled needs with gap > 0, take-home surplus, Assumptions inflationRate / investmentReturn / ageOfRetirement. | D9: planSum + planPrem (protection), planMth + planLump (wealth), investMth / investLump totals, plansOff. | E9: Suggested = enabled AND gap > 0. Default planSum = round(gap). planPrem = dummy indicative round((sum × 0.00078) / 10) × 10 (future: premium-quote API). Wealth horizon = years to retirement, or targetYear − this year. Lump / monthly caps = the amount that alone grows to the gap at realReturn (round up to S$1,000 / S$50). Default monthly = round((max(0, take-home − expense) × 12 − all protection premiums) × 50% / 12 / n_wealth / 50) × 50, then min(share, cap). Default lump = 0. Orange Include? columns are plansOff. | F9: frontend/src/lib/planProducts.ts, frontend/src/lib/local.ts seedProducts | G9: Plan Calculator | H9: Plan screen (not an HTTP engine)
A10: Budget Calculator | B10: GP UI | C10: take-home, expenseMonthly, investments, included planPrem / planMth / planLump. Not the economic rates. | D10: Nothing on the session. Plan-screen affordability only. | E10: available = max(0, takeHomeMonthly − expenseMonthly). free = round(available × 0.5). monthly = round(wealth contributions + protection premiums / 12). monthlyOver = monthly − free. lumpOver = wealth lumps − investments. Separate from the HappiU envelope (annualBudget 1500). | F10: planAfford in frontend/src/lib/planProducts.ts; availableBudget in types.ts | G10: Budget Calculator | H10: Plan screen
A11: FX | B11: Workbook only (not an HTTP engine) | C11: Personas currency + effective session money fields from People Like You. | D11: USD per 1 local, and each money field in USD. Validation reads these; engines stay local. | E11: Lookup ISO code in the FX rate table (USD per 1 local unit). USD = local × rate. Example: 5,000 SGD × 0.74 = 3,700 USD; 5,000 VND × 0.000038 = 0.19 USD. Edit the rate table on this tab. People Like You still stores local currency. | F11: Workbook FX tab (no src module — validation helper) | G11: FX | H11: Not in the live pipeline
A12: HappiU | B12: HU, via GP | C12: Whole session. Assumptions rates, CPF (inside HU), riskProfile, plan fields when set. Need amounts already stored. | D12: preHappiU, postHappiU. GP does not run the Monte Carlo. | E12: GP maps the session (src/hu_payload.py). Salary is gross incomeMonthly. N_HOS is renamed N_HSP. If retirement is off, GP still sends a synthetic N_RET = expense × 12 × (lifeExpectancy − retAge). Before a plan: benefitAmount = needAmount rounded to S$50,000, budget 200. With a plan: planSum / planPrem. This workbook does not score HappiU. | F12: src/hu_payload.py → POST /v1/score → HU | G12: Assumptions (envelope only) | H12: POST /v1/score
A13: Scenario Visualizer | B13: SV, via GP | C13: Session after Plan, all six rates, ageOfRetirement, endAge, stress chips. CPF inside SV. | D13: Year-by-year wealth path. GP does not run the year step. | E13: preWealth = session without the plan; postWealth = plus included planMth / planLump / planSum / planPrem. svNumSims defaults to 20. Investment contribution = max(0, take-home − expenseMonthly) once a year. This workbook does not project the path. | F13: src/sv_payload.py → POST /v1/project → SV | G13: Assumptions (stress catalogue) | H13: POST /v1/project
A14: Journey order (one session, each step adds attributes)
A15: Shared inputs (Assumptions · CPF · Need parameters · Risk · Stress events) → About you → CPF (on for Singapore only) → People Like You (or the customer edits the same money fields) → Need Profiler → Need Calculator → HappiU (no plan) → Plan Calculator → Budget Calculator → Scenario Visualizer → HappiU (with plan). Workbook-only: FX (local → USD) then Validation (USD rules).
A17: UNIFIED types in code order: N_INC, N_CRI, N_TPD, N_HOS (protection) · N_RET, N_EDU, N_SAV, N_PRP (wealth). Goal-card sliders live on the Need Calculator tab. Discrepancies lists remaining multi-country / multi-currency work.

Sheet Dictionary
A1: Dictionary — needs (N_), risks (R_) and parameter prefixes
A2: N_xxx = need. R_xxx = the risk or event that triggers it (N_CRI ↔ R_CRI; N_INC ↔ R_DEA). · Parameters are named <PREFIX>_<WHAT> in upper case, with the need's 3-letter prefix (CRI_COST, HOS_MONTHS). · Protection · calculator and Wealth · calculator needs get amount / have / gap. Coverage · parked needs are scored only. · One name per need in every component (e.g. TPD, never Disability or PTD). Where an engine still differs (HU: N_HSP, PTD) it is listed as open. · Code (src/, frontend/) still uses the old parameter names and 8 needs until the code follows V0-16.
A4: NEEDS
A5: Code | B5: Risk | C5: Prefix | D5: Category | E5: App label | F5: Profiler label (key) | G5: HappiU | H5: Scenario Visualizer | I5: Calculator | J5: Parameters | K5: Status
A6: N_INC | B6: R_DEA | C6: INC | D6: Protection · calculator | E6: Income & family protection | F6: Life Protection (life_protection) | G6: N_INC | H6: premium | I6: bequest + mortgage + PV of annual spend over support years | J6: INC_SUPPORT_MIN / MAX / PIVOT_AGE | K6: Live
A7: N_CRI | B7: R_CRI | C7: CRI | D7: Protection · calculator | E7: Critical illness | F7: Critical Illness (critical_illness) | G7: N_CRI | H7: premium | I7: annuity-due of income for CRI_YEARS + CRI_COST | J7: CRI_YEARS, CRI_COST | K7: Live
A8: N_TPD | B8: R_TPD | C8: TPD | D8: Protection · calculator | E8: Total & permanent disability (TPD) | F8: TPD (JSON key: disability) | G8: N_TPD (HU engine internals still say PTD: rename there) | H8: premium | I8: annuity-due of income for TPD_YEARS + TPD_COST | J8: TPD_YEARS, TPD_COST | K8: Live
A9: N_HOS | B9: R_HOS | C9: HOS | D9: Protection · calculator | E9: Hospitalisation | F9: Hospitalization (hospitalization) | G9: N_HSP: GP renames N_HOS → N_HSP in hu_payload.py because the HU engine only knows N_HSP | H9: premium | I9: incomeMonthly × HOS_MONTHS | J9: HOS_MONTHS | K9: Live. Open: one code (N_HOS) in GP and HU
A10: N_PAC | B10: R_PAC | C10: PAC | D10: Protection · calculator | E10: Personal accident (new) | F10: Personal Accident (personal_accident) | G10: N_PAC (HU engine supports it; GP does not send it yet) | H10: premium | I10: annuity-due of income for PAC_YEARS + PAC_COST | J10: PAC_YEARS, PAC_COST | K10: Agreed V0-18 (Excel). Code and HappiU payload to follow
A11: N_ADB | B11: R_ADB | C11: ADB | D11: Protection · candidate | E11: Accidental death | F11: none (no profiler label) | G11: N_ADB (HU engine supports it, death-type goal like N_INC) | H11: — | I11: not defined yet (proposal: lump like N_INC, paid only on accidental death) | J11: ADB_* (to define) | K11: Added V0-17 to the dictionary. No calculator, not scored
A12: N_RET | B12: R_LON | C12: RET | D12: Wealth · calculator | E12: Private retirement | F12: Retirement (retirement) | G12: N_RET | H12: RET pot | I12: annual spend × lifestyle, grown to retirement, × annuity over years in retirement | J12: RET_LIFESTYLE_FRUGAL / STRESSFREE / ONLYTHEBEST; LON_AGE (R_LON) | K12: Live. R_LON stress: need re-sized to LON_AGE 99
A13: N_EDU | B13: — | C13: EDU | D13: Wealth · calculator | E13: Child's university education | F13: Education (education) | G13: N_EDU | H13: goal pot | I13: EDU_COST grown at inflation to target year | J13: EDU_COST, EDU_YEARS_DEFAULT | K13: Live
A14: N_SAV | B14: — | C14: SAV | D14: Wealth · calculator | E14: Savings goal | F14: General Savings (general_savings) | G14: N_SAV | H14: goal pot | I14: stored amount, else SAV_INCOME_MULT × annual income | J14: SAV_INCOME_MULT | K14: Live. No longer swapped with N_PRP
A15: N_PRP | B15: — | C15: PRP | D15: Wealth · calculator | E15: Home purchase | F15: none (no home-purchase label) | G15: N_PRP | H15: goal pot | I15: stored amount, else PRP_INCOME_MULT × annual income | J15: PRP_INCOME_MULT | K15: Separated from Home Protection. Off unless the customer switches it on
A16: N_HOM | B16: — | C16: HOM | D16: Coverage · parked | E16: Home protection | F16: Home Protection (home) | G16: — | H16: — | I16: no calculator | J16: — | K16: Scored and prioritised only
... A19: — | B19: — | C19: — | D19: Dropped | E19: Farewell | F19: Farewell (farewell) | G19: funeral lump dropped | H19: — | I19: — | J19: funeralLump removed | K19: Dropped V0-16
A21: RISKS AND STRESS EVENTS
A22: Code | B22: Was (id) | C22: Label | D22: Need | E22: Kind
A23: R_DEA | B23: death | C23: Death | D23: N_INC | E23: Need risk
A24: R_CRI | B24: ci | C24: Critical illness | D24: N_CRI | E24: Need risk
A25: R_TPD | B25: tpd | C25: Total & permanent disability | D25: N_TPD | E25: Need risk
A26: R_HOS | B26: hosp | C26: Hospitalisation | D26: N_HOS | E26: Need risk
A27: R_PAC | B27: pa | C27: Personal accident | D27: N_PAC | E27: Need risk
A28: R_ADB | B28: — | C28: Accidental death | D28: N_ADB | E28: Need risk (no stress event yet)
A29: R_LON | B29: — (new V0-18) | C29: Longevity: live until LON_AGE (99) | D29: N_RET | E29: Need risk · stress event
A30: R_LTC | B30: care | C30: Long-term care | D30: — | E30: Stress event (no need yet)
A31: R_MKT | B31: crash | C31: Market crash | D31: — | E31: Market event
A32: R_CCY | B32: ccy | C32: Currency shock | D32: — | E32: Market event
A33: R_INF | B33: infl | C33: Inflation shock | D33: — | E33: Market event
... A37: R_BAB | B37: baby | C37: Newborn | D37: — | E37: Life event
A39: PARAMETER NAMES (Assumptions named cells)
A40: New name | B40: Was | C40: Need
A41: INC_SUPPORT_MIN | B41: lifeSupportMin | C41: N_INC
A42: INC_SUPPORT_MAX | B42: lifeSupportMax | C42: N_INC
A43: INC_SUPPORT_PIVOT_AGE | B43: lifeSupportPivotAge | C43: N_INC
A44: CRI_YEARS | B44: CI_YEARS | C44: N_CRI
A45: CRI_COST | B45: CI_COST | C45: N_CRI
A46: TPD_YEARS | B46: TPD_YEARS | C46: N_TPD
A47: TPD_COST | B47: TPD_COST | C47: N_TPD
A48: HOS_MONTHS | B48: HOSP_MONTHS | C48: N_HOS
A49: PAC_YEARS | B49: (new) | C49: N_PAC
A50: PAC_COST | B50: (new) | C50: N_PAC
A51: LON_AGE | B51: (new) | C51: N_RET · R_LON
... A60: (removed) | B60: funeralLump | C60: Farewell (dropped)

Sheet Selected persona
A1: Selected persona — pick one id here. Every calculation tab follows this cell.
A2: Selected persona | B2: P01 | C2: =IFERROR(INDEX(Personas!B$3:B$52,MATCH($B$2,Personas!$A$3:$A$52,0)),"") | D2: This is the only picker. CPF, People Like You, Need Profiler, Need Calculator, Plan, Budget, FX, and Validation follow this cell. | F2: A · INPUT DATA
A3: Attribute | B3: Value | C3: Kind | D3: Source / formula | F3: B · LLM PREDICTED DATA
A4: A · ABOUT YOU — from the Personas row (edit there) | F4: C · DETERMINISTICALLY CALCULATED
A5: name | B5: =IFERROR(INDEX(Personas!B$3:B$52,MATCH($B$2,Personas!$A$3:$A$52,0)),"") | C5: A · input | D5: Personas B. | F5: D · ASSUMPTIONS / SHARED DATA
A6: age | B6: =IFERROR(INDEX(Personas!C$3:C$52,MATCH($B$2,Personas!$A$3:$A$52,0)),"") | C6: A · input | D6: Personas C. | F6: E · USER / FRONTEND OVERRIDE
A7: gender | B7: =IFERROR(INDEX(Personas!D$3:D$52,MATCH($B$2,Personas!$A$3:$A$52,0)),"") | C7: A · input | D7: Personas D.
A8: residency | B8: =IFERROR(INDEX(Personas!E$3:E$52,MATCH($B$2,Personas!$A$3:$A$52,0)),"") | C8: A · input | D8: Personas E.
A9: country | B9: =IFERROR(INDEX(Personas!F$3:F$52,MATCH($B$2,Personas!$A$3:$A$52,0)),"") | C9: A · input | D9: Personas F. CPF on/off uses this.
A10: occupation | B10: =IFERROR(INDEX(Personas!G$3:G$52,MATCH($B$2,Personas!$A$3:$A$52,0)),"") | C10: A · input | D10: Personas G. Income clamp band.
A11: dependents | B11: =IFERROR(INDEX(Personas!H$3:H$52,MATCH($B$2,Personas!$A$3:$A$52,0)),"") | C11: A · input | D11: Personas H.
A12: maritalStatus | B12: =IFERROR(INDEX(Personas!I$3:I$52,MATCH($B$2,Personas!$A$3:$A$52,0)),"") | C12: A · input | D12: Personas I. Blank = infer on People Like You.
A13: what this row varies | B13: =IFERROR(INDEX(Personas!AD$3:AD$52,MATCH($B$2,Personas!$A$3:$A$52,0)),"") | C13: A · input | D13: Personas AD. Why this persona exists.
A15: B · LLM PREDICTED — from the Personas row (edit there)
A16: incomeMonthly (LLM) | B16: =IFERROR(INDEX(Personas!J$3:J$52,MATCH($B$2,Personas!$A$3:$A$52,0)),"") | C16: B · LLM predicted | D16: Personas J. Before clamp and CPF.
A17: currency | B17: =IFERROR(INDEX(Personas!K$3:K$52,MATCH($B$2,Personas!$A$3:$A$52,0)),"") | C17: B · LLM predicted | D17: Personas K. FX looks this up.
A18: risk ability | B18: =IFERROR(INDEX(Personas!L$3:L$52,MATCH($B$2,Personas!$A$3:$A$52,0)),"") | C18: B · LLM predicted | D18: Personas L.
A19: price sensitivity | B19: =IFERROR(INDEX(Personas!M$3:M$52,MATCH($B$2,Personas!$A$3:$A$52,0)),"") | C19: B · LLM predicted | D19: Personas M.
A20: owns property | B20: =IFERROR(INDEX(Personas!N$3:N$52,MATCH($B$2,Personas!$A$3:$A$52,0)),"") | C20: B · LLM predicted | D20: Personas N.
A21: owns car | B21: =IFERROR(INDEX(Personas!O$3:O$52,MATCH($B$2,Personas!$A$3:$A$52,0)),"") | C21: B · LLM predicted | D21: Personas O.
A22: is smoker | B22: =IFERROR(INDEX(Personas!U$3:U$52,MATCH($B$2,Personas!$A$3:$A$52,0)),"") | C22: B · LLM predicted | D22: Personas U.
A23: life expectancy | B23: =IFERROR(INDEX(Personas!V$3:V$52,MATCH($B$2,Personas!$A$3:$A$52,0)),"") | C23: B · LLM predicted | D23: Personas V.
A24: retirement lifestyle | B24: =IFERROR(INDEX(Personas!T$3:T$52,MATCH($B$2,Personas!$A$3:$A$52,0)),"") | C24: B · LLM predicted | D24: Personas T.
A26: C · EFFECTIVE SESSION — after CPF, People Like You, and Money-page overrides
A27: CPF on | B27: =CPF_on | C27: C · calculated | D27: From the CPF tab.
A28: incomeMonthly | B28: =PLU_incomeMonthly | C28: C · calculated | D28: Clamped LLM income.
A29: take-home | B29: =PLU_takeHome | C29: C · calculated | D29: Gross minus employee CPF when CPF is on.
A30: expenseMonthly | B30: =PLU_expenseMonthly | C30: C · calculated | D30: Override if Personas W is set.
A31: cash | B31: =PLU_cash | C31: C · calculated | D31: Cash & Savings.
A32: investments | B32: =PLU_investments | C32: C · calculated
A33: property | B33: =PLU_property | C33: C · calculated | D33: 0 if renter.
A34: mortgage | B34: =PLU_mortgage | C34: C · calculated
A35: PLU liabilities | B35: =PLU_liabilities | C35: C · calculated | D35: Not the mortgage.
A36: life sum assured | B36: =PLU_lifeSum | C36: C · calculated

Sheet Personas
A1: A · INPUT DATA — About you (typed / session) | J1: B · LLM PREDICTED DATA — 13 fields from people_like_you_all_fields.json | W1: E · USER / FRONTEND OVERRIDE — Money page (blank = keep People Like You calculated) | AD1: notes | AF1: A · INPUT DATA
A2: id | B2: name | C2: age | D2: gender | E2: residency | F2: country | G2: occupation | H2: dependents | I2: maritalStatus (blank = infer) | J2: income | K2: currency | L2: risk_ability | M2: price_sensitivity | N2: property | O2: car | P2: ward_type | Q2: hospitalization_type | R2: travelling | S2: sports | T2: retirement_lifestyle | U2: is_smoker | V2: life_expectancy | W2: expenseMonthly | X2: cash (Cash & Savings) | Y2: investments | Z2: property value | AA2: mortgage (loans) | AB2: PLU liabilities | AC2: life sum assured | AD2: What this row varies | AF2: B · LLM PREDICTED DATA
A3: P01 | B3: Aisha Rahman | C3: 22 | D3: Female | E3: Citizen | F3: Singapore | G3: Nurse | H3: 0 | J3: 4200 | K3: SGD | L3: conservative | M3: high | N3: FALSE | O3: FALSE | P3: Ward | Q3: Public | R3: FALSE | S3: Yoga | T3: Basic | U3: FALSE | V3: 86 | W3: 2268 | X3: 983 | Y3: 5569 | Z3: 0 | AA3: 0 | AB3: 4586.4 | AC3: 0 | AD3: Nurse; age 22; Citizen; 0 dep; rent; non-smoker | AF3: C · DETERMINISTICALLY CALCULATED
A4: P02 | B4: Wei Ling Tan | C4: 27 | D4: Male | E4: PR | F4: Singapore | G4: Teacher | H4: 0 | J4: 6020 | K4: SGD | L4: moderate | M4: medium | N4: FALSE | O4: TRUE | P4: Double | Q4: Private | R4: TRUE | S4: Running | T4: Comfortable | U4: FALSE | V4: 81 | W4: 3250.8 | X4: 8452 | Y4: 47895 | Z4: 0 | AA4: 0 | AB4: 39443.04 | AC4: 0 | AD4: Teacher; age 27; PR; 0 dep; rent; non-smoker | AF4: D · ASSUMPTIONS / SHARED DATA
A5: P03 | B5: Daniel Koh | C5: 34 | D5: Female | E5: Citizen | F5: Singapore | G5: Accountant | H5: 1 | J5: 7140 | K5: SGD | L5: moderate | M5: medium | N5: TRUE | O5: TRUE | P5: Single | Q5: Private | R5: TRUE | S5: Swimming | T5: Comfortable | U5: FALSE | V5: 88 | W5: 4141.2 | X5: 18378 | Y5: 104144 | Z5: 350000 | AA5: 192500 | AB5: 85765.68 | AC5: 428400 | AD5: Accountant; age 34; Citizen; 1 dep; home; non-smoker | AF5: E · USER / FRONTEND OVERRIDE
A6: P04 | B6: Priya Nair | C6: 41 | D6: Male | E6: Citizen | F6: Singapore | G6: Marketing Manager | H6: 2 | J6: 4550 | K6: SGD | L6: conservative | M6: high | N6: TRUE | O6: TRUE | P6: Ward | Q6: Public | R6: FALSE | S6: I dont do sports | T6: frugal | U6: TRUE | V6: 78 | W6: 2821 | X6: 14742 | Y6: 83538 | Z6: 350000 | AA6: 192500 | AB6: 68796 | AC6: 273000 | AD6: Marketing Manager; age 41; Citizen; 2 dep; home; smoker
A7: P05 | B7: Marcus Lim | C7: 47 | D7: Female | E7: Foreigner | F7: Singapore | G7: Software Engineer | H7: 2 | J7: 5000 | K7: SGD | L7: aggressive | M7: high | N7: TRUE | O7: FALSE | P7: A | Q7: Private | R7: TRUE | S7: Adventurous Sports | T7: only the best | U7: FALSE | V7: 90 | W7: 3875 | X7: 26325 | Y7: 149175 | Z7: 350000 | AA7: 192500 | AB7: 122850 | AC7: 300000 | AD7: Software Engineer; age 47; Foreigner; 2 dep; home; non-smoker
A8: P06 | B8: Hannah Wong | C8: 32 | D8: Male | E8: Citizen | F8: Singapore | G8: Doctor | H8: 1 | J8: 13910 | K8: SGD | L8: moderate | M8: medium | N8: TRUE | O8: TRUE | P8: B | Q8: Public | R8: TRUE | S8: Life style activities | T8: stress-free | U8: FALSE | V8: 83 | W8: 8924.75 | X8: 33514 | Y8: 189913 | Z8: 650000 | AA8: 357500 | AB8: 156398.55 | AC8: 834600 | AD8: Doctor; age 32; Citizen; 1 dep; home; non-smoker
A9: P07 | B9: Julian Chee | C9: 54 | D9: Female | E9: PR | F9: Singapore | G9: Investment Banker | H9: 0 | J9: 5525 | K9: SGD | L9: conservative | M9: high | N9: TRUE | O9: TRUE | P9: Single | Q9: Private | R9: FALSE | S9: Walking | T9: Basic | U9: FALSE | V9: 89 | W9: 2983.5 | X9: 42664 | Y9: 241763 | Z9: 350000 | AA9: 192500 | AB9: 199098.9 | AC9: 200000 | AD9: Investment Banker; age 54; PR; 0 dep; home; non-smoker
A10: P08 | B10: Mei Fen Ong | C10: 60 | D10: Male | E10: Citizen | F10: Singapore | G10: CEO | H10: 3 | J10: 5975 | K10: SGD | L10: conservative | M10: high | N10: TRUE | O10: TRUE | P10: Ward | Q10: Public | R10: FALSE | S10: I dont do sports | T10: frugal | U10: TRUE | V10: 76 | W10: 4042.5 | X10: 30098 | Y10: 170557 | Z10: 350000 | AA10: 192500 | AB10: 140458.5 | AC10: 358500 | AD10: CEO; age 60; Citizen; 3 dep; home; smoker
A11: P09 | B11: Hafiz Abdullah | C11: 25 | D11: Female | E11: Citizen | F11: Singapore | G11: Baker | H11: 0 | J11: 3350 | K11: SGD | L11: moderate | M11: high | N11: FALSE | O11: FALSE | P11: Ward | Q11: Public | R11: TRUE | S11: HIIT | T11: Comfortable | U11: FALSE | V11: 87 | W11: 1809 | X11: 3136 | Y11: 17768 | Z11: 0 | AA11: 0 | AB11: 14632.8 | AC11: 0 | AD11: Baker; age 25; Citizen; 0 dep; rent; non-smoker
A12: P10 | B12: Siti Hassan | C12: 37 | D12: Male | E12: Foreigner | F12: Singapore | G12: Driver | H12: 2 | J12: 4250 | K12: SGD | L12: aggressive | M12: high | N12: FALSE | O12: TRUE | P12: Double | Q12: Private | R12: TRUE | S12: Football | T12: Luxurious | U12: FALSE | V12: 80 | W12: 3293.75 | X12: 13770 | Y12: 78030 | Z12: 0 | AA12: 0 | AB12: 64260 | AC12: 255000 | AD12: Driver; age 37; Foreigner; 2 dep; rent; non-smoker
A13: P11 | B13: Aisha Ng | C13: 51 | D13: Female | E13: Citizen | F13: Singapore | G13: Nurse | H13: 1 | J13: 7140 | K13: SGD | L13: moderate | M13: medium | N13: TRUE | O13: TRUE | P13: A | Q13: Private | R13: TRUE | S13: Pilates | T13: only the best | U13: FALSE | V13: 91 | W13: 4141.2 | X13: 42412 | Y13: 240332 | Z13: 350000 | AA13: 192500 | AB13: 197920.8 | AC13: 428400 | AD13: Nurse; age 51; Citizen; 1 dep; home; non-smoker
A14: P12 | B14: Wei Ling Chua | C14: 66 | D14: Male | E14: Citizen | F14: Singapore | G14: Teacher | H14: 0 | J14: 9800 | K14: SGD | L14: conservative | M14: medium | N14: TRUE | O14: FALSE | P14: Ward | Q14: Public | R14: FALSE | S14: I dont do sports | T14: Basic | U14: FALSE | V14: 85 | W14: 6210 | X14: 121095 | Y14: 686205 | Z14: 350000 | AA14: 192500 | AB14: 565110 | AC14: 200000 | AD14: Teacher; age 66; Citizen; 0 dep; home; non-smoker
A15: P13 | B15: Daniel Lee | C15: 30 | D15: Female | E15: PR | F15: Singapore | G15: Accountant | H15: 1 | J15: 6580 | K15: SGD | L15: moderate | M15: medium | N15: FALSE | O15: TRUE | P15: Double | Q15: Public | R15: FALSE | S15: Running | T15: Comfortable | U15: TRUE | V15: 79 | W15: 3816.4 | X15: 11726 | Y15: 66445 | Z15: 0 | AA15: 0 | AB15: 54719.28 | AC15: 394800 | AD15: Accountant; age 30; PR; 1 dep; rent; smoker
A16: P14 | B16: Priya Goh | C16: 44 | D16: Male | E16: Citizen | F16: Singapore | G16: Marketing Manager | H16: 4 | J16: 4775 | K16: SGD | L16: aggressive | M16: high | N16: TRUE | O16: TRUE | P16: Single | Q16: Private | R16: TRUE | S16: Golf | T16: Luxurious | U16: FALSE | V16: 84 | W16: 3342.5 | X16: 9884 | Y16: 56011 | Z16: 350000 | AA16: 192500 | AB16: 46126.5 | AC16: 286500 | AD16: Marketing Manager; age 44; Citizen; 4 dep; home; non-smoker
A17: P15 | B17: Marcus Teo | C17: 57 | D17: Female | E17: Citizen | F17: Singapore | G17: Software Engineer | H17: 2 | J17: 5750 | K17: SGD | L17: conservative | M17: high | N17: TRUE | O17: TRUE | P17: B | Q17: Private | R17: FALSE | S17: Life style activities | T17: stress-free | U17: FALSE | V17: 92 | W17: 3654.12 | X17: 34373 | Y17: 194778 | Z17: 350000 | AA17: 192500 | AB17: 160405.06 | AC17: 345000 | AD17: Software Engineer; age 57; Citizen; 2 dep; home; non-smoker
... A52: P50 | B52: Siti Lim | C52: 47 | D52: Female | E52: Foreigner | F52: Singapore | G52: Driver | H52: 2 | J52: 5000 | K52: SGD | L52: aggressive | M52: high | N52: TRUE | O52: FALSE | P52: A | Q52: Private | R52: TRUE | S52: Adventurous Sports | T52: only the best | U52: FALSE | V52: 90 | W52: 3875 | X52: 26325 | Y52: 149175 | Z52: 350000 | AA52: 192500 | AB52: 122850 | AC52: 300000 | AD52: Driver; age 47; Foreigner; 2 dep; home; non-smoker

Sheet CPF
A1: CPF — social-security plug-in. In: gross, age, residency, country. Out: employee contribution, take-home. Runs in user currency.
A2: Selected persona | B2: =SelectedPersona | C2: =IFERROR(INDEX(Personas!B$3:B$52,MATCH($B$2,Personas!$A$3:$A$52,0)),"") | D2: Follows the dropdown on the Selected persona tab. | F2: A · INPUT DATA
A3: Attribute | B3: Value | C3: Kind | D3: Source / formula | F3: B · LLM PREDICTED DATA
A4: A · INPUT DATA — from the selected Personas row | F4: C · DETERMINISTICALLY CALCULATED | I4: D · MODULE PER COUNTRY — TRUE = SG-CPF module; FALSE = default module (no contribution)
A5: country | B5: =IFERROR(INDEX(Personas!F$3:F$52,MATCH($B$2,Personas!$A$3:$A$52,0)),"") | C5: A · input | D5: Personas F. Looks up the country switch. | F5: D · ASSUMPTIONS / SHARED DATA | I5: country | J5: CPF on? | K5: note
A6: residency | B6: =IFERROR(INDEX(Personas!E$3:E$52,MATCH($B$2,Personas!$A$3:$A$52,0)),"") | C6: A · input | D6: Personas E. When CPF is on, Foreigner → rate 0. | F6: E · USER / FRONTEND OVERRIDE | I6: Singapore | J6: TRUE | K6: src/cpf.py applies. Citizen / PR contribute; Foreigner rate 0.
A7: age | B7: =IFERROR(INDEX(Personas!C$3:C$52,MATCH($B$2,Personas!$A$3:$A$52,0)),"") | C7: A · input | D7: Personas C. Age-band rate when CPF is on. | I7: Vietnam | J7: FALSE | K7: No CPF. Take-home = gross.
A8: incomeMonthly | B8: =IFERROR(INDEX(Personas!J$3:J$52,MATCH($B$2,Personas!$A$3:$A$52,0)),"") | C8: A · input | D8: Personas J (LLM or user overwrite). | I8: Malaysia | J8: FALSE | K8: No CPF. Take-home = gross.
I9: Thailand | J9: FALSE | K9: No CPF. Take-home = gross.
A10: D · ASSUMPTIONS — src/cpf.py (used only when CPF is on) | I10: Philippines | J10: FALSE | K10: No CPF. Take-home = gross.
A11: OW_CEILING | B11: 8000 | C11: D · assumption / shared | D11: Ordinary-wage ceiling. Employee CPF is on min(gross, this). | I11: Australia | J11: FALSE | K11: No CPF. Take-home = gross.
A12: cpfRate_to55 | B12: 0.2 | C12: D · assumption / shared | D12: Employee rate age ≤ 55. | I12: Germany | J12: FALSE | K12: No CPF. Take-home = gross.
A13: cpfRate_to60 | B13: 0.18 | C13: D · assumption / shared | D13: Age 56–60. | I13: Hong Kong | J13: FALSE | K13: No CPF. Take-home = gross.
A14: cpfRate_to65 | B14: 0.125 | C14: D · assumption / shared | D14: Age 61–65. | I14: United States | J14: FALSE | K14: No CPF. Take-home = gross.
A15: cpfRate_to70 | B15: 0.075 | C15: D · assumption / shared | D15: Age 66–70.
A16: cpfRate_over70 | B16: 0.05 | C16: D · assumption / shared | D16: Age > 70.
A18: E · OVERRIDE — blank = country switch. TRUE / FALSE forces CPF on or off
A19: CPF on? (override) | C19: E · user / frontend override | D19: TRUE / FALSE / blank. Blank uses the country table.
A21: C · DETERMINISTICALLY CALCULATED — src/cpf.py when on; identity when off
A22: CPF on (effective) | B22: =IF(B19="",IFERROR(VLOOKUP(B5,CpfCountrySwitch,2,FALSE),FALSE),B19) | C22: C · calculated | D22: Country table, unless the orange override is set.
A23: module used | B23: =IF(B22=TRUE,"SG-CPF (src/cpf.py)","default: no contribution, take-home = gross") | C23: C · calculated | D23: Plug-in interface. Other countries get their own module later; the rest of the model does not change.
A24: Singapore age-band rate | B24: =IF(LOWER(B6)="foreigner",0,IF(B7<=55,cpfRate_to55,IF(B7<=60,cpfRate_to60,IF(B7<=65,cpfRate_to65,IF(B7<=70,cpfRate_to70,cpfRate_over70))))) | C24: C · calculated | D24: employee_cpf_rate. Ignored when CPF is off.
A25: CPF rate used | B25: =IF(B22=TRUE,B24,0) | C25: C · calculated | D25: 0 when CPF is off for this country.
A26: employee CPF | B26: =IF(OR(B22<>TRUE,B8<=0,B25<=0),0,FLOOR(MIN(B8,OW_CEILING)*B25,1)) | C26: C · calculated | D26: floor(min(gross, ceiling) × rate). 0 if CPF off.
A27: take-home | B27: =IF(B8<=0,0,ROUND(MAX(0,B8-B26),2)) | C27: C · calculated | D27: Gross minus employee CPF. Equals income when CPF is off.

Sheet People Like You
A1: People Like You — selected persona. Spend, assets, home, life cover. Take-home comes from the CPF tab.
A2: Selected persona | B2: =SelectedPersona | C2: =IFERROR(INDEX(Personas!B$3:B$52,MATCH($B$2,Personas!$A$3:$A$52,0)),"") | D2: Follows the dropdown on the Selected persona tab. | F2: A · INPUT DATA
A3: Attribute | B3: Value | C3: Kind | D3: Source / formula | F3: B · LLM PREDICTED DATA
A4: A · INPUT DATA — About you from the selected Personas row | F4: C · DETERMINISTICALLY CALCULATED
A5: age | B5: =IFERROR(INDEX(Personas!C$3:C$52,MATCH($B$2,Personas!$A$3:$A$52,0)),"") | C5: A · input | D5: Personas C. Working years = age − 21. | F5: D · ASSUMPTIONS / SHARED DATA
A6: gender | B6: =IFERROR(INDEX(Personas!D$3:D$52,MATCH($B$2,Personas!$A$3:$A$52,0)),"") | C6: A · input | D6: Personas D. Not used by this component. | F6: E · USER / FRONTEND OVERRIDE
A7: residency | B7: =IFERROR(INDEX(Personas!E$3:E$52,MATCH($B$2,Personas!$A$3:$A$52,0)),"") | C7: A · input | D7: Personas E. Passed to the CPF tab (Foreigner → 0 when CPF is on).
A8: country | B8: =IFERROR(INDEX(Personas!F$3:F$52,MATCH($B$2,Personas!$A$3:$A$52,0)),"") | C8: A · input | D8: Personas F. CPF on/off is decided on the CPF tab.
A9: occupation | B9: =IFERROR(INDEX(Personas!G$3:G$52,MATCH($B$2,Personas!$A$3:$A$52,0)),"") | C9: A · input | D9: Personas G. Looks up income_anchors.json Singapore band.
A10: dependents | B10: =IFERROR(INDEX(Personas!H$3:H$52,MATCH($B$2,Personas!$A$3:$A$52,0)),"") | C10: A · input | D10: Personas H. Spend-share +5 pp each; 5× income life cover if > 0.
A11: maritalStatus (typed) | B11: =IFERROR(INDEX(Personas!I$3:I$52,MATCH($B$2,Personas!$A$3:$A$52,0)),"") | C11: A · input | D11: Personas I. Blank → infer below.
A13: B · LLM PREDICTED DATA — fields this component reads from Personas
A14: income (LLM gross monthly) | B14: =IFERROR(INDEX(Personas!J$3:J$52,MATCH($B$2,Personas!$A$3:$A$52,0)),"") | C14: B · LLM predicted | D14: Personas J. people_like_you_all_fields.json income.
A15: currency | B15: =IFERROR(INDEX(Personas!K$3:K$52,MATCH($B$2,Personas!$A$3:$A$52,0)),"") | C15: B · LLM predicted | D15: Personas K. SGD in this workbook.
A16: property (owns home) | B16: =IFERROR(INDEX(Personas!N$3:N$52,MATCH($B$2,Personas!$A$3:$A$52,0)),"") | C16: B · LLM predicted | D16: Personas N. seed_property_value if TRUE.
A17: life_expectancy (raw) | B17: =IFERROR(INDEX(Personas!V$3:V$52,MATCH($B$2,Personas!$A$3:$A$52,0)),"") | C17: B · LLM predicted | D17: Personas V. Capped at 99. Missing or ≤ 0 → 85.
A19: D · ASSUMPTIONS / SHARED DATA — named cells on Assumptions (CPF is on the CPF tab)
A20: spendShareBase | B20: =spendShareBase | C20: D · assumption / shared | D20: 67.5% of take-home.
A21: spendSharePerDependant | B21: =spendSharePerDependant | C21: D · assumption / shared | D21: +5 pp per dependant.
A22: spendShareCap | B22: =spendShareCap | C22: D · assumption / shared | D22: 90% cap.
A23: assetsSaveShare | B23: =assetsSaveShare | C23: D · assumption / shared | D23: 50% of annual surplus saved.
A24: workStartAge | B24: =workStartAge | C24: D · assumption / shared | D24: 21. Working years = max(0, age − 21).
A25: CASH_SAVINGS_SHARE | B25: =CASH_SAVINGS_SHARE | C25: D · assumption / shared | D25: src/predict.py 15% cash.
A26: INVESTMENTS_SHARE | B26: =INVESTMENTS_SHARE | C26: D · assumption / shared | D26: src/predict.py 85%.
A27: liabilityRatio | B27: =liabilityRatio | C27: D · assumption / shared | D27: PLU liabilities = liquid assets × 0.7 (not the mortgage).
A28: propertyLow (USD) | B28: =propertyLow | C28: D · assumption / shared | D28: income < propertyIncomeLow (USD).
A29: propertyMid (USD) | B29: =propertyMid | C29: D · assumption / shared | D29: income between the two USD bands.
A30: propertyHigh (USD) | B30: =propertyHigh | C30: D · assumption / shared | D30: income > propertyIncomeHigh (USD).
A31: propertyIncomeLow (USD) | B31: =propertyIncomeLow | C31: D · assumption / shared | D31: Monthly gross income in USD.
A32: propertyIncomeHigh (USD) | B32: =propertyIncomeHigh | C32: D · assumption / shared | D32: Monthly gross income in USD.
A33: PROPERTY_LTV | B33: =PROPERTY_LTV | C33: D · assumption / shared | D33: Mortgage = round(property × 55%).
A34: lifePremiumRate | B34: =lifePremiumRate | C34: D · assumption / shared | D34: 0.31% of sum assured.
A35: life cover step (user currency) | B35: =FX_lifeRound | C35: D · assumption / shared | D35: lifeRoundUnit (USD) as a nice step in user currency (FX tab).
A36: lifeExpectancyDefault | B36: =lifeExpectancyDefault | C36: D · assumption / shared | D36: Used when raw LE is missing or ≤ 0.
A38: C · DETERMINISTICALLY CALCULATED — _apply_plu. Take-home is read from the CPF tab.
A39: band min | B39: =IFERROR(INDEX(Assumptions!$F$6:$F$13,MATCH(B9,Assumptions!$E$6:$E$13,0)),"") | C39: C · calculated | D39: income_anchors.json Singapore min for occupation.
A40: band max | B40: =IFERROR(INDEX(Assumptions!$G$6:$G$13,MATCH(B9,Assumptions!$E$6:$E$13,0)),"") | C40: C · calculated | D40: income_anchors.json Singapore max.
A41: incomeMonthly (clamped) | B41: =IF(OR(B39="",B14=0),B14,MIN(MAX(B14,B39),B40)) | C41: C · calculated | D41: Clamp LLM income into the occupation band. 0 stays 0.
A42: CPF on (from CPF tab) | B42: =CPF_on | C42: A · input | D42: Country switch or orange override on the CPF tab.
A43: CPF rate | B43: =CPF_rate | C43: C · calculated | D43: 0 when CPF is off for this country.
A44: employee CPF | B44: =CPF_employee | C44: C · calculated | D44: 0 when CPF is off.
A45: take-home | B45: =CPF_takeHome | C45: C · calculated | D45: Gross minus employee CPF. Equals income when CPF is off.
A46: spend share | B46: =MIN(spendShareBase+spendSharePerDependant*MAX(0,B10),spendShareCap) | C46: C · calculated | D46: min(67.5% + 5pp × dependents, 90%).
A47: expenseMonthly | B47: =IF(B45<=0,0,ROUND(B45*B46,2)) | C47: C · calculated | D47: expenses_from_gross / spend of take-home.
A48: surplus / mo | B48: =B45-B47 | C48: C · calculated | D48: take-home − expense.
A49: working years | B49: =MAX(0,B5-workStartAge) | C49: C · calculated | D49: max(0, age − 21).
A50: liquid assets | B50: =IF(AND(B14>0,B47>0,B5>workStartAge),MAX(0,B48*12*assetsSaveShare*B49),0) | C50: C · calculated | D50: surplus × 12 × 0.5 × working years.
A51: PLU liabilities | B51: =B50*liabilityRatio | C51: C · calculated | D51: liquid × 0.7. Not the mortgage.
A52: cash (15%) | B52: =IF(MOD(B50*CASH_SAVINGS_SHARE,1)=0.5,2*ROUND((B50*CASH_SAVINGS_SHARE)/2,0),ROUND(B50*CASH_SAVINGS_SHARE,0)) | C52: C · calculated | D52: CASH_SAVINGS_SHARE. Python round (half to even).
A53: investments (85%) | B53: =IF(MOD(B50*INVESTMENTS_SHARE,1)=0.5,2*ROUND((B50*INVESTMENTS_SHARE)/2,0),ROUND(B50*INVESTMENTS_SHARE,0)) | C53: C · calculated | D53: INVESTMENTS_SHARE. Python round (half to even).
A54: income USD (home seed) | B54: =B14*FX_usdPerLocal | C54: C · calculated | D54: System currency: user currency × USD per 1.
A55: property USD | B55: =IF(B16=FALSE,0,IF(B54<propertyIncomeLow*FX_priceLevel,propertyLow,IF(B54<=propertyIncomeHigh*FX_priceLevel,propertyMid,propertyHigh))*FX_priceLevel) | C55: C · calculated | D55: seed_property_value on USD bands.
A56: property | B56: =ROUND(B55/FX_usdPerLocal,0) | C56: C · calculated | D56: Back to user currency.
A57: mortgage | B57: =IF(B56=0,0,IF(MOD(B56*PROPERTY_LTV,1)=0.5,2*ROUND((B56*PROPERTY_LTV)/2,0),ROUND(B56*PROPERTY_LTV,0))) | C57: C · calculated | D57: round(property × 55%).
A58: life sum assured | B58: =MAX(IF(B56>0,INT((B57+FX_lifeRound/2)/FX_lifeRound)*FX_lifeRound,0),IF(B10>0,IF(MOD(B14*12*5,1)=0.5,2*ROUND((B14*12*5)/2,0),ROUND(B14*12*5,0)),0)) | C58: C · calculated | D58: _assumed_life_policy: max(mortgage rounded to the life cover step, 5 × annual income if dependents).
A59: life premium | B59: =IF(B58<=0,0,IF(MOD(B58*lifePremiumRate,1)=0.5,2*ROUND((B58*lifePremiumRate)/2,0),ROUND(B58*lifePremiumRate,0))) | C59: C · calculated | D59: round(sum × 0.31%), half to even like Python (790.5 → 790).
A60: lifeExpectancy used | B60: =MIN(99,IF(B17>0,B17,lifeExpectancyDefault)) | C60: C · calculated | D60: min(raw, 99). Missing or ≤ 0 → 85.
A61: marital (inferred) | B61: =IF(IFERROR(INDEX(Personas!I$3:I$52,MATCH($B$2,Personas!$A$3:$A$52,0)),"")<>"",LOWER(IFERROR(INDEX(Personas!I$3:I$52,MATCH($B$2,Personas!$A$3:$A$52,0)),"")),IF(B5<30,"single","married")) | C61: C · calculated | D61: Typed maritalStatus, else age < 30 → single.
A63: E · USER / FRONTEND OVERRIDE — Personas W–AC (Money page). Blank keeps the green calculated value.
A64: override expenseMonthly | B64: =IFERROR(INDEX(Personas!W$3:W$52,MATCH($B$2,Personas!$A$3:$A$52,0)),"") | C64: E · user / frontend override | D64: Money page spend. Frontend MIN_EXPENSE_MONTHLY = 100 SGD.
A65: override cash | B65: =IFERROR(INDEX(Personas!X$3:X$52,MATCH($B$2,Personas!$A$3:$A$52,0)),"") | C65: E · user / frontend override | D65: Cash & Savings. Provenance key cash / savings.
A66: override investments | B66: =IFERROR(INDEX(Personas!Y$3:Y$52,MATCH($B$2,Personas!$A$3:$A$52,0)),"") | C66: E · user / frontend override | D66: Investments.
A67: override property value | B67: =IFERROR(INDEX(Personas!Z$3:Z$52,MATCH($B$2,Personas!$A$3:$A$52,0)),"") | C67: E · user / frontend override | D67: Home value. Distinct from owns-home flag N.
A68: override mortgage | B68: =IFERROR(INDEX(Personas!AA$3:AA$52,MATCH($B$2,Personas!$A$3:$A$52,0)),"") | C68: E · user / frontend override | D68: Money page loans.
A69: override PLU liabilities | B69: =IFERROR(INDEX(Personas!AB$3:AB$52,MATCH($B$2,Personas!$A$3:$A$52,0)),"") | C69: E · user / frontend override | D69: Need Profiler TotalLiabilities. Not the mortgage.
A70: override life sum assured | B70: =IFERROR(INDEX(Personas!AC$3:AC$52,MATCH($B$2,Personas!$A$3:$A$52,0)),"") | C70: E · user / frontend override | D70: Existing Life Protection cover.
A72: C · EFFECTIVE SESSION — override if set, else calculated. Downstream and Validation read these.
A73: incomeMonthly | B73: =B14 | C73: C · calculated | D73: Personas J (LLM or user). The clamp row above is what /predict would force.
A74: expenseMonthly | B74: =IF(IFERROR(INDEX(Personas!W$3:W$52,MATCH($B$2,Personas!$A$3:$A$52,0)),"")="",B47,IFERROR(INDEX(Personas!W$3:W$52,MATCH($B$2,Personas!$A$3:$A$52,0)),"")) | C74: C · calculated
A75: take-home | B75: =B45 | C75: C · calculated | D75: From Personas J and CPF.
A76: surplus / mo | B76: =B75-B74 | C76: C · calculated
A77: cash | B77: =IF(IFERROR(INDEX(Personas!X$3:X$52,MATCH($B$2,Personas!$A$3:$A$52,0)),"")="",B52,IFERROR(INDEX(Personas!X$3:X$52,MATCH($B$2,Personas!$A$3:$A$52,0)),"")) | C77: C · calculated
A78: investments | B78: =IF(IFERROR(INDEX(Personas!Y$3:Y$52,MATCH($B$2,Personas!$A$3:$A$52,0)),"")="",B53,IFERROR(INDEX(Personas!Y$3:Y$52,MATCH($B$2,Personas!$A$3:$A$52,0)),"")) | C78: C · calculated
A79: liquid assets | B79: =B77+B78 | C79: C · calculated | D79: cash + investments.
A80: property | B80: =IF(IFERROR(INDEX(Personas!Z$3:Z$52,MATCH($B$2,Personas!$A$3:$A$52,0)),"")="",B56,IFERROR(INDEX(Personas!Z$3:Z$52,MATCH($B$2,Personas!$A$3:$A$52,0)),"")) | C80: C · calculated
A81: mortgage | B81: =IF(IFERROR(INDEX(Personas!AA$3:AA$52,MATCH($B$2,Personas!$A$3:$A$52,0)),"")="",B57,IFERROR(INDEX(Personas!AA$3:AA$52,MATCH($B$2,Personas!$A$3:$A$52,0)),"")) | C81: C · calculated
A82: PLU liabilities | B82: =IF(IFERROR(INDEX(Personas!AB$3:AB$52,MATCH($B$2,Personas!$A$3:$A$52,0)),"")="",B51,IFERROR(INDEX(Personas!AB$3:AB$52,MATCH($B$2,Personas!$A$3:$A$52,0)),"")) | C82: C · calculated
A83: life sum assured | B83: =IF(IFERROR(INDEX(Personas!AC$3:AC$52,MATCH($B$2,Personas!$A$3:$A$52,0)),"")="",B58,IFERROR(INDEX(Personas!AC$3:AC$52,MATCH($B$2,Personas!$A$3:$A$52,0)),"")) | C83: C · calculated
A84: life premium | B84: =IF(B83<=0,0,IF(MOD(B83*lifePremiumRate,1)=0.5,2*ROUND((B83*lifePremiumRate)/2,0),ROUND(B83*lifePremiumRate,0))) | C84: C · calculated | D84: Recomputed from effective sum.
A85: currency | B85: =IFERROR(INDEX(Personas!K$3:K$52,MATCH($B$2,Personas!$A$3:$A$52,0)),"") | C85: B · LLM predicted | D85: Personas K. FX converts with this ISO code.

Sheet Need Profiler
A1: Need Profiler — selected persona. Weighted scores → two protection + N_RET + one growth. Parked coverage needs are scored only.
A2: Selected persona | B2: =SelectedPersona | C2: =IFERROR(INDEX(Personas!B$3:B$52,MATCH($B$2,Personas!$A$3:$A$52,0)),"") | D2: Follows the dropdown on the Selected persona tab. | F2: A · INPUT DATA
A3: Attribute | B3: Value | C3: Kind | D3: Source / formula | F3: B · LLM PREDICTED DATA
A4: A · INPUT DATA — from selected Personas + People Like You results | F4: C · DETERMINISTICALLY CALCULATED
A5: age | B5: =IFERROR(INDEX(Personas!C$3:C$52,MATCH($B$2,Personas!$A$3:$A$52,0)),"") | C5: A · input | D5: Personas C. Bucket <21 / ≤30 / ≤40 / else. | F5: D · ASSUMPTIONS / SHARED DATA
A6: gender | B6: =IFERROR(INDEX(Personas!D$3:D$52,MATCH($B$2,Personas!$A$3:$A$52,0)),"") | C6: A · input | D6: Personas D. male=3, female=2. | F6: E · USER / FRONTEND OVERRIDE
A7: dependents | B7: =IFERROR(INDEX(Personas!H$3:H$52,MATCH($B$2,Personas!$A$3:$A$52,0)),"") | C7: A · input | D7: Personas H. 0 / 1 / ≥2 → 0 / 2 / 4.
A8: occupation | B8: =IFERROR(INDEX(Personas!G$3:G$52,MATCH($B$2,Personas!$A$3:$A$52,0)),"") | C8: A · input | D8: Personas G. Self-employed tokens → 2, else 1.
A9: incomeMonthly (from PLU) | B9: =PLU_incomeMonthly | C9: A · input | D9: People Like You calculated income, used as profiler Income.
A10: expenseMonthly (from PLU) | B10: =PLU_expenseMonthly | C10: A · input | D10: People Like You calculated spend.
A11: liquid assets (from PLU) | B11: =PLU_cash+PLU_investments | C11: A · input | D11: cash + investments.
A12: PLU liabilities (from PLU) | B12: =PLU_liabilities | C12: A · input | D12: Not the mortgage.
A14: B · LLM PREDICTED DATA — lifestyle flags this component reads
A15: is_smoker | B15: =IFERROR(INDEX(Personas!U$3:U$52,MATCH($B$2,Personas!$A$3:$A$52,0)),"") | C15: B · LLM predicted | D15: Personas U. TRUE→3, else 1 (JSON has no Smoking options).
A16: hospitalization_type | B16: =IFERROR(INDEX(Personas!Q$3:Q$52,MATCH($B$2,Personas!$A$3:$A$52,0)),"") | C16: B · LLM predicted | D16: Personas Q. private=4, public=2.
A17: ward_type | B17: =IFERROR(INDEX(Personas!P$3:P$52,MATCH($B$2,Personas!$A$3:$A$52,0)),"") | C17: B · LLM predicted | D17: Personas P. A=3, B=2. Single/Double/Ward score 0.
A18: retirement_lifestyle | B18: =IFERROR(INDEX(Personas!T$3:T$52,MATCH($B$2,Personas!$A$3:$A$52,0)),"") | C18: B · LLM predicted | D18: Personas T. frugal / stress-free / only the best.
A19: sports | B19: =IFERROR(INDEX(Personas!S$3:S$52,MATCH($B$2,Personas!$A$3:$A$52,0)),"") | C19: B · LLM predicted | D19: Personas S. Adventurous / I dont do sports / Life style.
A20: property (owns home) | B20: =IFERROR(INDEX(Personas!N$3:N$52,MATCH($B$2,Personas!$A$3:$A$52,0)),"") | C20: B · LLM predicted | D20: Personas N. V0-16: no longer swaps N_SAV / N_PRP (not used for selection).
A22: D · ASSUMPTIONS / SHARED DATA — used by this component
A23: Existing hospital cover | B23: 0 | C23: D · assumption / shared | D23: build_profiler_profile hard-codes Existing*Coverage = False → option weight 1.
A24: Existing disability cover | B24: 0 | C24: D · assumption / shared | D24: Same. Stored as 0 here; option weight of False is 1.
A25: USD per 1 local | B25: =FX_usdPerLocal | C25: D · assumption / shared | D25: From the FX tab. Income / expense / assets / liabilities convert local × this rate.
A26: Selection rule | B26: 2 prot + N_RET + 1 growth | C26: D · assumption / shared | D26: V0-16: protection from N_INC/N_CRI/N_TPD/N_HOS/N_PAC; growth N_EDU vs N_SAV. N_PRP is never auto-picked (no profiler label).
A27: Profiler weight matrix | B27: Assumptions!B90:L104 | C27: D · assumption / shared | D27: Need_profiler.json needs_factor_weights. SUMPRODUCT with option weights.
A29: C · DETERMINISTICALLY CALCULATED — local × FX → USD, then 15 option weights
A30: usd Income | B30: =IF(FX_usdPerLocal="","",PLU_incomeMonthly*FX_usdPerLocal) | C30: C · calculated | D30: local income × FX. S$5,000 × 0.74 ≈ 3,700 USD → Income weight 2.
A31: usd Expense | B31: =IF(FX_usdPerLocal="","",PLU_expenseMonthly*FX_usdPerLocal) | C31: C · calculated | D31: local expense × FX.
A32: usd Assets | B32: =IF(FX_usdPerLocal="","",(PLU_cash+PLU_investments)*FX_usdPerLocal) | C32: C · calculated | D32: cash + investments × FX.
A33: usd Liab | B33: =IF(FX_usdPerLocal="","",PLU_liabilities*FX_usdPerLocal) | C33: C · calculated | D33: PLU liabilities × FX.
A34: ow Age | B34: =IF(B5<21,1,IF(B5<=30,2,IF(B5<=40,3,4))) | C34: C · calculated | D34: _get_option_weight Date of Birth.
A35: ow Gender | B35: =IF(LOWER(B6)="male",3,IF(LOWER(B6)="female",2,0)) | C35: C · calculated | D35: male=3, female=2.
A36: ow Deps | B36: =IF(B7=0,0,IF(B7=1,2,4)) | C36: C · calculated | D36: 0 / 1 / else.
A37: ow Occ | B37: =IF(OR(ISNUMBER(SEARCH("self",B8)),ISNUMBER(SEARCH("entrepreneur",B8)),ISNUMBER(SEARCH("own business",B8)),ISNUMBER(SEARCH("freelance",B8))),2,1) | C37: C · calculated | D37: Self-employed tokens.
A38: ow Smoke | B38: =IF(B15=TRUE,3,1) | C38: C · calculated | D38: No Smoking options in JSON.
A39: ow Income | B39: =IF(B30<1000,4,IF(B30<2500,3,IF(B30<5000,2,IF(B30<10000,1,0)))) | C39: C · calculated | D39: Need_profiler.json Income lt bands (USD after FX).
A40: ow Expense | B40: =IF(B31<600,4,IF(B31<1500,3,IF(B31<3000,2,IF(B31<6000,1,0)))) | C40: C · calculated | D40: Expense USD bands (~0.6× income).
A41: ow Assets | B41: =IF(B32<10000,4,IF(B32<50000,3,IF(B32<150000,2,IF(B32<500000,1,0)))) | C41: C · calculated | D41: Assets USD bands (stock).
A42: ow Liab | B42: =IF(B33<5000,4,IF(B33<25000,3,IF(B33<100000,2,IF(B33<250000,1,0)))) | C42: C · calculated | D42: Liabilities USD bands (stock).
A43: ow HospExist | B43: 1 | C43: C · calculated | D43: Existing hospital coverage always False → 1.
A44: ow DisExist | B44: 1 | C44: C · calculated | D44: Existing disability coverage always False → 1.
A45: ow HospType | B45: =IF(LOWER(B16)="private",4,IF(LOWER(B16)="public",2,0)) | C45: C · calculated | D45: Hospital Type.
A46: ow Ward | B46: =IF(UPPER(B17)="A",3,IF(UPPER(B17)="B",2,0)) | C46: C · calculated | D46: Ward Type.
A47: ow Lifestyle | B47: =IF(LOWER(B18)="frugal",1,IF(OR(LOWER(B18)="stress-free",LOWER(B18)="stress free"),2,IF(LOWER(B18)="only the best",4,0))) | C47: C · calculated | D47: Basic/Comfortable/Luxurious score 0.
A48: ow Sports | B48: =IF(ISNUMBER(SEARCH("adventurous",B19)),4,IF(ISNUMBER(SEARCH("dont do sports",B19)),0,IF(ISNUMBER(SEARCH("life style",B19)),1,0))) | C48: C · calculated | D48: Free-text sports.
A50: C · RESULTS — raw Σ (factor × option), then min–max scale 0–10
A51: raw Life Protection | B51: =ROUND(SUMPRODUCT($B$34:$B$48,Assumptions!B$90:B$104),2) | C51: C · calculated | D51: Need_profiler.json column Life Protection.
A52: raw Critical Illness | B52: =ROUND(SUMPRODUCT($B$34:$B$48,Assumptions!C$90:C$104),2) | C52: C · calculated | D52: Need_profiler.json column Critical Illness.
A53: raw TPD | B53: =ROUND(SUMPRODUCT($B$34:$B$48,Assumptions!D$90:D$104),2) | C53: C · calculated | D53: Need_profiler.json column Disability. Shown as TPD.
A54: raw Retirement | B54: =ROUND(SUMPRODUCT($B$34:$B$48,Assumptions!E$90:E$104),2) | C54: C · calculated | D54: Need_profiler.json column Retirement.
A55: raw Education | B55: =ROUND(SUMPRODUCT($B$34:$B$48,Assumptions!F$90:F$104),2) | C55: C · calculated | D55: Need_profiler.json column Education.
A56: raw Hospitalization | B56: =ROUND(SUMPRODUCT($B$34:$B$48,Assumptions!G$90:G$104),2) | C56: C · calculated | D56: Need_profiler.json column Hospitalization.
A57: raw General Savings | B57: =ROUND(SUMPRODUCT($B$34:$B$48,Assumptions!H$90:H$104),2) | C57: C · calculated | D57: Need_profiler.json column General Savings.
A58: raw Personal Accident | B58: =ROUND(SUMPRODUCT($B$34:$B$48,Assumptions!I$90:I$104),2) | C58: C · calculated | D58: Need_profiler.json column Personal Accident.
A59: raw Car Protection | B59: =ROUND(SUMPRODUCT($B$34:$B$48,Assumptions!J$90:J$104),2) | C59: C · calculated | D59: Need_profiler.json column Car Protection.
A60: raw Home Protection | B60: =ROUND(SUMPRODUCT($B$34:$B$48,Assumptions!K$90:K$104),2) | C60: C · calculated | D60: Need_profiler.json column Home Protection.
A61: raw Travel Protection | B61: =ROUND(SUMPRODUCT($B$34:$B$48,Assumptions!L$90:L$104),2) | C61: C · calculated | D61: Need_profiler.json column Travel Protection.
A62: min raw | B62: =MIN(B51:B61) | C62: C · calculated | D62: scale_scores min.
A63: max raw | B63: =MAX(B51:B61) | C63: C · calculated | D63: If max=min, divisor is forced to 1 so every scaled value is 0.
A64: scaled Life Protection | B64: =ROUND(((B51-B62)/IF(B63>B62,B63-B62,1))*10,1) | C64: C · calculated | D64: 0–10, 1 decimal.
A65: scaled Critical Illness | B65: =ROUND(((B52-B62)/IF(B63>B62,B63-B62,1))*10,1) | C65: C · calculated | D65: 0–10, 1 decimal.
A66: scaled TPD | B66: =ROUND(((B53-B62)/IF(B63>B62,B63-B62,1))*10,1) | C66: C · calculated | D66: 0–10, 1 decimal.
A67: scaled Retirement | B67: =ROUND(((B54-B62)/IF(B63>B62,B63-B62,1))*10,1) | C67: C · calculated | D67: 0–10, 1 decimal.
A68: scaled Education | B68: =ROUND(((B55-B62)/IF(B63>B62,B63-B62,1))*10,1) | C68: C · calculated | D68: 0–10, 1 decimal.
A69: scaled Hospitalization | B69: =ROUND(((B56-B62)/IF(B63>B62,B63-B62,1))*10,1) | C69: C · calculated | D69: 0–10, 1 decimal.
A70: scaled General Savings | B70: =ROUND(((B57-B62)/IF(B63>B62,B63-B62,1))*10,1) | C70: C · calculated | D70: 0–10, 1 decimal.
A71: scaled Personal Accident | B71: =ROUND(((B58-B62)/IF(B63>B62,B63-B62,1))*10,1) | C71: C · calculated | D71: 0–10, 1 decimal.
A72: scaled Car Protection | B72: =ROUND(((B59-B62)/IF(B63>B62,B63-B62,1))*10,1) | C72: C · calculated | D72: 0–10, 1 decimal.
A73: scaled Home Protection | B73: =ROUND(((B60-B62)/IF(B63>B62,B63-B62,1))*10,1) | C73: C · calculated | D73: 0–10, 1 decimal.
A74: scaled Travel Protection | B74: =ROUND(((B61-B62)/IF(B63>B62,B63-B62,1))*10,1) | C74: C · calculated | D74: 0–10, 1 decimal.
A76: tb N_INC | B76: =B64+0.005 | C76: C · calculated | D76: Tie-break bonus. Life Protection first in label order.
A77: tb N_CRI | B77: =B65+0.004 | C77: C · calculated | D77: Tie-break bonus. Critical Illness second.
A78: tb N_TPD | B78: =B66+0.003 | C78: C · calculated | D78: Tie-break bonus. TPD third.
A79: tb N_HOS | B79: =B69+0.002 | C79: C · calculated | D79: Tie-break bonus. Hospitalization fourth.
A80: tb N_PAC | B80: =B71+0.001 | C80: C · calculated | D80: Tie-break bonus. Personal Accident last (V0-16).
A81: prot1 | B81: =IF(B76=MAX(B76,B77,B78,B79,B80),"N_INC",IF(B77=MAX(B76,B77,B78,B79,B80),"N_CRI",IF(B78=MAX(B76,B77,B78,B79,B80),"N_TPD",IF(B79=MAX(B76,B77,B78,B79,B80),"N_HOS","N_PAC")))) | C81: C · calculated | D81: Highest protection score after the order bonus.
A82: tb2 N_INC | B82: =IF(B81="N_INC",-1,B64+0.005) | C82: C · calculated | D82: Winner of prot1 is excluded.
A83: tb2 N_CRI | B83: =IF(B81="N_CRI",-1,B65+0.004) | C83: C · calculated | D83: Winner of prot1 is excluded.
A84: tb2 N_TPD | B84: =IF(B81="N_TPD",-1,B66+0.003) | C84: C · calculated | D84: Winner of prot1 is excluded.
A85: tb2 N_HOS | B85: =IF(B81="N_HOS",-1,B69+0.002) | C85: C · calculated | D85: Winner of prot1 is excluded.
A86: tb2 N_PAC | B86: =IF(B81="N_PAC",-1,B71+0.001) | C86: C · calculated | D86: Winner of prot1 is excluded.
A87: prot2 | B87: =IF(B82=MAX(B82,B83,B84,B85,B86),"N_INC",IF(B83=MAX(B82,B83,B84,B85,B86),"N_CRI",IF(B84=MAX(B82,B83,B84,B85,B86),"N_TPD",IF(B85=MAX(B82,B83,B84,B85,B86),"N_HOS","N_PAC")))) | C87: C · calculated | D87: Second protection.
A88: tb N_EDU | B88: =B68+0.002 | C88: C · calculated | D88: Education first on a tie.
A89: tb N_SAV | B89: =B70+0.001 | C89: C · calculated | D89: General Savings second.
A90: grow2 | B90: =IF(B88>=B89,"N_EDU","N_SAV") | C90: C · calculated | D90: Second growth after forced N_RET. V0-16: N_EDU vs N_SAV only; no home-ownership swap; N_PRP never auto-picked.
A92: C · RESULTS — nine calculator needs, then three parked coverage needs (scored, no calculator)
A93: type | B93: calc on | C93: Enable? | D93: on (effective) | E93: priority | F93: scaled score
A94: N_INC | B94: =OR($B$81="N_INC",$B$87="N_INC") | D94: =IF(C94="",B94,C94) | E94: =IF(B64>7,5,3) | F94: =B64
A95: N_CRI | B95: =OR($B$81="N_CRI",$B$87="N_CRI") | D95: =IF(C95="",B95,C95) | E95: =IF(B65>7,5,3) | F95: =B65
A96: N_TPD | B96: =OR($B$81="N_TPD",$B$87="N_TPD") | D96: =IF(C96="",B96,C96) | E96: =IF(B66>7,5,3) | F96: =B66
A97: N_HOS | B97: =OR($B$81="N_HOS",$B$87="N_HOS") | D97: =IF(C97="",B97,C97) | E97: =IF(B69>7,5,3) | F97: =B69
A98: N_PAC | B98: =OR($B$81="N_PAC",$B$87="N_PAC") | D98: =IF(C98="",B98,C98) | E98: =IF(B71>7,5,3) | F98: =B71
A99: N_RET | B99: =TRUE() | D99: =IF(C99="",B99,C99) | E99: =IF(B67>7,5,3) | F99: =B67
A100: N_EDU | B100: =$B$90="N_EDU" | D100: =IF(C100="",B100,C100) | E100: =IF(B68>7,5,3) | F100: =B68
A101: N_SAV | B101: =$B$90="N_SAV" | D101: =IF(C101="",B101,C101) | E101: =IF(B70>7,5,3) | F101: =B70
A102: N_PRP | B102: =FALSE() | D102: =IF(C102="",B102,C102) | E102: 3 | F102: no label
A103: N_HOM | B103: parked | D103: coverage need | E103: =IF(B73>7,5,3) | F103: =B73
A104: N_CAR | B104: parked | D104: coverage need | E104: =IF(B72>7,5,3) | F104: =B72
A105: N_TRV | B105: parked | D105: coverage need | E105: =IF(B74>7,5,3) | F105: =B74
A106: N_PRP (home purchase) is never switched on by the profiler: there is no home-purchase label. Enable? = TRUE switches it on.

Sheet Need Calculator
A1: Need Calculator — selected persona. Runs in USD (S-block), results back in user currency. Orange cells are goal-card sliders (user currency).
A2: Selected persona | B2: =SelectedPersona | C2: =IFERROR(INDEX(Personas!B$3:B$52,MATCH($B$2,Personas!$A$3:$A$52,0)),"") | D2: Follows the dropdown on the Selected persona tab. | F2: A · INPUT DATA
A3: Attribute | B3: Value | C3: Kind | D3: Source / formula | F3: B · LLM PREDICTED DATA
A4: A · INPUT DATA — from Personas, People Like You, and Need Profiler | F4: C · DETERMINISTICALLY CALCULATED
A5: age | B5: =IFERROR(INDEX(Personas!C$3:C$52,MATCH($B$2,Personas!$A$3:$A$52,0)),"") | C5: A · input | D5: Personas C. | F5: D · ASSUMPTIONS / SHARED DATA
A6: incomeMonthly (from PLU) | B6: =PLU_incomeMonthly | C6: A · input | D6: Clamped gross monthly. | F6: E · USER / FRONTEND OVERRIDE
A7: expenseMonthly (from PLU) | B7: =PLU_expenseMonthly | C7: A · input | D7: Annual spend = this × 12.
A8: mortgage (from PLU) | B8: =PLU_mortgage | C8: A · input | D8: Added to N_INC amount.
A9: life sum (from PLU) | B9: =PLU_lifeSum | C9: A · input | D9: N_INC have.
A10: investments (from PLU) | B10: =PLU_investments | C10: A · input | D10: Tagged wealth pot only. Cash is never allocated.
A11: lifeExpectancy used (from PLU) | B11: =PLU_leUsed | C11: A · input | D11: yearsInRet = max(0, LE − retAge).
A13: O · GOAL-CARD SLIDERS / OVERRIDES — orange. Blank years keep the age rule
A14: lifestyle (1/2/3) | B14: 2 | C14: E · user / frontend override | D14: 1=frugal, 2=stress-free, 3=only the best. Default 2.
A15: retAge | B15: =ageOfRetirement | C15: E · user / frontend override | D15: Default from Assumptions (65).
A16: targetYear | B16: =currentYear+EDU_YEARS_DEFAULT | C16: E · user / frontend override | D16: Education horizon year.
A17: bequest | B17: 0 | C17: E · user / frontend override | D17: Added to N_INC amount.
A18: dependYears (blank = age rule) | C18: E · user / frontend override | D18: Blank or ≤0 → supportYears.
A19: incomeReplace (blank = income) | C19: E · user / frontend override | D19: Blank → incomeMonthly for CI / TPD.
A20: N_SAV stored | B20: 0 | C20: E · user / frontend override | D20: If > 0, this is N_SAV amount; else 1× annual income.
A21: N_PRP stored | B21: 0 | C21: E · user / frontend override | D21: If > 0, this is N_PRP amount; else 5× annual income.
A22: tag N_RET | B22: 0 | C22: E · user / frontend override | D22: Investments tagged to retirement, then grown at realReturn.
A23: tag N_EDU | B23: 0 | C23: E · user / frontend override | D23: apply_investment_pot walk order: RET, EDU, SAV, PRP.
A24: tag N_SAV | B24: 0 | C24: E · user / frontend override | D24: Takes from remaining investments after RET and EDU.
A25: tag N_PRP | B25: 0 | C25: E · user / frontend override | D25: Last in the walk.
A27: S · SYSTEM CURRENCY (USD) — user-currency inputs × USD per 1. The calculator below runs on these
A28: USD per 1 user-currency unit | B28: =FX_usdPerLocal | C28: D · assumption / shared | D28: FX tab. #N/A if the currency is unknown.
A29: price level (option B) | B29: =FX_priceLevel | C29: D · assumption / shared | D29: 1 under option A. Scales the USD fixed amounts.
A30: incomeMonthly USD | B30: =PLU_incomeMonthly*B28 | C30: C · calculated
A31: expenseMonthly USD | B31: =PLU_expenseMonthly*B28 | C31: C · calculated
A32: mortgage USD | B32: =PLU_mortgage*B28 | C32: C · calculated
A33: life sum USD | B33: =PLU_lifeSum*B28 | C33: C · calculated
A34: investments USD | B34: =PLU_investments*B28 | C34: C · calculated
A35: bequest USD | B35: =B17*B28 | C35: C · calculated
A36: N_SAV stored USD | B36: =B20*B28 | C36: C · calculated
A37: N_PRP stored USD | B37: =B21*B28 | C37: C · calculated
A38: tag N_RET USD | B38: =B22*B28 | C38: C · calculated
A39: tag N_EDU USD | B39: =B23*B28 | C39: C · calculated
A40: tag N_SAV USD | B40: =B24*B28 | C40: C · calculated
A41: tag N_PRP USD | B41: =B25*B28 | C41: C · calculated
A42: incomeReplace USD | B42: =IF(B19="","",B19*B28) | C42: C · calculated | D42: Blank → income.
A43: CRI_COST USD (× price level) | B43: =CRI_COST*B29 | C43: C · calculated | D43: Fixed amount, USD.
A44: TPD_COST USD (× price level) | B44: =TPD_COST*B29 | C44: C · calculated | D44: Fixed amount, USD.
A45: EDU_COST USD (× price level) | B45: =EDU_COST*B29 | C45: C · calculated | D45: Fixed amount, USD.
A46: PAC_COST USD (× price level) | B46: =PAC_COST*B29 | C46: C · calculated | D46: Fixed amount, USD.
A48: D · ASSUMPTIONS / SHARED DATA — rates and need parameters
A49: inflationRate | B49: =inflationRate | C49: D · assumption / shared | D49: Grows EDU cost. N_RET grows at realReturn, not inflation.
A50: investmentReturn | B50: =investmentReturn | C50: D · assumption / shared | D50: Used to form realReturn.
A51: realReturn | B51: =realReturn | C51: D · assumption / shared | D51: max(0, (1+i)/(1+π) − 1). Discount rate.
A52: RET_LIFESTYLE_FRUGAL | B52: =RET_LIFESTYLE_FRUGAL | C52: D · assumption / shared | D52: N_RET spend multiple when lifestyle=1.
A53: RET_LIFESTYLE_STRESSFREE | B53: =RET_LIFESTYLE_STRESSFREE | C53: D · assumption / shared | D53: Default lifestyle=2.
A54: RET_LIFESTYLE_ONLYTHEBEST | B54: =RET_LIFESTYLE_ONLYTHEBEST | C54: D · assumption / shared | D54: lifestyle=3.
A55: INC_SUPPORT_MIN / Max / Pivot | B55: =INC_SUPPORT_MIN | C55: D · assumption / shared | D55: supportYears = min(max(10, 50 − age), 25).
A56: CRI_YEARS / CRI_COST | B56: =CRI_YEARS | C56: D · assumption / shared | D56: 3 years annuity-due + CRI_COST (USD, S-block).
A57: TPD_YEARS / TPD_COST | B57: =TPD_YEARS | C57: D · assumption / shared | D57: 5 years annuity-due + TPD_COST (USD, S-block).
A58: PAC_YEARS / PAC_COST | B58: =PAC_YEARS | C58: D · assumption / shared | D58: 1 year annuity-due + PAC_COST (USD, S-block). Agreed V0-18.
A59: HOS_MONTHS | B59: =HOS_MONTHS | C59: D · assumption / shared | D59: N_HOS = income × 6.
A60: EDU_COST (USD) | B60: =EDU_COST | C60: D · assumption / shared | D60: USD course cost, grown at inflation.
A61: SAV_INCOME_MULT | B61: =SAV_INCOME_MULT | C61: D · assumption / shared | D61: 1 × annual income if stored is 0.
A62: PRP_INCOME_MULT | B62: =PRP_INCOME_MULT | C62: D · assumption / shared | D62: 5 × annual income if stored is 0.
A63: currentYear / ageOfRetirement | B63: =currentYear | C63: D · assumption / shared | D63: 2026 / 65 in this workbook.
A65: C · DETERMINISTICALLY CALCULATED — horizons
A66: supportYears | B66: =MIN(MAX(INC_SUPPORT_MIN,INC_SUPPORT_PIVOT_AGE-B5),INC_SUPPORT_MAX) | C66: C · calculated | D66: life_support_years(age).
A67: yearsToRet | B67: =MAX(0,B15-B5) | C67: C · calculated | D67: years_to_retirement.
A68: yearsInRet | B68: =MAX(0,PLU_leUsed-B15) | C68: C · calculated | D68: years_in_retirement(retAge, session LE).
A69: eduYears | B69: =MAX(0,B16-currentYear) | C69: C · calculated | D69: max(0, targetYear − thisYear).
A71: C · RESULTS — amount / have / gap for every UNIFIED type (even when off)
A72: type | B72: needAmount | C72: have | D72: gap | E72: Enable? | F72: on (effective) | H72: needAmount USD | I72: have USD | J72: gap USD
A73: N_INC | B73: =ROUND(H73/$B$28,0) | C73: =ROUND(I73/$B$28,0) | D73: =MAX(0,B73-C73) | F73: =IF(E73="",NP_on_N_INC,E73) | G73: bequest + mortgage + PV of annual spend over dependYears. | H73: =MAX(0,B35+B32+IF(OR((IF(OR(B18="",B18<=0),B66,B18))<=0,(B31*12)<=0),0,IF(ABS(realReturn)<1E-12,(B31*12)*(IF(OR(B18="",B18<=0),B66,B18)),(B31*12)*(1-(1+realReturn)^(-(IF(OR(B18="",B18<=0),B66,B18))))/(realReturn)))) | I73: =B33 | J73: =MAX(0,H73-I73)
A74: N_CRI | B74: =ROUND(H74/$B$28,0) | C74: =ROUND(I74/$B$28,0) | D74: =MAX(0,B74-C74) | F74: =IF(E74="",NP_on_N_CRI,E74) | G74: Annuity-due of replacement income for CRI_YEARS + CRI_COST. | H74: =MAX(0,IF(OR((CRI_YEARS)<=0,((IF(B42="",B30,B42))*12)<=0),0,IF(ABS(realReturn)<1E-12,((IF(B42="",B30,B42))*12)*(CRI_YEARS),((IF(B42="",B30,B42))*12)*(1-(1/((1+realReturn)))^(CRI_YEARS))/(1-(1/((1+realReturn))))))+B43) | I74: =0 | J74: =MAX(0,H74-I74)
A75: N_TPD | B75: =ROUND(H75/$B$28,0) | C75: =ROUND(I75/$B$28,0) | D75: =MAX(0,B75-C75) | F75: =IF(E75="",NP_on_N_TPD,E75) | G75: Annuity-due of replacement income for TPD_YEARS + TPD_COST. | H75: =MAX(0,IF(OR((TPD_YEARS)<=0,((IF(B42="",B30,B42))*12)<=0),0,IF(ABS(realReturn)<1E-12,((IF(B42="",B30,B42))*12)*(TPD_YEARS),((IF(B42="",B30,B42))*12)*(1-(1/((1+realReturn)))^(TPD_YEARS))/(1-(1/((1+realReturn))))))+B44) | I75: =0 | J75: =MAX(0,H75-I75)
A76: N_HOS | B76: =ROUND(H76/$B$28,0) | C76: =ROUND(I76/$B$28,0) | D76: =MAX(0,B76-C76) | F76: =IF(E76="",NP_on_N_HOS,E76) | G76: incomeMonthly × HOS_MONTHS. | H76: =MAX(0,B30*HOS_MONTHS) | I76: =0 | J76: =MAX(0,H76-I76)
A77: N_PAC | B77: =ROUND(H77/$B$28,0) | C77: =ROUND(I77/$B$28,0) | D77: =MAX(0,B77-C77) | F77: =IF(E77="",NP_on_N_PAC,E77) | G77: Annuity-due of replacement income for PAC_YEARS + PAC_COST. | H77: =MAX(0,IF(OR((PAC_YEARS)<=0,((IF(B42="",B30,B42))*12)<=0),0,IF(ABS(realReturn)<1E-12,((IF(B42="",B30,B42))*12)*(PAC_YEARS),((IF(B42="",B30,B42))*12)*(1-(1/((1+realReturn)))^(PAC_YEARS))/(1-(1/((1+realReturn))))))+B46) | I77: =0 | J77: =MAX(0,H77-I77)
A78: N_RET | B78: =ROUND(H78/$B$28,0) | C78: =ROUND(I78/$B$28,0) | D78: =MAX(0,B78-C78) | F78: =IF(E78="",NP_on_N_RET,E78) | G78: annualSpend × (1+realReturn)^T × a(realReturn, yearsInRet). | H78: =MAX(0,IF(OR((B68)<=0,(IF((B67)<=0,MAX(0,B31*12*(IF(B14=1,RET_LIFESTYLE_FRUGAL,IF(B14=3,RET_LIFESTYLE_ONLYTHEBEST,RET_LIFESTYLE_STRESSFREE)))),(B31*12*(IF(B14=1,RET_LIFESTYLE_FRUGAL,IF(B14=3,RET_LIFESTYLE_ONLYTHEBEST,RET_LIFESTYLE_STRESSFREE))))*(1+realReturn)^(B67)))<=0),0,IF(ABS(realReturn)<1E-12,(IF((B67)<=0,MAX(0,B31*12*(IF(B14=1,RET_LIFESTYLE_FRUGAL,IF(B14=3,RET_LIFESTYLE_ONLYTHEBEST,RET_LIFESTYLE_STRESSFREE)))),(B31*12*(IF(B14=1,RET_LIFESTYLE_FRUGAL,IF(B14=3,RET_LIFESTYLE_ONLYTHEBEST,RET_LIFESTYLE_STRESSFREE))))*(1+realReturn)^(B67)))*(B68),(IF((B67)<=0,MAX(0,B31*12*(IF(B14=1,RET_LIFESTYLE_FRUGAL,IF(B14=3,RET_LIFESTYLE_ONLYTHEBEST,RET_LIFESTYLE_STRESSFREE)))),(B31*12*(IF(B14=1,RET_LIFESTYLE_FRUGAL,IF(B14=3,RET_LIFESTYLE_ONLYTHEBEST,RET_LIFESTYLE_STRESSFREE))))*(1+realReturn)^(B67)))*(1-(1+realReturn)^(-(B68)))/(realReturn)))) | I78: =IF((B67)<=0,MAX(0,MIN(MAX(0,B38),MAX(0,B34))),(MIN(MAX(0,B38),MAX(0,B34)))*(1+realReturn)^(B67)) | J78: =MAX(0,H78-I78)
A79: N_EDU | B79: =ROUND(H79/$B$28,0) | C79: =ROUND(I79/$B$28,0) | D79: =MAX(0,B79-C79) | F79: =IF(E79="",NP_on_N_EDU,E79) | G79: EDU_COST (USD) × (1+inflation)^eduYears. | H79: =MAX(0,B45*(1+inflationRate)^B69) | I79: =IF((B69)<=0,MAX(0,MIN(MAX(0,B39),MAX(0,B34-MIN(MAX(0,B38),MAX(0,B34))))),(MIN(MAX(0,B39),MAX(0,B34-MIN(MAX(0,B38),MAX(0,B34)))))*(1+realReturn)^(B69)) | J79: =MAX(0,H79-I79)
A80: N_SAV | B80: =ROUND(H80/$B$28,0) | C80: =ROUND(I80/$B$28,0) | D80: =MAX(0,B80-C80) | F80: =IF(E80="",NP_on_N_SAV,E80) | G80: Stored or 1× annual income. | H80: =IF(B20>0,B36,B30*12*SAV_INCOME_MULT) | I80: =IF((B69)<=0,MAX(0,MIN(MAX(0,B40),MAX(0,MAX(0,B34-MIN(MAX(0,B38),MAX(0,B34)))-MIN(MAX(0,B39),MAX(0,B34-MIN(MAX(0,B38),MAX(0,B34))))))),(MIN(MAX(0,B40),MAX(0,MAX(0,B34-MIN(MAX(0,B38),MAX(0,B34)))-MIN(MAX(0,B39),MAX(0,B34-MIN(MAX(0,B38),MAX(0,B34)))))))*(1+realReturn)^(B69)) | J80: =MAX(0,H80-I80)
A81: N_PRP | B81: =ROUND(H81/$B$28,0) | C81: =ROUND(I81/$B$28,0) | D81: =MAX(0,B81-C81) | F81: =IF(E81="",NP_on_N_PRP,E81) | G81: Stored or 5× annual income. | H81: =IF(B21>0,B37,B30*12*PRP_INCOME_MULT) | I81: =IF((B69)<=0,MAX(0,MIN(MAX(0,B41),MAX(0,MAX(0,MAX(0,B34-MIN(MAX(0,B38),MAX(0,B34)))-MIN(MAX(0,B39),MAX(0,B34-MIN(MAX(0,B38),MAX(0,B34)))))-MIN(MAX(0,B40),MAX(0,MAX(0,B34-MIN(MAX(0,B38),MAX(0,B34)))-MIN(MAX(0,B39),MAX(0,B34-MIN(MAX(0,B38),MAX(0,B34))))))))),(MIN(MAX(0,B41),MAX(0,MAX(0,MAX(0,B34-MIN(MAX(0,B38),MAX(0,B34)))-MIN(MAX(0,B39),MAX(0,B34-MIN(MAX(0,B38),MAX(0,B34)))))-MIN(MAX(0,B40),MAX(0,MAX(0,B34-MIN(MAX(0,B38),MAX(0,B34)))-MIN(MAX(0,B39),MAX(0,B34-MIN(MAX(0,B38),MAX(0,B34)))))))))*(1+realReturn)^(B69)) | J81: =MAX(0,H81-I81)
A83: C · STRESS R_LON — longevity: N_RET if the customer lives until LON_AGE (99). Does not change the plan
A84: LON_AGE | B84: =LON_AGE | C84: D · assumption / shared | D84: Assumptions. Life expectancy under R_LON.
A85: yearsInRet at LON_AGE | B85: =MAX(0,LON_AGE-B15) | C85: C · calculated | D85: LON_AGE − retAge.
A86: N_RET need at LON_AGE USD | B86: =MAX(0,IF(OR((B85)<=0,(IF((B67)<=0,MAX(0,B31*12*(IF(B14=1,RET_LIFESTYLE_FRUGAL,IF(B14=3,RET_LIFESTYLE_ONLYTHEBEST,RET_LIFESTYLE_STRESSFREE)))),(B31*12*(IF(B14=1,RET_LIFESTYLE_FRUGAL,IF(B14=3,RET_LIFESTYLE_ONLYTHEBEST,RET_LIFESTYLE_STRESSFREE))))*(1+realReturn)^(B67)))<=0),0,IF(ABS(realReturn)<1E-12,(IF((B67)<=0,MAX(0,B31*12*(IF(B14=1,RET_LIFESTYLE_FRUGAL,IF(B14=3,RET_LIFESTYLE_ONLYTHEBEST,RET_LIFESTYLE_STRESSFREE)))),(B31*12*(IF(B14=1,RET_LIFESTYLE_FRUGAL,IF(B14=3,RET_LIFESTYLE_ONLYTHEBEST,RET_LIFESTYLE_STRESSFREE))))*(1+realReturn)^(B67)))*(B85),(IF((B67)<=0,MAX(0,B31*12*(IF(B14=1,RET_LIFESTYLE_FRUGAL,IF(B14=3,RET_LIFESTYLE_ONLYTHEBEST,RET_LIFESTYLE_STRESSFREE)))),(B31*12*(IF(B14=1,RET_LIFESTYLE_FRUGAL,IF(B14=3,RET_LIFESTYLE_ONLYTHEBEST,RET_LIFESTYLE_STRESSFREE))))*(1+realReturn)^(B67)))*(1-(1+realReturn)^(-(B85)))/(realReturn)))) | C86: C · calculated | D86: Same formula as N_RET, years to LON_AGE.
A87: N_RET need at LON_AGE | B87: =ROUND(B86/$B$28,0) | C87: C · calculated | D87: User currency.
A88: N_RET gap at LON_AGE | B88: =MAX(0,B87-C78) | C88: C · calculated | D88: Need at 99 − have.
A89: extra need from longevity | B89: =MAX(0,B87-B78) | C89: C · calculated | D89: Need at 99 − base need.

Sheet Plan Calculator
A1: Plan Calculator — selected persona. seedProducts / planProducts.ts. Suggested = enabled AND gap > 0.
A2: Selected persona | B2: =SelectedPersona | C2: =IFERROR(INDEX(Personas!B$3:B$52,MATCH($B$2,Personas!$A$3:$A$52,0)),"") | D2: Follows the dropdown on the Selected persona tab. | F2: A · INPUT DATA
A3: Attribute | B3: Value | C3: Kind | D3: Source / formula | F3: B · LLM PREDICTED DATA
A4: A · INPUT DATA — from People Like You and Need Calculator | F4: C · DETERMINISTICALLY CALCULATED
A5: take-home (from PLU) | B5: =PLU_takeHome | C5: A · input | D5: Surplus uses take-home, not gross income. | F5: D · ASSUMPTIONS / SHARED DATA
A6: expenseMonthly (from PLU) | B6: =PLU_expenseMonthly | C6: A · input | D6: types.ts availableBudget. | F6: E · USER / FRONTEND OVERRIDE
A7: N_INC on (from Need Calculator) | B7: =NC_on_N_INC | C7: A · input | D7: Effective enable after Need Calculator override.
A8: N_INC gap (from Need Calculator) | B8: =NC_gap_N_INC | C8: A · input | D8: remaining_gap.
A9: N_CRI on (from Need Calculator) | B9: =NC_on_N_CRI | C9: A · input | D9: Effective enable after Need Calculator override.
A10: N_CRI gap (from Need Calculator) | B10: =NC_gap_N_CRI | C10: A · input | D10: remaining_gap.
A11: N_TPD on (from Need Calculator) | B11: =NC_on_N_TPD | C11: A · input | D11: Effective enable after Need Calculator override.
A12: N_TPD gap (from Need Calculator) | B12: =NC_gap_N_TPD | C12: A · input | D12: remaining_gap.
A13: N_HOS on (from Need Calculator) | B13: =NC_on_N_HOS | C13: A · input | D13: Effective enable after Need Calculator override.
A14: N_HOS gap (from Need Calculator) | B14: =NC_gap_N_HOS | C14: A · input | D14: remaining_gap.
A15: N_PAC on (from Need Calculator) | B15: =NC_on_N_PAC | C15: A · input | D15: Effective enable after Need Calculator override.
A16: N_PAC gap (from Need Calculator) | B16: =NC_gap_N_PAC | C16: A · input | D16: remaining_gap.
A17: N_RET on (from Need Calculator) | B17: =NC_on_N_RET | C17: A · input | D17: Effective enable after Need Calculator override.
A18: N_RET gap (from Need Calculator) | B18: =NC_gap_N_RET | C18: A · input | D18: remaining_gap.
A19: N_EDU on (from Need Calculator) | B19: =NC_on_N_EDU | C19: A · input | D19: Effective enable after Need Calculator override.
A20: N_EDU gap (from Need Calculator) | B20: =NC_gap_N_EDU | C20: A · input | D20: remaining_gap.
A21: N_SAV on (from Need Calculator) | B21: =NC_on_N_SAV | C21: A · input | D21: Effective enable after Need Calculator override.
A22: N_SAV gap (from Need Calculator) | B22: =NC_gap_N_SAV | C22: A · input | D22: remaining_gap.
A23: N_PRP on (from Need Calculator) | B23: =NC_on_N_PRP | C23: A · input | D23: Effective enable after Need Calculator override.
A24: N_PRP gap (from Need Calculator) | B24: =NC_gap_N_PRP | C24: A · input | D24: remaining_gap.
A25: yearsToRet (from Need Calculator) | B25: =NC_yearsToRet | C25: A · input | D25: Retirement contribution horizon.
A26: eduYears (from Need Calculator) | B26: =NC_eduYears | C26: A · input | D26: EDU / SAV / PRP contribution horizon.
A28: D · ASSUMPTIONS / SHARED DATA
A29: protectionPremiumRate | B29: =protectionPremiumRate | C29: D · assumption / shared | D29: Dummy 0.00078. Future: premium-quote calculator API.
A30: FREE_BUDGET_SHARE | B30: =FREE_BUDGET_SHARE | C30: D · assumption / shared | D30: Half of leftover surplus split across wealth needs.
A31: monthly step (user currency) | B31: =FX_monthlyStep | C31: D · assumption / shared | D31: monthlyRoundStep (USD) as a nice step in user currency. SGD: 50.
A32: premium step (user currency) | B32: =FX_coverPremStep | C32: D · assumption / shared | D32: coverPremRoundStep (USD) as a nice step in user currency. SGD: 10.
A33: realReturn | B33: =realReturn | C33: D · assumption / shared | D33: annualPmtToHitFv for the wealth cap.
A35: C · DETERMINISTICALLY CALCULATED — suggested flags and protection sizing
A36: sug N_INC | B36: =AND(NC_on_N_INC,NC_gap_N_INC>0) | C36: C · calculated | D36: enabled AND gap > 0.
A37: sug N_CRI | B37: =AND(NC_on_N_CRI,NC_gap_N_CRI>0) | C37: C · calculated | D37: enabled AND gap > 0.
A38: sug N_TPD | B38: =AND(NC_on_N_TPD,NC_gap_N_TPD>0) | C38: C · calculated | D38: enabled AND gap > 0.
A39: sug N_HOS | B39: =AND(NC_on_N_HOS,NC_gap_N_HOS>0) | C39: C · calculated | D39: enabled AND gap > 0.
A40: sug N_PAC | B40: =AND(NC_on_N_PAC,NC_gap_N_PAC>0) | C40: C · calculated | D40: enabled AND gap > 0.
A41: sug N_RET | B41: =AND(NC_on_N_RET,NC_gap_N_RET>0) | C41: C · calculated | D41: enabled AND gap > 0.
A42: sug N_EDU | B42: =AND(NC_on_N_EDU,NC_gap_N_EDU>0) | C42: C · calculated | D42: enabled AND gap > 0.
A43: sug N_SAV | B43: =AND(NC_on_N_SAV,NC_gap_N_SAV>0) | C43: C · calculated | D43: enabled AND gap > 0.
A44: sug N_PRP | B44: =AND(NC_on_N_PRP,NC_gap_N_PRP>0) | C44: C · calculated | D44: enabled AND gap > 0.
A45: n wealth suggested | B45: =(B41*1)+(B42*1)+(B43*1)+(B44*1) | C45: C · calculated | D45: Count of suggested wealth needs.
A46: planSum N_INC | B46: =IF(B36,MAX(0,ROUND(NC_gap_N_INC,0)),0) | C46: C · calculated | D46: Suggested protection sum = gap.
A47: planPrem N_INC | B47: =IF(B46<=0,0,MAX(0,ROUND((B46*protectionPremiumRate)/FX_coverPremStep,0)*FX_coverPremStep)) | C47: C · calculated | D47: coverPremiumFor(sum). Indicative, not half of slider max.
A48: planSum N_CRI | B48: =IF(B37,MAX(0,ROUND(NC_gap_N_CRI,0)),0) | C48: C · calculated | D48: Suggested protection sum = gap.
A49: planPrem N_CRI | B49: =IF(B48<=0,0,MAX(0,ROUND((B48*protectionPremiumRate)/FX_coverPremStep,0)*FX_coverPremStep)) | C49: C · calculated | D49: coverPremiumFor(sum). Indicative, not half of slider max.
A50: planSum N_TPD | B50: =IF(B38,MAX(0,ROUND(NC_gap_N_TPD,0)),0) | C50: C · calculated | D50: Suggested protection sum = gap.
A51: planPrem N_TPD | B51: =IF(B50<=0,0,MAX(0,ROUND((B50*protectionPremiumRate)/FX_coverPremStep,0)*FX_coverPremStep)) | C51: C · calculated | D51: coverPremiumFor(sum). Indicative, not half of slider max.
A52: planSum N_HOS | B52: =IF(B39,MAX(0,ROUND(NC_gap_N_HOS,0)),0) | C52: C · calculated | D52: Suggested protection sum = gap.
A53: planPrem N_HOS | B53: =IF(B52<=0,0,MAX(0,ROUND((B52*protectionPremiumRate)/FX_coverPremStep,0)*FX_coverPremStep)) | C53: C · calculated | D53: coverPremiumFor(sum). Indicative, not half of slider max.
A54: planSum N_PAC | B54: =IF(B40,MAX(0,ROUND(NC_gap_N_PAC,0)),0) | C54: C · calculated | D54: Suggested protection sum = gap.
A55: planPrem N_PAC | B55: =IF(B54<=0,0,MAX(0,ROUND((B54*protectionPremiumRate)/FX_coverPremStep,0)*FX_coverPremStep)) | C55: C · calculated | D55: coverPremiumFor(sum). Indicative, not half of slider max.
A56: prot prem / yr | B56: =B47+B49+B51+B53+B55 | C56: C · calculated | D56: Sum of suggested protection premiums (before Include?).
A57: default wealth mth share | B57: =IF(B45=0,0,MAX(0,ROUND((MAX(0,(PLU_takeHome-PLU_expenseMonthly)*12-B56)*FREE_BUDGET_SHARE)/12/B45/FX_monthlyStep,0)*FX_monthlyStep)) | C57: C · calculated | D57: Leftover surplus × 50% / 12 / n wealth, rounded to the monthly step.
A58: cap mth N_RET | B58: =IF((IF(OR((NC_gap_N_RET)<=0,(NC_yearsToRet)<=0),0,IF(ABS(realReturn)<1E-12,(NC_gap_N_RET)/(NC_yearsToRet),(NC_gap_N_RET)*realReturn/((1+realReturn)^(NC_yearsToRet)-1))))<=0,0,ROUNDUP((IF(OR((NC_gap_N_RET)<=0,(NC_yearsToRet)<=0),0,IF(ABS(realReturn)<1E-12,(NC_gap_N_RET)/(NC_yearsToRet),(NC_gap_N_RET)*realReturn/((1+realReturn)^(NC_yearsToRet)-1))))/12/FX_monthlyStep,0)*FX_monthlyStep) | C58: C · calculated | D58: annualPmtToHitFv / 12, rounded up to the monthly step.
A59: planMth N_RET | B59: =IF(B41,MIN(B57,B58),0) | C59: C · calculated | D59: min(default share, cap).
A60: planLump N_RET | B60: 0 | C60: C · calculated | D60: Default lump is 0.
A61: cap mth N_EDU | B61: =IF((IF(OR((NC_gap_N_EDU)<=0,(NC_eduYears)<=0),0,IF(ABS(realReturn)<1E-12,(NC_gap_N_EDU)/(NC_eduYears),(NC_gap_N_EDU)*realReturn/((1+realReturn)^(NC_eduYears)-1))))<=0,0,ROUNDUP((IF(OR((NC_gap_N_EDU)<=0,(NC_eduYears)<=0),0,IF(ABS(realReturn)<1E-12,(NC_gap_N_EDU)/(NC_eduYears),(NC_gap_N_EDU)*realReturn/((1+realReturn)^(NC_eduYears)-1))))/12/FX_monthlyStep,0)*FX_monthlyStep) | C61: C · calculated | D61: annualPmtToHitFv / 12, rounded up to the monthly step.
A62: planMth N_EDU | B62: =IF(B42,MIN(B57,B61),0) | C62: C · calculated | D62: min(default share, cap).
A63: planLump N_EDU | B63: 0 | C63: C · calculated | D63: Default lump is 0.
A64: cap mth N_SAV | B64: =IF((IF(OR((NC_gap_N_SAV)<=0,(NC_eduYears)<=0),0,IF(ABS(realReturn)<1E-12,(NC_gap_N_SAV)/(NC_eduYears),(NC_gap_N_SAV)*realReturn/((1+realReturn)^(NC_eduYears)-1))))<=0,0,ROUNDUP((IF(OR((NC_gap_N_SAV)<=0,(NC_eduYears)<=0),0,IF(ABS(realReturn)<1E-12,(NC_gap_N_SAV)/(NC_eduYears),(NC_gap_N_SAV)*realReturn/((1+realReturn)^(NC_eduYears)-1))))/12/FX_monthlyStep,0)*FX_monthlyStep) | C64: C · calculated | D64: annualPmtToHitFv / 12, rounded up to the monthly step.
A65: planMth N_SAV | B65: =IF(B43,MIN(B57,B64),0) | C65: C · calculated | D65: min(default share, cap).
A66: planLump N_SAV | B66: 0 | C66: C · calculated | D66: Default lump is 0.
A67: cap mth N_PRP | B67: =IF((IF(OR((NC_gap_N_PRP)<=0,(NC_eduYears)<=0),0,IF(ABS(realReturn)<1E-12,(NC_gap_N_PRP)/(NC_eduYears),(NC_gap_N_PRP)*realReturn/((1+realReturn)^(NC_eduYears)-1))))<=0,0,ROUNDUP((IF(OR((NC_gap_N_PRP)<=0,(NC_eduYears)<=0),0,IF(ABS(realReturn)<1E-12,(NC_gap_N_PRP)/(NC_eduYears),(NC_gap_N_PRP)*realReturn/((1+realReturn)^(NC_eduYears)-1))))/12/FX_monthlyStep,0)*FX_monthlyStep) | C67: C · calculated | D67: annualPmtToHitFv / 12, rounded up to the monthly step.
A68: planMth N_PRP | B68: =IF(B44,MIN(B57,B67),0) | C68: C · calculated | D68: min(default share, cap).
A69: planLump N_PRP | B69: 0 | C69: C · calculated | D69: Default lump is 0.
A71: C · RESULTS — Include? blank keeps the suggested product
A72: type | B72: suggested | C72: Include? | D72: included
A73: N_INC | B73: =B36 | D73: =AND(B73,IF(C73="",TRUE,C73))
A74: N_CRI | B74: =B37 | D74: =AND(B74,IF(C74="",TRUE,C74))
A75: N_TPD | B75: =B38 | D75: =AND(B75,IF(C75="",TRUE,C75))
A76: N_HOS | B76: =B39 | D76: =AND(B76,IF(C76="",TRUE,C76))
A77: N_PAC | B77: =B40 | D77: =AND(B77,IF(C77="",TRUE,C77))
A78: N_RET | B78: =B41 | D78: =AND(B78,IF(C78="",TRUE,C78))
A79: N_EDU | B79: =B42 | D79: =AND(B79,IF(C79="",TRUE,C79))
A80: N_SAV | B80: =B43 | D80: =AND(B80,IF(C80="",TRUE,C80))
A81: N_PRP | B81: =B44 | D81: =AND(B81,IF(C81="",TRUE,C81))
A83: investMth | B83: =(D78*B59)+(D79*B62)+(D80*B65)+(D81*B68) | C83: C · calculated | D83: Sum of included wealth monthly contributions.
A84: investLump | B84: =(D78*B60)+(D79*B63)+(D80*B66)+(D81*B69) | C84: C · calculated | D84: Sum of included wealth lumps (default 0).

Sheet Budget Calculator
A1: Budget Calculator — selected persona. planAfford. Surplus is take-home minus expense.
A2: Selected persona | B2: =SelectedPersona | C2: =IFERROR(INDEX(Personas!B$3:B$52,MATCH($B$2,Personas!$A$3:$A$52,0)),"") | D2: Follows the dropdown on the Selected persona tab. | F2: A · INPUT DATA
A3: Attribute | B3: Value | C3: Kind | D3: Source / formula | F3: B · LLM PREDICTED DATA
A4: A · INPUT DATA — from People Like You and Plan Calculator | F4: C · DETERMINISTICALLY CALCULATED
A5: take-home (from PLU) | B5: =PLU_takeHome | C5: A · input | D5: types.ts availableBudget uses take-home. | F5: D · ASSUMPTIONS / SHARED DATA
A6: expenseMonthly (from PLU) | B6: =PLU_expenseMonthly | C6: A · input | D6: Not gross income. | F6: E · USER / FRONTEND OVERRIDE
A7: investments (from PLU) | B7: =PLU_investments | C7: A · input | D7: Cap for lumps.
A8: included N_INC premium | B8: =IF(PLAN_included_N_INC,PLAN_prem_N_INC,0) | C8: A · input | D8: Only included protection.
A9: included N_CRI premium | B9: =IF(PLAN_included_N_CRI,PLAN_prem_N_CRI,0) | C9: A · input
A10: included N_TPD premium | B10: =IF(PLAN_included_N_TPD,PLAN_prem_N_TPD,0) | C10: A · input
A11: included N_HOS premium | B11: =IF(PLAN_included_N_HOS,PLAN_prem_N_HOS,0) | C11: A · input
A12: included N_PAC premium | B12: =IF(PLAN_included_N_PAC,PLAN_prem_N_PAC,0) | C12: A · input | D12: V0-16.
A13: investMth (from Plan) | B13: =PLAN_investMth | C13: A · input | D13: Included wealth contributions.
A14: investLump (from Plan) | B14: =PLAN_investLump | C14: A · input | D14: Included wealth lumps.
A16: D · ASSUMPTIONS / SHARED DATA
A17: FREE_BUDGET_SHARE | B17: =FREE_BUDGET_SHARE | C17: D · assumption / shared | D17: Half of monthly surplus is the free budget.
A19: C · DETERMINISTICALLY CALCULATED — planAfford
A20: available | B20: =MAX(0,PLU_takeHome-PLU_expenseMonthly) | C20: C · calculated | D20: max(0, take-home − expense).
A21: free (50%) | B21: =ROUND(B20*FREE_BUDGET_SHARE,0) | C21: C · calculated | D21: available × 50%, rounded.
A22: included prot prem / yr | B22: =IF(PLAN_included_N_INC,PLAN_prem_N_INC,0)+IF(PLAN_included_N_CRI,PLAN_prem_N_CRI,0)+IF(PLAN_included_N_TPD,PLAN_prem_N_TPD,0)+IF(PLAN_included_N_HOS,PLAN_prem_N_HOS,0)+IF(PLAN_included_N_PAC,PLAN_prem_N_PAC,0) | C22: C · calculated | D22: Sum of included protection premiums.
A23: premMth (display) | B23: =ROUND(B22/12,0) | C23: C · calculated | D23: Annual premiums / 12.
A24: contribMth | B24: =PLAN_investMth | C24: C · calculated | D24: Same as investMth.
A25: monthly | B25: =ROUND(PLAN_investMth+B22/12,0) | C25: C · calculated | D25: contrib + prem/12.
A26: monthlyOver | B26: =B25-B21 | C26: C · calculated | D26: > 0 means the plan exceeds the free budget.
A27: lumps | B27: =PLAN_investLump | C27: C · calculated | D27: Included lumps.
A28: lumpOver | B28: =B27-PLU_investments | C28: C · calculated | D28: > 0 means lumps exceed current investments.

Sheet Scenario Visualizer
A1: Scenario Visualizer — selected persona. One deterministic path of SV CashFlowGeneratorV2 on GP's payload.
A2: Selected persona | B2: =SelectedPersona | C2: =IFERROR(INDEX(Personas!B$3:B$52,MATCH($B$2,Personas!$A$3:$A$52,0)),"") | D2: Follows the dropdown on the Selected persona tab. | F2: A · INPUT DATA
A3: Attribute | B3: Value | C3: Kind | D3: Source / formula | F3: B · LLM PREDICTED DATA
A4: A · INPUT DATA — effective session (People Like You, Need Calculator, Plan Calculator) | F4: C · DETERMINISTICALLY CALCULATED | H4: D · SV CPF TABLES — SocialSecurityR_SGP (by age at contribution)
A5: age | B5: =IFERROR(INDEX(Personas!C$3:C$52,MATCH($B$2,Personas!$A$3:$A$52,0)),"") | C5: A · input | D5: Personas C. | F5: D · ASSUMPTIONS / SHARED DATA | H5: from age | I5: to age | J5: total rate | K5: employee rate | L5: OA share | M5: SA share | N5: MA share
A6: residency | B6: =IFERROR(INDEX(Personas!E$3:E$52,MATCH($B$2,Personas!$A$3:$A$52,0)),"") | C6: A · input | D6: Personas E. sv_payload.py sends CPF region R_SGP unless Foreigner. | F6: E · USER / FRONTEND OVERRIDE | H6: 0 | I6: 35 | J6: 0.37 | K6: 0.2 | L6: 0.6217 | M6: 0.1621 | N6: 0.2162
A7: incomeMonthly | B7: =PLU_incomeMonthly | C7: A · input | D7: Salary I_SAL = round(× 12). | H7: 36 | I7: 45 | J7: 0.37 | K7: 0.2 | L7: 0.5677 | M7: 0.1891 | N7: 0.2432
A8: take-home | B8: =PLU_takeHome | C8: A · input | D8: Investment contribution = take-home − spend. | H8: 46 | I8: 50 | J8: 0.37 | K8: 0.2 | L8: 0.5136 | M8: 0.2162 | N8: 0.2702
A9: expenseMonthly | B9: =PLU_expenseMonthly | C9: A · input | D9: PERSONAL_EXPENSE = round(× 12). | H9: 51 | I9: 55 | J9: 0.37 | K9: 0.2 | L9: 0.4055 | M9: 0.3108 | N9: 0.2837
A10: cash | B10: =PLU_cash | C10: A · input | D10: A_SAV, grows at interestRate. | H10: 56 | I10: 60 | J10: 0.325 | K10: 0.17 | L10: 0.4069 | M10: 0.2372 | N10: 0.3559
A11: investments | B11: =PLU_investments | C11: A · input | D11: INVESTMENT_PORTFOLIO, grows at investmentReturn. | H11: 61 | I11: 65 | J11: 0.235 | K11: 0.115 | L11: 0.1709 | M11: 0.317 | N11: 0.5121
A12: property | B12: =PLU_property | C12: A · input | D12: RESIDENTIAL_PROPERTY (illiquid). | H12: 66 | I12: 70 | J12: 0.165 | K12: 0.075 | L12: 0.0646 | M12: 0.258 | N12: 0.6774
A13: mortgage | B13: =PLU_mortgage | C13: A · input | D13: Mortgage loan, 20-year annuity at loanRate. | H13: 71 | I13: 999 | J13: 0.125 | K13: 0.05 | L13: 0.08 | M13: 0.08 | N13: 0.84
A14: life sum assured | B14: =PLU_lifeSum | C14: A · input | D14: Existing life policy (only when > 0).
A15: life premium / yr | B15: =PLU_lifePrem | C15: A · input | D15: regularPremium of the existing policy. | H15: D · CPF LIFE — BRS and monthly payout by (55 − age)+ + year − 2023
H16: row | I16: BRS | J16: payout × 1 | K16: payout × 2 | L16: payout × 3
A17: D · ASSUMPTIONS — SV helium tenant conf.ini and SocialSecurityR_SGP | H17: 0 | I17: 99400 | J17: 870 | K17: 1620 | L17: 2370
A18: lifeExpectancy (SV tenant) | B18: 100 | C18: D · assumption / shared | D18: helium conf.ini. The path runs to age 100, not the session LE. | H18: 1 | I18: 102900 | J18: 900 | K18: 1640 | L18: 2350
A19: savingsRate | B19: 0.01 | C19: D · assumption / shared | D19: helium conf.ini. Savings account growth; also the premium load (× 1.01). | H19: 2 | I19: 106500 | J19: 930 | K19: 1730 | L19: 2530
A20: ageOfRetirement | B20: =ageOfRetirement | C20: D · assumption / shared | D20: Assumptions. | H20: 3 | I20: 110200 | J20: 950 | K20: 1780 | L20: 2610
A21: loan / premium term (years) | B21: 20 | C21: D · assumption / shared | D21: Mortgage remainingYears and existing policyTerm in sv_payload.py. | H21: 4 | I21: 114100 | J21: 980 | K21: 1840 | L21: 2690
A22: property rate premium | B22: 0.004 | C22: D · assumption / shared | D22: Property grows at max(0, assetReturn + 0.4%).
A23: currency shock share | B23: 0.66666667 | C23: D · assumption / shared | D23: Liquid assets fall by 2/3 of the slider.
A24: CPF ordinary-wage cap / yr | B24: 96000 | C24: D · assumption / shared | D24: SocialSecurityR_SGP.
A25: CPF MA cap | B25: 63000 | C25: D · assumption / shared | D25: Medisave excess moves to RA at payout age; MA is capped from then.
A26: CPF OA rate | B26: 0.025 | C26: D · assumption / shared
A27: CPF SA / MA rate | B27: 0.04 | C27: D · assumption / shared
A28: CPF RA / LIFE growth factor | B28: 1.04 | C28: D · assumption / shared | D28: RA and the CPF LIFE pot grow × 1.04 a year.
A29: BRS / payout growth | B29: 0.03 | C29: D · assumption / shared | D29: Past the 2027 row, and per year of payout age past 55.
A30: payout bonus per deferral year | B30: 0.07 | C30: D · assumption / shared | D30: × (1 + 7% × (payout age − 65)).
A32: C · DETERMINISTICALLY CALCULATED — sv_payload.py values as SV reads them
A33: years on the path (T) | B33: =MAX(SV_LE-SV_age,0) | C33: C · calculated | D33: SV numYears = 100 − age.
A34: array length (T + 1) | B34: =SV_T+1 | C34: C · calculated | D34: Asset / CPF columns run 0..T.
A35: years to retirement | B35: =MAX(SV_ret-SV_age,0) | C35: C · calculated
A36: salary zero from index | B36: =IF(SV_dtr>=1,SV_dtr-1,SV_T-1) | C36: C · calculated | D36: numpy arr[dtr−1:] = 0. When dtr = 0 only the last year is zeroed (SV keeps salary for retirees).
A37: salary / yr | B37: =IF(MOD(SV_income*12,1)=0.5,2*ROUND((SV_income*12)/2,0),ROUND(SV_income*12,0)) | C37: C · calculated | D37: I_SAL absoluteValue. Python round (half to even).
A38: spend / yr | B38: =IF(MOD(SV_expense*12,1)=0.5,2*ROUND((SV_expense*12)/2,0),ROUND(SV_expense*12,0)) | C38: C · calculated | D38: PERSONAL_EXPENSE absoluteValue. Python round (half to even).
A39: mortgage principal | B39: =INT(SV_mortgage) | C39: C · calculated | D39: int(mortgage).
A40: mortgage instalment / yr | B40: =IF(SV_mortgage>0,IF(MOD(IF(loanRate=0,SV_mortgage/SV_loanYears,SV_mortgage*loanRate/(1-(1+loanRate)^(-SV_loanYears))),1)=0.5,2*ROUND((IF(loanRate=0,SV_mortgage/SV_loanYears,SV_mortgage*loanRate/(1-(1+loanRate)^(-SV_loanYears))))/2,0),ROUND(IF(loanRate=0,SV_mortgage/SV_loanYears,SV_mortgage*loanRate/(1-(1+loanRate)^(-SV_loanYears))),0)),0) | C40: C · calculated | D40: Level annual annuity that clears the loan in 20 years, interest included (goal_math.annual_loan_payment). rate 0 → mortgage / 20. Paid from spend for 20 years. Python round (half to even).
A41: investment contribution / yr | B41: =IF(MOD(MAX(0,SV_takeHome-SV_expense),1)=0.5,2*ROUND((MAX(0,SV_takeHome-SV_expense))/2,0),ROUND(MAX(0,SV_takeHome-SV_expense),0)) | C41: C · calculated | D41: sv_payload.py sends the MONTHLY surplus; SV adds it once a year. Python round (half to even).
A42: existing life premium / yr | B42: =IF(SV_lifeSum>0,SV_lifePrem,0)*(1+SV_savRate) | C42: C · calculated | D42: InsuranceBaseClass premium × (1 + savingsRate), first 20 years.
A43: property growth | B43: =MAX(0,assetReturn+SV_propPremium) | C43: C · calculated
A44: goal withdrawal year | B44: =IF(NC_eduYears>=1,NC_eduYears,SV_T) | C44: C · calculated | D44: EDU / SAV / PRP fundsNeededYear − now (default 10).
A45: goal withdrawal amount | B45: =IF(NC_eduYears<=SV_T,NC_on_N_EDU*NC_amount_N_EDU+NC_on_N_SAV*NC_amount_N_SAV+NC_on_N_PRP*NC_amount_N_PRP,0) | C45: C · calculated | D45: capitalSumRequired of each enabled goal, not inflated. Leaves savings in that year.
A46: plan RET monthly | B46: =IF(PLAN_included_N_RET,PLAN_mth_N_RET,0) | C46: C · calculated | D46: plan_benefit_visualizer pot.
A47: plan RET lump | B47: =IF(PLAN_included_N_RET,PLAN_lump_N_RET,0) | C47: C · calculated
A48: plan RET pay years | B48: =MAX(1,SV_ret-SV_age) | C48: C · calculated
A49: plan EDU + SAV + PRP monthly | B49: =IF(PLAN_included_N_EDU,PLAN_mth_N_EDU,0)+IF(PLAN_included_N_SAV,PLAN_mth_N_SAV,0)+IF(PLAN_included_N_PRP,PLAN_mth_N_PRP,0) | C49: C · calculated | D49: Same pay years and rate, so one pot column.
A50: plan EDU + SAV + PRP lump | B50: =IF(PLAN_included_N_EDU,PLAN_lump_N_EDU,0)+IF(PLAN_included_N_SAV,PLAN_lump_N_SAV,0)+IF(PLAN_included_N_PRP,PLAN_lump_N_PRP,0) | C50: C · calculated
A51: plan goal pay years | B51: =MAX(1,NC_eduYears) | C51: C · calculated
A52: plan protection premium / yr | B52: =IF(PLAN_included_N_INC,PLAN_prem_N_INC,0)+IF(PLAN_included_N_CRI,PLAN_prem_N_CRI,0)+IF(PLAN_included_N_TPD,PLAN_prem_N_TPD,0)+IF(PLAN_included_N_HOS,PLAN_prem_N_HOS,0)+IF(PLAN_included_N_PAC,PLAN_prem_N_PAC,0) | C52: C · calculated | D52: Premiums only: protection pots have no account value on SV's no-death path. Includes N_PAC (V0-16).
A53: plan protection pay years | B53: =MAX(1,SV_ret-SV_age) | C53: C · calculated
A55: E · OVERRIDE — stress events (blank size = off). Slider years as on the SV screen
A56: R_MKT market crash: year | C56: E · user / frontend override | D56: Slider year; SV applies it at year + 1.
A57: R_MKT market crash: size | C57: E · user / frontend override | D57: e.g. 0.35. Every asset × (1 − size).
A58: R_CCY currency shock: year | C58: E · user / frontend override
A59: R_CCY currency shock: size | C59: E · user / frontend override | D59: Liquid assets × (1 − size × 2/3).
A60: R_INF inflation shock: from | C60: E · user / frontend override
A61: R_INF inflation shock: to | C61: E · user / frontend override
A62: R_INF inflation shock: extra | C62: E · user / frontend override | D62: Added to inflationRate for the window.
A63: R_ICT income impact: from | C63: E · user / frontend override
A64: R_ICT income impact: to | C64: E · user / frontend override
A65: R_ICT income impact: size | C65: E · user / frontend override | D65: −0.2 = salary × 0.8 (also the CPF wage).
A66: R_EXP expense impact: from | C66: E · user / frontend override
A67: R_EXP expense impact: to | C67: E · user / frontend override
A68: R_EXP expense impact: size | C68: E · user / frontend override | D68: Scales spend, instalment and goal withdrawals.
A69: crash on | B69: =SV_crashV<>"" | C69: C · calculated
A70: crash year (SV) | B70: =MAX(1,N(SV_crashY)+1) | C70: C · calculated
A71: crash factor | B71: =1-ABS(N(SV_crashV)) | C71: C · calculated
A72: currency on | B72: =SV_ccyV<>"" | C72: C · calculated
A73: currency year (SV) | B73: =MAX(1,N(SV_ccyY)+1) | C73: C · calculated
A74: currency factor | B74: =1-ABS(N(SV_ccyV))*SV_fxShare | C74: C · calculated
A75: inflation on | B75: =SV_inflV<>"" | C75: C · calculated
A76: inflation first year (SV) | B76: =MAX(1,N(SV_inflFrom)+1) | C76: C · calculated
A77: inflation last year (SV) | B77: =MAX(SV_inflS,N(SV_inflTo)+1) | C77: C · calculated
A78: income on | B78: =SV_incV<>"" | C78: C · calculated
A79: income first year (SV) | B79: =MAX(1,N(SV_incFrom)+1) | C79: C · calculated
A80: income last year (SV) | B80: =MAX(SV_incS,N(SV_incTo)+1) | C80: C · calculated
A81: expense on | B81: =SV_expV<>"" | C81: C · calculated
A82: expense first year (SV) | B82: =MAX(1,N(SV_expFrom)+1) | C82: C · calculated
A83: expense last year (SV) | B83: =MAX(SV_expS,N(SV_expTo)+1) | C83: C · calculated
A84: shock inflation rate | B84: =inflationRate+ABS(N(SV_inflV)) | C84: C · calculated
A85: income impact | B85: =IF(N(SV_incV)<=0,N(SV_incV),-ABS(N(SV_incV))) | C85: C · calculated
A86: expense impact | B86: =ABS(N(SV_expV)) | C86: C · calculated
A87: R_LON longevity: on (TRUE / blank) | C87: E · user / frontend override | D87: Chart horizon to LON_AGE (99). SV already runs the path to 100.
A88: R_LON on | B88: =SV_lonV=TRUE | C88: C · calculated
A89: chart horizon (age) | B89: =IF(SV_lonOn,LON_AGE,endAge) | C89: C · calculated | D89: endAge (85), or LON_AGE under R_LON.
A91: C · CPF AT PAYOUT AGE — numpy indexing as SV runs it (negative index counts from the end)
A92: CPF on | B92: =SV_residency<>"Foreigner" | C92: C · calculated | D92: sv_payload.py: region R_SGP unless Foreigner (not the CPF tab country switch).
A93: payout age | B93: =MAX(65,SV_ret) | C93: C · calculated | D93: ageStartPayout.
A94: contribution stop index | B94: =MIN(70,SV_ret)-SV_age+1 | C94: C · calculated | D94: Contributions zero from here.
A95: payout index | B95: =SV_asp-SV_age+1 | C95: C · calculated | D95: Past age 66 the payout index is negative, so SV wraps RA into year 0 (Discrepancies).
A96: contributions zero from (effective) | B96: =IF(SV_stop>=0,MIN(SV_stop,SV_L),MAX(0,SV_L+(SV_stop))) | C96: C · calculated
A97: employee CPF zero from (effective) | B97: =IF(SV_stop-1>=0,MIN(SV_stop-1,SV_L),MAX(0,SV_L+(SV_stop-1))) | C97: C · calculated
A98: payout column (effective) | B98: =IF(SV_sp>=0,MIN(SV_sp,SV_L),MAX(0,SV_L+(SV_sp))) | C98: C · calculated
A99: column before payout (effective) | B99: =IF(SV_sp-1>=0,MIN(SV_sp-1,SV_L),MAX(0,SV_L+(SV_sp-1))) | C99: C · calculated
A100: BRS row | B100: =MAX(55-SV_age,0)+currentYear-2023 | C100: C · calculated
A101: BRS at payout age | B101: =IF(SV_brsIdx<5,INDEX(SV_brsTbl,SV_brsIdx+1),INDEX(SV_brsTbl,5)*(1+SV_brsGrowth)^(SV_brsIdx-4))*(1+SV_brsGrowth)^(SV_asp-55) | C101: C · calculated
A102: RA at payout (before CPF LIFE) | B102: =INDEX($W$129:$W$211,SV_pIdx+1)+INDEX($X$129:$X$211,SV_pIdx+1)+MAX(INDEX($U$129:$U$211,SV_pIdx+1)-SV_maCap,0) | C102: C · calculated | D102: OA + SA + MA above the cap, one column before payout.
A103: BRS multiple (max 3) | B103: =IF(SV_brs>0,MIN(3,INT(SV_raS/SV_brs)),0) | C103: C · calculated
...

Sheet HappiU
A1: HappiU — selected persona. Deterministic HU score: expected values weighted by survival, on HU's cashflow rules.
A2: Selected persona | B2: =SelectedPersona | C2: =IFERROR(INDEX(Personas!B$3:B$52,MATCH($B$2,Personas!$A$3:$A$52,0)),"") | D2: Follows the dropdown on the Selected persona tab. | F2: A · INPUT DATA
A3: Attribute | B3: Value | C3: Kind | D3: Source / formula | F3: B · LLM PREDICTED DATA
A4: A · INPUT DATA — effective session (what hu_payload.py sends) | F4: C · DETERMINISTICALLY CALCULATED | H4: C · GOALS — enabled needs plus N_RET (GP always sends it)
A5: age | B5: =IFERROR(INDEX(Personas!C$3:C$52,MATCH($B$2,Personas!$A$3:$A$52,0)),"") | C5: A · input | D5: Personas C. HU needs 18–83. | F5: D · ASSUMPTIONS / SHARED DATA | H5: type | I5: code | J5: in list | K5: need | L5: existing | M5: in plan | N5: benefit | O5: priority | P5: duration | Q5: D | R5: path | S5: w0 | T5: whl | U5: v(0) | V5: U base | W5: U pre | X5: U rec | Y5: U full | Z5: denominator | AA5: pre | AB5: post | AC5: flag | AD5: log priority | AE5: calibration | AF5: weight
A6: gender | B6: =IFERROR(INDEX(Personas!D$3:D$52,MATCH($B$2,Personas!$A$3:$A$52,0)),"") | C6: A · input | D6: Personas D. Picks the q(age) column. | F6: E · USER / FRONTEND OVERRIDE | H6: N_INC | I6: N_INC | J6: =NC_on_N_INC | K6: =NC_amount_N_INC | L6: =HU_lifeSum | M6: =NOT(AND(PLAN_sug_N_INC,NOT(PLAN_included_N_INC))) | N6: =IF(NOT($M$6),0,IF(PLAN_sug_N_INC,MAX(0,PLAN_sum_N_INC),MAX(0,ROUND($K$6/HU_benefitRound,0)*HU_benefitRound))) | O6: =NP_priority_N_INC | P6: =IF($M$6,MIN(HU_term,HU_depYears),HU_depYears)+1 | Q6: =MIN($P$6,HU_T) | R6: W | S6: =INDEX($AD$68:$AD$150,IF(HU_T>=1,2,1))+$K$6 | T6: =HU_whl*$K$6 | U6: =IF($S$6=0,0,IF(0>$S$6/HU_alpha+$K$6,0.5*$S$6/HU_alpha,IF(0>=$K$6,(0-$K$6)-0.5*HU_alpha/$S$6*(0-$K$6)^2,IF(0>=$T$6,HU_beta*(0-$K$6),HU_beta*($T$6-$K$6))))) | V6: =$U$6*SUM($AF$68:$AF$150) | W6: =SUMPRODUCT($AF$68:$AF$150,$AG$68:$AG$150) | X6: =SUMPRODUCT($AF$68:$AF$150,$AH$68:$AH$150) | Y6: =SUMPRODUCT($AF$68:$AF$150,$AI$68:$AI$150) | Z6: =$Y$6-$V$6 | AA6: =IF(NOT($J$6),"",IF($S$6=0,1,IF($Z$6=0,1,IF(AND($Z$6=$W$6-$V$6,$W$6>0),1,MAX(0,MIN(1,($W$6-$V$6)/$Z$6)))))) | AB6: =IF(NOT($J$6),"",IF($S$6=0,1,IF($Z$6=0,1,IF(AND($Z$6=$X$6-$V$6,$X$6>0),1,MAX(0,MIN(1,($X$6-$V$6)/$Z$6)))))) | AC6: =IF(NOT($J$6),"",IF($S$6=0,"w0 = 0 (HU raises an error)",IF($Z$6=0,"denominator 0",""))) | AD6: =IF($J$6,MAX(LN($O$6+1),LN(1+1)),0) | AE6: =IF($J$6,1,0) | AF6: =IF($J$6,$AD$6*$AE$6/SUMPRODUCT($AD$6:$AD$13,$AE$6:$AE$13),0)
A7: is smoker | B7: =IFERROR(INDEX(Personas!U$3:U$52,MATCH($B$2,Personas!$A$3:$A$52,0)),"") | C7: A · input | D7: Personas U. | H7: N_CRI | I7: N_CRI | J7: =NC_on_N_CRI | K7: =NC_amount_N_CRI | L7: 0 | M7: =NOT(AND(PLAN_sug_N_CRI,NOT(PLAN_included_N_CRI))) | N7: =IF(NOT($M$7),0,IF(PLAN_sug_N_CRI,MAX(0,PLAN_sum_N_CRI),MAX(0,ROUND($K$7/HU_benefitRound,0)*HU_benefitRound))) | O7: =NP_priority_N_CRI | P7: =IF($M$7,HU_term,HU_ciMaxAge-HU_age)+1 | Q7: =MIN($P$7,HU_T) | R7: C | S7: =$K$7 | T7: =HU_whl*$K$7 | U7: =IF($S$7=0,0,IF(0>$S$7/HU_alpha+$K$7,0.5*$S$7/HU_alpha,IF(0>=$K$7,(0-$K$7)-0.5*HU_alpha/$S$7*(0-$K$7)^2,IF(0>=$T$7,HU_beta*(0-$K$7),HU_beta*($T$7-$K$7))))) | V7: =$U$7*SUM($AJ$68:$AJ$150) | W7: =SUMPRODUCT($AJ$68:$AJ$150,$AK$68:$AK$150) | X7: =SUMPRODUCT($AJ$68:$AJ$150,$AL$68:$AL$150) | Y7: =SUMPRODUCT($AJ$68:$AJ$150,$AM$68:$AM$150) | Z7: =$Y$7-$V$7 | AA7: =IF(NOT($J$7),"",IF($S$7=0,1,IF($Z$7=0,1,IF(AND($Z$7=$W$7-$V$7,$W$7>0),1,MAX(0,MIN(1,($W$7-$V$7)/$Z$7)))))) | AB7: =IF(NOT($J$7),"",IF($S$7=0,1,IF($Z$7=0,1,IF(AND($Z$7=$X$7-$V$7,$X$7>0),1,MAX(0,MIN(1,($X$7-$V$7)/$Z$7)))))) | AC7: =IF(NOT($J$7),"",IF($S$7=0,"w0 = 0 (HU raises an error)",IF($Z$7=0,"denominator 0",""))) | AD7: =IF($J$7,MAX(LN($O$7+1),LN(1+1)),0) | AE7: =IF($J$7,1/HU_nCons,0) | AF7: =IF($J$7,$AD$7*$AE$7/SUMPRODUCT($AD$6:$AD$13,$AE$6:$AE$13),0)
A8: incomeMonthly | B8: =PLU_incomeMonthly | C8: A · input | H8: N_TPD | I8: N_TPD | J8: =NC_on_N_TPD | K8: =NC_amount_N_TPD | L8: 0 | M8: =NOT(AND(PLAN_sug_N_TPD,NOT(PLAN_included_N_TPD))) | N8: =IF(NOT($M$8),0,IF(PLAN_sug_N_TPD,MAX(0,PLAN_sum_N_TPD),MAX(0,ROUND($K$8/HU_benefitRound,0)*HU_benefitRound))) | O8: =NP_priority_N_TPD | P8: =IF($M$8,HU_term,HU_ciMaxAge-HU_age)+1 | Q8: =MIN($P$8,HU_T) | R8: C | S8: =$K$8 | T8: =HU_whl*$K$8 | U8: =IF($S$8=0,0,IF(0>$S$8/HU_alpha+$K$8,0.5*$S$8/HU_alpha,IF(0>=$K$8,(0-$K$8)-0.5*HU_alpha/$S$8*(0-$K$8)^2,IF(0>=$T$8,HU_beta*(0-$K$8),HU_beta*($T$8-$K$8))))) | V8: =$U$8*SUM($AN$68:$AN$150) | W8: =SUMPRODUCT($AN$68:$AN$150,$AO$68:$AO$150) | X8: =SUMPRODUCT($AN$68:$AN$150,$AP$68:$AP$150) | Y8: =SUMPRODUCT($AN$68:$AN$150,$AQ$68:$AQ$150) | Z8: =$Y$8-$V$8 | AA8: =IF(NOT($J$8),"",IF($S$8=0,1,IF($Z$8=0,1,IF(AND($Z$8=$W$8-$V$8,$W$8>0),1,MAX(0,MIN(1,($W$8-$V$8)/$Z$8)))))) | AB8: =IF(NOT($J$8),"",IF($S$8=0,1,IF($Z$8=0,1,IF(AND($Z$8=$X$8-$V$8,$X$8>0),1,MAX(0,MIN(1,($X$8-$V$8)/$Z$8)))))) | AC8: =IF(NOT($J$8),"",IF($S$8=0,"w0 = 0 (HU raises an error)",IF($Z$8=0,"denominator 0",""))) | AD8: =IF($J$8,MAX(LN($O$8+1),LN(0+1)),0) | AE8: =IF($J$8,1/HU_nCons,0) | AF8: =IF($J$8,$AD$8*$AE$8/SUMPRODUCT($AD$6:$AD$13,$AE$6:$AE$13),0)
A9: expenseMonthly | B9: =PLU_expenseMonthly | C9: A · input | H9: N_HOS | I9: N_HSP | J9: =NC_on_N_HOS | K9: =NC_amount_N_HOS | L9: 0 | M9: =NOT(AND(PLAN_sug_N_HOS,NOT(PLAN_included_N_HOS))) | N9: =IF(NOT($M$9),0,IF(PLAN_sug_N_HOS,MAX(0,PLAN_sum_N_HOS),MAX(0,ROUND($K$9/HU_benefitRound,0)*HU_benefitRound))) | O9: =NP_priority_N_HOS | P9: =IF($M$9,HU_term,HU_ciMaxAge-HU_age)+1 | Q9: =MIN($P$9,HU_T) | R9: C | S9: =$K$9 | T9: =HU_whl*$K$9 | U9: =IF($S$9=0,0,IF(0>$S$9/HU_alpha+$K$9,0.5*$S$9/HU_alpha,IF(0>=$K$9,(0-$K$9)-0.5*HU_alpha/$S$9*(0-$K$9)^2,IF(0>=$T$9,HU_beta*(0-$K$9),HU_beta*($T$9-$K$9))))) | V9: =$U$9*SUM($AR$68:$AR$150) | W9: =SUMPRODUCT($AR$68:$AR$150,$AS$68:$AS$150) | X9: =SUMPRODUCT($AR$68:$AR$150,$AT$68:$AT$150) | Y9: =SUMPRODUCT($AR$68:$AR$150,$AU$68:$AU$150) | Z9: =$Y$9-$V$9 | AA9: =IF(NOT($J$9),"",IF($S$9=0,1,IF($Z$9=0,1,IF(AND($Z$9=$W$9-$V$9,$W$9>0),1,MAX(0,MIN(1,($W$9-$V$9)/$Z$9)))))) | AB9: =IF(NOT($J$9),"",IF($S$9=0,1,IF($Z$9=0,1,IF(AND($Z$9=$X$9-$V$9,$X$9>0),1,MAX(0,MIN(1,($X$9-$V$9)/$Z$9)))))) | AC9: =IF(NOT($J$9),"",IF($S$9=0,"w0 = 0 (HU raises an error)",IF($Z$9=0,"denominator 0",""))) | AD9: =IF($J$9,MAX(LN($O$9+1),LN(0+1)),0) | AE9: =IF($J$9,1/HU_nCons,0) | AF9: =IF($J$9,$AD$9*$AE$9/SUMPRODUCT($AD$6:$AD$13,$AE$6:$AE$13),0)
A10: cash | B10: =PLU_cash | C10: A · input | D10: A_SAV. HU starts savings at 1 when cash is 0. | H10: N_RET | I10: N_RET | J10: =TRUE | K10: =IF(NC_on_N_RET,NC_amount_N_RET,HU_expense*12*MAX(0,HU_leS-HU_ret)) | L10: 0 | M10: =NOT(AND(PLAN_sug_N_RET,NOT(PLAN_included_N_RET))) | N10: =IF(NOT($M$10),0,MAX(0,ROUND($K$10/HU_benefitRound,0)*HU_benefitRound)) | O10: =IF(NC_on_N_RET,NP_priority_N_RET,5) | P10: =MAX(0,HU_ret-HU_age) | Q10: =MIN($P$10,HU_T) | R10: W | S10: =INDEX($AD$68:$AD$150,IF(HU_T>=1,2,1))+$K$10 | T10: =HU_whl*$K$10 | U10: =IF($S$10=0,0,IF(0>$S$10/HU_alpha+$K$10,0.5*$S$10/HU_alpha,IF(0>=$K$10,(0-$K$10)-0.5*HU_alpha/$S$10*(0-$K$10)^2,IF(0>=$T$10,HU_beta*(0-$K$10),HU_beta*($T$10-$K$10))))) | V10: =$U$10*SUM($AV$68:$AV$150) | W10: =SUMPRODUCT($AV$68:$AV$150,$AW$68:$AW$150) | X10: =SUMPRODUCT($AV$68:$AV$150,$AX$68:$AX$150) | Y10: =SUMPRODUCT($AV$68:$AV$150,$AY$68:$AY$150) | Z10: =$Y$10-$V$10 | AA10: =IF(NOT($J$10),"",IF($S$10=0,1,IF($Z$10=0,1,IF(AND($Z$10=$W$10-$V$10,$W$10>0),1,MAX(0,MIN(1,($W$10-$V$10)/$Z$10)))))) | AB10: =IF(NOT($J$10),"",IF($S$10=0,1,IF($Z$10=0,1,IF(AND($Z$10=$X$10-$V$10,$X$10>0),1,MAX(0,MIN(1,($X$10-$V$10)/$Z$10)))))) | AC10: =IF(NOT($J$10),"",IF($S$10=0,"w0 = 0 (HU raises an error)",IF($Z$10=0,"denominator 0",""))) | AD10: =IF($J$10,MAX(LN($O$10+1),LN(1+1)),0) | AE10: =IF($J$10,HU_calRet,0) | AF10: =IF($J$10,$AD$10*$AE$10/SUMPRODUCT($AD$6:$AD$13,$AE$6:$AE$13),0)
A11: investments | B11: =PLU_investments | C11: A · input | D11: A_INV. Deterministic growth e^(mu·t). | H11: N_EDU | I11: N_EDU | J11: =NC_on_N_EDU | K11: =NC_amount_N_EDU | L11: 0 | M11: =NOT(AND(PLAN_sug_N_EDU,NOT(PLAN_included_N_EDU))) | N11: =IF(NOT($M$11),0,MAX(0,ROUND($K$11/HU_benefitRound,0)*HU_benefitRound)) | O11: =NP_priority_N_EDU | P11: =MAX(0,NC_eduYears) | Q11: =MIN($P$11,HU_T) | R11: C | S11: =$K$11 | T11: =HU_whl*$K$11 | U11: =IF($S$11=0,0,IF(0>$S$11/HU_alpha+$K$11,0.5*$S$11/HU_alpha,IF(0>=$K$11,(0-$K$11)-0.5*HU_alpha/$S$11*(0-$K$11)^2,IF(0>=$T$11,HU_beta*(0-$K$11),HU_beta*($T$11-$K$11))))) | V11: =$U$11*SUM($AZ$68:$AZ$150) | W11: =SUMPRODUCT($AZ$68:$AZ$150,$BA$68:$BA$150) | X11: =SUMPRODUCT($AZ$68:$AZ$150,$BB$68:$BB$150) | Y11: =SUMPRODUCT($AZ$68:$AZ$150,$BC$68:$BC$150) | Z11: =$Y$11-$V$11 | AA11: =IF(NOT($J$11),"",IF($S$11=0,1,IF($Z$11=0,1,IF(AND($Z$11=$W$11-$V$11,$W$11>0),1,MAX(0,MIN(1,($W$11-$V$11)/$Z$11)))))) | AB11: =IF(NOT($J$11),"",IF($S$11=0,1,IF($Z$11=0,1,IF(AND($Z$11=$X$11-$V$11,$X$11>0),1,MAX(0,MIN(1,($X$11-$V$11)/$Z$11)))))) | AC11: =IF(NOT($J$11),"",IF($S$11=0,"w0 = 0 (HU raises an error)",IF($Z$11=0,"denominator 0",""))) | AD11: =IF($J$11,MAX(LN($O$11+1),LN(0+1)),0) | AE11: =IF($J$11,1/HU_nCons,0) | AF11: =IF($J$11,$AD$11*$AE$11/SUMPRODUCT($AD$6:$AD$13,$AE$6:$AE$13),0)
A12: life sum assured | B12: =PLU_lifeSum | C12: A · input | D12: N_INC existing cover. | H12: N_SAV | I12: N_SAV | J12: =NC_on_N_SAV | K12: =NC_amount_N_SAV | L12: 0 | M12: =NOT(AND(PLAN_sug_N_SAV,NOT(PLAN_included_N_SAV))) | N12: =IF(NOT($M$12),0,MAX(0,ROUND($K$12/HU_benefitRound,0)*HU_benefitRound)) | O12: =NP_priority_N_SAV | P12: =MAX(0,NC_eduYears) | Q12: =MIN($P$12,HU_T) | R12: C | S12: =$K$12 | T12: =HU_whl*$K$12 | U12: =IF($S$12=0,0,IF(0>$S$12/HU_alpha+$K$12,0.5*$S$12/HU_alpha,IF(0>=$K$12,(0-$K$12)-0.5*HU_alpha/$S$12*(0-$K$12)^2,IF(0>=$T$12,HU_beta*(0-$K$12),HU_beta*($T$12-$K$12))))) | V12: =$U$12*SUM($BD$68:$BD$150) | W12: =SUMPRODUCT($BD$68:$BD$150,$BE$68:$BE$150) | X12: =SUMPRODUCT($BD$68:$BD$150,$BF$68:$BF$150) | Y12: =SUMPRODUCT($BD$68:$BD$150,$BG$68:$BG$150) | Z12: =$Y$12-$V$12 | AA12: =IF(NOT($J$12),"",IF($S$12=0,1,IF($Z$12=0,1,IF(AND($Z$12=$W$12-$V$12,$W$12>0),1,MAX(0,MIN(1,($W$12-$V$12)/$Z$12)))))) | AB12: =IF(NOT($J$12),"",IF($S$12=0,1,IF($Z$12=0,1,IF(AND($Z$12=$X$12-$V$12,$X$12>0),1,MAX(0,MIN(1,($X$12-$V$12)/$Z$12)))))) | AC12: =IF(NOT($J$12),"",IF($S$12=0,"w0 = 0 (HU raises an error)",IF($Z$12=0,"denominator 0",""))) | AD12: =IF($J$12,MAX(LN($O$12+1),LN(0+1)),0) | AE12: =IF($J$12,1/HU_nCons,0) | AF12: =IF($J$12,$AD$12*$AE$12/SUMPRODUCT($AD$6:$AD$13,$AE$6:$AE$13),0)
A13: session life expectancy | B13: =MIN(PLU_leUsed,99) | C13: A · input | D13: durationOfRetirement = LE − retirement age. | H13: N_PRP | I13: N_PRP | J13: =NC_on_N_PRP | K13: =NC_amount_N_PRP | L13: 0 | M13: =NOT(AND(PLAN_sug_N_PRP,NOT(PLAN_included_N_PRP))) | N13: =IF(NOT($M$13),0,MAX(0,ROUND($K$13/HU_benefitRound,0)*HU_benefitRound)) | O13: =NP_priority_N_PRP | P13: =MAX(0,NC_eduYears) | Q13: =MIN($P$13,HU_T) | R13: C | S13: =$K$13 | T13: =HU_whl*$K$13 | U13: =IF($S$13=0,0,IF(0>$S$13/HU_alpha+$K$13,0.5*$S$13/HU_alpha,IF(0>=$K$13,(0-$K$13)-0.5*HU_alpha/$S$13*(0-$K$13)^2,IF(0>=$T$13,HU_beta*(0-$K$13),HU_beta*($T$13-$K$13))))) | V13: =$U$13*SUM($BH$68:$BH$150) | W13: =SUMPRODUCT($BH$68:$BH$150,$BI$68:$BI$150) | X13: =SUMPRODUCT($BH$68:$BH$150,$BJ$68:$BJ$150) | Y13: =SUMPRODUCT($BH$68:$BH$150,$BK$68:$BK$150) | Z13: =$Y$13-$V$13 | AA13: =IF(NOT($J$13),"",IF($S$13=0,1,IF($Z$13=0,1,IF(AND($Z$13=$W$13-$V$13,$W$13>0),1,MAX(0,MIN(1,($W$13-$V$13)/$Z$13)))))) | AB13: =IF(NOT($J$13),"",IF($S$13=0,1,IF($Z$13=0,1,IF(AND($Z$13=$X$13-$V$13,$X$13>0),1,MAX(0,MIN(1,($X$13-$V$13)/$Z$13)))))) | AC13: =IF(NOT($J$13),"",IF($S$13=0,"w0 = 0 (HU raises an error)",IF($Z$13=0,"denominator 0",""))) | AD13: =IF($J$13,MAX(LN($O$13+1),LN(0+1)),0) | AE13: =IF($J$13,1/HU_nCons,0) | AF13: =IF($J$13,$AD$13*$AE$13/SUMPRODUCT($AD$6:$AD$13,$AE$6:$AE$13),0)
A15: D · ASSUMPTIONS — HU conf.json / config/default/conf.ini / hu_payload.py
A16: ageOfRetirement | B16: =ageOfRetirement | C16: D · assumption / shared
A17: default life expectancy | B17: 83 | C17: D · assumption / shared | D17: HU uses 83 when durationOfRetirement is 0.
A18: CI income years (N_CRI on) | B18: =CRI_YEARS | C18: D · assumption / shared | D18: numYearsIncomeNeeded from GP.
A19: CI income years (N_CRI off) | B19: 5 | C19: D · assumption / shared | D19: HU ciAssumptions default.
A20: CI medical cost | B20: 200000 | C20: D · assumption / shared | D20: HU ciAssumptions medicalCost, × inflation.
A21: TPD medical cost | B21: 444000 | C21: D · assumption / shared | D21: HU ProductPTD (engine still says PTD), × inflation, first TPD only.
A22: TPD income cut | B22: 0.5 | C22: D · assumption / shared
A23: dismemberment income cut | B23: 1 | C23: D · assumption / shared | D23: From the year after.
A24: cover age (off-plan CI / TPD / HSP) | B24: 75 | C24: D · assumption / shared | D24: Off-plan protection runs to age 75.
A25: dependent years (N_INC) | B25: 10 | C25: D · assumption / shared | D25: numYearDependents default.
A26: plan policy term | B26: 10 | C26: D · assumption / shared | D26: segregatedBudget policyTerm in hu_payload.py.
A27: wealth high-loss factor | B27: 0.25 | C27: D · assumption / shared | D27: conf.ini wealth_hight_loss_factor.
A28: beta | B28: 1 | C28: D · assumption / shared | D28: conf.ini beta.
A29: minimum equity drift | B29: 0.01 | C29: D · assumption / shared | D29: ProductEquity mu floor.
A30: riskProfile | B30: 4 | C30: D · assumption / shared | D30: hu_payload.py default.
A31: retirement lifestyle rate | B31: =RET_LIFESTYLE_STRESSFREE | C31: D · assumption / shared | D31: N_RET lifestyle 2.
A32: retirement spend share | B32: 0.75 | C32: D · assumption / shared | D32: expectedLivingExpenseInTheCountry = living × 0.75.
A33: benefit round (user currency) | B33: =FX_benefitRound | C33: D · assumption / shared | D33: benefitRound (USD) as a nice step in user currency. SGD: 50,000.
A34: N_RET calibration | B34: 2 | C34: D · assumption / shared | D34: N_INC 1, N_RET 2, consumption goals 1 / count.
A36: C · DETERMINISTICALLY CALCULATED — HU input mapping
A37: life expectancy (HU) | B37: =IF(HU_leS>HU_ret,HU_leS,HU_defaultLE) | C37: C · calculated | D37: durationOfRetirement + 65, or 83.
A38: years on the path (T) | B38: =MAX(HU_le-HU_age,0) | C38: C · calculated
A39: years to retirement | B39: =MAX(HU_ret-HU_age,0) | C39: C · calculated
A40: q(age) column | B40: =IF(HU_gender="Male",1,3)+IF(HU_smoker=TRUE,1,0) | C40: C · calculated | D40: 1 Male, 2 Male smoker, 3 Female, 4 Female smoker.
A41: income / yr (HU) | B41: =1+HU_income*12 | C41: C · calculated | D41: HU adds 1 to the salary.
A42: spend / yr | B42: =HU_expense*12 | C42: C · calculated
A43: retirement spend / yr | B43: =HU_exp0*HU_retLifestyle*HU_retShare | C43: C · calculated | D43: Replaces spend after retirement.
A44: CI income years | B44: =IF(NC_on_N_CRI,HU_ciYearsGP,HU_ciDefaultYears) | C44: C · calculated
A45: CI income share | B45: =MAX(0,MIN(1,HU_exp0/HU_inc0)) | C45: C · calculated | D45: Share of income lost while ill.
A46: savings at t = 0 | B46: =IF(N(HU_cash)=0,1,HU_cash) | C46: C · calculated
A47: equity drift | B47: =IF(HU_inv>0,MAX(HU_minMu,investmentReturn),0) | C47: C · calculated
A48: HU errors (retiree with investments) | B48: =AND(HU_inv>0,HU_dtr=0) | C48: C · calculated | D48: Live HU returns NaN here; this tab still scores (Discrepancies).
A49: alpha | B49: =1+(HU_riskProfile-1)*0.5 | C49: C · calculated | D49: Value-function curvature from riskProfile.
A50: goal withdrawals on the path | B50: =AND(HU_T>0,NC_eduYears<=HU_T) | C50: C · calculated
A51: goal withdrawal year | B51: =IF(HU_T>0,MOD(NC_eduYears-1,HU_T)+1,0) | C51: C · calculated | D51: fundsNeededYear − now.
A52: SAV + PRP booked as income | B52: =NC_on_N_SAV*NC_amount_N_SAV+NC_on_N_PRP*NC_amount_N_PRP | C52: C · calculated | D52: HU adds the SAV / PRP amount as income in the target year and spends it again (net 0).
A53: EDU + SAV + PRP spent | B53: =NC_on_N_EDU*NC_amount_N_EDU+NC_on_N_SAV*NC_amount_N_SAV+NC_on_N_PRP*NC_amount_N_PRP | C53: C · calculated
A55: C · RESULTS — weights, sigmoid, HappiU (0–100)
A56: goals scored | B56: =COUNTIF($J$6:$J$13,TRUE) | C56: C · calculated
A57: consumption goals | B57: =COUNTIFS($J$6:$J$13,TRUE,$R$6:$R$13,"C") | C57: C · calculated | D57: Everything except N_INC / N_ADB / N_RET.
A58: sigmoid divisor | B58: =1+EXP(-HU_nGoals) | C58: C · calculated | D58: Weighted sum ÷ (1 + e^(−number of goals)).
A59: pre (0–1) | B59: =SUMPRODUCT($AA$6:$AA$13,$AF$6:$AF$13)/HU_sig | C59: C · calculated
A60: post (0–1) | B60: =SUMPRODUCT($AB$6:$AB$13,$AF$6:$AF$13)/HU_sig | C60: C · calculated
A61: preHappiU | B61: =ROUND(HU_preRaw*100,0) | C61: C · calculated | D61: Today's cover.
A62: postHappiU | B62: =ROUND(HU_postRaw*100,0) | C62: C · calculated | D62: With the plan's benefits.
A66: year | D66: D · q(age + year) from Assumptions | I66: C · PROBABILITIES | R66: C · EXPECTED CASH FLOWS AND PATHS (alive) | AF66: C · N_INC (W path) | AJ66: C · N_CRI (consumption path) | AN66: C · N_TPD (consumption path) | AR66: C · N_HOS (consumption path) | AV66: C · N_RET (W path) | AZ66: C · N_EDU (consumption path) | BD66: C · N_SAV (consumption path) | BH66: C · N_PRP (consumption path)
A67: year | B67: age | C67: on path | D67: q mortality | E67: q accidental death | F67: q critical illness | G67: q TPD | H67: q dismemberment | I67: alive | J67: score weight | K67: no TPD yet | L67: P(TPD so far) | M67: P(first TPD) | N67: no dismemberment | O67: P(dismembered before) | P67: no CI (running) | Q67: P(CI in window) | R67: inflation index | S67: salary | T67: ss growth index | U67: social-security lump | V67: income + lump + SAV/PRP | W67: expected income cut | X67: income after cut | Y67: spend | Z67: spend + goals | AA67: expected medical | AB67: savings | AC67: equity | AD67: WEALTH | AE67: CONSUMPTION WEALTH | AF67: N_INC weight | AG67: N_INC v pre | AH67: N_INC v rec | AI67: N_INC v full | AJ67: N_CRI weight | AK67: N_CRI v pre | AL67: N_CRI v rec | AM67: N_CRI v full | AN67: N_TPD weight | AO67: N_TPD v pre | AP67: N_TPD v rec | AQ67: N_TPD v full | AR67: N_HOS weight | AS67: N_HOS v pre | AT67: N_HOS v rec | AU67: N_HOS v full | AV67: N_RET weight | AW67: N_RET v pre | AX67: N_RET v rec | AY67: N_RET v full | AZ67: N_EDU weight | BA67: N_EDU v pre | BB67: N_EDU v rec | BC67: N_EDU v full | BD67: N_SAV weight | BE67: N_SAV v pre | BF67: N_SAV v rec | BG67: N_SAV v full | BH67: N_PRP weight | BI67: N_PRP v pre | BJ67: N_PRP v rec | BK67: N_PRP v full
A68: 0 | B68: =HU_age+A68 | C68: =A68<=HU_T | D68: =IF(OR(A68<1,A68>HU_T),0,INDEX(HU_q_mort,HU_age+A68-17,HU_col)) | E68: =IF(OR(A68<1,A68>HU_T),0,INDEX(HU_q_adb,HU_age+A68-17,HU_col)) | F68: =IF(OR(A68<1,A68>HU_T),0,INDEX(HU_q_morb,HU_age+A68-17,HU_col)) | G68: =IF(OR(A68<1,A68>HU_T),0,INDEX(HU_q_ptd,HU_age+A68-17,HU_col)) | H68: =IF(OR(A68<1,A68>HU_T),0,INDEX(HU_q_dis,HU_age+A68-17,HU_col)) | I68: 1 | J68: =IF(A68>=HU_T,0,N(I69)) | K68: 1 | L68: 0 | M68: 0 | N68: 1 | O68: 0 | P68: 1 | Q68: 0 | R68: =(1+inflationRate)^A68 | S68: 0 | T68: 1 | U68: 0 | V68: 0 | W68: 0 | X68: 0 | Y68: 0 | Z68: 0 | AA68: 0 | AB68: =HU_cash0 | AC68: =IF(A68>HU_T,0,HU_inv*EXP(HU_mu*A68)) | AD68: =IF(A68>HU_T,0,MAX(0,AC68+AB68)) | AE68: 0 | AF68: =IF(AND($J$6,A68>=1,A68<=$Q$6-1),J68,0) | AG68: =IF(OR(AF68=0,$S$6=0),0,IF((AD68+$L$6)>$S$6/HU_alpha+$K$6,0.5*$S$6/HU_alpha,IF((AD68+$L$6)>=$K$6,((AD68+$L$6)-$K$6)-0.5*HU_alpha/$S$6*((AD68+$L$6)-$K$6)^2,IF((AD68+$L$6)>=$T$6,HU_beta*((AD68+$L$6)-$K$6),HU_beta*($T$6-$K$6))))) | AH68: =IF(OR(AF68=0,$S$6=0),0,IF((AD68+$L$6+$N$6)>$S$6/HU_alpha+$K$6,0.5*$S$6/HU_alpha,IF((AD68+$L$6+$N$6)>=$K$6,((AD68+$L$6+$N$6)-$K$6)-0.5*HU_alpha/$S$6*((AD68+$L$6+$N$6)-$K$6)^2,IF((AD68+$L$6+$N$6)>=$T$6,HU_beta*((AD68+$L$6+$N$6)-$K$6),HU_beta*($T$6-$K$6))))) | AI68: =IF(OR(AF68=0,$S$6=0),0,IF((AD68+$K$6)>$S$6/HU_alpha+$K$6,0.5*$S$6/HU_alpha,IF((AD68+$K$6)>=$K$6,((AD68+$K$6)-$K$6)-0.5*HU_alpha/$S$6*((AD68+$K$6)-$K$6)^2,IF((AD68+$K$6)>=$T$6,HU_beta*((AD68+$K$6)-$K$6),HU_beta*($T$6-$K$6))))) | AJ68: =IF(AND($J$7,A68>=1,A68<=$Q$7-1),J68,0) | AK68: =IF(OR(AJ68=0,$S$7=0),0,IF((AE68+$L$7)>$S$7/HU_alpha+$K$7,0.5*$S$7/HU_alpha,IF((AE68+$L$7)>=$K$7,((AE68+$L$7)-$K$7)-0.5*HU_alpha/$S$7*((AE68+$L$7)-$K$7)^2,IF((AE68+$L$7)>=$T$7,HU_beta*((AE68+$L$7)-$K$7),HU_beta*($T$7-$K$7))))) | AL68: =IF(OR(AJ68=0,$S$7=0),0,IF((AE68+$L$7+$N$7)>$S$7/HU_alpha+$K$7,0.5*$S$7/HU_alpha,IF((AE68+$L$7+$N$7)>=$K$7,((AE68+$L$7+$N$7)-$K$7)-0.5*HU_alpha/$S$7*((AE68+$L$7+$N$7)-$K$7)^2,IF((AE68+$L$7+$N$7)>=$T$7,HU_beta*((AE68+$L$7+$N$7)-$K$7),HU_beta*($T$7-$K$7))))) | AM68: =IF(OR(AJ68=0,$S$7=0),0,IF((AE68+$K$7)>$S$7/HU_alpha+$K$7,0.5*$S$7/HU_alpha,IF((AE68+$K$7)>=$K$7,((AE68+$K$7)-$K$7)-0.5*HU_alpha/$S$7*((AE68+$K$7)-$K$7)^2,IF((AE68+$K$7)>=$T$7,HU_beta*((AE68+$K$7)-$K$7),HU_beta*($T$7-$K$7))))) | AN68: =IF(AND($J$8,A68>=1,A68<=$Q$8-1),J68,0) | AO68: =IF(OR(AN68=0,$S$8=0),0,IF((AE68+$L$8)>$S$8/HU_alpha+$K$8,0.5*$S$8/HU_alpha,IF((AE68+$L$8)>=$K$8,((AE68+$L$8)-$K$8)-0.5*HU_alpha/$S$8*((AE68+$L$8)-$K$8)^2,IF((AE68+$L$8)>=$T$8,HU_beta*((AE68+$L$8)-$K$8),HU_beta*($T$8-$K$8))))) | AP68: =IF(OR(AN68=0,$S$8=0),0,IF((AE68+$L$8+$N$8)>$S$8/HU_alpha+$K$8,0.5*$S$8/HU_alpha,IF((AE68+$L$8+$N$8)>=$K$8,((AE68+$L$8+$N$8)-$K$8)-0.5*HU_alpha/$S$8*((AE68+$L$8+$N$8)-$K$8)^2,IF((AE68+$L$8+$N$8)>=$T$8,HU_beta*((AE68+$L$8+$N$8)-$K$8),HU_beta*($T$8-$K$8))))) | AQ68: =IF(OR(AN68=0,$S$8=0),0,IF((AE68+$K$8)>$S$8/HU_alpha+$K$8,0.5*$S$8/HU_alpha,IF((AE68+$K$8)>=$K$8,((AE68+$K$8)-$K$8)-0.5*HU_alpha/$S$8*((AE68+$K$8)-$K$8)^2,IF((AE68+$K$8)>=$T$8,HU_beta*((AE68+$K$8)-$K$8),HU_beta*($T$8-$K$8))))) | AR68: =IF(AND($J$9,A68>=1,A68<=$Q$9-1),J68,0) | AS68: =IF(OR(AR68=0,$S$9=0),0,IF((AE68+$L$9)>$S$9/HU_alpha+$K$9,0.5*$S$9/HU_alpha,IF((AE68+$L$9)>=$K$9,((AE68+$L$9)-$K$9)-0.5*HU_alpha/$S$9*((AE68+$L$9)-$K$9)^2,IF((AE68+$L$9)>=$T$9,HU_beta*((AE68+$L$9)-$K$9),HU_beta*($T$9-$K$9))))) | AT68: =IF(OR(AR68=0,$S$9=0),0,IF((AE68+$L$9+$N$9)>$S$9/HU_alpha+$K$9,0.5*$S$9/HU_alpha,IF((AE68+$L$9+$N$9)>=$K$9,((AE68+$L$9+$N$9)-$K$9)-0.5*HU_alpha/$S$9*((AE68+$L$9+$N$9)-$K$9)^2,IF((AE68+$L$9+$N$9)>=$T$9,HU_beta*((AE68+$L$9+$N$9)-$K$9),HU_beta*($T$9-$K$9))))) | AU68: =IF(OR(AR68=0,$S$9=0),0,IF((AE68+$K$9)>$S$9/HU_alpha+$K$9,0.5*$S$9/HU_alpha,IF((AE68+$K$9)>=$K$9,((AE68+$K$9)-$K$9)-0.5*HU_alpha/$S$9*((AE68+$K$9)-$K$9)^2,IF((AE68+$K$9)>=$T$9,HU_beta*((AE68+$K$9)-$K$9),HU_beta*($T$9-$K$9))))) | AV68: =IF(AND($J$10,A68=$Q$10),J68,0) | AW68: =IF(OR(AV68=0,$S$10=0),0,IF((AD68+$L$10)>$S$10/HU_alpha+$K$10,0.5*$S$10/HU_alpha,IF((AD68+$L$10)>=$K$10,((AD68+$L$10)-$K$10)-0.5*HU_alpha/$S$10*((AD68+$L$10)-$K$10)^2,IF((AD68+$L$10)>=$T$10,HU_beta*((AD68+$L$10)-$K$10),HU_beta*($T$10-$K$10))))) | AX68: =IF(OR(AV68=0,$S$10=0),0,IF((AD68+$L$10+$N$10)>$S$10/HU_alpha+$K$10,0.5*$S$10/HU_alpha,IF((AD68+$L$10+$N$10)>=$K$10,((AD68+$L$10+$N$10)-$K$10)-0.5*HU_alpha/$S$10*((AD68+$L$10+$N$10)-$K$10)^2,IF((AD68+$L$10+$N$10)>=$T$10,HU_beta*((AD68+$L$10+$N$10)-$K$10),HU_beta*($T$10-$K$10))))) | AY68: =IF(OR(AV68=0,$S$10=0),0,IF((AD68+$K$10)>$S$10/HU_alpha+$K$10,0.5*$S$10/HU_alpha,IF((AD68+$K$10)>=$K$10,((AD68+$K$10)-$K$10)-0.5*HU_alpha/$S$10*((AD68+$K$10)-$K$10)^2,IF((AD68+$K$10)>=$T$10,HU_beta*((AD68+$K$10)-$K$10),HU_beta*($T$10-$K$10))))) | AZ68: =IF(AND($J$11,A68=$Q$11),J68,0) | BA68: =IF(OR(AZ68=0,$S$11=0),0,IF((AE68+$L$11)>$S$11/HU_alpha+$K$11,0.5*$S$11/HU_alpha,IF((AE68+$L$11)>=$K$11,((AE68+$L$11)-$K$11)-0.5*HU_alpha/$S$11*((AE68+$L$11)-$K$11)^2,IF((AE68+$L$11)>=$T$11,HU_beta*((AE68+$L$11)-$K$11),HU_beta*($T$11-$K$11))))) | BB68: =IF(OR(AZ68=0,$S$11=0),0,IF((AE68+$L$11+$N$11)>$S$11/HU_alpha+$K$11,0.5*$S$11/HU_alpha,IF((AE68+$L$11+$N$11)>=$K$11,((AE68+$L$11+$N$11)-$K$11)-0.5*HU_alpha/$S$11*((AE68+$L$11+$N$11)-$K$11)^2,IF((AE68+$L$11+$N$11)>=$T$11,HU_beta*((AE68+$L$11+$N$11)-$K$11),HU_beta*($T$11-$K$11))))) | BC68: =IF(OR(AZ68=0,$S$11=0),0,IF((AE68+$K$11)>$S$11/HU_alpha+$K$11,0.5*$S$11/HU_alpha,IF((AE68+$K$11)>=$K$11,((AE68+$K$11)-$K$11)-0.5*HU_alpha/$S$11*((AE68+$K$11)-$K$11)^2,IF((AE68+$K$11)>=$T$11,HU_beta*((AE68+$K$11)-$K$11),HU_beta*($T$11-$K$11))))) | BD68: =IF(AND($J$12,A68=$Q$12),J68,0) | BE68: =IF(OR(BD68=0,$S$12=0),0,IF((AE68+$L$12)>$S$12/HU_alpha+$K$12,0.5*$S$12/HU_alpha,IF((AE68+$L$12)>=$K$12,((AE68+$L$12)-$K$12)-0.5*HU_alpha/$S$12*((AE68+$L$12)-$K$12)^2,IF((AE68+$L$12)>=$T$12,HU_beta*((AE68+$L$12)-$K$12),HU_beta*($T$12-$K$12))))) | BF68: =IF(OR(BD68=0,$S$12=0),0,IF((AE68+$L$12+$N$12)>$S$12/HU_alpha+$K$12,0.5*$S$12/HU_alpha,IF((AE68+$L$12+$N$12)>=$K$12,((AE68+$L$12+$N$12)-$K$12)-0.5*HU_alpha/$S$12*((AE68+$L$12+$N$12)-$K$12)^2,IF((AE68+$L$12+$N$12)>=$T$12,HU_beta*((AE68+$L$12+$N$12)-$K$12),HU_beta*($T$12-$K$12))))) | BG68: =IF(OR(BD68=0,$S$12=0),0,IF((AE68+$K$12)>$S$12/HU_alpha+$K$12,0.5*$S$12/HU_alpha,IF((AE68+$K$12)>=$K$12,((AE68+$K$12)-$K$12)-0.5*HU_alpha/$S$12*((AE68+$K$12)-$K$12)^2,IF((AE68+$K$12)>=$T$12,HU_beta*((AE68+$K$12)-$K$12),HU_beta*($T$12-$K$12))))) | BH68: =IF(AND($J$13,A68=$Q$13),J68,0) | BI68: =IF(OR(BH68=0,$S$13=0),0,IF((AE68+$L$13)>$S$13/HU_alpha+$K$13,0.5*$S$13/HU_alpha,IF((AE68+$L$13)>=$K$13,((AE68+$L$13)-$K$13)-0.5*HU_alpha/$S$13*((AE68+$L$13)-$K$13)^2,IF((AE68+$L$13)>=$T$13,HU_beta*((AE68+$L$13)-$K$13),HU_beta*($T$13-$K$13))))) | BJ68: =IF(OR(BH68=0,$S$13=0),0,IF((AE68+$L$13+$N$13)>$S$13/HU_alpha+$K$13,0.5*$S$13/HU_alpha,IF((AE68+$L$13+$N$13)>=$K$13,((AE68+$L$13+$N$13)-$K$13)-0.5*HU_alpha/$S$13*((AE68+$L$13+$N$13)-$K$13)^2,IF((AE68+$L$13+$N$13)>=$T$13,HU_beta*((AE68+$L$13+$N$13)-$K$13),HU_beta*($T$13-$K$13))))) | BK68: =IF(OR(BH68=0,$S$13=0),0,IF((AE68+$K$13)>$S$13/HU_alpha+$K$13,0.5*$S$13/HU_alpha,IF((AE68+$K$13)>=$K$13,((AE68+$K$13)-$K$13)-0.5*HU_alpha/$S$13*((AE68+$K$13)-$K$13)^2,IF((AE68+$K$13)>=$T$13,HU_beta*((AE68+$K$13)-$K$13),HU_beta*($T$13-$K$13)))))
A69: 1 | B69: =HU_age+A69 | C69: =A69<=HU_T | D69: =IF(OR(A69<1,A69>HU_T),0,INDEX(HU_q_mort,HU_age+A69-17,HU_col)) | E69: =IF(OR(A69<1,A69>HU_T),0,INDEX(HU_q_adb,HU_age+A69-17,HU_col)) | F69: =IF(OR(A69<1,A69>HU_T),0,INDEX(HU_q_morb,HU_age+A69-17,HU_col)) | G69: =IF(OR(A69<1,A69>HU_T),0,INDEX(HU_q_ptd,HU_age+A69-17,HU_col)) | H69: =IF(OR(A69<1,A69>HU_T),0,INDEX(HU_q_dis,HU_age+A69-17,HU_col)) | I69: =IF(A69>HU_T,0,I68*(1-D69)*(1-E69)) | J69: =IF(A69>=HU_T,0,N(I70)) | K69: =K68*(1-G69) | L69: =1-K69 | M69: =K68*G69 | N69: =N68*(1-H69) | O69: =1-N68 | P69: =P68*(1-F69) | Q69: =1-P68/INDEX($P$68:$P$150,MAX(1,A69-HU_ciYears)) | R69: =(1+inflationRate)^A69 | S69: =IF(OR(OR(A69<1,A69>HU_T),A69-1>=HU_dtr),0,HU_inc0*(1+incomeGrowthRate)^A69) | T69: =IF(A69>HU_T,T68,T68*(1+INDEX(HU_ssG,HU_age+A69-17))) | U69: =IF(AND(HU_dtr>=1,A69=HU_dtr,A69<=HU_T),MIN(S69*INDEX(HU_ssC,HU_age+A69-17)/(1-INDEX(HU_ssC,HU_age+A69-17)),INDEX(HU_ssCap,HU_age+A69-17))*T69,0) | V69: =S69+U69+IF(AND(HU_wdOn,A69=HU_wdYear),HU_wdIncome,0) | W69: =HU_ciProp*Q69+HU_tpdCut*L69+HU_disCut*O69 | X69: =IF(OR(A69<1,A69>HU_T),0,V69*(1-W69)) | Y69: =IF(OR(A69<1,A69>HU_T),0,IF(AND(HU_retExp>0,A69-1>=HU_dtr),HU_retExp,HU_exp0)*R69) | Z69: =-Y69-IF(AND(HU_wdOn,A69=HU_wdYear),HU_wdOut,0) | AA69: =IF(OR(A69<1,A69>HU_T),0,-HU_medCost*R69*F69-HU_tpdCost*R69*M69) | AB69: =IF(A69>HU_T,0,AB68*(1+interestRate)+X69+Z69+AA69) | AC69: =IF(A69>HU_T,0,HU_inv*EXP(HU_mu*A69)) | AD69: =IF(A69>HU_T,0,MAX(0,AC69+AB69)) | AE69: =IF(A69>HU_T,0,MAX(0,X69-Y69)) | AF69: =IF(AND($J$6,A69>=1,A69<=$Q$6-1),J69,0) | AG69: =IF(OR(AF69=0,$S$6=0),0,IF((AD69+$L$6)>$S$6/HU_alpha+$K$6,0.5*$S$6/HU_alpha,IF((AD69+$L$6)>=$K$6,((AD69+$L$6)-$K$6)-0.5*HU_alpha/$S$6*((AD69+$L$6)-$K$6)^2,IF((AD69+$L$6)>=$T$6,HU_beta*((AD69+$L$6)-$K$6),HU_beta*($T$6-$K$6))))) | AH69: =IF(OR(AF69=0,$S$6=0),0,IF((AD69+$L$6+$N$6)>$S$6/HU_alpha+$K$6,0.5*$S$6/HU_alpha,IF((AD69+$L$6+$N$6)>=$K$6,((AD69+$L$6+$N$6)-$K$6)-0.5*HU_alpha/$S$6*((AD69+$L$6+$N$6)-$K$6)^2,IF((AD69+$L$6+$N$6)>=$T$6,HU_beta*((AD69+$L$6+$N$6)-$K$6),HU_beta*($T$6-$K$6))))) | AI69: =IF(OR(AF69=0,$S$6=0),0,IF((AD69+$K$6)>$S$6/HU_alpha+$K$6,0.5*$S$6/HU_alpha,IF((AD69+$K$6)>=$K$6,((AD69+$K$6)-$K$6)-0.5*HU_alpha/$S$6*((AD69+$K$6)-$K$6)^2,IF((AD69+$K$6)>=$T$6,HU_beta*((AD69+$K$6)-$K$6),HU_beta*($T$6-$K$6))))) | AJ69: =IF(AND($J$7,A69>=1,A69<=$Q$7-1),J69,0) | AK69: =IF(OR(AJ69=0,$S$7=0),0,IF((AE69+$L$7)>$S$7/HU_alpha+$K$7,0.5*$S$7/HU_alpha,IF((AE69+$L$7)>=$K$7,((AE69+$L$7)-$K$7)-0.5*HU_alpha/$S$7*((AE69+$L$7)-$K$7)^2,IF((AE69+$L$7)>=$T$7,HU_beta*((AE69+$L$7)-$K$7),HU_beta*($T$7-$K$7))))) | AL69: =IF(OR(AJ69=0,$S$7=0),0,IF((AE69+$L$7+$N$7)>$S$7/HU_alpha+$K$7,0.5*$S$7/HU_alpha,IF((AE69+$L$7+$N$7)>=$K$7,((AE69+$L$7+$N$7)-$K$7)-0.5*HU_alpha/$S$7*((AE69+$L$7+$N$7)-$K$7)^2,IF((AE69+$L$7+$N$7)>=$T$7,HU_beta*((AE69+$L$7+$N$7)-$K$7),HU_beta*($T$7-$K$7))))) | AM69: =IF(OR(AJ69=0,$S$7=0),0,IF((AE69+$K$7)>$S$7/HU_alpha+$K$7,0.5*$S$7/HU_alpha,IF((AE69+$K$7)>=$K$7,((AE69+$K$7)-$K$7)-0.5*HU_alpha/$S$7*((AE69+$K$7)-$K$7)^2,IF((AE69+$K$7)>=$T$7,HU_beta*((AE69+$K$7)-$K$7),HU_beta*($T$7-$K$7))))) | AN69: =IF(AND($J$8,A69>=1,A69<=$Q$8-1),J69,0) | AO69: =IF(OR(AN69=0,$S$8=0),0,IF((AE69+$L$8)>$S$8/HU_alpha+$K$8,0.5*$S$8/HU_alpha,IF((AE69+$L$8)>=$K$8,((AE69+$L$8)-$K$8)-0.5*HU_alpha/$S$8*((AE69+$L$8)-$K$8)^2,IF((AE69+$L$8)>=$T$8,HU_beta*((AE69+$L$8)-$K$8),HU_beta*($T$8-$K$8))))) | AP69: =IF(OR(AN69=0,$S$8=0),0,IF((AE69+$L$8+$N$8)>$S$8/HU_alpha+$K$8,0.5*$S$8/HU_alpha,IF((AE69+$L$8+$N$8)>=$K$8,((AE69+$L$8+$N$8)-$K$8)-0.5*HU_alpha/$S$8*((AE69+$L$8+$N$8)-$K$8)^2,IF((AE69+$L$8+$N$8)>=$T$8,HU_beta*((AE69+$L$8+$N$8)-$K$8),HU_beta*($T$8-$K$8))))) | AQ69: =IF(OR(AN69=0,$S$8=0),0,IF((AE69+$K$8)>$S$8/HU_alpha+$K$8,0.5*$S$8/HU_alpha,IF((AE69+$K$8)>=$K$8,((AE69+$K$8)-$K$8)-0.5*HU_alpha/$S$8*((AE69+$K$8)-$K$8)^2,IF((AE69+$K$8)>=$T$8,HU_beta*((AE69+$K$8)-$K$8),HU_beta*($T$8-$K$8))))) | AR69: =IF(AND($J$9,A69>=1,A69<=$Q$9-1),J69,0) | AS69: =IF(OR(AR69=0,$S$9=0),0,IF((AE69+$L$9)>$S$9/HU_alpha+$K$9,0.5*$S$9/HU_alpha,IF((AE69+$L$9)>=$K$9,((AE69+$L$9)-$K$9)-0.5*HU_alpha/$S$9*((AE69+$L$9)-$K$9)^2,IF((AE69+$L$9)>=$T$9,HU_beta*((AE69+$L$9)-$K$9),HU_beta*($T$9-$K$9))))) | AT69: =IF(OR(AR69=0,$S$9=0),0,IF((AE69+$L$9+$N$9)>$S$9/HU_alpha+$K$9,0.5*$S$9/HU_alpha,IF((AE69+$L$9+$N$9)>=$K$9,((AE69+$L$9+$N$9)-$K$9)-0.5*HU_alpha/$S$9*((AE69+$L$9+$N$9)-$K$9)^2,IF((AE69+$L$9+$N$9)>=$T$9,HU_beta*((AE69+$L$9+$N$9)-$K$9),HU_beta*($T$9-$K$9))))) | AU69: =IF(OR(AR69=0,$S$9=0),0,IF((AE69+$K$9)>$S$9/HU_alpha+$K$9,0.5*$S$9/HU_alpha,IF((AE69+$K$9)>=$K$9,((AE69+$K$9)-$K$9)-0.5*HU_alpha/$S$9*((AE69+$K$9)-$K$9)^2,IF((AE69+$K$9)>=$T$9,HU_beta*((AE69+$K$9)-$K$9),HU_beta*($T$9-$K$9))))) | AV69: =IF(AND($J$10,A69=$Q$10),J69,0) | AW69: =IF(OR(AV69=0,$S$10=0),0,IF((AD69+$L$10)>$S$10/HU_alpha+$K$10,0.5*$S$10/HU_alpha,IF((AD69+$L$10)>=$K$10,((AD69+$L$10)-$K$10)-0.5*HU_alpha/$S$10*((AD69+$L$10)-$K$10)^2,IF((AD69+$L$10)>=$T$10,HU_beta*((AD69+$L$10)-$K$10),HU_beta*($T$10-$K$10))))) | AX69: =IF(OR(AV69=0,$S$10=0),0,IF((AD69+$L$10+$N$10)>$S$10/HU_alpha+$K$10,0.5*$S$10/HU_alpha,IF((AD69+$L$10+$N$10)>=$K$10,((AD69+$L$10+$N$10)-$K$10)-0.5*HU_alpha/$S$10*((AD69+$L$10+$N$10)-$K$10)^2,IF((AD69+$L$10+$N$10)>=$T$10,HU_beta*((AD69+$L$10+$N$10)-$K$10),HU_beta*($T$10-$K$10))))) | AY69: =IF(OR(AV69=0,$S$10=0),0,IF((AD69+$K$10)>$S$10/HU_alpha+$K$10,0.5*$S$10/HU_alpha,IF((AD69+$K$10)>=$K$10,((AD69+$K$10)-$K$10)-0.5*HU_alpha/$S$10*((AD69+$K$10)-$K$10)^2,IF((AD69+$K$10)>=$T$10,HU_beta*((AD69+$K$10)-$K$10),HU_beta*($T$10-$K$10))))) | AZ69: =IF(AND($J$11,A69=$Q$11),J69,0) | BA69: =IF(OR(AZ69=0,$S$11=0),0,IF((AE69+$L$11)>$S$11/HU_alpha+$K$11,0.5*$S$11/HU_alpha,IF((AE69+$L$11)>=$K$11,((AE69+$L$11)-$K$11)-0.5*HU_alpha/$S$11*((AE69+$L$11)-$K$11)^2,IF((AE69+$L$11)>=$T$11,HU_beta*((AE69+$L$11)-$K$11),HU_beta*($T$11-$K$11))))) | BB69: =IF(OR(AZ69=0,$S$11=0),0,IF((AE69+$L$11+$N$11)>$S$11/HU_alpha+$K$11,0.5*$S$11/HU_alpha,IF((AE69+$L$11+$N$11)>=$K$11,((AE69+$L$11+$N$11)-$K$11)-0.5*HU_alpha/$S$11*((AE69+$L$11+$N$11)-$K$11)^2,IF((AE69+$L$11+$N$11)>=$T$11,HU_beta*((AE69+$L$11+$N$11)-$K$11),HU_beta*($T$11-$K$11))))) | BC69: =IF(OR(AZ69=0,$S$11=0),0,IF((AE69+$K$11)>$S$11/HU_alpha+$K$11,0.5*$S$11/HU_alpha,IF((AE69+$K$11)>=$K$11,((AE69+$K$11)-$K$11)-0.5*HU_alpha/$S$11*((AE69+$K$11)-$K$11)^2,IF((AE69+$K$11)>=$T$11,HU_beta*((AE69+$K$11)-$K$11),HU_beta*($T$11-$K$11))))) | BD69: =IF(AND($J$12,A69=$Q$12),J69,0) | BE69: =IF(OR(BD69=0,$S$12=0),0,IF((AE69+$L$12)>$S$12/HU_alpha+$K$12,0.5*$S$12/HU_alpha,IF((AE69+$L$12)>=$K$12,((AE69+$L$12)-$K$12)-0.5*HU_alpha/$S$12*((AE69+$L$12)-$K$12)^2,IF((AE69+$L$12)>=$T$12,HU_beta*((AE69+$L$12)-$K$12),HU_beta*($T$12-$K$12))))) | BF69: =IF(OR(BD69=0,$S$12=0),0,IF((AE69+$L$12+$N$12)>$S$12/HU_alpha+$K$12,0.5*$S$12/HU_alpha,IF((AE69+$L$12+$N$12)>=$K$12,((AE69+$L$12+$N$12)-$K$12)-0.5*HU_alpha/$S$12*((AE69+$L$12+$N$12)-$K$12)^2,IF((AE69+$L$12+$N$12)>=$T$12,HU_beta*((AE69+$L$12+$N$12)-$K$12),HU_beta*($T$12-$K$12))))) | BG69: =IF(OR(BD69=0,$S$12=0),0,IF((AE69+$K$12)>$S$12/HU_alpha+$K$12,0.5*$S$12/HU_alpha,IF((AE69+$K$12)>=$K$12,((AE69+$K$12)-$K$12)-0.5*HU_alpha/$S$12*((AE69+$K$12)-$K$12)^2,IF((AE69+$K$12)>=$T$12,HU_beta*((AE69+$K$12)-$K$12),HU_beta*($T$12-$K$12))))) | BH69: =IF(AND($J$13,A69=$Q$13),J69,0) | BI69: =IF(OR(BH69=0,$S$13=0),0,IF((AE69+$L$13)>$S$13/HU_alpha+$K$13,0.5*$S$13/HU_alpha,IF((AE69+$L$13)>=$K$13,((AE69+$L$13)-$K$13)-0.5*HU_alpha/$S$13*((AE69+$L$13)-$K$13)^2,IF((AE69+$L$13)>=$T$13,HU_beta*((AE69+$L$13)-$K$13),HU_beta*($T$13-$K$13))))) | BJ69: =IF(OR(BH69=0,$S$13=0),0,IF((AE69+$L$13+$N$13)>$S$13/HU_alpha+$K$13,0.5*$S$13/HU_alpha,IF((AE69+$L$13+$N$13)>=$K$13,((AE69+$L$13+$N$13)-$K$13)-0.5*HU_alpha/$S$13*((AE69+$L$13+$N$13)-$K$13)^2,IF((AE69+$L$13+$N$13)>=$T$13,HU_beta*((AE69+$L$13+$N$13)-$K$13),HU_beta*($T$13-$K$13))))) | BK69: =IF(OR(BH69=0,$S$13=0),0,IF((AE69+$K$13)>$S$13/HU_alpha+$K$13,0.5*$S$13/HU_alpha,IF((AE69+$K$13)>=$K$13,((AE69+$K$13)-$K$13)-0.5*HU_alpha/$S$13*((AE69+$K$13)-$K$13)^2,IF((AE69+$K$13)>=$T$13,HU_beta*((AE69+$K$13)-$K$13),HU_beta*($T$13-$K$13)))))
A70: 2 | B70: =HU_age+A70 | C70: =A70<=HU_T | D70: =IF(OR(A70<1,A70>HU_T),0,INDEX(HU_q_mort,HU_age+A70-17,HU_col)) | E70: =IF(OR(A70<1,A70>HU_T),0,INDEX(HU_q_adb,HU_age+A70-17,HU_col)) | F70: =IF(OR(A70<1,A70>HU_T),0,INDEX(HU_q_morb,HU_age+A70-17,HU_col)) | G70: =IF(OR(A70<1,A70>HU_T),0,INDEX(HU_q_ptd,HU_age+A70-17,HU_col)) | H70: =IF(OR(A70<1,A70>HU_T),0,INDEX(HU_q_dis,HU_age+A70-17,HU_col)) | I70: =IF(A70>HU_T,0,I69*(1-D70)*(1-E70)) | J70: =IF(A70>=HU_T,0,N(I71)) | K70: =K69*(1-G70) | L70: =1-K70 | M70: =K69*G70 | N70: =N69*(1-H70) | O70: =1-N69 | P70: =P69*(1-F70) | Q70: =1-P69/INDEX($P$68:$P$150,MAX(1,A70-HU_ciYears)) | R70: =(1+inflationRate)^A70 | S70: =IF(OR(OR(A70<1,A70>HU_T),A70-1>=HU_dtr),0,HU_inc0*(1+incomeGrowthRate)^A70) | T70: =IF(A70>HU_T,T69,T69*(1+INDEX(HU_ssG,HU_age+A70-17))) | U70: =IF(AND(HU_dtr>=1,A70=HU_dtr,A70<=HU_T),MIN(S70*INDEX(HU_ssC,HU_age+A70-17)/(1-INDEX(HU_ssC,HU_age+A70-17)),INDEX(HU_ssCap,HU_age+A70-17))*T70,0) | V70: =S70+U70+IF(AND(HU_wdOn,A70=HU_wdYear),HU_wdIncome,0) | W70: =HU_ciProp*Q70+HU_tpdCut*L70+HU_disCut*O70 | X70: =IF(OR(A70<1,A70>HU_T),0,V70*(1-W70)) | Y70: =IF(OR(A70<1,A70>HU_T),0,IF(AND(HU_retExp>0,A70-1>=HU_dtr),HU_retExp,HU_exp0)*R70) | Z70: =-Y70-IF(AND(HU_wdOn,A70=HU_wdYear),HU_wdOut,0) | AA70: =IF(OR(A70<1,A70>HU_T),0,-HU_medCost*R70*F70-HU_tpdCost*R70*M70) | AB70: =IF(A70>HU_T,0,AB69*(1+interestRate)+X70+Z70+AA70) | AC70: =IF(A70>HU_T,0,HU_inv*EXP(HU_mu*A70)) | AD70: =IF(A70>HU_T,0,MAX(0,AC70+AB70)) | AE70: =IF(A70>HU_T,0,MAX(0,X70-Y70)) | AF70: =IF(AND($J$6,A70>=1,A70<=$Q$6-1),J70,0) | AG70: =IF(OR(AF70=0,$S$6=0),0,IF((AD70+$L$6)>$S$6/HU_alpha+$K$6,0.5*$S$6/HU_alpha,IF((AD70+$L$6)>=$K$6,((AD70+$L$6)-$K$6)-0.5*HU_alpha/$S$6*((AD70+$L$6)-$K$6)^2,IF((AD70+$L$6)>=$T$6,HU_beta*((AD70+$L$6)-$K$6),HU_beta*($T$6-$K$6))))) | AH70: =IF(OR(AF70=0,$S$6=0),0,IF((AD70+$L$6+$N$6)>$S$6/HU_alpha+$K$6,0.5*$S$6/HU_alpha,IF((AD70+$L$6+$N$6)>=$K$6,((AD70+$L$6+$N$6)-$K$6)-0.5*HU_alpha/$S$6*((AD70+$L$6+$N$6)-$K$6)^2,IF((AD70+$L$6+$N$6)>=$T$6,HU_beta*((AD70+$L$6+$N$6)-$K$6),HU_beta*($T$6-$K$6))))) | AI70: =IF(OR(AF70=0,$S$6=0),0,IF((AD70+$K$6)>$S$6/HU_alpha+$K$6,0.5*$S$6/HU_alpha,IF((AD70+$K$6)>=$K$6,((AD70+$K$6)-$K$6)-0.5*HU_alpha/$S$6*((AD70+$K$6)-$K$6)^2,IF((AD70+$K$6)>=$T$6,HU_beta*((AD70+$K$6)-$K$6),HU_beta*($T$6-$K$6))))) | AJ70: =IF(AND($J$7,A70>=1,A70<=$Q$7-1),J70,0) | AK70: =IF(OR(AJ70=0,$S$7=0),0,IF((AE70+$L$7)>$S$7/HU_alpha+$K$7,0.5*$S$7/HU_alpha,IF((AE70+$L$7)>=$K$7,((AE70+$L$7)-$K$7)-0.5*HU_alpha/$S$7*((AE70+$L$7)-$K$7)^2,IF((AE70+$L$7)>=$T$7,HU_beta*((AE70+$L$7)-$K$7),HU_beta*($T$7-$K$7))))) | AL70: =IF(OR(AJ70=0,$S$7=0),0,IF((AE70+$L$7+$N$7)>$S$7/HU_alpha+$K$7,0.5*$S$7/HU_alpha,IF((AE70+$L$7+$N$7)>=$K$7,((AE70+$L$7+$N$7)-$K$7)-0.5*HU_alpha/$S$7*((AE70+$L$7+$N$7)-$K$7)^2,IF((AE70+$L$7+$N$7)>=$T$7,HU_beta*((AE70+$L$7+$N$7)-$K$7),HU_beta*($T$7-$K$7))))) | AM70: =IF(OR(AJ70=0,$S$7=0),0,IF((AE70+$K$7)>$S$7/HU_alpha+$K$7,0.5*$S$7/HU_alpha,IF((AE70+$K$7)>=$K$7,((AE70+$K$7)-$K$7)-0.5*HU_alpha/$S$7*((AE70+$K$7)-$K$7)^2,IF((AE70+$K$7)>=$T$7,HU_beta*((AE70+$K$7)-$K$7),HU_beta*($T$7-$K$7))))) | AN70: =IF(AND($J$8,A70>=1,A70<=$Q$8-1),J70,0) | AO70: =IF(OR(AN70=0,$S$8=0),0,IF((AE70+$L$8)>$S$8/HU_alpha+$K$8,0.5*$S$8/HU_alpha,IF((AE70+$L$8)>=$K$8,((AE70+$L$8)-$K$8)-0.5*HU_alpha/$S$8*((AE70+$L$8)-$K$8)^2,IF((AE70+$L$8)>=$T$8,HU_beta*((AE70+$L$8)-$K$8),HU_beta*($T$8-$K$8))))) | AP70: =IF(OR(AN70=0,$S$8=0),0,IF((AE70+$L$8+$N$8)>$S$8/HU_alpha+$K$8,0.5*$S$8/HU_alpha,IF((AE70+$L$8+$N$8)>=$K$8,((AE70+$L$8+$N$8)-$K$8)-0.5*HU_alpha/$S$8*((AE70+$L$8+$N$8)-$K$8)^2,IF((AE70+$L$8+$N$8)>=$T$8,HU_beta*((AE70+$L$8+$N$8)-$K$8),HU_beta*($T$8-$K$8))))) | AQ70: =IF(OR(AN70=0,$S$8=0),0,IF((AE70+$K$8)>$S$8/HU_alpha+$K$8,0.5*$S$8/HU_alpha,IF((AE70+$K$8)>=$K$8,((AE70+$K$8)-$K$8)-0.5*HU_alpha/$S$8*((AE70+$K$8)-$K$8)^2,IF((AE70+$K$8)>=$T$8,HU_beta*((AE70+$K$8)-$K$8),HU_beta*($T$8-$K$8))))) | AR70: =IF(AND($J$9,A70>=1,A70<=$Q$9-1),J70,0) | AS70: =IF(OR(AR70=0,$S$9=0),0,IF((AE70+$L$9)>$S$9/HU_alpha+$K$9,0.5*$S$9/HU_alpha,IF((AE70+$L$9)>=$K$9,((AE70+$L$9)-$K$9)-0.5*HU_alpha/$S$9*((AE70+$L$9)-$K$9)^2,IF((AE70+$L$9)>=$T$9,HU_beta*((AE70+$L$9)-$K$9),HU_beta*($T$9-$K$9))))) | AT70: =IF(OR(AR70=0,$S$9=0),0,IF((AE70+$L$9+$N$9)>$S$9/HU_alpha+$K$9,0.5*$S$9/HU_alpha,IF((AE70+$L$9+$N$9)>=$K$9,((AE70+$L$9+$N$9)-$K$9)-0.5*HU_alpha/$S$9*((AE70+$L$9+$N$9)-$K$9)^2,IF((AE70+$L$9+$N$9)>=$T$9,HU_beta*((AE70+$L$9+$N$9)-$K$9),HU_beta*($T$9-$K$9))))) | AU70: =IF(OR(AR70=0,$S$9=0),0,IF((AE70+$K$9)>$S$9/HU_alpha+$K$9,0.5*$S$9/HU_alpha,IF((AE70+$K$9)>=$K$9,((AE70+$K$9)-$K$9)-0.5*HU_alpha/$S$9*((AE70+$K$9)-$K$9)^2,IF((AE70+$K$9)>=$T$9,HU_beta*((AE70+$K$9)-$K$9),HU_beta*($T$9-$K$9))))) | AV70: =IF(AND($J$10,A70=$Q$10),J70,0) | AW70: =IF(OR(AV70=0,$S$10=0),0,IF((AD70+$L$10)>$S$10/HU_alpha+$K$10,0.5*$S$10/HU_alpha,IF((AD70+$L$10)>=$K$10,((AD70+$L$10)-$K$10)-0.5*HU_alpha/$S$10*((AD70+$L$10)-$K$10)^2,IF((AD70+$L$10)>=$T$10,HU_beta*((AD70+$L$10)-$K$10),HU_beta*($T$10-$K$10))))) | AX70: =IF(OR(AV70=0,$S$10=0),0,IF((AD70+$L$10+$N$10)>$S$10/HU_alpha+$K$10,0.5*$S$10/HU_alpha,IF((AD70+$L$10+$N$10)>=$K$10,((AD70+$L$10+$N$10)-$K$10)-0.5*HU_alpha/$S$10*((AD70+$L$10+$N$10)-$K$10)^2,IF((AD70+$L$10+$N$10)>=$T$10,HU_beta*((AD70+$L$10+$N$10)-$K$10),HU_beta*($T$10-$K$10))))) | AY70: =IF(OR(AV70=0,$S$10=0),0,IF((AD70+$K$10)>$S$10/HU_alpha+$K$10,0.5*$S$10/HU_alpha,IF((AD70+$K$10)>=$K$10,((AD70+$K$10)-$K$10)-0.5*HU_alpha/$S$10*((AD70+$K$10)-$K$10)^2,IF((AD70+$K$10)>=$T$10,HU_beta*((AD70+$K$10)-$K$10),HU_beta*($T$10-$K$10))))) | AZ70: =IF(AND($J$11,A70=$Q$11),J70,0) | BA70: =IF(OR(AZ70=0,$S$11=0),0,IF((AE70+$L$11)>$S$11/HU_alpha+$K$11,0.5*$S$11/HU_alpha,IF((AE70+$L$11)>=$K$11,((AE70+$L$11)-$K$11)-0.5*HU_alpha/$S$11*((AE70+$L$11)-$K$11)^2,IF((AE70+$L$11)>=$T$11,HU_beta*((AE70+$L$11)-$K$11),HU_beta*($T$11-$K$11))))) | BB70: =IF(OR(AZ70=0,$S$11=0),0,IF((AE70+$L$11+$N$11)>$S$11/HU_alpha+$K$11,0.5*$S$11/HU_alpha,IF((AE70+$L$11+$N$11)>=$K$11,((AE70+$L$11+$N$11)-$K$11)-0.5*HU_alpha/$S$11*((AE70+$L$11+$N$11)-$K$11)^2,IF((AE70+$L$11+$N$11)>=$T$11,HU_beta*((AE70+$L$11+$N$11)-$K$11),HU_beta*($T$11-$K$11))))) | BC70: =IF(OR(AZ70=0,$S$11=0),0,IF((AE70+$K$11)>$S$11/HU_alpha+$K$11,0.5*$S$11/HU_alpha,IF((AE70+$K$11)>=$K$11,((AE70+$K$11)-$K$11)-0.5*HU_alpha/$S$11*((AE70+$K$11)-$K$11)^2,IF((AE70+$K$11)>=$T$11,HU_beta*((AE70+$K$11)-$K$11),HU_beta*($T$11-$K$11))))) | BD70: =IF(AND($J$12,A70=$Q$12),J70,0) | BE70: =IF(OR(BD70=0,$S$12=0),0,IF((AE70+$L$12)>$S$12/HU_alpha+$K$12,0.5*$S$12/HU_alpha,IF((AE70+$L$12)>=$K$12,((AE70+$L$12)-$K$12)-0.5*HU_alpha/$S$12*((AE70+$L$12)-$K$12)^2,IF((AE70+$L$12)>=$T$12,HU_beta*((AE70+$L$12)-$K$12),HU_beta*($T$12-$K$12))))) | BF70: =IF(OR(BD70=0,$S$12=0),0,IF((AE70+$L$12+$N$12)>$S$12/HU_alpha+$K$12,0.5*$S$12/HU_alpha,IF((AE70+$L$12+$N$12)>=$K$12,((AE70+$L$12+$N$12)-$K$12)-0.5*HU_alpha/$S$12*((AE70+$L$12+$N$12)-$K$12)^2,IF((AE70+$L$12+$N$12)>=$T$12,HU_beta*((AE70+$L$12+$N$12)-$K$12),HU_beta*($T$12-$K$12))))) | BG70: =IF(OR(BD70=0,$S$12=0),0,IF((AE70+$K$12)>$S$12/HU_alpha+$K$12,0.5*$S$12/HU_alpha,IF((AE70+$K$12)>=$K$12,((AE70+$K$12)-$K$12)-0.5*HU_alpha/$S$12*((AE70+$K$12)-$K$12)^2,IF((AE70+$K$12)>=$T$12,HU_beta*((AE70+$K$12)-$K$12),HU_beta*($T$12-$K$12))))) | BH70: =IF(AND($J$13,A70=$Q$13),J70,0) | BI70: =IF(OR(BH70=0,$S$13=0),0,IF((AE70+$L$13)>$S$13/HU_alpha+$K$13,0.5*$S$13/HU_alpha,IF((AE70+$L$13)>=$K$13,((AE70+$L$13)-$K$13)-0.5*HU_alpha/$S$13*((AE70+$L$13)-$K$13)^2,IF((AE70+$L$13)>=$T$13,HU_beta*((AE70+$L$13)-$K$13),HU_beta*($T$13-$K$13))))) | BJ70: =IF(OR(BH70=0,$S$13=0),0,IF((AE70+$L$13+$N$13)>$S$13/HU_alpha+$K$13,0.5*$S$13/HU_alpha,IF((AE70+$L$13+$N$13)>=$K$13,((AE70+$L$13+$N$13)-$K$13)-0.5*HU_alpha/$S$13*((AE70+$L$13+$N$13)-$K$13)^2,IF((AE70+$L$13+$N$13)>=$T$13,HU_beta*((AE70+$L$13+$N$13)-$K$13),HU_beta*($T$13-$K$13))))) | BK70: =IF(OR(BH70=0,$S$13=0),0,IF((AE70+$K$13)>$S$13/HU_alpha+$K$13,0.5*$S$13/HU_alpha,IF((AE70+$K$13)>=$K$13,((AE70+$K$13)-$K$13)-0.5*HU_alpha/$S$13*((AE70+$K$13)-$K$13)^2,IF((AE70+$K$13)>=$T$13,HU_beta*((AE70+$K$13)-$K$13),HU_beta*($T$13-$K$13)))))
A71: 3 | B71: =HU_age+A71 | C71: =A71<=HU_T | D71: =IF(OR(A71<1,A71>HU_T),0,INDEX(HU_q_mort,HU_age+A71-17,HU_col)) | E71: =IF(OR(A71<1,A71>HU_T),0,INDEX(HU_q_adb,HU_age+A71-17,HU_col)) | F71: =IF(OR(A71<1,A71>HU_T),0,INDEX(HU_q_morb,HU_age+A71-17,HU_col)) | G71: =IF(OR(A71<1,A71>HU_T),0,INDEX(HU_q_ptd,HU_age+A71-17,HU_col)) | H71: =IF(OR(A71<1,A71>HU_T),0,INDEX(HU_q_dis,HU_age+A71-17,HU_col)) | I71: =IF(A71>HU_T,0,I70*(1-D71)*(1-E71)) | J71: =IF(A71>=HU_T,0,N(I72)) | K71: =K70*(1-G71) | L71: =1-K71 | M71: =K70*G71 | N71: =N70*(1-H71) | O71: =1-N70 | P71: =P70*(1-F71) | Q71: =1-P70/INDEX($P$68:$P$150,MAX(1,A71-HU_ciYears)) | R71: =(1+inflationRate)^A71 | S71: =IF(OR(OR(A71<1,A71>HU_T),A71-1>=HU_dtr),0,HU_inc0*(1+incomeGrowthRate)^A71) | T71: =IF(A71>HU_T,T70,T70*(1+INDEX(HU_ssG,HU_age+A71-17))) | U71: =IF(AND(HU_dtr>=1,A71=HU_dtr,A71<=HU_T),MIN(S71*INDEX(HU_ssC,HU_age+A71-17)/(1-INDEX(HU_ssC,HU_age+A71-17)),INDEX(HU_ssCap,HU_age+A71-17))*T71,0) | V71: =S71+U71+IF(AND(HU_wdOn,A71=HU_wdYear),HU_wdIncome,0) | W71: =HU_ciProp*Q71+HU_tpdCut*L71+HU_disCut*O71 | X71: =IF(OR(A71<1,A71>HU_T),0,V71*(1-W71)) | Y71: =IF(OR(A71<1,A71>HU_T),0,IF(AND(HU_retExp>0,A71-1>=HU_dtr),HU_retExp,HU_exp0)*R71) | Z71: =-Y71-IF(AND(HU_wdOn,A71=HU_wdYear),HU_wdOut,0) | AA71: =IF(OR(A71<1,A71>HU_T),0,-HU_medCost*R71*F71-HU_tpdCost*R71*M71) | AB71: =IF(A71>HU_T,0,AB70*(1+interestRate)+X71+Z71+AA71) | AC71: =IF(A71>HU_T,0,HU_inv*EXP(HU_mu*A71)) | AD71: =IF(A71>HU_T,0,MAX(0,AC71+AB71)) | AE71: =IF(A71>HU_T,0,MAX(0,X71-Y71)) | AF71: =IF(AND($J$6,A71>=1,A71<=$Q$6-1),J71,0) | AG71: =IF(OR(AF71=0,$S$6=0),0,IF((AD71+$L$6)>$S$6/HU_alpha+$K$6,0.5*$S$6/HU_alpha,IF((AD71+$L$6)>=$K$6,((AD71+$L$6)-$K$6)-0.5*HU_alpha/$S$6*((AD71+$L$6)-$K$6)^2,IF((AD71+$L$6)>=$T$6,HU_beta*((AD71+$L$6)-$K$6),HU_beta*($T$6-$K$6))))) | AH71: =IF(OR(AF71=0,$S$6=0),0,IF((AD71+$L$6+$N$6)>$S$6/HU_alpha+$K$6,0.5*$S$6/HU_alpha,IF((AD71+$L$6+$N$6)>=$K$6,((AD71+$L$6+$N$6)-$K$6)-0.5*HU_alpha/$S$6*((AD71+$L$6+$N$6)-$K$6)^2,IF((AD71+$L$6+$N$6)>=$T$6,HU_beta*((AD71+$L$6+$N$6)-$K$6),HU_beta*($T$6-$K$6))))) | AI71: =IF(OR(AF71=0,$S$6=0),0,IF((AD71+$K$6)>$S$6/HU_alpha+$K$6,0.5*$S$6/HU_alpha,IF((AD71+$K$6)>=$K$6,((AD71+$K$6)-$K$6)-0.5*HU_alpha/$S$6*((AD71+$K$6)-$K$6)^2,IF((AD71+$K$6)>=$T$6,HU_beta*((AD71+$K$6)-$K$6),HU_beta*($T$6-$K$6))))) | AJ71: =IF(AND($J$7,A71>=1,A71<=$Q$7-1),J71,0) | AK71: =IF(OR(AJ71=0,$S$7=0),0,IF((AE71+$L$7)>$S$7/HU_alpha+$K$7,0.5*$S$7/HU_alpha,IF((AE71+$L$7)>=$K$7,((AE71+$L$7)-$K$7)-0.5*HU_alpha/$S$7*((AE71+$L$7)-$K$7)^2,IF((AE71+$L$7)>=$T$7,HU_beta*((AE71+$L$7)-$K$7),HU_beta*($T$7-$K$7))))) | AL71: =IF(OR(AJ71=0,$S$7=0),0,IF((AE71+$L$7+$N$7)>$S$7/HU_alpha+$K$7,0.5*$S$7/HU_alpha,IF((AE71+$L$7+$N$7)>=$K$7,((AE71+$L$7+$N$7)-$K$7)-0.5*HU_alpha/$S$7*((AE71+$L$7+$N$7)-$K$7)^2,IF((AE71+$L$7+$N$7)>=$T$7,HU_beta*((AE71+$L$7+$N$7)-$K$7),HU_beta*($T$7-$K$7))))) | AM71: =IF(OR(AJ71=0,$S$7=0),0,IF((AE71+$K$7)>$S$7/HU_alpha+$K$7,0.5*$S$7/HU_alpha,IF((AE71+$K$7)>=$K$7,((AE71+$K$7)-$K$7)-0.5*HU_alpha/$S$7*((AE71+$K$7)-$K$7)^2,IF((AE71+$K$7)>=$T$7,HU_beta*((AE71+$K$7)-$K$7),HU_beta*($T$7-$K$7))))) | AN71: =IF(AND($J$8,A71>=1,A71<=$Q$8-1),J71,0) | AO71: =IF(OR(AN71=0,$S$8=0),0,IF((AE71+$L$8)>$S$8/HU_alpha+$K$8,0.5*$S$8/HU_alpha,IF((AE71+$L$8)>=$K$8,((AE71+$L$8)-$K$8)-0.5*HU_alpha/$S$8*((AE71+$L$8)-$K$8)^2,IF((AE71+$L$8)>=$T$8,HU_beta*((AE71+$L$8)-$K$8),HU_beta*($T$8-$K$8))))) | AP71: =IF(OR(AN71=0,$S$8=0),0,IF((AE71+$L$8+$N$8)>$S$8/HU_alpha+$K$8,0.5*$S$8/HU_alpha,IF((AE71+$L$8+$N$8)>=$K$8,((AE71+$L$8+$N$8)-$K$8)-0.5*HU_alpha/$S$8*((AE71+$L$8+$N$8)-$K$8)^2,IF((AE71+$L$8+$N$8)>=$T$8,HU_beta*((AE71+$L$8+$N$8)-$K$8),HU_beta*($T$8-$K$8))))) | AQ71: =IF(OR(AN71=0,$S$8=0),0,IF((AE71+$K$8)>$S$8/HU_alpha+$K$8,0.5*$S$8/HU_alpha,IF((AE71+$K$8)>=$K$8,((AE71+$K$8)-$K$8)-0.5*HU_alpha/$S$8*((AE71+$K$8)-$K$8)^2,IF((AE71+$K$8)>=$T$8,HU_beta*((AE71+$K$8)-$K$8),HU_beta*($T$8-$K$8))))) | AR71: =IF(AND($J$9,A71>=1,A71<=$Q$9-1),J71,0) | AS71: =IF(OR(AR71=0,$S$9=0),0,IF((AE71+$L$9)>$S$9/HU_alpha+$K$9,0.5*$S$9/HU_alpha,IF((AE71+$L$9)>=$K$9,((AE71+$L$9)-$K$9)-0.5*HU_alpha/$S$9*((AE71+$L$9)-$K$9)^2,IF((AE71+$L$9)>=$T$9,HU_beta*((AE71+$L$9)-$K$9),HU_beta*($T$9-$K$9))))) | AT71: =IF(OR(AR71=0,$S$9=0),0,IF((AE71+$L$9+$N$9)>$S$9/HU_alpha+$K$9,0.5*$S$9/HU_alpha,IF((AE71+$L$9+$N$9)>=$K$9,((AE71+$L$9+$N$9)-$K$9)-0.5*HU_alpha/$S$9*((AE71+$L$9+$N$9)-$K$9)^2,IF((AE71+$L$9+$N$9)>=$T$9,HU_beta*((AE71+$L$9+$N$9)-$K$9),HU_beta*($T$9-$K$9))))) | AU71: =IF(OR(AR71=0,$S$9=0),0,IF((AE71+$K$9)>$S$9/HU_alpha+$K$9,0.5*$S$9/HU_alpha,IF((AE71+$K$9)>=$K$9,((AE71+$K$9)-$K$9)-0.5*HU_alpha/$S$9*((AE71+$K$9)-$K$9)^2,IF((AE71+$K$9)>=$T$9,HU_beta*((AE71+$K$9)-$K$9),HU_beta*($T$9-$K$9))))) | AV71: =IF(AND($J$10,A71=$Q$10),J71,0) | AW71: =IF(OR(AV71=0,$S$10=0),0,IF((AD71+$L$10)>$S$10/HU_alpha+$K$10,0.5*$S$10/HU_alpha,IF((AD71+$L$10)>=$K$10,((AD71+$L$10)-$K$10)-0.5*HU_alpha/$S$10*((AD71+$L$10)-$K$10)^2,IF((AD71+$L$10)>=$T$10,HU_beta*((AD71+$L$10)-$K$10),HU_beta*($T$10-$K$10))))) | AX71: =IF(OR(AV71=0,$S$10=0),0,IF((AD71+$L$10+$N$10)>$S$10/HU_alpha+$K$10,0.5*$S$10/HU_alpha,IF((AD71+$L$10+$N$10)>=$K$10,((AD71+$L$10+$N$10)-$K$10)-0.5*HU_alpha/$S$10*((AD71+$L$10+$N$10)-$K$10)^2,IF((AD71+$L$10+$N$10)>=$T$10,HU_beta*((AD71+$L$10+$N$10)-$K$10),HU_beta*($T$10-$K$10))))) | AY71: =IF(OR(AV71=0,$S$10=0),0,IF((AD71+$K$10)>$S$10/HU_alpha+$K$10,0.5*$S$10/HU_alpha,IF((AD71+$K$10)>=$K$10,((AD71+$K$10)-$K$10)-0.5*HU_alpha/$S$10*((AD71+$K$10)-$K$10)^2,IF((AD71+$K$10)>=$T$10,HU_beta*((AD71+$K$10)-$K$10),HU_beta*($T$10-$K$10))))) | AZ71: =IF(AND($J$11,A71=$Q$11),J71,0) | BA71: =IF(OR(AZ71=0,$S$11=0),0,IF((AE71+$L$11)>$S$11/HU_alpha+$K$11,0.5*$S$11/HU_alpha,IF((AE71+$L$11)>=$K$11,((AE71+$L$11)-$K$11)-0.5*HU_alpha/$S$11*((AE71+$L$11)-$K$11)^2,IF((AE71+$L$11)>=$T$11,HU_beta*((AE71+$L$11)-$K$11),HU_beta*($T$11-$K$11))))) | BB71: =IF(OR(AZ71=0,$S$11=0),0,IF((AE71+$L$11+$N$11)>$S$11/HU_alpha+$K$11,0.5*$S$11/HU_alpha,IF((AE71+$L$11+$N$11)>=$K$11,((AE71+$L$11+$N$11)-$K$11)-0.5*HU_alpha/$S$11*((AE71+$L$11+$N$11)-$K$11)^2,IF((AE71+$L$11+$N$11)>=$T$11,HU_beta*((AE71+$L$11+$N$11)-$K$11),HU_beta*($T$11-$K$11))))) | BC71: =IF(OR(AZ71=0,$S$11=0),0,IF((AE71+$K$11)>$S$11/HU_alpha+$K$11,0.5*$S$11/HU_alpha,IF((AE71+$K$11)>=$K$11,((AE71+$K$11)-$K$11)-0.5*HU_alpha/$S$11*((AE71+$K$11)-$K$11)^2,IF((AE71+$K$11)>=$T$11,HU_beta*((AE71+$K$11)-$K$11),HU_beta*($T$11-$K$11))))) | BD71: =IF(AND($J$12,A71=$Q$12),J71,0) | BE71: =IF(OR(BD71=0,$S$12=0),0,IF((AE71+$L$12)>$S$12/HU_alpha+$K$12,0.5*$S$12/HU_alpha,IF((AE71+$L$12)>=$K$12,((AE71+$L$12)-$K$12)-0.5*HU_alpha/$S$12*((AE71+$L$12)-$K$12)^2,IF((AE71+$L$12)>=$T$12,HU_beta*((AE71+$L$12)-$K$12),HU_beta*($T$12-$K$12))))) | BF71: =IF(OR(BD71=0,$S$12=0),0,IF((AE71+$L$12+$N$12)>$S$12/HU_alpha+$K$12,0.5*$S$12/HU_alpha,IF((AE71+$L$12+$N$12)>=$K$12,((AE71+$L$12+$N$12)-$K$12)-0.5*HU_alpha/$S$12*((AE71+$L$12+$N$12)-$K$12)^2,IF((AE71+$L$12+$N$12)>=$T$12,HU_beta*((AE71+$L$12+$N$12)-$K$12),HU_beta*($T$12-$K$12))))) | BG71: =IF(OR(BD71=0,$S$12=0),0,IF((AE71+$K$12)>$S$12/HU_alpha+$K$12,0.5*$S$12/HU_alpha,IF((AE71+$K$12)>=$K$12,((AE71+$K$12)-$K$12)-0.5*HU_alpha/$S$12*((AE71+$K$12)-$K$12)^2,IF((AE71+$K$12)>=$T$12,HU_beta*((AE71+$K$12)-$K$12),HU_beta*($T$12-$K$12))))) | BH71: =IF(AND($J$13,A71=$Q$13),J71,0) | BI71: =IF(OR(BH71=0,$S$13=0),0,IF((AE71+$L$13)>$S$13/HU_alpha+$K$13,0.5*$S$13/HU_alpha,IF((AE71+$L$13)>=$K$13,((AE71+$L$13)-$K$13)-0.5*HU_alpha/$S$13*((AE71+$L$13)-$K$13)^2,IF((AE71+$L$13)>=$T$13,HU_beta*((AE71+$L$13)-$K$13),HU_beta*($T$13-$K$13))))) | BJ71: =IF(OR(BH71=0,$S$13=0),0,IF((AE71+$L$13+$N$13)>$S$13/HU_alpha+$K$13,0.5*$S$13/HU_alpha,IF((AE71+$L$13+$N$13)>=$K$13,((AE71+$L$13+$N$13)-$K$13)-0.5*HU_alpha/$S$13*((AE71+$L$13+$N$13)-$K$13)^2,IF((AE71+$L$13+$N$13)>=$T$13,HU_beta*((AE71+$L$13+$N$13)-$K$13),HU_beta*($T$13-$K$13))))) | BK71: =IF(OR(BH71=0,$S$13=0),0,IF((AE71+$K$13)>$S$13/HU_alpha+$K$13,0.5*$S$13/HU_alpha,IF((AE71+$K$13)>=$K$13,((AE71+$K$13)-$K$13)-0.5*HU_alpha/$S$13*((AE71+$K$13)-$K$13)^2,IF((AE71+$K$13)>=$T$13,HU_beta*((AE71+$K$13)-$K$13),HU_beta*($T$13-$K$13)))))
A72: 4 | B72: =HU_age+A72 | C72: =A72<=HU_T | D72: =IF(OR(A72<1,A72>HU_T),0,INDEX(HU_q_mort,HU_age+A72-17,HU_col)) | E72: =IF(OR(A72<1,A72>HU_T),0,INDEX(HU_q_adb,HU_age+A72-17,HU_col)) | F72: =IF(OR(A72<1,A72>HU_T),0,INDEX(HU_q_morb,HU_age+A72-17,HU_col)) | G72: =IF(OR(A72<1,A72>HU_T),0,INDEX(HU_q_ptd,HU_age+A72-17,HU_col)) | H72: =IF(OR(A72<1,A72>HU_T),0,INDEX(HU_q_dis,HU_age+A72-17,HU_col)) | I72: =IF(A72>HU_T,0,I71*(1-D72)*(1-E72)) | J72: =IF(A72>=HU_T,0,N(I73)) | K72: =K71*(1-G72) | L72: =1-K72 | M72: =K71*G72 | N72: =N71*(1-H72) | O72: =1-N71 | P72: =P71*(1-F72) | Q72: =1-P71/INDEX($P$68:$P$150,MAX(1,A72-HU_ciYears)) | R72: =(1+inflationRate)^A72 | S72: =IF(OR(OR(A72<1,A72>HU_T),A72-1>=HU_dtr),0,HU_inc0*(1+incomeGrowthRate)^A72) | T72: =IF(A72>HU_T,T71,T71*(1+INDEX(HU_ssG,HU_age+A72-17))) | U72: =IF(AND(HU_dtr>=1,A72=HU_dtr,A72<=HU_T),MIN(S72*INDEX(HU_ssC,HU_age+A72-17)/(1-INDEX(HU_ssC,HU_age+A72-17)),INDEX(HU_ssCap,HU_age+A72-17))*T72,0) | V72: =S72+U72+IF(AND(HU_wdOn,A72=HU_wdYear),HU_wdIncome,0) | W72: =HU_ciProp*Q72+HU_tpdCut*L72+HU_disCut*O72 | X72: =IF(OR(A72<1,A72>HU_T),0,V72*(1-W72)) | Y72: =IF(OR(A72<1,A72>HU_T),0,IF(AND(HU_retExp>0,A72-1>=HU_dtr),HU_retExp,HU_exp0)*R72) | Z72: =-Y72-IF(AND(HU_wdOn,A72=HU_wdYear),HU_wdOut,0) | AA72: =IF(OR(A72<1,A72>HU_T),0,-HU_medCost*R72*F72-HU_tpdCost*R72*M72) | AB72: =IF(A72>HU_T,0,AB71*(1+interestRate)+X72+Z72+AA72) | AC72: =IF(A72>HU_T,0,HU_inv*EXP(HU_mu*A72)) | AD72: =IF(A72>HU_T,0,MAX(0,AC72+AB72)) | AE72: =IF(A72>HU_T,0,MAX(0,X72-Y72)) | AF72: =IF(AND($J$6,A72>=1,A72<=$Q$6-1),J72,0) | AG72: =IF(OR(AF72=0,$S$6=0),0,IF((AD72+$L$6)>$S$6/HU_alpha+$K$6,0.5*$S$6/HU_alpha,IF((AD72+$L$6)>=$K$6,((AD72+$L$6)-$K$6)-0.5*HU_alpha/$S$6*((AD72+$L$6)-$K$6)^2,IF((AD72+$L$6)>=$T$6,HU_beta*((AD72+$L$6)-$K$6),HU_beta*($T$6-$K$6))))) | AH72: =IF(OR(AF72=0,$S$6=0),0,IF((AD72+$L$6+$N$6)>$S$6/HU_alpha+$K$6,0.5*$S$6/HU_alpha,IF((AD72+$L$6+$N$6)>=$K$6,((AD72+$L$6+$N$6)-$K$6)-0.5*HU_alpha/$S$6*((AD72+$L$6+$N$6)-$K$6)^2,IF((AD72+$L$6+$N$6)>=$T$6,HU_beta*((AD72+$L$6+$N$6)-$K$6),HU_beta*($T$6-$K$6))))) | AI72: =IF(OR(AF72=0,$S$6=0),0,IF((AD72+$K$6)>$S$6/HU_alpha+$K$6,0.5*$S$6/HU_alpha,IF((AD72+$K$6)>=$K$6,((AD72+$K$6)-$K$6)-0.5*HU_alpha/$S$6*((AD72+$K$6)-$K$6)^2,IF((AD72+$K$6)>=$T$6,HU_beta*((AD72+$K$6)-$K$6),HU_beta*($T$6-$K$6))))) | AJ72: =IF(AND($J$7,A72>=1,A72<=$Q$7-1),J72,0) | AK72: =IF(OR(AJ72=0,$S$7=0),0,IF((AE72+$L$7)>$S$7/HU_alpha+$K$7,0.5*$S$7/HU_alpha,IF((AE72+$L$7)>=$K$7,((AE72+$L$7)-$K$7)-0.5*HU_alpha/$S$7*((AE72+$L$7)-$K$7)^2,IF((AE72+$L$7)>=$T$7,HU_beta*((AE72+$L$7)-$K$7),HU_beta*($T$7-$K$7))))) | AL72: =IF(OR(AJ72=0,$S$7=0),0,IF((AE72+$L$7+$N$7)>$S$7/HU_alpha+$K$7,0.5*$S$7/HU_alpha,IF((AE72+$L$7+$N$7)>=$K$7,((AE72+$L$7+$N$7)-$K$7)-0.5*HU_alpha/$S$7*((AE72+$L$7+$N$7)-$K$7)^2,IF((AE72+$L$7+$N$7)>=$T$7,HU_beta*((AE72+$L$7+$N$7)-$K$7),HU_beta*($T$7-$K$7))))) | AM72: =IF(OR(AJ72=0,$S$7=0),0,IF((AE72+$K$7)>$S$7/HU_alpha+$K$7,0.5*$S$7/HU_alpha,IF((AE72+$K$7)>=$K$7,((AE72+$K$7)-$K$7)-0.5*HU_alpha/$S$7*((AE72+$K$7)-$K$7)^2,IF((AE72+$K$7)>=$T$7,HU_beta*((AE72+$K$7)-$K$7),HU_beta*($T$7-$K$7))))) | AN72: =IF(AND($J$8,A72>=1,A72<=$Q$8-1),J72,0) | AO72: =IF(OR(AN72=0,$S$8=0),0,IF((AE72+$L$8)>$S$8/HU_alpha+$K$8,0.5*$S$8/HU_alpha,IF((AE72+$L$8)>=$K$8,((AE72+$L$8)-$K$8)-0.5*HU_alpha/$S$8*((AE72+$L$8)-$K$8)^2,IF((AE72+$L$8)>=$T$8,HU_beta*((AE72+$L$8)-$K$8),HU_beta*($T$8-$K$8))))) | AP72: =IF(OR(AN72=0,$S$8=0),0,IF((AE72+$L$8+$N$8)>$S$8/HU_alpha+$K$8,0.5*$S$8/HU_alpha,IF((AE72+$L$8+$N$8)>=$K$8,((AE72+$L$8+$N$8)-$K$8)-0.5*HU_alpha/$S$8*((AE72+$L$8+$N$8)-$K$8)^2,IF((AE72+$L$8+$N$8)>=$T$8,HU_beta*((AE72+$L$8+$N$8)-$K$8),HU_beta*($T$8-$K$8))))) | AQ72: =IF(OR(AN72=0,$S$8=0),0,IF((AE72+$K$8)>$S$8/HU_alpha+$K$8,0.5*$S$8/HU_alpha,IF((AE72+$K$8)>=$K$8,((AE72+$K$8)-$K$8)-0.5*HU_alpha/$S$8*((AE72+$K$8)-$K$8)^2,IF((AE72+$K$8)>=$T$8,HU_beta*((AE72+$K$8)-$K$8),HU_beta*($T$8-$K$8))))) | AR72: =IF(AND($J$9,A72>=1,A72<=$Q$9-1),J72,0) | AS72: =IF(OR(AR72=0,$S$9=0),0,IF((AE72+$L$9)>$S$9/HU_alpha+$K$9,0.5*$S$9/HU_alpha,IF((AE72+$L$9)>=$K$9,((AE72+$L$9)-$K$9)-0.5*HU_alpha/$S$9*((AE72+$L$9)-$K$9)^2,IF((AE72+$L$9)>=$T$9,HU_beta*((AE72+$L$9)-$K$9),HU_beta*($T$9-$K$9))))) | AT72: =IF(OR(AR72=0,$S$9=0),0,IF((AE72+$L$9+$N$9)>$S$9/HU_alpha+$K$9,0.5*$S$9/HU_alpha,IF((AE72+$L$9+$N$9)>=$K$9,((AE72+$L$9+$N$9)-$K$9)-0.5*HU_alpha/$S$9*((AE72+$L$9+$N$9)-$K$9)^2,IF((AE72+$L$9+$N$9)>=$T$9,HU_beta*((AE72+$L$9+$N$9)-$K$9),HU_beta*($T$9-$K$9))))) | AU72: =IF(OR(AR72=0,$S$9=0),0,IF((AE72+$K$9)>$S$9/HU_alpha+$K$9,0.5*$S$9/HU_alpha,IF((AE72+$K$9)>=$K$9,((AE72+$K$9)-$K$9)-0.5*HU_alpha/$S$9*((AE72+$K$9)-$K$9)^2,IF((AE72+$K$9)>=$T$9,HU_beta*((AE72+$K$9)-$K$9),HU_beta*($T$9-$K$9))))) | AV72: =IF(AND($J$10,A72=$Q$10),J72,0) | AW72: =IF(OR(AV72=0,$S$10=0),0,IF((AD72+$L$10)>$S$10/HU_alpha+$K$10,0.5*$S$10/HU_alpha,IF((AD72+$L$10)>=$K$10,((AD72+$L$10)-$K$10)-0.5*HU_alpha/$S$10*((AD72+$L$10)-$K$10)^2,IF((AD72+$L$10)>=$T$10,HU_beta*((AD72+$L$10)-$K$10),HU_beta*($T$10-$K$10))))) | AX72: =IF(OR(AV72=0,$S$10=0),0,IF((AD72+$L$10+$N$10)>$S$10/HU_alpha+$K$10,0.5*$S$10/HU_alpha,IF((AD72+$L$10+$N$10)>=$K$10,((AD72+$L$10+$N$10)-$K$10)-0.5*HU_alpha/$S$10*((AD72+$L$10+$N$10)-$K$10)^2,IF((AD72+$L$10+$N$10)>=$T$10,HU_beta*((AD72+$L$10+$N$10)-$K$10),HU_beta*($T$10-$K$10))))) | AY72: =IF(OR(AV72=0,$S$10=0),0,IF((AD72+$K$10)>$S$10/HU_alpha+$K$10,0.5*$S$10/HU_alpha,IF((AD72+$K$10)>=$K$10,((AD72+$K$10)-$K$10)-0.5*HU_alpha/$S$10*((AD72+$K$10)-$K$10)^2,IF((AD72+$K$10)>=$T$10,HU_beta*((AD72+$K$10)-$K$10),HU_beta*($T$10-$K$10))))) | AZ72: =IF(AND($J$11,A72=$Q$11),J72,0) | BA72: =IF(OR(AZ72=0,$S$11=0),0,IF((AE72+$L$11)>$S$11/HU_alpha+$K$11,0.5*$S$11/HU_alpha,IF((AE72+$L$11)>=$K$11,((AE72+$L$11)-$K$11)-0.5*HU_alpha/$S$11*((AE72+$L$11)-$K$11)^2,IF((AE72+$L$11)>=$T$11,HU_beta*((AE72+$L$11)-$K$11),HU_beta*($T$11-$K$11))))) | BB72: =IF(OR(AZ72=0,$S$11=0),0,IF((AE72+$L$11+$N$11)>$S$11/HU_alpha+$K$11,0.5*$S$11/HU_alpha,IF((AE72+$L$11+$N$11)>=$K$11,((AE72+$L$11+$N$11)-$K$11)-0.5*HU_alpha/$S$11*((AE72+$L$11+$N$11)-$K$11)^2,IF((AE72+$L$11+$N$11)>=$T$11,HU_beta*((AE72+$L$11+$N$11)-$K$11),HU_beta*($T$11-$K$11))))) | BC72: =IF(OR(AZ72=0,$S$11=0),0,IF((AE72+$K$11)>$S$11/HU_alpha+$K$11,0.5*$S$11/HU_alpha,IF((AE72+$K$11)>=$K$11,((AE72+$K$11)-$K$11)-0.5*HU_alpha/$S$11*((AE72+$K$11)-$K$11)^2,IF((AE72+$K$11)>=$T$11,HU_beta*((AE72+$K$11)-$K$11),HU_beta*($T$11-$K$11))))) | BD72: =IF(AND($J$12,A72=$Q$12),J72,0) | BE72: =IF(OR(BD72=0,$S$12=0),0,IF((AE72+$L$12)>$S$12/HU_alpha+$K$12,0.5*$S$12/HU_alpha,IF((AE72+$L$12)>=$K$12,((AE72+$L$12)-$K$12)-0.5*HU_alpha/$S$12*((AE72+$L$12)-$K$12)^2,IF((AE72+$L$12)>=$T$12,HU_beta*((AE72+$L$12)-$K$12),HU_beta*($T$12-$K$12))))) | BF72: =IF(OR(BD72=0,$S$12=0),0,IF((AE72+$L$12+$N$12)>$S$12/HU_alpha+$K$12,0.5*$S$12/HU_alpha,IF((AE72+$L$12+$N$12)>=$K$12,((AE72+$L$12+$N$12)-$K$12)-0.5*HU_alpha/$S$12*((AE72+$L$12+$N$12)-$K$12)^2,IF((AE72+$L$12+$N$12)>=$T$12,HU_beta*((AE72+$L$12+$N$12)-$K$12),HU_beta*($T$12-$K$12))))) | BG72: =IF(OR(BD72=0,$S$12=0),0,IF((AE72+$K$12)>$S$12/HU_alpha+$K$12,0.5*$S$12/HU_alpha,IF((AE72+$K$12)>=$K$12,((AE72+$K$12)-$K$12)-0.5*HU_alpha/$S$12*((AE72+$K$12)-$K$12)^2,IF((AE72+$K$12)>=$T$12,HU_beta*((AE72+$K$12)-$K$12),HU_beta*($T$12-$K$12))))) | BH72: =IF(AND($J$13,A72=$Q$13),J72,0) | BI72: =IF(OR(BH72=0,$S$13=0),0,IF((AE72+$L$13)>$S$13/HU_alpha+$K$13,0.5*$S$13/HU_alpha,IF((AE72+$L$13)>=$K$13,((AE72+$L$13)-$K$13)-0.5*HU_alpha/$S$13*((AE72+$L$13)-$K$13)^2,IF((AE72+$L$13)>=$T$13,HU_beta*((AE72+$L$13)-$K$13),HU_beta*($T$13-$K$13))))) | BJ72: =IF(OR(BH72=0,$S$13=0),0,IF((AE72+$L$13+$N$13)>$S$13/HU_alpha+$K$13,0.5*$S$13/HU_alpha,IF((AE72+$L$13+$N$13)>=$K$13,((AE72+$L$13+$N$13)-$K$13)-0.5*HU_alpha/$S$13*((AE72+$L$13+$N$13)-$K$13)^2,IF((AE72+$L$13+$N$13)>=$T$13,HU_beta*((AE72+$L$13+$N$13)-$K$13),HU_beta*($T$13-$K$13))))) | BK72: =IF(OR(BH72=0,$S$13=0),0,IF((AE72+$K$13)>$S$13/HU_alpha+$K$13,0.5*$S$13/HU_alpha,IF((AE72+$K$13)>=$K$13,((AE72+$K$13)-$K$13)-0.5*HU_alpha/$S$13*((AE72+$K$13)-$K$13)^2,IF((AE72+$K$13)>=$T$13,HU_beta*((AE72+$K$13)-$K$13),HU_beta*($T$13-$K$13)))))
A73: 5 | B73: =HU_age+A73 | C73: =A73<=HU_T | D73: =IF(OR(A73<1,A73>HU_T),0,INDEX(HU_q_mort,HU_age+A73-17,HU_col)) | E73: =IF(OR(A73<1,A73>HU_T),0,INDEX(HU_q_adb,HU_age+A73-17,HU_col)) | F73: =IF(OR(A73<1,A73>HU_T),0,INDEX(HU_q_morb,HU_age+A73-17,HU_col)) | G73: =IF(OR(A73<1,A73>HU_T),0,INDEX(HU_q_ptd,HU_age+A73-17,HU_col)) | H73: =IF(OR(A73<1,A73>HU_T),0,INDEX(HU_q_dis,HU_age+A73-17,HU_col)) | I73: =IF(A73>HU_T,0,I72*(1-D73)*(1-E73)) | J73: =IF(A73>=HU_T,0,N(I74)) | K73: =K72*(1-G73) | L73: =1-K73 | M73: =K72*G73 | N73: =N72*(1-H73) | O73: =1-N72 | P73: =P72*(1-F73) | Q73: =1-P72/INDEX($P$68:$P$150,MAX(1,A73-HU_ciYears)) | R73: =(1+inflationRate)^A73 | S73: =IF(OR(OR(A73<1,A73>HU_T),A73-1>=HU_dtr),0,HU_inc0*(1+incomeGrowthRate)^A73) | T73: =IF(A73>HU_T,T72,T72*(1+INDEX(HU_ssG,HU_age+A73-17))) | U73: =IF(AND(HU_dtr>=1,A73=HU_dtr,A73<=HU_T),MIN(S73*INDEX(HU_ssC,HU_age+A73-17)/(1-INDEX(HU_ssC,HU_age+A73-17)),INDEX(HU_ssCap,HU_age+A73-17))*T73,0) | V73: =S73+U73+IF(AND(HU_wdOn,A73=HU_wdYear),HU_wdIncome,0) | W73: =HU_ciProp*Q73+HU_tpdCut*L73+HU_disCut*O73 | X73: =IF(OR(A73<1,A73>HU_T),0,V73*(1-W73)) | Y73: =IF(OR(A73<1,A73>HU_T),0,IF(AND(HU_retExp>0,A73-1>=HU_dtr),HU_retExp,HU_exp0)*R73) | Z73: =-Y73-IF(AND(HU_wdOn,A73=HU_wdYear),HU_wdOut,0) | AA73: =IF(OR(A73<1,A73>HU_T),0,-HU_medCost*R73*F73-HU_tpdCost*R73*M73) | AB73: =IF(A73>HU_T,0,AB72*(1+interestRate)+X73+Z73+AA73) | AC73: =IF(A73>HU_T,0,HU_inv*EXP(HU_mu*A73)) | AD73: =IF(A73>HU_T,0,MAX(0,AC73+AB73)) | AE73: =IF(A73>HU_T,0,MAX(0,X73-Y73)) | AF73: =IF(AND($J$6,A73>=1,A73<=$Q$6-1),J73,0) | AG73: =IF(OR(AF73=0,$S$6=0),0,IF((AD73+$L$6)>$S$6/HU_alpha+$K$6,0.5*$S$6/HU_alpha,IF((AD73+$L$6)>=$K$6,((AD73+$L$6)-$K$6)-0.5*HU_alpha/$S$6*((AD73+$L$6)-$K$6)^2,IF((AD73+$L$6)>=$T$6,HU_beta*((AD73+$L$6)-$K$6),HU_beta*($T$6-$K$6))))) | AH73: =IF(OR(AF73=0,$S$6=0),0,IF((AD73+$L$6+$N$6)>$S$6/HU_alpha+$K$6,0.5*$S$6/HU_alpha,IF((AD73+$L$6+$N$6)>=$K$6,((AD73+$L$6+$N$6)-$K$6)-0.5*HU_alpha/$S$6*((AD73+$L$6+$N$6)-$K$6)^2,IF((AD73+$L$6+$N$6)>=$T$6,HU_beta*((AD73+$L$6+$N$6)-$K$6),HU_beta*($T$6-$K$6))))) | AI73: =IF(OR(AF73=0,$S$6=0),0,IF((AD73+$K$6)>$S$6/HU_alpha+$K$6,0.5*$S$6/HU_alpha,IF((AD73+$K$6)>=$K$6,((AD73+$K$6)-$K$6)-0.5*HU_alpha/$S$6*((AD73+$K$6)-$K$6)^2,IF((AD73+$K$6)>=$T$6,HU_beta*((AD73+$K$6)-$K$6),HU_beta*($T$6-$K$6))))) | AJ73: =IF(AND($J$7,A73>=1,A73<=$Q$7-1),J73,0) | AK73: =IF(OR(AJ73=0,$S$7=0),0,IF((AE73+$L$7)>$S$7/HU_alpha+$K$7,0.5*$S$7/HU_alpha,IF((AE73+$L$7)>=$K$7,((AE73+$L$7)-$K$7)-0.5*HU_alpha/$S$7*((AE73+$L$7)-$K$7)^2,IF((AE73+$L$7)>=$T$7,HU_beta*((AE73+$L$7)-$K$7),HU_beta*($T$7-$K$7))))) | AL73: =IF(OR(AJ73=0,$S$7=0),0,IF((AE73+$L$7+$N$7)>$S$7/HU_alpha+$K$7,0.5*$S$7/HU_alpha,IF((AE73+$L$7+$N$7)>=$K$7,((AE73+$L$7+$N$7)-$K$7)-0.5*HU_alpha/$S$7*((AE73+$L$7+$N$7)-$K$7)^2,IF((AE73+$L$7+$N$7)>=$T$7,HU_beta*((AE73+$L$7+$N$7)-$K$7),HU_beta*($T$7-$K$7))))) | AM73: =IF(OR(AJ73=0,$S$7=0),0,IF((AE73+$K$7)>$S$7/HU_alpha+$K$7,0.5*$S$7/HU_alpha,IF((AE73+$K$7)>=$K$7,((AE73+$K$7)-$K$7)-0.5*HU_alpha/$S$7*((AE73+$K$7)-$K$7)^2,IF((AE73+$K$7)>=$T$7,HU_beta*((AE73+$K$7)-$K$7),HU_beta*($T$7-$K$7))))) | AN73: =IF(AND($J$8,A73>=1,A73<=$Q$8-1),J73,0) | AO73: =IF(OR(AN73=0,$S$8=0),0,IF((AE73+$L$8)>$S$8/HU_alpha+$K$8,0.5*$S$8/HU_alpha,IF((AE73+$L$8)>=$K$8,((AE73+$L$8)-$K$8)-0.5*HU_alpha/$S$8*((AE73+$L$8)-$K$8)^2,IF((AE73+$L$8)>=$T$8,HU_beta*((AE73+$L$8)-$K$8),HU_beta*($T$8-$K$8))))) | AP73: =IF(OR(AN73=0,$S$8=0),0,IF((AE73+$L$8+$N$8)>$S$8/HU_alpha+$K$8,0.5*$S$8/HU_alpha,IF((AE73+$L$8+$N$8)>=$K$8,((AE73+$L$8+$N$8)-$K$8)-0.5*HU_alpha/$S$8*((AE73+$L$8+$N$8)-$K$8)^2,IF((AE73+$L$8+$N$8)>=$T$8,HU_beta*((AE73+$L$8+$N$8)-$K$8),HU_beta*($T$8-$K$8))))) | AQ73: =IF(OR(AN73=0,$S$8=0),0,IF((AE73+$K$8)>$S$8/HU_alpha+$K$8,0.5*$S$8/HU_alpha,IF((AE73+$K$8)>=$K$8,((AE73+$K$8)-$K$8)-0.5*HU_alpha/$S$8*((AE73+$K$8)-$K$8)^2,IF((AE73+$K$8)>=$T$8,HU_beta*((AE73+$K$8)-$K$8),HU_beta*($T$8-$K$8))))) | AR73: =IF(AND($J$9,A73>=1,A73<=$Q$9-1),J73,0) | AS73: =IF(OR(AR73=0,$S$9=0),0,IF((AE73+$L$9)>$S$9/HU_alpha+$K$9,0.5*$S$9/HU_alpha,IF((AE73+$L$9)>=$K$9,((AE73+$L$9)-$K$9)-0.5*HU_alpha/$S$9*((AE73+$L$9)-$K$9)^2,IF((AE73+$L$9)>=$T$9,HU_beta*((AE73+$L$9)-$K$9),HU_beta*($T$9-$K$9))))) | AT73: =IF(OR(AR73=0,$S$9=0),0,IF((AE73+$L$9+$N$9)>$S$9/HU_alpha+$K$9,0.5*$S$9/HU_alpha,IF((AE73+$L$9+$N$9)>=$K$9,((AE73+$L$9+$N$9)-$K$9)-0.5*HU_alpha/$S$9*((AE73+$L$9+$N$9)-$K$9)^2,IF((AE73+$L$9+$N$9)>=$T$9,HU_beta*((AE73+$L$9+$N$9)-$K$9),HU_beta*($T$9-$K$9))))) | AU73: =IF(OR(AR73=0,$S$9=0),0,IF((AE73+$K$9)>$S$9/HU_alpha+$K$9,0.5*$S$9/HU_alpha,IF((AE73+$K$9)>=$K$9,((AE73+$K$9)-$K$9)-0.5*HU_alpha/$S$9*((AE73+$K$9)-$K$9)^2,IF((AE73+$K$9)>=$T$9,HU_beta*((AE73+$K$9)-$K$9),HU_beta*($T$9-$K$9))))) | AV73: =IF(AND($J$10,A73=$Q$10),J73,0) | AW73: =IF(OR(AV73=0,$S$10=0),0,IF((AD73+$L$10)>$S$10/HU_alpha+$K$10,0.5*$S$10/HU_alpha,IF((AD73+$L$10)>=$K$10,((AD73+$L$10)-$K$10)-0.5*HU_alpha/$S$10*((AD73+$L$10)-$K$10)^2,IF((AD73+$L$10)>=$T$10,HU_beta*((AD73+$L$10)-$K$10),HU_beta*($T$10-$K$10))))) | AX73: =IF(OR(AV73=0,$S$10=0),0,IF((AD73+$L$10+$N$10)>$S$10/HU_alpha+$K$10,0.5*$S$10/HU_alpha,IF((AD73+$L$10+$N$10)>=$K$10,((AD73+$L$10+$N$10)-$K$10)-0.5*HU_alpha/$S$10*((AD73+$L$10+$N$10)-$K$10)^2,IF((AD73+$L$10+$N$10)>=$T$10,HU_beta*((AD73+$L$10+$N$10)-$K$10),HU_beta*($T$10-$K$10))))) | AY73: =IF(OR(AV73=0,$S$10=0),0,IF((AD73+$K$10)>$S$10/HU_alpha+$K$10,0.5*$S$10/HU_alpha,IF((AD73+$K$10)>=$K$10,((AD73+$K$10)-$K$10)-0.5*HU_alpha/$S$10*((AD73+$K$10)-$K$10)^2,IF((AD73+$K$10)>=$T$10,HU_beta*((AD73+$K$10)-$K$10),HU_beta*($T$10-$K$10))))) | AZ73: =IF(AND($J$11,A73=$Q$11),J73,0) | BA73: =IF(OR(AZ73=0,$S$11=0),0,IF((AE73+$L$11)>$S$11/HU_alpha+$K$11,0.5*$S$11/HU_alpha,IF((AE73+$L$11)>=$K$11,((AE73+$L$11)-$K$11)-0.5*HU_alpha/$S$11*((AE73+$L$11)-$K$11)^2,IF((AE73+$L$11)>=$T$11,HU_beta*((AE73+$L$11)-$K$11),HU_beta*($T$11-$K$11))))) | BB73: =IF(OR(AZ73=0,$S$11=0),0,IF((AE73+$L$11+$N$11)>$S$11/HU_alpha+$K$11,0.5*$S$11/HU_alpha,IF((AE73+$L$11+$N$11)>=$K$11,((AE73+$L$11+$N$11)-$K$11)-0.5*HU_alpha/$S$11*((AE73+$L$11+$N$11)-$K$11)^2,IF((AE73+$L$11+$N$11)>=$T$11,HU_beta*((AE73+$L$11+$N$11)-$K$11),HU_beta*($T$11-$K$11))))) | BC73: =IF(OR(AZ73=0,$S$11=0),0,IF((AE73+$K$11)>$S$11/HU_alpha+$K$11,0.5*$S$11/HU_alpha,IF((AE73+$K$11)>=$K$11,((AE73+$K$11)-$K$11)-0.5*HU_alpha/$S$11*((AE73+$K$11)-$K$11)^2,IF((AE73+$K$11)>=$T$11,HU_beta*((AE73+$K$11)-$K$11),HU_beta*($T$11-$K$11))))) | BD73: =IF(AND($J$12,A73=$Q$12),J73,0) | BE73: =IF(OR(BD73=0,$S$12=0),0,IF((AE73+$L$12)>$S$12/HU_alpha+$K$12,0.5*$S$12/HU_alpha,IF((AE73+$L$12)>=$K$12,((AE73+$L$12)-$K$12)-0.5*HU_alpha/$S$12*((AE73+$L$12)-$K$12)^2,IF((AE73+$L$12)>=$T$12,HU_beta*((AE73+$L$12)-$K$12),HU_beta*($T$12-$K$12))))) | BF73: =IF(OR(BD73=0,$S$12=0),0,IF((AE73+$L$12+$N$12)>$S$12/HU_alpha+$K$12,0.5*$S$12/HU_alpha,IF((AE73+$L$12+$N$12)>=$K$12,((AE73+$L$12+$N$12)-$K$12)-0.5*HU_alpha/$S$12*((AE73+$L$12+$N$12)-$K$12)^2,IF((AE73+$L$12+$N$12)>=$T$12,HU_beta*((AE73+$L$12+$N$12)-$K$12),HU_beta*($T$12-$K$12))))) | BG73: =IF(OR(BD73=0,$S$12=0),0,IF((AE73+$K$12)>$S$12/HU_alpha+$K$12,0.5*$S$12/HU_alpha,IF((AE73+$K$12)>=$K$12,((AE73+$K$12)-$K$12)-0.5*HU_alpha/$S$12*((AE73+$K$12)-$K$12)^2,IF((AE73+$K$12)>=$T$12,HU_beta*((AE73+$K$12)-$K$12),HU_beta*($T$12-$K$12))))) | BH73: =IF(AND($J$13,A73=$Q$13),J73,0) | BI73: =IF(OR(BH73=0,$S$13=0),0,IF((AE73+$L$13)>$S$13/HU_alpha+$K$13,0.5*$S$13/HU_alpha,IF((AE73+$L$13)>=$K$13,((AE73+$L$13)-$K$13)-0.5*HU_alpha/$S$13*((AE73+$L$13)-$K$13)^2,IF((AE73+$L$13)>=$T$13,HU_beta*((AE73+$L$13)-$K$13),HU_beta*($T$13-$K$13))))) | BJ73: =IF(OR(BH73=0,$S$13=0),0,IF((AE73+$L$13+$N$13)>$S$13/HU_alpha+$K$13,0.5*$S$13/HU_alpha,IF((AE73+$L$13+$N$13)>=$K$13,((AE73+$L$13+$N$13)-$K$13)-0.5*HU_alpha/$S$13*((AE73+$L$13+$N$13)-$K$13)^2,IF((AE73+$L$13+$N$13)>=$T$13,HU_beta*((AE73+$L$13+$N$13)-$K$13),HU_beta*($T$13-$K$13))))) | BK73: =IF(OR(BH73=0,$S$13=0),0,IF((AE73+$K$13)>$S$13/HU_alpha+$K$13,0.5*$S$13/HU_alpha,IF((AE73+$K$13)>=$K$13,((AE73+$K$13)-$K$13)-0.5*HU_alpha/$S$13*((AE73+$K$13)-$K$13)^2,IF((AE73+$K$13)>=$T$13,HU_beta*((AE73+$K$13)-$K$13),HU_beta*($T$13-$K$13)))))
A74: 6 | B74: =HU_age+A74 | C74: =A74<=HU_T | D74: =IF(OR(A74<1,A74>HU_T),0,INDEX(HU_q_mort,HU_age+A74-17,HU_col)) | E74: =IF(OR(A74<1,A74>HU_T),0,INDEX(HU_q_adb,HU_age+A74-17,HU_col)) | F74: =IF(OR(A74<1,A74>HU_T),0,INDEX(HU_q_morb,HU_age+A74-17,HU_col)) | G74: =IF(OR(A74<1,A74>HU_T),0,INDEX(HU_q_ptd,HU_age+A74-17,HU_col)) | H74: =IF(OR(A74<1,A74>HU_T),0,INDEX(HU_q_dis,HU_age+A74-17,HU_col)) | I74: =IF(A74>HU_T,0,I73*(1-D74)*(1-E74)) | J74: =IF(A74>=HU_T,0,N(I75)) | K74: =K73*(1-G74) | L74: =1-K74 | M74: =K73*G74 | N74: =N73*(1-H74) | O74: =1-N73 | P74: =P73*(1-F74) | Q74: =1-P73/INDEX($P$68:$P$150,MAX(1,A74-HU_ciYears)) | R74: =(1+inflationRate)^A74 | S74: =IF(OR(OR(A74<1,A74>HU_T),A74-1>=HU_dtr),0,HU_inc0*(1+incomeGrowthRate)^A74) | T74: =IF(A74>HU_T,T73,T73*(1+INDEX(HU_ssG,HU_age+A74-17))) | U74: =IF(AND(HU_dtr>=1,A74=HU_dtr,A74<=HU_T),MIN(S74*INDEX(HU_ssC,HU_age+A74-17)/(1-INDEX(HU_ssC,HU_age+A74-17)),INDEX(HU_ssCap,HU_age+A74-17))*T74,0) | V74: =S74+U74+IF(AND(HU_wdOn,A74=HU_wdYear),HU_wdIncome,0) | W74: =HU_ciProp*Q74+HU_tpdCut*L74+HU_disCut*O74 | X74: =IF(OR(A74<1,A74>HU_T),0,V74*(1-W74)) | Y74: =IF(OR(A74<1,A74>HU_T),0,IF(AND(HU_retExp>0,A74-1>=HU_dtr),HU_retExp,HU_exp0)*R74) | Z74: =-Y74-IF(AND(HU_wdOn,A74=HU_wdYear),HU_wdOut,0) | AA74: =IF(OR(A74<1,A74>HU_T),0,-HU_medCost*R74*F74-HU_tpdCost*R74*M74) | AB74: =IF(A74>HU_T,0,AB73*(1+interestRate)+X74+Z74+AA74) | AC74: =IF(A74>HU_T,0,HU_inv*EXP(HU_mu*A74)) | AD74: =IF(A74>HU_T,0,MAX(0,AC74+AB74)) | AE74: =IF(A74>HU_T,0,MAX(0,X74-Y74)) | AF74: =IF(AND($J$6,A74>=1,A74<=$Q$6-1),J74,0) | AG74: =IF(OR(AF74=0,$S$6=0),0,IF((AD74+$L$6)>$S$6/HU_alpha+$K$6,0.5*$S$6/HU_alpha,IF((AD74+$L$6)>=$K$6,((AD74+$L$6)-$K$6)-0.5*HU_alpha/$S$6*((AD74+$L$6)-$K$6)^2,IF((AD74+$L$6)>=$T$6,HU_beta*((AD74+$L$6)-$K$6),HU_beta*($T$6-$K$6))))) | AH74: =IF(OR(AF74=0,$S$6=0),0,IF((AD74+$L$6+$N$6)>$S$6/HU_alpha+$K$6,0.5*$S$6/HU_alpha,IF((AD74+$L$6+$N$6)>=$K$6,((AD74+$L$6+$N$6)-$K$6)-0.5*HU_alpha/$S$6*((AD74+$L$6+$N$6)-$K$6)^2,IF((AD74+$L$6+$N$6)>=$T$6,HU_beta*((AD74+$L$6+$N$6)-$K$6),HU_beta*($T$6-$K$6))))) | AI74: =IF(OR(AF74=0,$S$6=0),0,IF((AD74+$K$6)>$S$6/HU_alpha+$K$6,0.5*$S$6/HU_alpha,IF((AD74+$K$6)>=$K$6,((AD74+$K$6)-$K$6)-0.5*HU_alpha/$S$6*((AD74+$K$6)-$K$6)^2,IF((AD74+$K$6)>=$T$6,HU_beta*((AD74+$K$6)-$K$6),HU_beta*($T$6-$K$6))))) | AJ74: =IF(AND($J$7,A74>=1,A74<=$Q$7-1),J74,0) | AK74: =IF(OR(AJ74=0,$S$7=0),0,IF((AE74+$L$7)>$S$7/HU_alpha+$K$7,0.5*$S$7/HU_alpha,IF((AE74+$L$7)>=$K$7,((AE74+$L$7)-$K$7)-0.5*HU_alpha/$S$7*((AE74+$L$7)-$K$7)^2,IF((AE74+$L$7)>=$T$7,HU_beta*((AE74+$L$7)-$K$7),HU_beta*($T$7-$K$7))))) | AL74: =IF(OR(AJ74=0,$S$7=0),0,IF((AE74+$L$7+$N$7)>$S$7/HU_alpha+$K$7,0.5*$S$7/HU_alpha,IF((AE74+$L$7+$N$7)>=$K$7,((AE74+$L$7+$N$7)-$K$7)-0.5*HU_alpha/$S$7*((AE74+$L$7+$N$7)-$K$7)^2,IF((AE74+$L$7+$N$7)>=$T$7,HU_beta*((AE74+$L$7+$N$7)-$K$7),HU_beta*($T$7-$K$7))))) | AM74: =IF(OR(AJ74=0,$S$7=0),0,IF((AE74+$K$7)>$S$7/HU_alpha+$K$7,0.5*$S$7/HU_alpha,IF((AE74+$K$7)>=$K$7,((AE74+$K$7)-$K$7)-0.5*HU_alpha/$S$7*((AE74+$K$7)-$K$7)^2,IF((AE74+$K$7)>=$T$7,HU_beta*((AE74+$K$7)-$K$7),HU_beta*($T$7-$K$7))))) | AN74: =IF(AND($J$8,A74>=1,A74<=$Q$8-1),J74,0) | AO74: =IF(OR(AN74=0,$S$8=0),0,IF((AE74+$L$8)>$S$8/HU_alpha+$K$8,0.5*$S$8/HU_alpha,IF((AE74+$L$8)>=$K$8,((AE74+$L$8)-$K$8)-0.5*HU_alpha/$S$8*((AE74+$L$8)-$K$8)^2,IF((AE74+$L$8)>=$T$8,HU_beta*((AE74+$L$8)-$K$8),HU_beta*($T$8-$K$8))))) | AP74: =IF(OR(AN74=0,$S$8=0),0,IF((AE74+$L$8+$N$8)>$S$8/HU_alpha+$K$8,0.5*$S$8/HU_alpha,IF((AE74+$L$8+$N$8)>=$K$8,((AE74+$L$8+$N$8)-$K$8)-0.5*HU_alpha/$S$8*((AE74+$L$8+$N$8)-$K$8)^2,IF((AE74+$L$8+$N$8)>=$T$8,HU_beta*((AE74+$L$8+$N$8)-$K$8),HU_beta*($T$8-$K$8))))) | AQ74: =IF(OR(AN74=0,$S$8=0),0,IF((AE74+$K$8)>$S$8/HU_alpha+$K$8,0.5*$S$8/HU_alpha,IF((AE74+$K$8)>=$K$8,((AE74+$K$8)-$K$8)-0.5*HU_alpha/$S$8*((AE74+$K$8)-$K$8)^2,IF((AE74+$K$8)>=$T$8,HU_beta*((AE74+$K$8)-$K$8),HU_beta*($T$8-$K$8))))) | AR74: =IF(AND($J$9,A74>=1,A74<=$Q$9-1),J74,0) | AS74: =IF(OR(AR74=0,$S$9=0),0,IF((AE74+$L$9)>$S$9/HU_alpha+$K$9,0.5*$S$9/HU_alpha,IF((AE74+$L$9)>=$K$9,((AE74+$L$9)-$K$9)-0.5*HU_alpha/$S$9*((AE74+$L$9)-$K$9)^2,IF((AE74+$L$9)>=$T$9,HU_beta*((AE74+$L$9)-$K$9),HU_beta*($T$9-$K$9))))) | AT74: =IF(OR(AR74=0,$S$9=0),0,IF((AE74+$L$9+$N$9)>$S$9/HU_alpha+$K$9,0.5*$S$9/HU_alpha,IF((AE74+$L$9+$N$9)>=$K$9,((AE74+$L$9+$N$9)-$K$9)-0.5*HU_alpha/$S$9*((AE74+$L$9+$N$9)-$K$9)^2,IF((AE74+$L$9+$N$9)>=$T$9,HU_beta*((AE74+$L$9+$N$9)-$K$9),HU_beta*($T$9-$K$9))))) | AU74: =IF(OR(AR74=0,$S$9=0),0,IF((AE74+$K$9)>$S$9/HU_alpha+$K$9,0.5*$S$9/HU_alpha,IF((AE74+$K$9)>=$K$9,((AE74+$K$9)-$K$9)-0.5*HU_alpha/$S$9*((AE74+$K$9)-$K$9)^2,IF((AE74+$K$9)>=$T$9,HU_beta*((AE74+$K$9)-$K$9),HU_beta*($T$9-$K$9))))) | AV74: =IF(AND($J$10,A74=$Q$10),J74,0) | AW74: =IF(OR(AV74=0,$S$10=0),0,IF((AD74+$L$10)>$S$10/HU_alpha+$K$10,0.5*$S$10/HU_alpha,IF((AD74+$L$10)>=$K$10,((AD74+$L$10)-$K$10)-0.5*HU_alpha/$S$10*((AD74+$L$10)-$K$10)^2,IF((AD74+$L$10)>=$T$10,HU_beta*((AD74+$L$10)-$K$10),HU_beta*($T$10-$K$10))))) | AX74: =IF(OR(AV74=0,$S$10=0),0,IF((AD74+$L$10+$N$10)>$S$10/HU_alpha+$K$10,0.5*$S$10/HU_alpha,IF((AD74+$L$10+$N$10)>=$K$10,((AD74+$L$10+$N$10)-$K$10)-0.5*HU_alpha/$S$10*((AD74+$L$10+$N$10)-$K$10)^2,IF((AD74+$L$10+$N$10)>=$T$10,HU_beta*((AD74+$L$10+$N$10)-$K$10),HU_beta*($T$10-$K$10))))) | AY74: =IF(OR(AV74=0,$S$10=0),0,IF((AD74+$K$10)>$S$10/HU_alpha+$K$10,0.5*$S$10/HU_alpha,IF((AD74+$K$10)>=$K$10,((AD74+$K$10)-$K$10)-0.5*HU_alpha/$S$10*((AD74+$K$10)-$K$10)^2,IF((AD74+$K$10)>=$T$10,HU_beta*((AD74+$K$10)-$K$10),HU_beta*($T$10-$K$10))))) | AZ74: =IF(AND($J$11,A74=$Q$11),J74,0) | BA74: =IF(OR(AZ74=0,$S$11=0),0,IF((AE74+$L$11)>$S$11/HU_alpha+$K$11,0.5*$S$11/HU_alpha,IF((AE74+$L$11)>=$K$11,((AE74+$L$11)-$K$11)-0.5*HU_alpha/$S$11*((AE74+$L$11)-$K$11)^2,IF((AE74+$L$11)>=$T$11,HU_beta*((AE74+$L$11)-$K$11),HU_beta*($T$11-$K$11))))) | BB74: =IF(OR(AZ74=0,$S$11=0),0,IF((AE74+$L$11+$N$11)>$S$11/HU_alpha+$K$11,0.5*$S$11/HU_alpha,IF((AE74+$L$11+$N$11)>=$K$11,((AE74+$L$11+$N$11)-$K$11)-0.5*HU_alpha/$S$11*((AE74+$L$11+$N$11)-$K$11)^2,IF((AE74+$L$11+$N$11)>=$T$11,HU_beta*((AE74+$L$11+$N$11)-$K$11),HU_beta*($T$11-$K$11))))) | BC74: =IF(OR(AZ74=0,$S$11=0),0,IF((AE74+$K$11)>$S$11/HU_alpha+$K$11,0.5*$S$11/HU_alpha,IF((AE74+$K$11)>=$K$11,((AE74+$K$11)-$K$11)-0.5*HU_alpha/$S$11*((AE74+$K$11)-$K$11)^2,IF((AE74+$K$11)>=$T$11,HU_beta*((AE74+$K$11)-$K$11),HU_beta*($T$11-$K$11))))) | BD74: =IF(AND($J$12,A74=$Q$12),J74,0) | BE74: =IF(OR(BD74=0,$S$12=0),0,IF((AE74+$L$12)>$S$12/HU_alpha+$K$12,0.5*$S$12/HU_alpha,IF((AE74+$L$12)>=$K$12,((AE74+$L$12)-$K$12)-0.5*HU_alpha/$S$12*((AE74+$L$12)-$K$12)^2,IF((AE74+$L$12)>=$T$12,HU_beta*((AE74+$L$12)-$K$12),HU_beta*($T$12-$K$12))))) | BF74: =IF(OR(BD74=0,$S$12=0),0,IF((AE74+$L$12+$N$12)>$S$12/HU_alpha+$K$12,0.5*$S$12/HU_alpha,IF((AE74+$L$12+$N$12)>=$K$12,((AE74+$L$12+$N$12)-$K$12)-0.5*HU_alpha/$S$12*((AE74+$L$12+$N$12)-$K$12)^2,IF((AE74+$L$12+$N$12)>=$T$12,HU_beta*((AE74+$L$12+$N$12)-$K$12),HU_beta*($T$12-$K$12))))) | BG74: =IF(OR(BD74=0,$S$12=0),0,IF((AE74+$K$12)>$S$12/HU_alpha+$K$12,0.5*$S$12/HU_alpha,IF((AE74+$K$12)>=$K$12,((AE74+$K$12)-$K$12)-0.5*HU_alpha/$S$12*((AE74+$K$12)-$K$12)^2,IF((AE74+$K$12)>=$T$12,HU_beta*((AE74+$K$12)-$K$12),HU_beta*($T$12-$K$12))))) | BH74: =IF(AND($J$13,A74=$Q$13),J74,0) | BI74: =IF(OR(BH74=0,$S$13=0),0,IF((AE74+$L$13)>$S$13/HU_alpha+$K$13,0.5*$S$13/HU_alpha,IF((AE74+$L$13)>=$K$13,((AE74+$L$13)-$K$13)-0.5*HU_alpha/$S$13*((AE74+$L$13)-$K$13)^2,IF((AE74+$L$13)>=$T$13,HU_beta*((AE74+$L$13)-$K$13),HU_beta*($T$13-$K$13))))) | BJ74: =IF(OR(BH74=0,$S$13=0),0,IF((AE74+$L$13+$N$13)>$S$13/HU_alpha+$K$13,0.5*$S$13/HU_alpha,IF((AE74+$L$13+$N$13)>=$K$13,((AE74+$L$13+$N$13)-$K$13)-0.5*HU_alpha/$S$13*((AE74+$L$13+$N$13)-$K$13)^2,IF((AE74+$L$13+$N$13)>=$T$13,HU_beta*((AE74+$L$13+$N$13)-$K$13),HU_beta*($T$13-$K$13))))) | BK74: =IF(OR(BH74=0,$S$13=0),0,IF((AE74+$K$13)>$S$13/HU_alpha+$K$13,0.5*$S$13/HU_alpha,IF((AE74+$K$13)>=$K$13,((AE74+$K$13)-$K$13)-0.5*HU_alpha/$S$13*((AE74+$K$13)-$K$13)^2,IF((AE74+$K$13)>=$T$13,HU_beta*((AE74+$K$13)-$K$13),HU_beta*($T$13-$K$13)))))
A75: 7 | B75: =HU_age+A75 | C75: =A75<=HU_T | D75: =IF(OR(A75<1,A75>HU_T),0,INDEX(HU_q_mort,HU_age+A75-17,HU_col)) | E75: =IF(OR(A75<1,A75>HU_T),0,INDEX(HU_q_adb,HU_age+A75-17,HU_col)) | F75: =IF(OR(A75<1,A75>HU_T),0,INDEX(HU_q_morb,HU_age+A75-17,HU_col)) | G75: =IF(OR(A75<1,A75>HU_T),0,INDEX(HU_q_ptd,HU_age+A75-17,HU_col)) | H75: =IF(OR(A75<1,A75>HU_T),0,INDEX(HU_q_dis,HU_age+A75-17,HU_col)) | I75: =IF(A75>HU_T,0,I74*(1-D75)*(1-E75)) | J75: =IF(A75>=HU_T,0,N(I76)) | K75: =K74*(1-G75) | L75: =1-K75 | M75: =K74*G75 | N75: =N74*(1-H75) | O75: =1-N74 | P75: =P74*(1-F75) | Q75: =1-P74/INDEX($P$68:$P$150,MAX(1,A75-HU_ciYears)) | R75: =(1+inflationRate)^A75 | S75: =IF(OR(OR(A75<1,A75>HU_T),A75-1>=HU_dtr),0,HU_inc0*(1+incomeGrowthRate)^A75) | T75: =IF(A75>HU_T,T74,T74*(1+INDEX(HU_ssG,HU_age+A75-17))) | U75: =IF(AND(HU_dtr>=1,A75=HU_dtr,A75<=HU_T),MIN(S75*INDEX(HU_ssC,HU_age+A75-17)/(1-INDEX(HU_ssC,HU_age+A75-17)),INDEX(HU_ssCap,HU_age+A75-17))*T75,0) | V75: =S75+U75+IF(AND(HU_wdOn,A75=HU_wdYear),HU_wdIncome,0) | W75: =HU_ciProp*Q75+HU_tpdCut*L75+HU_disCut*O75 | X75: =IF(OR(A75<1,A75>HU_T),0,V75*(1-W75)) | Y75: =IF(OR(A75<1,A75>HU_T),0,IF(AND(HU_retExp>0,A75-1>=HU_dtr),HU_retExp,HU_exp0)*R75) | Z75: =-Y75-IF(AND(HU_wdOn,A75=HU_wdYear),HU_wdOut,0) | AA75: =IF(OR(A75<1,A75>HU_T),0,-HU_medCost*R75*F75-HU_tpdCost*R75*M75) | AB75: =IF(A75>HU_T,0,AB74*(1+interestRate)+X75+Z75+AA75) | AC75: =IF(A75>HU_T,0,HU_inv*EXP(HU_mu*A75)) | AD75: =IF(A75>HU_T,0,MAX(0,AC75+AB75)) | AE75: =IF(A75>HU_T,0,MAX(0,X75-Y75)) | AF75: =IF(AND($J$6,A75>=1,A75<=$Q$6-1),J75,0) | AG75: =IF(OR(AF75=0,$S$6=0),0,IF((AD75+$L$6)>$S$6/HU_alpha+$K$6,0.5*$S$6/HU_alpha,IF((AD75+$L$6)>=$K$6,((AD75+$L$6)-$K$6)-0.5*HU_alpha/$S$6*((AD75+$L$6)-$K$6)^2,IF((AD75+$L$6)>=$T$6,HU_beta*((AD75+$L$6)-$K$6),HU_beta*($T$6-$K$6))))) | AH75: =IF(OR(AF75=0,$S$6=0),0,IF((AD75+$L$6+$N$6)>$S$6/HU_alpha+$K$6,0.5*$S$6/HU_alpha,IF((AD75+$L$6+$N$6)>=$K$6,((AD75+$L$6+$N$6)-$K$6)-0.5*HU_alpha/$S$6*((AD75+$L$6+$N$6)-$K$6)^2,IF((AD75+$L$6+$N$6)>=$T$6,HU_beta*((AD75+$L$6+$N$6)-$K$6),HU_beta*($T$6-$K$6))))) | AI75: =IF(OR(AF75=0,$S$6=0),0,IF((AD75+$K$6)>$S$6/HU_alpha+$K$6,0.5*$S$6/HU_alpha,IF((AD75+$K$6)>=$K$6,((AD75+$K$6)-$K$6)-0.5*HU_alpha/$S$6*((AD75+$K$6)-$K$6)^2,IF((AD75+$K$6)>=$T$6,HU_beta*((AD75+$K$6)-$K$6),HU_beta*($T$6-$K$6))))) | AJ75: =IF(AND($J$7,A75>=1,A75<=$Q$7-1),J75,0) | AK75: =IF(OR(AJ75=0,$S$7=0),0,IF((AE75+$L$7)>$S$7/HU_alpha+$K$7,0.5*$S$7/HU_alpha,IF((AE75+$L$7)>=$K$7,((AE75+$L$7)-$K$7)-0.5*HU_alpha/$S$7*((AE75+$L$7)-$K$7)^2,IF((AE75+$L$7)>=$T$7,HU_beta*((AE75+$L$7)-$K$7),HU_beta*($T$7-$K$7))))) | AL75: =IF(OR(AJ75=0,$S$7=0),0,IF((AE75+$L$7+$N$7)>$S$7/HU_alpha+$K$7,0.5*$S$7/HU_alpha,IF((AE75+$L$7+$N$7)>=$K$7,((AE75+$L$7+$N$7)-$K$7)-0.5*HU_alpha/$S$7*((AE75+$L$7+$N$7)-$K$7)^2,IF((AE75+$L$7+$N$7)>=$T$7,HU_beta*((AE75+$L$7+$N$7)-$K$7),HU_beta*($T$7-$K$7))))) | AM75: =IF(OR(AJ75=0,$S$7=0),0,IF((AE75+$K$7)>$S$7/HU_alpha+$K$7,0.5*$S$7/HU_alpha,IF((AE75+$K$7)>=$K$7,((AE75+$K$7)-$K$7)-0.5*HU_alpha/$S$7*((AE75+$K$7)-$K$7)^2,IF((AE75+$K$7)>=$T$7,HU_beta*((AE75+$K$7)-$K$7),HU_beta*($T$7-$K$7))))) | AN75: =IF(AND($J$8,A75>=1,A75<=$Q$8-1),J75,0) | AO75: =IF(OR(AN75=0,$S$8=0),0,IF((AE75+$L$8)>$S$8/HU_alpha+$K$8,0.5*$S$8/HU_alpha,IF((AE75+$L$8)>=$K$8,((AE75+$L$8)-$K$8)-0.5*HU_alpha/$S$8*((AE75+$L$8)-$K$8)^2,IF((AE75+$L$8)>=$T$8,HU_beta*((AE75+$L$8)-$K$8),HU_beta*($T$8-$K$8))))) | AP75: =IF(OR(AN75=0,$S$8=0),0,IF((AE75+$L$8+$N$8)>$S$8/HU_alpha+$K$8,0.5*$S$8/HU_alpha,IF((AE75+$L$8+$N$8)>=$K$8,((AE75+$L$8+$N$8)-$K$8)-0.5*HU_alpha/$S$8*((AE75+$L$8+$N$8)-$K$8)^2,IF((AE75+$L$8+$N$8)>=$T$8,HU_beta*((AE75+$L$8+$N$8)-$K$8),HU_beta*($T$8-$K$8))))) | AQ75: =IF(OR(AN75=0,$S$8=0),0,IF((AE75+$K$8)>$S$8/HU_alpha+$K$8,0.5*$S$8/HU_alpha,IF((AE75+$K$8)>=$K$8,((AE75+$K$8)-$K$8)-0.5*HU_alpha/$S$8*((AE75+$K$8)-$K$8)^2,IF((AE75+$K$8)>=$T$8,HU_beta*((AE75+$K$8)-$K$8),HU_beta*($T$8-$K$8))))) | AR75: =IF(AND($J$9,A75>=1,A75<=$Q$9-1),J75,0) | AS75: =IF(OR(AR75=0,$S$9=0),0,IF((AE75+$L$9)>$S$9/HU_alpha+$K$9,0.5*$S$9/HU_alpha,IF((AE75+$L$9)>=$K$9,((AE75+$L$9)-$K$9)-0.5*HU_alpha/$S$9*((AE75+$L$9)-$K$9)^2,IF((AE75+$L$9)>=$T$9,HU_beta*((AE75+$L$9)-$K$9),HU_beta*($T$9-$K$9))))) | AT75: =IF(OR(AR75=0,$S$9=0),0,IF((AE75+$L$9+$N$9)>$S$9/HU_alpha+$K$9,0.5*$S$9/HU_alpha,IF((AE75+$L$9+$N$9)>=$K$9,((AE75+$L$9+$N$9)-$K$9)-0.5*HU_alpha/$S$9*((AE75+$L$9+$N$9)-$K$9)^2,IF((AE75+$L$9+$N$9)>=$T$9,HU_beta*((AE75+$L$9+$N$9)-$K$9),HU_beta*($T$9-$K$9))))) | AU75: =IF(OR(AR75=0,$S$9=0),0,IF((AE75+$K$9)>$S$9/HU_alpha+$K$9,0.5*$S$9/HU_alpha,IF((AE75+$K$9)>=$K$9,((AE75+$K$9)-$K$9)-0.5*HU_alpha/$S$9*((AE75+$K$9)-$K$9)^2,IF((AE75+$K$9)>=$T$9,HU_beta*((AE75+$K$9)-$K$9),HU_beta*($T$9-$K$9))))) | AV75: =IF(AND($J$10,A75=$Q$10),J75,0) | AW75: =IF(OR(AV75=0,$S$10=0),0,IF((AD75+$L$10)>$S$10/HU_alpha+$K$10,0.5*$S$10/HU_alpha,IF((AD75+$L$10)>=$K$10,((AD75+$L$10)-$K$10)-0.5*HU_alpha/$S$10*((AD75+$L$10)-$K$10)^2,IF((AD75+$L$10)>=$T$10,HU_beta*((AD75+$L$10)-$K$10),HU_beta*($T$10-$K$10))))) | AX75: =IF(OR(AV75=0,$S$10=0),0,IF((AD75+$L$10+$N$10)>$S$10/HU_alpha+$K$10,0.5*$S$10/HU_alpha,IF((AD75+$L$10+$N$10)>=$K$10,((AD75+$L$10+$N$10)-$K$10)-0.5*HU_alpha/$S$10*((AD75+$L$10+$N$10)-$K$10)^2,IF((AD75+$L$10+$N$10)>=$T$10,HU_beta*((AD75+$L$10+$N$10)-$K$10),HU_beta*($T$10-$K$10))))) | AY75: =IF(OR(AV75=0,$S$10=0),0,IF((AD75+$K$10)>$S$10/HU_alpha+$K$10,0.5*$S$10/HU_alpha,IF((AD75+$K$10)>=$K$10,((AD75+$K$10)-$K$10)-0.5*HU_alpha/$S$10*((AD75+$K$10)-$K$10)^2,IF((AD75+$K$10)>=$T$10,HU_beta*((AD75+$K$10)-$K$10),HU_beta*($T$10-$K$10))))) | AZ75: =IF(AND($J$11,A75=$Q$11),J75,0) | BA75: =IF(OR(AZ75=0,$S$11=0),0,IF((AE75+$L$11)>$S$11/HU_alpha+$K$11,0.5*$S$11/HU_alpha,IF((AE75+$L$11)>=$K$11,((AE75+$L$11)-$K$11)-0.5*HU_alpha/$S$11*((AE75+$L$11)-$K$11)^2,IF((AE75+$L$11)>=$T$11,HU_beta*((AE75+$L$11)-$K$11),HU_beta*($T$11-$K$11))))) | BB75: =IF(OR(AZ75=0,$S$11=0),0,IF((AE75+$L$11+$N$11)>$S$11/HU_alpha+$K$11,0.5*$S$11/HU_alpha,IF((AE75+$L$11+$N$11)>=$K$11,((AE75+$L$11+$N$11)-$K$11)-0.5*HU_alpha/$S$11*((AE75+$L$11+$N$11)-$K$11)^2,IF((AE75+$L$11+$N$11)>=$T$11,HU_beta*((AE75+$L$11+$N$11)-$K$11),HU_beta*($T$11-$K$11))))) | BC75: =IF(OR(AZ75=0,$S$11=0),0,IF((AE75+$K$11)>$S$11/HU_alpha+$K$11,0.5*$S$11/HU_alpha,IF((AE75+$K$11)>=$K$11,((AE75+$K$11)-$K$11)-0.5*HU_alpha/$S$11*((AE75+$K$11)-$K$11)^2,IF((AE75+$K$11)>=$T$11,HU_beta*((AE75+$K$11)-$K$11),HU_beta*($T$11-$K$11))))) | BD75: =IF(AND($J$12,A75=$Q$12),J75,0) | BE75: =IF(OR(BD75=0,$S$12=0),0,IF((AE75+$L$12)>$S$12/HU_alpha+$K$12,0.5*$S$12/HU_alpha,IF((AE75+$L$12)>=$K$12,((AE75+$L$12)-$K$12)-0.5*HU_alpha/$S$12*((AE75+$L$12)-$K$12)^2,IF((AE75+$L$12)>=$T$12,HU_beta*((AE75+$L$12)-$K$12),HU_beta*($T$12-$K$12))))) | BF75: =IF(OR(BD75=0,$S$12=0),0,IF((AE75+$L$12+$N$12)>$S$12/HU_alpha+$K$12,0.5*$S$12/HU_alpha,IF((AE75+$L$12+$N$12)>=$K$12,((AE75+$L$12+$N$12)-$K$12)-0.5*HU_alpha/$S$12*((AE75+$L$12+$N$12)-$K$12)^2,IF((AE75+$L$12+$N$12)>=$T$12,HU_beta*((AE75+$L$12+$N$12)-$K$12),HU_beta*($T$12-$K$12))))) | BG75: =IF(OR(BD75=0,$S$12=0),0,IF((AE75+$K$12)>$S$12/HU_alpha+$K$12,0.5*$S$12/HU_alpha,IF((AE75+$K$12)>=$K$12,((AE75+$K$12)-$K$12)-0.5*HU_alpha/$S$12*((AE75+$K$12)-$K$12)^2,IF((AE75+$K$12)>=$T$12,HU_beta*((AE75+$K$12)-$K$12),HU_beta*($T$12-$K$12))))) | BH75: =IF(AND($J$13,A75=$Q$13),J75,0) | BI75: =IF(OR(BH75=0,$S$13=0),0,IF((AE75+$L$13)>$S$13/HU_alpha+$K$13,0.5*$S$13/HU_alpha,IF((AE75+$L$13)>=$K$13,((AE75+$L$13)-$K$13)-0.5*HU_alpha/$S$13*((AE75+$L$13)-$K$13)^2,IF((AE75+$L$13)>=$T$13,HU_beta*((AE75+$L$13)-$K$13),HU_beta*($T$13-$K$13))))) | BJ75: =IF(OR(BH75=0,$S$13=0),0,IF((AE75+$L$13+$N$13)>$S$13/HU_alpha+$K$13,0.5*$S$13/HU_alpha,IF((AE75+$L$13+$N$13)>=$K$13,((AE75+$L$13+$N$13)-$K$13)-0.5*HU_alpha/$S$13*((AE75+$L$13+$N$13)-$K$13)^2,IF((AE75+$L$13+$N$13)>=$T$13,HU_beta*((AE75+$L$13+$N$13)-$K$13),HU_beta*($T$13-$K$13))))) | BK75: =IF(OR(BH75=0,$S$13=0),0,IF((AE75+$K$13)>$S$13/HU_alpha+$K$13,0.5*$S$13/HU_alpha,IF((AE75+$K$13)>=$K$13,((AE75+$K$13)-$K$13)-0.5*HU_alpha/$S$13*((AE75+$K$13)-$K$13)^2,IF((AE75+$K$13)>=$T$13,HU_beta*((AE75+$K$13)-$K$13),HU_beta*($T$13-$K$13)))))
A76: 8 | B76: =HU_age+A76 | C76: =A76<=HU_T | D76: =IF(OR(A76<1,A76>HU_T),0,INDEX(HU_q_mort,HU_age+A76-17,HU_col)) | E76: =IF(OR(A76<1,A76>HU_T),0,INDEX(HU_q_adb,HU_age+A76-17,HU_col)) | F76: =IF(OR(A76<1,A76>HU_T),0,INDEX(HU_q_morb,HU_age+A76-17,HU_col)) | G76: =IF(OR(A76<1,A76>HU_T),0,INDEX(HU_q_ptd,HU_age+A76-17,HU_col)) | H76: =IF(OR(A76<1,A76>HU_T),0,INDEX(HU_q_dis,HU_age+A76-17,HU_col)) | I76: =IF(A76>HU_T,0,I75*(1-D76)*(1-E76)) | J76: =IF(A76>=HU_T,0,N(I77)) | K76: =K75*(1-G76) | L76: =1-K76 | M76: =K75*G76 | N76: =N75*(1-H76) | O76: =1-N75 | P76: =P75*(1-F76) | Q76: =1-P75/INDEX($P$68:$P$150,MAX(1,A76-HU_ciYears)) | R76: =(1+inflationRate)^A76 | S76: =IF(OR(OR(A76<1,A76>HU_T),A76-1>=HU_dtr),0,HU_inc0*(1+incomeGrowthRate)^A76) | T76: =IF(A76>HU_T,T75,T75*(1+INDEX(HU_ssG,HU_age+A76-17))) | U76: =IF(AND(HU_dtr>=1,A76=HU_dtr,A76<=HU_T),MIN(S76*INDEX(HU_ssC,HU_age+A76-17)/(1-INDEX(HU_ssC,HU_age+A76-17)),INDEX(HU_ssCap,HU_age+A76-17))*T76,0) | V76: =S76+U76+IF(AND(HU_wdOn,A76=HU_wdYear),HU_wdIncome,0) | W76: =HU_ciProp*Q76+HU_tpdCut*L76+HU_disCut*O76 | X76: =IF(OR(A76<1,A76>HU_T),0,V76*(1-W76)) | Y76: =IF(OR(A76<1,A76>HU_T),0,IF(AND(HU_retExp>0,A76-1>=HU_dtr),HU_retExp,HU_exp0)*R76) | Z76: =-Y76-IF(AND(HU_wdOn,A76=HU_wdYear),HU_wdOut,0) | AA76: =IF(OR(A76<1,A76>HU_T),0,-HU_medCost*R76*F76-HU_tpdCost*R76*M76) | AB76: =IF(A76>HU_T,0,AB75*(1+interestRate)+X76+Z76+AA76) | AC76: =IF(A76>HU_T,0,HU_inv*EXP(HU_mu*A76)) | AD76: =IF(A76>HU_T,0,MAX(0,AC76+AB76)) | AE76: =IF(A76>HU_T,0,MAX(0,X76-Y76)) | AF76: =IF(AND($J$6,A76>=1,A76<=$Q$6-1),J76,0) | AG76: =IF(OR(AF76=0,$S$6=0),0,IF((AD76+$L$6)>$S$6/HU_alpha+$K$6,0.5*$S$6/HU_alpha,IF((AD76+$L$6)>=$K$6,((AD76+$L$6)-$K$6)-0.5*HU_alpha/$S$6*((AD76+$L$6)-$K$6)^2,IF((AD76+$L$6)>=$T$6,HU_beta*((AD76+$L$6)-$K$6),HU_beta*($T$6-$K$6))))) | AH76: =IF(OR(AF76=0,$S$6=0),0,IF((AD76+$L$6+$N$6)>$S$6/HU_alpha+$K$6,0.5*$S$6/HU_alpha,IF((AD76+$L$6+$N$6)>=$K$6,((AD76+$L$6+$N$6)-$K$6)-0.5*HU_alpha/$S$6*((AD76+$L$6+$N$6)-$K$6)^2,IF((AD76+$L$6+$N$6)>=$T$6,HU_beta*((AD76+$L$6+$N$6)-$K$6),HU_beta*($T$6-$K$6))))) | AI76: =IF(OR(AF76=0,$S$6=0),0,IF((AD76+$K$6)>$S$6/HU_alpha+$K$6,0.5*$S$6/HU_alpha,IF((AD76+$K$6)>=$K$6,((AD76+$K$6)-$K$6)-0.5*HU_alpha/$S$6*((AD76+$K$6)-$K$6)^2,IF((AD76+$K$6)>=$T$6,HU_beta*((AD76+$K$6)-$K$6),HU_beta*($T$6-$K$6))))) | AJ76: =IF(AND($J$7,A76>=1,A76<=$Q$7-1),J76,0) | AK76: =IF(OR(AJ76=0,$S$7=0),0,IF((AE76+$L$7)>$S$7/HU_alpha+$K$7,0.5*$S$7/HU_alpha,IF((AE76+$L$7)>=$K$7,((AE76+$L$7)-$K$7)-0.5*HU_alpha/$S$7*((AE76+$L$7)-$K$7)^2,IF((AE76+$L$7)>=$T$7,HU_beta*((AE76+$L$7)-$K$7),HU_beta*($T$7-$K$7))))) | AL76: =IF(OR(AJ76=0,$S$7=0),0,IF((AE76+$L$7+$N$7)>$S$7/HU_alpha+$K$7,0.5*$S$7/HU_alpha,IF((AE76+$L$7+$N$7)>=$K$7,((AE76+$L$7+$N$7)-$K$7)-0.5*HU_alpha/$S$7*((AE76+$L$7+$N$7)-$K$7)^2,IF((AE76+$L$7+$N$7)>=$T$7,HU_beta*((AE76+$L$7+$N$7)-$K$7),HU_beta*($T$7-$K$7))))) | AM76: =IF(OR(AJ76=0,$S$7=0),0,IF((AE76+$K$7)>$S$7/HU_alpha+$K$7,0.5*$S$7/HU_alpha,IF((AE76+$K$7)>=$K$7,((AE76+$K$7)-$K$7)-0.5*HU_alpha/$S$7*((AE76+$K$7)-$K$7)^2,IF((AE76+$K$7)>=$T$7,HU_beta*((AE76+$K$7)-$K$7),HU_beta*($T$7-$K$7))))) | AN76: =IF(AND($J$8,A76>=1,A76<=$Q$8-1),J76,0) | AO76: =IF(OR(AN76=0,$S$8=0),0,IF((AE76+$L$8)>$S$8/HU_alpha+$K$8,0.5*$S$8/HU_alpha,IF((AE76+$L$8)>=$K$8,((AE76+$L$8)-$K$8)-0.5*HU_alpha/$S$8*((AE76+$L$8)-$K$8)^2,IF((AE76+$L$8)>=$T$8,HU_beta*((AE76+$L$8)-$K$8),HU_beta*($T$8-$K$8))))) | AP76: =IF(OR(AN76=0,$S$8=0),0,IF((AE76+$L$8+$N$8)>$S$8/HU_alpha+$K$8,0.5*$S$8/HU_alpha,IF((AE76+$L$8+$N$8)>=$K$8,((AE76+$L$8+$N$8)-$K$8)-0.5*HU_alpha/$S$8*((AE76+$L$8+$N$8)-$K$8)^2,IF((AE76+$L$8+$N$8)>=$T$8,HU_beta*((AE76+$L$8+$N$8)-$K$8),HU_beta*($T$8-$K$8))))) | AQ76: =IF(OR(AN76=0,$S$8=0),0,IF((AE76+$K$8)>$S$8/HU_alpha+$K$8,0.5*$S$8/HU_alpha,IF((AE76+$K$8)>=$K$8,((AE76+$K$8)-$K$8)-0.5*HU_alpha/$S$8*((AE76+$K$8)-$K$8)^2,IF((AE76+$K$8)>=$T$8,HU_beta*((AE76+$K$8)-$K$8),HU_beta*($T$8-$K$8))))) | AR76: =IF(AND($J$9,A76>=1,A76<=$Q$9-1),J76,0) | AS76: =IF(OR(AR76=0,$S$9=0),0,IF((AE76+$L$9)>$S$9/HU_alpha+$K$9,0.5*$S$9/HU_alpha,IF((AE76+$L$9)>=$K$9,((AE76+$L$9)-$K$9)-0.5*HU_alpha/$S$9*((AE76+$L$9)-$K$9)^2,IF((AE76+$L$9)>=$T$9,HU_beta*((AE76+$L$9)-$K$9),HU_beta*($T$9-$K$9))))) | AT76: =IF(OR(AR76=0,$S$9=0),0,IF((AE76+$L$9+$N$9)>$S$9/HU_alpha+$K$9,0.5*$S$9/HU_alpha,IF((AE76+$L$9+$N$9)>=$K$9,((AE76+$L$9+$N$9)-$K$9)-0.5*HU_alpha/$S$9*((AE76+$L$9+$N$9)-$K$9)^2,IF((AE76+$L$9+$N$9)>=$T$9,HU_beta*((AE76+$L$9+$N$9)-$K$9),HU_beta*($T$9-$K$9))))) | AU76: =IF(OR(AR76=0,$S$9=0),0,IF((AE76+$K$9)>$S$9/HU_alpha+$K$9,0.5*$S$9/HU_alpha,IF((AE76+$K$9)>=$K$9,((AE76+$K$9)-$K$9)-0.5*HU_alpha/$S$9*((AE76+$K$9)-$K$9)^2,IF((AE76+$K$9)>=$T$9,HU_beta*((AE76+$K$9)-$K$9),HU_beta*($T$9-$K$9))))) | AV76: =IF(AND($J$10,A76=$Q$10),J76,0) | AW76: =IF(OR(AV76=0,$S$10=0),0,IF((AD76+$L$10)>$S$10/HU_alpha+$K$10,0.5*$S$10/HU_alpha,IF((AD76+$L$10)>=$K$10,((AD76+$L$10)-$K$10)-0.5*HU_alpha/$S$10*((AD76+$L$10)-$K$10)^2,IF((AD76+$L$10)>=$T$10,HU_beta*((AD76+$L$10)-$K$10),HU_beta*($T$10-$K$10))))) | AX76: =IF(OR(AV76=0,$S$10=0),0,IF((AD76+$L$10+$N$10)>$S$10/HU_alpha+$K$10,0.5*$S$10/HU_alpha,IF((AD76+$L$10+$N$10)>=$K$10,((AD76+$L$10+$N$10)-$K$10)-0.5*HU_alpha/$S$10*((AD76+$L$10+$N$10)-$K$10)^2,IF((AD76+$L$10+$N$10)>=$T$10,HU_beta*((AD76+$L$10+$N$10)-$K$10),HU_beta*($T$10-$K$10))))) | AY76: =IF(OR(AV76=0,$S$10=0),0,IF((AD76+$K$10)>$S$10/HU_alpha+$K$10,0.5*$S$10/HU_alpha,IF((AD76+$K$10)>=$K$10,((AD76+$K$10)-$K$10)-0.5*HU_alpha/$S$10*((AD76+$K$10)-$K$10)^2,IF((AD76+$K$10)>=$T$10,HU_beta*((AD76+$K$10)-$K$10),HU_beta*($T$10-$K$10))))) | AZ76: =IF(AND($J$11,A76=$Q$11),J76,0) | BA76: =IF(OR(AZ76=0,$S$11=0),0,IF((AE76+$L$11)>$S$11/HU_alpha+$K$11,0.5*$S$11/HU_alpha,IF((AE76+$L$11)>=$K$11,((AE76+$L$11)-$K$11)-0.5*HU_alpha/$S$11*((AE76+$L$11)-$K$11)^2,IF((AE76+$L$11)>=$T$11,HU_beta*((AE76+$L$11)-$K$11),HU_beta*($T$11-$K$11))))) | BB76: =IF(OR(AZ76=0,$S$11=0),0,IF((AE76+$L$11+$N$11)>$S$11/HU_alpha+$K$11,0.5*$S$11/HU_alpha,IF((AE76+$L$11+$N$11)>=$K$11,((AE76+$L$11+$N$11)-$K$11)-0.5*HU_alpha/$S$11*((AE76+$L$11+$N$11)-$K$11)^2,IF((AE76+$L$11+$N$11)>=$T$11,HU_beta*((AE76+$L$11+$N$11)-$K$11),HU_beta*($T$11-$K$11))))) | BC76: =IF(OR(AZ76=0,$S$11=0),0,IF((AE76+$K$11)>$S$11/HU_alpha+$K$11,0.5*$S$11/HU_alpha,IF((AE76+$K$11)>=$K$11,((AE76+$K$11)-$K$11)-0.5*HU_alpha/$S$11*((AE76+$K$11)-$K$11)^2,IF((AE76+$K$11)>=$T$11,HU_beta*((AE76+$K$11)-$K$11),HU_beta*($T$11-$K$11))))) | BD76: =IF(AND($J$12,A76=$Q$12),J76,0) | BE76: =IF(OR(BD76=0,$S$12=0),0,IF((AE76+$L$12)>$S$12/HU_alpha+$K$12,0.5*$S$12/HU_alpha,IF((AE76+$L$12)>=$K$12,((AE76+$L$12)-$K$12)-0.5*HU_alpha/$S$12*((AE76+$L$12)-$K$12)^2,IF((AE76+$L$12)>=$T$12,HU_beta*((AE76+$L$12)-$K$12),HU_beta*($T$12-$K$12))))) | BF76: =IF(OR(BD76=0,$S$12=0),0,IF((AE76+$L$12+$N$12)>$S$12/HU_alpha+$K$12,0.5*$S$12/HU_alpha,IF((AE76+$L$12+$N$12)>=$K$12,((AE76+$L$12+$N$12)-$K$12)-0.5*HU_alpha/$S$12*((AE76+$L$12+$N$12)-$K$12)^2,IF((AE76+$L$12+$N$12)>=$T$12,HU_beta*((AE76+$L$12+$N$12)-$K$12),HU_beta*($T$12-$K$12))))) | BG76: =IF(OR(BD76=0,$S$12=0),0,IF((AE76+$K$12)>$S$12/HU_alpha+$K$12,0.5*$S$12/HU_alpha,IF((AE76+$K$12)>=$K$12,((AE76+$K$12)-$K$12)-0.5*HU_alpha/$S$12*((AE76+$K$12)-$K$12)^2,IF((AE76+$K$12)>=$T$12,HU_beta*((AE76+$K$12)-$K$12),HU_beta*($T$12-$K$12))))) | BH76: =IF(AND($J$13,A76=$Q$13),J76,0) | BI76: =IF(OR(BH76=0,$S$13=0),0,IF((AE76+$L$13)>$S$13/HU_alpha+$K$13,0.5*$S$13/HU_alpha,IF((AE76+$L$13)>=$K$13,((AE76+$L$13)-$K$13)-0.5*HU_alpha/$S$13*((AE76+$L$13)-$K$13)^2,IF((AE76+$L$13)>=$T$13,HU_beta*((AE76+$L$13)-$K$13),HU_beta*($T$13-$K$13))))) | BJ76: =IF(OR(BH76=0,$S$13=0),0,IF((AE76+$L$13+$N$13)>$S$13/HU_alpha+$K$13,0.5*$S$13/HU_alpha,IF((AE76+$L$13+$N$13)>=$K$13,((AE76+$L$13+$N$13)-$K$13)-0.5*HU_alpha/$S$13*((AE76+$L$13+$N$13)-$K$13)^2,IF((AE76+$L$13+$N$13)>=$T$13,HU_beta*((AE76+$L$13+$N$13)-$K$13),HU_beta*($T$13-$K$13))))) | BK76: =IF(OR(BH76=0,$S$13=0),0,IF((AE76+$K$13)>$S$13/HU_alpha+$K$13,0.5*$S$13/HU_alpha,IF((AE76+$K$13)>=$K$13,((AE76+$K$13)-$K$13)-0.5*HU_alpha/$S$13*((AE76+$K$13)-$K$13)^2,IF((AE76+$K$13)>=$T$13,HU_beta*((AE76+$K$13)-$K$13),HU_beta*($T$13-$K$13)))))
A77: 9 | B77: =HU_age+A77 | C77: =A77<=HU_T | D77: =IF(OR(A77<1,A77>HU_T),0,INDEX(HU_q_mort,HU_age+A77-17,HU_col)) | E77: =IF(OR(A77<1,A77>HU_T),0,INDEX(HU_q_adb,HU_age+A77-17,HU_col)) | F77: =IF(OR(A77<1,A77>HU_T),0,INDEX(HU_q_morb,HU_age+A77-17,HU_col)) | G77: =IF(OR(A77<1,A77>HU_T),0,INDEX(HU_q_ptd,HU_age+A77-17,HU_col)) | H77: =IF(OR(A77<1,A77>HU_T),0,INDEX(HU_q_dis,HU_age+A77-17,HU_col)) | I77: =IF(A77>HU_T,0,I76*(1-D77)*(1-E77)) | J77: =IF(A77>=HU_T,0,N(I78)) | K77: =K76*(1-G77) | L77: =1-K77 | M77: =K76*G77 | N77: =N76*(1-H77) | O77: =1-N76 | P77: =P76*(1-F77) | Q77: =1-P76/INDEX($P$68:$P$150,MAX(1,A77-HU_ciYears)) | R77: =(1+inflationRate)^A77 | S77: =IF(OR(OR(A77<1,A77>HU_T),A77-1>=HU_dtr),0,HU_inc0*(1+incomeGrowthRate)^A77) | T77: =IF(A77>HU_T,T76,T76*(1+INDEX(HU_ssG,HU_age+A77-17))) | U77: =IF(AND(HU_dtr>=1,A77=HU_dtr,A77<=HU_T),MIN(S77*INDEX(HU_ssC,HU_age+A77-17)/(1-INDEX(HU_ssC,HU_age+A77-17)),INDEX(HU_ssCap,HU_age+A77-17))*T77,0) | V77: =S77+U77+IF(AND(HU_wdOn,A77=HU_wdYear),HU_wdIncome,0) | W77: =HU_ciProp*Q77+HU_tpdCut*L77+HU_disCut*O77 | X77: =IF(OR(A77<1,A77>HU_T),0,V77*(1-W77)) | Y77: =IF(OR(A77<1,A77>HU_T),0,IF(AND(HU_retExp>0,A77-1>=HU_dtr),HU_retExp,HU_exp0)*R77) | Z77: =-Y77-IF(AND(HU_wdOn,A77=HU_wdYear),HU_wdOut,0) | AA77: =IF(OR(A77<1,A77>HU_T),0,-HU_medCost*R77*F77-HU_tpdCost*R77*M77) | AB77: =IF(A77>HU_T,0,AB76*(1+interestRate)+X77+Z77+AA77) | AC77: =IF(A77>HU_T,0,HU_inv*EXP(HU_mu*A77)) | AD77: =IF(A77>HU_T,0,MAX(0,AC77+AB77)) | AE77: =IF(A77>HU_T,0,MAX(0,X77-Y77)) | AF77: =IF(AND($J$6,A77>=1,A77<=$Q$6-1),J77,0) | AG77: =IF(OR(AF77=0,$S$6=0),0,IF((AD77+$L$6)>$S$6/HU_alpha+$K$6,0.5*$S$6/HU_alpha,IF((AD77+$L$6)>=$K$6,((AD77+$L$6)-$K$6)-0.5*HU_alpha/$S$6*((AD77+$L$6)-$K$6)^2,IF((AD77+$L$6)>=$T$6,HU_beta*((AD77+$L$6)-$K$6),HU_beta*($T$6-$K$6))))) | AH77: =IF(OR(AF77=0,$S$6=0),0,IF((AD77+$L$6+$N$6)>$S$6/HU_alpha+$K$6,0.5*$S$6/HU_alpha,IF((AD77+$L$6+$N$6)>=$K$6,((AD77+$L$6+$N$6)-$K$6)-0.5*HU_alpha/$S$6*((AD77+$L$6+$N$6)-$K$6)^2,IF((AD77+$L$6+$N$6)>=$T$6,HU_beta*((AD77+$L$6+$N$6)-$K$6),HU_beta*($T$6-$K$6))))) | AI77: =IF(OR(AF77=0,$S$6=0),0,IF((AD77+$K$6)>$S$6/HU_alpha+$K$6,0.5*$S$6/HU_alpha,IF((AD77+$K$6)>=$K$6,((AD77+$K$6)-$K$6)-0.5*HU_alpha/$S$6*((AD77+$K$6)-$K$6)^2,IF((AD77+$K$6)>=$T$6,HU_beta*((AD77+$K$6)-$K$6),HU_beta*($T$6-$K$6))))) | AJ77: =IF(AND($J$7,A77>=1,A77<=$Q$7-1),J77,0) | AK77: =IF(OR(AJ77=0,$S$7=0),0,IF((AE77+$L$7)>$S$7/HU_alpha+$K$7,0.5*$S$7/HU_alpha,IF((AE77+$L$7)>=$K$7,((AE77+$L$7)-$K$7)-0.5*HU_alpha/$S$7*((AE77+$L$7)-$K$7)^2,IF((AE77+$L$7)>=$T$7,HU_beta*((AE77+$L$7)-$K$7),HU_beta*($T$7-$K$7))))) | AL77: =IF(OR(AJ77=0,$S$7=0),0,IF((AE77+$L$7+$N$7)>$S$7/HU_alpha+$K$7,0.5*$S$7/HU_alpha,IF((AE77+$L$7+$N$7)>=$K$7,((AE77+$L$7+$N$7)-$K$7)-0.5*HU_alpha/$S$7*((AE77+$L$7+$N$7)-$K$7)^2,IF((AE77+$L$7+$N$7)>=$T$7,HU_beta*((AE77+$L$7+$N$7)-$K$7),HU_beta*($T$7-$K$7))))) | AM77: =IF(OR(AJ77=0,$S$7=0),0,IF((AE77+$K$7)>$S$7/HU_alpha+$K$7,0.5*$S$7/HU_alpha,IF((AE77+$K$7)>=$K$7,((AE77+$K$7)-$K$7)-0.5*HU_alpha/$S$7*((AE77+$K$7)-$K$7)^2,IF((AE77+$K$7)>=$T$7,HU_beta*((AE77+$K$7)-$K$7),HU_beta*($T$7-$K$7))))) | AN77: =IF(AND($J$8,A77>=1,A77<=$Q$8-1),J77,0) | AO77: =IF(OR(AN77=0,$S$8=0),0,IF((AE77+$L$8)>$S$8/HU_alpha+$K$8,0.5*$S$8/HU_alpha,IF((AE77+$L$8)>=$K$8,((AE77+$L$8)-$K$8)-0.5*HU_alpha/$S$8*((AE77+$L$8)-$K$8)^2,IF((AE77+$L$8)>=$T$8,HU_beta*((AE77+$L$8)-$K$8),HU_beta*($T$8-$K$8))))) | AP77: =IF(OR(AN77=0,$S$8=0),0,IF((AE77+$L$8+$N$8)>$S$8/HU_alpha+$K$8,0.5*$S$8/HU_alpha,IF((AE77+$L$8+$N$8)>=$K$8,((AE77+$L$8+$N$8)-$K$8)-0.5*HU_alpha/$S$8*((AE77+$L$8+$N$8)-$K$8)^2,IF((AE77+$L$8+$N$8)>=$T$8,HU_beta*((AE77+$L$8+$N$8)-$K$8),HU_beta*($T$8-$K$8))))) | AQ77: =IF(OR(AN77=0,$S$8=0),0,IF((AE77+$K$8)>$S$8/HU_alpha+$K$8,0.5*$S$8/HU_alpha,IF((AE77+$K$8)>=$K$8,((AE77+$K$8)-$K$8)-0.5*HU_alpha/$S$8*((AE77+$K$8)-$K$8)^2,IF((AE77+$K$8)>=$T$8,HU_beta*((AE77+$K$8)-$K$8),HU_beta*($T$8-$K$8))))) | AR77: =IF(AND($J$9,A77>=1,A77<=$Q$9-1),J77,0) | AS77: =IF(OR(AR77=0,$S$9=0),0,IF((AE77+$L$9)>$S$9/HU_alpha+$K$9,0.5*$S$9/HU_alpha,IF((AE77+$L$9)>=$K$9,((AE77+$L$9)-$K$9)-0.5*HU_alpha/$S$9*((AE77+$L$9)-$K$9)^2,IF((AE77+$L$9)>=$T$9,HU_beta*((AE77+$L$9)-$K$9),HU_beta*($T$9-$K$9))))) | AT77: =IF(OR(AR77=0,$S$9=0),0,IF((AE77+$L$9+$N$9)>$S$9/HU_alpha+$K$9,0.5*$S$9/HU_alpha,IF((AE77+$L$9+$N$9)>=$K$9,((AE77+$L$9+$N$9)-$K$9)-0.5*HU_alpha/$S$9*((AE77+$L$9+$N$9)-$K$9)^2,IF((AE77+$L$9+$N$9)>=$T$9,HU_beta*((AE77+$L$9+$N$9)-$K$9),HU_beta*($T$9-$K$9))))) | AU77: =IF(OR(AR77=0,$S$9=0),0,IF((AE77+$K$9)>$S$9/HU_alpha+$K$9,0.5*$S$9/HU_alpha,IF((AE77+$K$9)>=$K$9,((AE77+$K$9)-$K$9)-0.5*HU_alpha/$S$9*((AE77+$K$9)-$K$9)^2,IF((AE77+$K$9)>=$T$9,HU_beta*((AE77+$K$9)-$K$9),HU_beta*($T$9-$K$9))))) | AV77: =IF(AND($J$10,A77=$Q$10),J77,0) | AW77: =IF(OR(AV77=0,$S$10=0),0,IF((AD77+$L$10)>$S$10/HU_alpha+$K$10,0.5*$S$10/HU_alpha,IF((AD77+$L$10)>=$K$10,((AD77+$L$10)-$K$10)-0.5*HU_alpha/$S$10*((AD77+$L$10)-$K$10)^2,IF((AD77+$L$10)>=$T$10,HU_beta*((AD77+$L$10)-$K$10),HU_beta*($T$10-$K$10))))) | AX77: =IF(OR(AV77=0,$S$10=0),0,IF((AD77+$L$10+$N$10)>$S$10/HU_alpha+$K$10,0.5*$S$10/HU_alpha,IF((AD77+$L$10+$N$10)>=$K$10,((AD77+$L$10+$N$10)-$K$10)-0.5*HU_alpha/$S$10*((AD77+$L$10+$N$10)-$K$10)^2,IF((AD77+$L$10+$N$10)>=$T$10,HU_beta*((AD77+$L$10+$N$10)-$K$10),HU_beta*($T$10-$K$10))))) | AY77: =IF(OR(AV77=0,$S$10=0),0,IF((AD77+$K$10)>$S$10/HU_alpha+$K$10,0.5*$S$10/HU_alpha,IF((AD77+$K$10)>=$K$10,((AD77+$K$10)-$K$10)-0.5*HU_alpha/$S$10*((AD77+$K$10)-$K$10)^2,IF((AD77+$K$10)>=$T$10,HU_beta*((AD77+$K$10)-$K$10),HU_beta*($T$10-$K$10))))) | AZ77: =IF(AND($J$11,A77=$Q$11),J77,0) | BA77: =IF(OR(AZ77=0,$S$11=0),0,IF((AE77+$L$11)>$S$11/HU_alpha+$K$11,0.5*$S$11/HU_alpha,IF((AE77+$L$11)>=$K$11,((AE77+$L$11)-$K$11)-0.5*HU_alpha/$S$11*((AE77+$L$11)-$K$11)^2,IF((AE77+$L$11)>=$T$11,HU_beta*((AE77+$L$11)-$K$11),HU_beta*($T$11-$K$11))))) | BB77: =IF(OR(AZ77=0,$S$11=0),0,IF((AE77+$L$11+$N$11)>$S$11/HU_alpha+$K$11,0.5*$S$11/HU_alpha,IF((AE77+$L$11+$N$11)>=$K$11,((AE77+$L$11+$N$11)-$K$11)-0.5*HU_alpha/$S$11*((AE77+$L$11+$N$11)-$K$11)^2,IF((AE77+$L$11+$N$11)>=$T$11,HU_beta*((AE77+$L$11+$N$11)-$K$11),HU_beta*($T$11-$K$11))))) | BC77: =IF(OR(AZ77=0,$S$11=0),0,IF((AE77+$K$11)>$S$11/HU_alpha+$K$11,0.5*$S$11/HU_alpha,IF((AE77+$K$11)>=$K$11,((AE77+$K$11)-$K$11)-0.5*HU_alpha/$S$11*((AE77+$K$11)-$K$11)^2,IF((AE77+$K$11)>=$T$11,HU_beta*((AE77+$K$11)-$K$11),HU_beta*($T$11-$K$11))))) | BD77: =IF(AND($J$12,A77=$Q$12),J77,0) | BE77: =IF(OR(BD77=0,$S$12=0),0,IF((AE77+$L$12)>$S$12/HU_alpha+$K$12,0.5*$S$12/HU_alpha,IF((AE77+$L$12)>=$K$12,((AE77+$L$12)-$K$12)-0.5*HU_alpha/$S$12*((AE77+$L$12)-$K$12)^2,IF((AE77+$L$12)>=$T$12,HU_beta*((AE77+$L$12)-$K$12),HU_beta*($T$12-$K$12))))) | BF77: =IF(OR(BD77=0,$S$12=0),0,IF((AE77+$L$12+$N$12)>$S$12/HU_alpha+$K$12,0.5*$S$12/HU_alpha,IF((AE77+$L$12+$N$12)>=$K$12,((AE77+$L$12+$N$12)-$K$12)-0.5*HU_alpha/$S$12*((AE77+$L$12+$N$12)-$K$12)^2,IF((AE77+$L$12+$N$12)>=$T$12,HU_beta*((AE77+$L$12+$N$12)-$K$12),HU_beta*($T$12-$K$12))))) | BG77: =IF(OR(BD77=0,$S$12=0),0,IF((AE77+$K$12)>$S$12/HU_alpha+$K$12,0.5*$S$12/HU_alpha,IF((AE77+$K$12)>=$K$12,((AE77+$K$12)-$K$12)-0.5*HU_alpha/$S$12*((AE77+$K$12)-$K$12)^2,IF((AE77+$K$12)>=$T$12,HU_beta*((AE77+$K$12)-$K$12),HU_beta*($T$12-$K$12))))) | BH77: =IF(AND($J$13,A77=$Q$13),J77,0) | BI77: =IF(OR(BH77=0,$S$13=0),0,IF((AE77+$L$13)>$S$13/HU_alpha+$K$13,0.5*$S$13/HU_alpha,IF((AE77+$L$13)>=$K$13,((AE77+$L$13)-$K$13)-0.5*HU_alpha/$S$13*((AE77+$L$13)-$K$13)^2,IF((AE77+$L$13)>=$T$13,HU_beta*((AE77+$L$13)-$K$13),HU_beta*($T$13-$K$13))))) | BJ77: =IF(OR(BH77=0,$S$13=0),0,IF((AE77+$L$13+$N$13)>$S$13/HU_alpha+$K$13,0.5*$S$13/HU_alpha,IF((AE77+$L$13+$N$13)>=$K$13,((AE77+$L$13+$N$13)-$K$13)-0.5*HU_alpha/$S$13*((AE77+$L$13+$N$13)-$K$13)^2,IF((AE77+$L$13+$N$13)>=$T$13,HU_beta*((AE77+$L$13+$N$13)-$K$13),HU_beta*($T$13-$K$13))))) | BK77: =IF(OR(BH77=0,$S$13=0),0,IF((AE77+$K$13)>$S$13/HU_alpha+$K$13,0.5*$S$13/HU_alpha,IF((AE77+$K$13)>=$K$13,((AE77+$K$13)-$K$13)-0.5*HU_alpha/$S$13*((AE77+$K$13)-$K$13)^2,IF((AE77+$K$13)>=$T$13,HU_beta*((AE77+$K$13)-$K$13),HU_beta*($T$13-$K$13)))))
