Workbook
Name inflationRate: Assumptions!$B$5
Name systemCurrency: Assumptions!$B$22
Name fxMode: Assumptions!$B$23
Name PPP_BASE_COUNTRY: Assumptions!$B$78
Name priceLevelOn: Assumptions!$B$24
Name LTC_COST: Assumptions!$B$25
Name LTC_START_AGE: Assumptions!$B$26
Name interestRate: Assumptions!$B$6
Name loanRate: Assumptions!$B$7
Name incomeGrowthRate: Assumptions!$B$8
Name investmentReturn: Assumptions!$B$9
Name assetReturn: Assumptions!$B$10
Name realReturn: Assumptions!$B$11
Name ageOfRetirement: Assumptions!$B$14
Name lifeExpectancyDefault: Assumptions!$B$15
Name currentYear: Assumptions!$B$16
Name endAge: Assumptions!$B$17
Name RET_LIFESTYLE_FRUGAL: Assumptions!$B$28
Name RET_LIFESTYLE_STRESSFREE: Assumptions!$B$29
Name RET_LIFESTYLE_ONLYTHEBEST: Assumptions!$B$30
Name INC_SUPPORT_MIN: Assumptions!$B$31
Name INC_SUPPORT_MAX: Assumptions!$B$32
Name INC_SUPPORT_PIVOT_AGE: Assumptions!$B$33
Name CRI_YEARS: Assumptions!$B$34
Name CRI_COST: Assumptions!$B$35
Name TPD_YEARS: Assumptions!$B$36
Name TPD_COST: Assumptions!$B$37
Name HOS_MONTHS: Assumptions!$B$38
Name EDU_COST: Assumptions!$B$39
Name EDU_TARGET_AGE: Assumptions!$B$40
Name SAV_TARGET_AGE: Assumptions!$B$18
Name PRP_TARGET_AGE: Assumptions!$B$19
Name SAV_INCOME_MULT: Assumptions!$B$41
Name PRP_INCOME_MULT: Assumptions!$B$42
Name PAC_YEARS: Assumptions!$B$43
Name PAC_COST: Assumptions!$B$44
Name LON_AGE: Assumptions!$B$45
Name spendShareBase: Assumptions!$B$47
Name spendSharePerDependant: Assumptions!$B$48
Name spendShareCap: Assumptions!$B$49
Name assetsSaveShare: Assumptions!$B$50
Name workStartAge: Assumptions!$B$51
Name liabilityRatio: Assumptions!$B$52
Name CASH_SAVINGS_SHARE: Assumptions!$B$53
Name INVESTMENTS_SHARE: Assumptions!$B$54
Name propertyLow: Assumptions!$B$55
Name propertyMid: Assumptions!$B$56
Name propertyHigh: Assumptions!$B$57
Name propertyIncomeLow: Assumptions!$B$58
Name propertyIncomeHigh: Assumptions!$B$59
Name PROPERTY_LTV: Assumptions!$B$60
Name lifePremiumRate: Assumptions!$B$61
Name lifeRoundUnit: Assumptions!$B$62
Name protectionPremiumRate: Assumptions!$B$65
Name FREE_BUDGET_SHARE: Assumptions!$B$66
Name lumpRoundStep: Assumptions!$B$67
Name monthlyRoundStep: Assumptions!$B$68
Name coverPremRoundStep: Assumptions!$B$69
Name coverSliderPremFloor: Assumptions!$B$70
Name annualBudget: Assumptions!$B$73

Sheet Overview
A1: FinPlan360 calculation components — live code, September 2026
A2: Yellow = type here. Orange = override (leave blank to keep the calculated value). Pick the persona on the Selected persona tab; every later tab follows that id. Gold = persona input, blue = LLM, orange = user / Money-page override, green = calculated, purple = assumptions. FX converts local amounts to USD. Validation applies USD-only rules. CPF is its own tab and is on only when the country switch says so (Singapore on, others off). HappiU and Scenario Visualizer are mapped here but scored / projected in HU and SV.
A3: Component | B3: Owner | C3: Reads | D3: Writes | E3: How it calculates (code) | F3: Code | G3: Tab | H3: HTTP / UI
A4: CPF | B4: GP pipeline (Singapore only) | C4: country, residency, age, incomeMonthly. Country switch on the CPF tab. | D4: employee CPF, take-home. 0 / income when CPF is off. | E4: On only when the country table (or orange override) is TRUE. Singapore Citizen/PR: employee CPF = floor(min(gross, OW_CEILING) × age-band rate). Foreigner → 0. Any other country → off, take-home = gross. src/cpf.py. | F4: src/cpf.py | G4: CPF | H4: Inside POST /v1/predict (take-home)
A5: People Like You | B5: GP pipeline | C5: age / DOB, occupation, gender, dependents, residency. CPF box for take-home. Does not read Assumptions. | D5: incomeMonthly, expenseMonthly, cash, investments, property, mortgage, one Life Protection policy, lifeExpectancy, isSmoker. | E5: LLM proposes gross monthly income and lifestyle flags. Income is clamped to the Singapore occupation band. Employee CPF = floor(min(gross, 8000) × age-band rate); 0 if Foreigner. expenseMonthly = round(take-home × min(67.5% + 5pp × dependents, 90%), 2). Liquid assets = max(0, surplus × 12 × 0.5 × (age − 21)), then cash 15% / investments 85%. If the model says they own a home: property from income band, mortgage = round(property × 55%). Assumed life cover = max(mortgage rounded up to S$100k, 5 × annual income if dependents > 0); premium = round(sum × 0.31%). PLU liabilities (= assets × 0.7) is not the mortgage. If this step fails, predict returns 503. | F5: src/pipeline/people_like_you.py, src/cpf.py, src/predict.py _apply_plu | G5: People Like You | H5: POST /v1/predict (first of three)
A6: Need Profiler | B6: GP pipeline | C6: Age, gender, dependents, occupation, smoker, income, expense, liquid assets, PLU liabilities, hospital/ward/lifestyle/sports, car/home/travel flags. Existing cover is hard-coded 0. No Assumptions. No LLM. | D6: needs[].enabled, needs[].priority, needs[].weightageScore. Four UNIFIED types on: two protection + two growth (retirement always one of the growth pair). | E6: Twelve AI labels are scored as Σ (factor_weight × option_weight), rounded to 2 dp, then min–max scaled 0–10. Income / expense / assets / liabilities convert local × FX to USD, then retuned USD bands. Car ownership, home ownership, travel, and existing life / CI cover have factor weights but no matching weight_options, so they add 0. select_unified_top ignores top_n (app.py still passes 4). If has_property, N_PRP replaces N_SAV in the second growth slot. priority = 5 if scaled score > 7 else 3. Personal accident / motor / travel / farewell are scored and dropped. Orange Enable? columns let you force a need on or off. | F6: src/pipeline/need_profiler.py, src/pipeline/prompts/Need_profiler.json, src/app.py top_n=4 | G6: Need Profiler | H6: POST /v1/predict
A7: Need Calculator | B7: GP pipeline | C7: Money attributes, enabled needs, goal-card sliders (lifestyle, retAge, targetYear, incomeReplaceMonthly, dependYears, bequest, monthlyContribution, tagged existing), Assumptions rates, Need parameters. | D7: For every UNIFIED type: needAmount, have, gap. Copies ageOfRetirement from the retirement row. | E7: realReturn = max(0, (1 + investmentReturn) / (1 + inflationRate) − 1). N_RET = annualSpend × (1+realReturn)^T × a(realReturn, n), n = min(LE,99) − retAge. N_INC = bequest + mortgage + ordinary annuity of annual spend over supportYears = min(max(10, 50 − age), 25). N_CRI / N_TPD = annuity-due of replacement income for 3 / 5 years + S$200,000. N_HOS = income × 6. N_EDU = 75,000 × (1 + inflation)^(targetYear − thisYear). N_SAV / N_PRP = stored needAmount if > 0, else 1× / 5× annual income. Protection have = policy sum (life is seeded by PLU). Wealth have = tagged investments only, grown at realReturn; cash is never allocated. Amounts are computed for all eight types even when a need is off. Orange Enable? and slider columns are the goal-card inputs. | F7: src/pipeline/need_calculator.py evaluate_session, src/pipeline/goal_math.py, src/hu_payload.py need_existing / apply_investment_pot | G7: Need Calculator | H7: POST /v1/predict and POST /v1/needs
A8: Goal cards | B8: GP UI | C8: Last calculator row (have, gap, stored sliders). | D8: Slider fields on the need; then POST /v1/needs (debounced). Does not recompute amounts in the browser. | E8: fillNeedEdit reads stored fields. patchNeedInputs writes lifestyle / retAge / targetYear / existing / … onto the session. Retirement stays on. The Score/Plan cap of four needs is UI-only (needEdit.capEnabledNeeds); this workbook lets you switch any need. | F8: frontend/src/lib/needEdit.ts | G8: Need Calculator (slider columns) | H8: Score and Plan screens
A9: Plan Calculator | B9: GP UI | C9: Enabled needs with gap > 0, take-home surplus, Assumptions inflationRate / investmentReturn / ageOfRetirement. | D9: planSum + planPrem (protection), planMth + planLump (wealth), investMth / investLump totals, plansOff. | E9: Suggested = enabled AND gap > 0. Default planSum = round(gap). planPrem = dummy indicative round((sum × 0.00078) / 10) × 10 (future: premium-quote API). Wealth horizon = years to retirement, or targetYear − this year. Lump / monthly caps = the amount that alone grows to the gap at realReturn (round up to S$1,000 / S$50). Default monthly = round((max(0, take-home − expense) × 12 − all protection premiums) × 50% / 12 / n_wealth / 50) × 50, then min(share, cap). Default lump = 0. Orange Include? columns are plansOff. | F9: frontend/src/lib/planProducts.ts, frontend/src/lib/local.ts seedProducts | G9: Plan Calculator | H9: Plan screen (not an HTTP engine)
A10: Budget Calculator | B10: GP UI | C10: take-home, expenseMonthly, investments, included planPrem / planMth / planLump. Not the economic rates. | D10: Nothing on the session. Plan-screen affordability only. | E10: available = max(0, takeHomeMonthly − expenseMonthly). free = round(available × 0.5). monthly = round(wealth contributions + protection premiums / 12). monthlyOver = monthly − free. lumpOver = wealth lumps − investments. Separate from the HappiU envelope (annualBudget 1500). | F10: planAfford in frontend/src/lib/planProducts.ts; availableBudget in types.ts | G10: Budget Calculator | H10: Plan screen
A11: FX | B11: Workbook only (not an HTTP engine) | C11: Personas currency + effective session money fields from People Like You. | D11: USD per 1 local, and each money field in USD. Validation reads these; engines stay local. | E11: Lookup ISO code in the FX rate table (USD per 1 local unit). USD = local × rate. Example: 5,000 SGD × 0.74 = 3,700 USD; 5,000 VND × 0.000038 = 0.19 USD. Edit the rate table on this tab. People Like You still stores local currency. | F11: Workbook FX tab (no src module — validation helper) | G11: FX | H11: Not in the live pipeline
A12: HappiU | B12: HU, via GP | C12: Whole session. Assumptions rates, CPF (inside HU), riskProfile, plan fields when set. Need amounts already stored. | D12: preHappiU, postHappiU. GP does not run the Monte Carlo. | E12: GP maps the session (src/hu_payload.py). Salary is gross incomeMonthly. N_HOS is renamed N_HSP. If retirement is off, GP still sends a synthetic N_RET = expense × 12 × (lifeExpectancy − retAge). Before a plan: benefitAmount = needAmount rounded to S$50,000, budget 200. With a plan: planSum / planPrem. This workbook does not score HappiU. | F12: src/hu_payload.py → POST /v1/score → HU | G12: Assumptions (envelope only) | H12: POST /v1/score
A13: Scenario Visualizer | B13: SV, via GP | C13: Session after Plan, all six rates, ageOfRetirement, endAge, stress chips. CPF inside SV. | D13: Year-by-year wealth path. GP does not run the year step. | E13: preWealth = session without the plan; postWealth = plus included planMth / planLump / planSum / planPrem. svNumSims defaults to 20. Investment contribution = max(0, take-home − expenseMonthly) once a year. This workbook does not project the path. | F13: src/sv_payload.py → POST /v1/project → SV | G13: Assumptions (stress catalogue) | H13: POST /v1/project
A14: Journey order (one session, each step adds attributes)
A15: Shared inputs (Assumptions · CPF · Need parameters · Risk · Stress events) → About you → CPF (on for Singapore only) → People Like You (or the customer edits the same money fields) → Need Profiler → Need Calculator → HappiU (no plan) → Plan Calculator → Budget Calculator → Scenario Visualizer → HappiU (with plan). Workbook-only: FX (local → USD) then Validation (USD rules).
A17: UNIFIED types in code order: N_INC, N_CRI, N_TPD, N_HOS (protection) · N_RET, N_EDU, N_SAV, N_PRP (wealth). Goal-card sliders live on the Need Calculator tab. Discrepancies lists remaining multi-country / multi-currency work.

Sheet Dictionary
A1: Dictionary — needs (N_), risks (R_) and parameter prefixes
A2: N_xxx = need. R_xxx = the risk or event that triggers it (N_CRI ↔ R_CRI; N_INC ↔ R_DEA). · Parameters are named <PREFIX>_<WHAT> in upper case, with the need's 3-letter prefix (CRI_COST, HOS_MONTHS). · Protection · calculator and Wealth · calculator needs get amount / have / gap. Coverage · parked needs are scored only. · One name per need in every component (e.g. TPD, never Disability or PTD). Where an engine still differs (HU: N_HSP, PTD) it is listed as open. · Code (src/, frontend/) still uses the old parameter names and 8 needs until the code follows V0-16.
A4: NEEDS
A5: Code | B5: Risk | C5: Prefix | D5: Category | E5: App label | F5: Profiler label (key) | G5: HappiU | H5: Scenario Visualizer | I5: Calculator | J5: Parameters | K5: Status
A6: N_INC | B6: R_DEA | C6: INC | D6: Protection · calculator | E6: Income & family protection | F6: Life Protection (life_protection) | G6: N_INC | H6: premium | I6: bequest + mortgage + PV of annual spend over support years | J6: INC_SUPPORT_MIN / MAX / PIVOT_AGE | K6: Live
A7: N_CRI | B7: R_CRI | C7: CRI | D7: Protection · calculator | E7: Critical illness | F7: Critical Illness (critical_illness) | G7: N_CRI | H7: premium | I7: annuity-due of income for CRI_YEARS + CRI_COST | J7: CRI_YEARS, CRI_COST | K7: Live
A8: N_TPD | B8: R_TPD | C8: TPD | D8: Protection · calculator | E8: Total & permanent disability (TPD) | F8: TPD (JSON key: disability) | G8: N_TPD (HU engine internals still say PTD: rename there) | H8: premium | I8: annuity-due of income for TPD_YEARS + TPD_COST | J8: TPD_YEARS, TPD_COST | K8: Live
A9: N_HOS | B9: R_HOS | C9: HOS | D9: Protection · calculator | E9: Hospitalisation | F9: Hospitalization (hospitalization) | G9: N_HSP: GP renames N_HOS → N_HSP in hu_payload.py because the HU engine only knows N_HSP | H9: premium | I9: incomeMonthly × HOS_MONTHS | J9: HOS_MONTHS | K9: Live. Open: one code (N_HOS) in GP and HU
A10: N_PAC | B10: R_PAC | C10: PAC | D10: Protection · calculator | E10: Personal accident (new) | F10: Personal Accident (personal_accident) | G10: N_PAC (HU engine supports it; GP does not send it yet) | H10: premium | I10: annuity-due of income for PAC_YEARS + PAC_COST | J10: PAC_YEARS, PAC_COST | K10: Agreed V0-18 (Excel). Code and HappiU payload to follow
A11: N_ADB | B11: R_ADB | C11: ADB | D11: Protection · candidate | E11: Accidental death | F11: none (no profiler label) | G11: N_ADB (HU engine supports it, death-type goal like N_INC) | H11: — | I11: not defined yet (proposal: lump like N_INC, paid only on accidental death) | J11: ADB_* (to define) | K11: Added V0-17 to the dictionary. No calculator, not scored
A12: N_LTC | B12: R_LTC | C12: LTC | D12: Protection · calculator | E12: Long-term care | F12: none (no profiler label) | G12: not sent (HU engine has no LTC) | H12: premium | I12: annuity-due of LTC_COST over care years (LTC start age → life expectancy) | J12: LTC_COST, LTC_START_AGE (front-end input) | K12: New V0-19. Off unless the customer switches it on
A13: N_RET | B13: R_LON | C13: RET | D13: Wealth · calculator | E13: Private retirement | F13: Retirement (retirement) | G13: N_RET | H13: RET pot | I13: annual spend × lifestyle, grown to retirement, × annuity over years in retirement | J13: RET_LIFESTYLE_FRUGAL / STRESSFREE / ONLYTHEBEST; LON_AGE (R_LON) | K13: Live. R_LON stress: need re-sized to LON_AGE 99
A14: N_EDU | B14: — | C14: EDU | D14: Wealth · calculator | E14: Child's university education | F14: Education (education) | G14: N_EDU | H14: goal pot | I14: EDU_COST grown at inflation to target year | J14: EDU_COST, EDU_TARGET_AGE (50) | K14: Live
A15: N_SAV | B15: — | C15: SAV | D15: Wealth · calculator | E15: Savings goal | F15: General Savings (general_savings) | G15: N_SAV | H15: goal pot | I15: stored amount, else SAV_INCOME_MULT × annual income | J15: SAV_INCOME_MULT, SAV_TARGET_AGE (40) | K15: Live. No longer swapped with N_PRP
A16: N_PRP | B16: — | C16: PRP | D16: Wealth · calculator | E16: Home purchase | F16: none (no home-purchase label) | G16: N_PRP | H16: goal pot | I16: stored amount, else PRP_INCOME_MULT × annual income | J16: PRP_INCOME_MULT, PRP_TARGET_AGE (33) | K16: Separated from Home Protection. Off unless the customer switches it on
... A20: — | B20: — | C20: — | D20: Dropped | E20: Farewell | F20: Farewell (farewell) | G20: funeral lump dropped | H20: — | I20: — | J20: funeralLump removed | K20: Dropped V0-16
A22: RISKS AND STRESS EVENTS
A23: Code | B23: Was (id) | C23: Label | D23: Need | E23: Kind
A24: R_DEA | B24: death | C24: Death | D24: N_INC | E24: Need risk
A25: R_CRI | B25: ci | C25: Critical illness | D25: N_CRI | E25: Need risk
A26: R_TPD | B26: tpd | C26: Total & permanent disability | D26: N_TPD | E26: Need risk
A27: R_HOS | B27: hosp | C27: Hospitalisation | D27: N_HOS | E27: Need risk
A28: R_PAC | B28: pa | C28: Personal accident | D28: N_PAC | E28: Need risk
A29: R_ADB | B29: — | C29: Accidental death | D29: N_ADB | E29: Need risk (no stress event yet)
A30: R_LON | B30: — (new V0-18) | C30: Longevity: live until LON_AGE (99) | D30: N_RET | E30: Need risk · stress event
A31: R_LTC | B31: care | C31: Long-term care | D31: N_LTC | E31: Need risk · stress event
A32: R_MKT | B32: crash | C32: Market crash | D32: — | E32: Market event
A33: R_CCY | B33: ccy | C33: Currency shock | D33: — | E33: Market event
A34: R_INF | B34: infl | C34: Inflation shock | D34: — | E34: Market event
... A38: R_BAB | B38: baby | C38: Newborn | D38: — | E38: Life event
A40: PARAMETER NAMES (Assumptions named cells)
A41: New name | B41: Was | C41: Need
A42: INC_SUPPORT_MIN | B42: lifeSupportMin | C42: N_INC
A43: INC_SUPPORT_MAX | B43: lifeSupportMax | C43: N_INC
A44: INC_SUPPORT_PIVOT_AGE | B44: lifeSupportPivotAge | C44: N_INC
A45: CRI_YEARS | B45: CI_YEARS | C45: N_CRI
A46: CRI_COST | B46: CI_COST | C46: N_CRI
A47: TPD_YEARS | B47: TPD_YEARS | C47: N_TPD
A48: TPD_COST | B48: TPD_COST | C48: N_TPD
A49: HOS_MONTHS | B49: HOSP_MONTHS | C49: N_HOS
A50: PAC_YEARS | B50: (new) | C50: N_PAC
A51: PAC_COST | B51: (new) | C51: N_PAC
A52: LON_AGE | B52: (new) | C52: N_RET · R_LON
... A67: (removed) | B67: funeralLump | C67: Farewell (dropped)

Sheet Selected persona
A1: Selected persona — pick one id here. Every calculation tab follows this cell.
A2: Selected persona | B2: P01 | C2: =IFERROR(INDEX(Personas!B$3:B$52,MATCH($B$2,Personas!$A$3:$A$52,0)),"") | D2: This is the only picker. CPF, People Like You, Need Profiler, Need Calculator, Plan, Budget, FX, and Validation follow this cell. | F2: A · INPUT DATA
A3: Attribute | B3: Value | C3: Kind | D3: Source / formula | F3: B · LLM PREDICTED DATA
A4: A · ABOUT YOU — from the Personas row (edit there) | F4: C · DETERMINISTICALLY CALCULATED
A5: name | B5: =IFERROR(INDEX(Personas!B$3:B$52,MATCH($B$2,Personas!$A$3:$A$52,0)),"") | C5: A · input | D5: Personas B. | F5: D · ASSUMPTIONS / SHARED DATA
A6: age | B6: =IFERROR(INDEX(Personas!C$3:C$52,MATCH($B$2,Personas!$A$3:$A$52,0)),"") | C6: A · input | D6: Personas C. | F6: E · USER / FRONTEND OVERRIDE
A7: gender | B7: =IFERROR(INDEX(Personas!D$3:D$52,MATCH($B$2,Personas!$A$3:$A$52,0)),"") | C7: A · input | D7: Personas D.
A8: residency | B8: =IFERROR(INDEX(Personas!E$3:E$52,MATCH($B$2,Personas!$A$3:$A$52,0)),"") | C8: A · input | D8: Personas E.
A9: country | B9: =IFERROR(INDEX(Personas!F$3:F$52,MATCH($B$2,Personas!$A$3:$A$52,0)),"") | C9: A · input | D9: Personas F. CPF on/off uses this.
A10: occupation | B10: =IFERROR(INDEX(Personas!G$3:G$52,MATCH($B$2,Personas!$A$3:$A$52,0)),"") | C10: A · input | D10: Personas G. Income clamp band.
A11: dependents | B11: =IFERROR(INDEX(Personas!H$3:H$52,MATCH($B$2,Personas!$A$3:$A$52,0)),"") | C11: A · input | D11: Personas H.
A12: maritalStatus | B12: =IFERROR(INDEX(Personas!I$3:I$52,MATCH($B$2,Personas!$A$3:$A$52,0)),"") | C12: A · input | D12: Personas I. Blank = infer on People Like You.
A13: what this row varies | B13: =IFERROR(INDEX(Personas!AD$3:AD$52,MATCH($B$2,Personas!$A$3:$A$52,0)),"") | C13: A · input | D13: Personas AD. Why this persona exists.
A15: B · LLM PREDICTED — from the Personas row (edit there)
A16: incomeMonthly (LLM) | B16: =IFERROR(INDEX(Personas!J$3:J$52,MATCH($B$2,Personas!$A$3:$A$52,0)),"") | C16: B · LLM predicted | D16: Personas J. Before clamp and CPF.
A17: currency | B17: =IFERROR(INDEX(Personas!K$3:K$52,MATCH($B$2,Personas!$A$3:$A$52,0)),"") | C17: B · LLM predicted | D17: Personas K. FX looks this up.
A18: risk ability | B18: =IFERROR(INDEX(Personas!L$3:L$52,MATCH($B$2,Personas!$A$3:$A$52,0)),"") | C18: B · LLM predicted | D18: Personas L.
A19: price sensitivity | B19: =IFERROR(INDEX(Personas!M$3:M$52,MATCH($B$2,Personas!$A$3:$A$52,0)),"") | C19: B · LLM predicted | D19: Personas M.
A20: owns property | B20: =IFERROR(INDEX(Personas!N$3:N$52,MATCH($B$2,Personas!$A$3:$A$52,0)),"") | C20: B · LLM predicted | D20: Personas N.
A21: owns car | B21: =IFERROR(INDEX(Personas!O$3:O$52,MATCH($B$2,Personas!$A$3:$A$52,0)),"") | C21: B · LLM predicted | D21: Personas O.
A22: is smoker | B22: =IFERROR(INDEX(Personas!U$3:U$52,MATCH($B$2,Personas!$A$3:$A$52,0)),"") | C22: B · LLM predicted | D22: Personas U.
A23: life expectancy | B23: =IFERROR(INDEX(Personas!V$3:V$52,MATCH($B$2,Personas!$A$3:$A$52,0)),"") | C23: B · LLM predicted | D23: Personas V.
A24: retirement lifestyle | B24: =IFERROR(INDEX(Personas!T$3:T$52,MATCH($B$2,Personas!$A$3:$A$52,0)),"") | C24: B · LLM predicted | D24: Personas T.
A26: C · EFFECTIVE SESSION — after CPF, People Like You, and Money-page overrides
A27: CPF on | B27: =CPF_on | C27: C · calculated | D27: From the CPF tab.
A28: incomeMonthly | B28: =PLU_incomeMonthly | C28: C · calculated | D28: Clamped LLM income.
A29: take-home | B29: =PLU_takeHome | C29: C · calculated | D29: Gross minus employee CPF when CPF is on.
A30: expenseMonthly | B30: =PLU_expenseMonthly | C30: C · calculated | D30: Override if Personas W is set.
A31: cash | B31: =PLU_cash | C31: C · calculated | D31: Cash & Savings.
A32: investments | B32: =PLU_investments | C32: C · calculated
A33: property | B33: =PLU_property | C33: C · calculated | D33: 0 if renter.
A34: mortgage | B34: =PLU_mortgage | C34: C · calculated
A35: PLU liabilities | B35: =PLU_liabilities | C35: C · calculated | D35: Not the mortgage.
A36: life sum assured | B36: =PLU_lifeSum | C36: C · calculated

Sheet Personas
A1: A · INPUT DATA — About you (typed / session) | J1: B · LLM PREDICTED DATA — 13 fields from people_like_you_all_fields.json | W1: E · USER / FRONTEND OVERRIDE — Money page (blank = keep People Like You calculated) | AD1: notes | AF1: A · INPUT DATA
A2: id | B2: name | C2: age | D2: gender | E2: residency | F2: country | G2: occupation | H2: dependents | I2: maritalStatus (blank = infer) | J2: income | K2: currency | L2: risk_ability | M2: price_sensitivity | N2: property | O2: car | P2: ward_type | Q2: hospitalization_type | R2: travelling | S2: sports | T2: retirement_lifestyle | U2: is_smoker | V2: life_expectancy | W2: expenseMonthly | X2: cash (Cash & Savings) | Y2: investments | Z2: property value | AA2: mortgage (loans) | AB2: PLU liabilities | AC2: life sum assured | AD2: What this row varies | AF2: B · LLM PREDICTED DATA
A3: P01 | B3: Aisha Rahman | C3: 22 | D3: Female | E3: Citizen | F3: Singapore | G3: Nurse | H3: 0 | J3: 4200 | K3: SGD | L3: conservative | M3: high | N3: FALSE | O3: FALSE | P3: Ward | Q3: Public | R3: FALSE | S3: Yoga | T3: Basic | U3: FALSE | V3: 86 | AD3: Nurse; age 22; Citizen; 0 dep; rent; non-smoker | AF3: C · DETERMINISTICALLY CALCULATED
A4: P02 | B4: Wei Ling Tan | C4: 27 | D4: Male | E4: PR | F4: Singapore | G4: Teacher | H4: 0 | J4: 6020 | K4: SGD | L4: moderate | M4: medium | N4: FALSE | O4: TRUE | P4: Double | Q4: Private | R4: TRUE | S4: Running | T4: Comfortable | U4: FALSE | V4: 81 | AD4: Teacher; age 27; PR; 0 dep; rent; non-smoker | AF4: D · ASSUMPTIONS / SHARED DATA
A5: P03 | B5: Daniel Koh | C5: 34 | D5: Female | E5: Citizen | F5: Singapore | G5: Accountant | H5: 1 | J5: 7140 | K5: SGD | L5: moderate | M5: medium | N5: TRUE | O5: TRUE | P5: Single | Q5: Private | R5: TRUE | S5: Swimming | T5: Comfortable | U5: FALSE | V5: 88 | AD5: Accountant; age 34; Citizen; 1 dep; home; non-smoker | AF5: E · USER / FRONTEND OVERRIDE
A6: P04 | B6: Priya Nair | C6: 41 | D6: Male | E6: Citizen | F6: Singapore | G6: Marketing Manager | H6: 2 | J6: 4550 | K6: SGD | L6: conservative | M6: high | N6: TRUE | O6: TRUE | P6: Ward | Q6: Public | R6: FALSE | S6: I dont do sports | T6: frugal | U6: TRUE | V6: 78 | AD6: Marketing Manager; age 41; Citizen; 2 dep; home; smoker
A7: P05 | B7: Marcus Lim | C7: 47 | D7: Female | E7: Foreigner | F7: Singapore | G7: Software Engineer | H7: 2 | J7: 5000 | K7: SGD | L7: aggressive | M7: high | N7: TRUE | O7: FALSE | P7: A | Q7: Private | R7: TRUE | S7: Adventurous Sports | T7: only the best | U7: FALSE | V7: 90 | AD7: Software Engineer; age 47; Foreigner; 2 dep; home; non-smoker
A8: P06 | B8: Hannah Wong | C8: 32 | D8: Male | E8: Citizen | F8: Singapore | G8: Doctor | H8: 1 | J8: 13910 | K8: SGD | L8: moderate | M8: medium | N8: TRUE | O8: TRUE | P8: B | Q8: Public | R8: TRUE | S8: Life style activities | T8: stress-free | U8: FALSE | V8: 83 | AD8: Doctor; age 32; Citizen; 1 dep; home; non-smoker
A9: P07 | B9: Julian Chee | C9: 54 | D9: Female | E9: PR | F9: Singapore | G9: Investment Banker | H9: 0 | J9: 5525 | K9: SGD | L9: conservative | M9: high | N9: TRUE | O9: TRUE | P9: Single | Q9: Private | R9: FALSE | S9: Walking | T9: Basic | U9: FALSE | V9: 89 | AD9: Investment Banker; age 54; PR; 0 dep; home; non-smoker
A10: P08 | B10: Mei Fen Ong | C10: 60 | D10: Male | E10: Citizen | F10: Singapore | G10: CEO | H10: 3 | J10: 5975 | K10: SGD | L10: conservative | M10: high | N10: TRUE | O10: TRUE | P10: Ward | Q10: Public | R10: FALSE | S10: I dont do sports | T10: frugal | U10: TRUE | V10: 76 | AD10: CEO; age 60; Citizen; 3 dep; home; smoker
A11: P09 | B11: Hafiz Abdullah | C11: 25 | D11: Female | E11: Citizen | F11: Singapore | G11: Baker | H11: 0 | J11: 3350 | K11: SGD | L11: moderate | M11: high | N11: FALSE | O11: FALSE | P11: Ward | Q11: Public | R11: TRUE | S11: HIIT | T11: Comfortable | U11: FALSE | V11: 87 | AD11: Baker; age 25; Citizen; 0 dep; rent; non-smoker
A12: P10 | B12: Siti Hassan | C12: 37 | D12: Male | E12: Foreigner | F12: Singapore | G12: Driver | H12: 2 | J12: 4250 | K12: SGD | L12: aggressive | M12: high | N12: FALSE | O12: TRUE | P12: Double | Q12: Private | R12: TRUE | S12: Football | T12: Luxurious | U12: FALSE | V12: 80 | AD12: Driver; age 37; Foreigner; 2 dep; rent; non-smoker
A13: P11 | B13: Aisha Ng | C13: 51 | D13: Female | E13: Citizen | F13: Singapore | G13: Nurse | H13: 1 | J13: 7140 | K13: SGD | L13: moderate | M13: medium | N13: TRUE | O13: TRUE | P13: A | Q13: Private | R13: TRUE | S13: Pilates | T13: only the best | U13: FALSE | V13: 91 | AD13: Nurse; age 51; Citizen; 1 dep; home; non-smoker
A14: P12 | B14: Wei Ling Chua | C14: 66 | D14: Male | E14: Citizen | F14: Singapore | G14: Teacher | H14: 0 | J14: 9800 | K14: SGD | L14: conservative | M14: medium | N14: TRUE | O14: FALSE | P14: Ward | Q14: Public | R14: FALSE | S14: I dont do sports | T14: Basic | U14: FALSE | V14: 85 | AD14: Teacher; age 66; Citizen; 0 dep; home; non-smoker
A15: P13 | B15: Daniel Lee | C15: 30 | D15: Female | E15: PR | F15: Singapore | G15: Accountant | H15: 1 | J15: 6580 | K15: SGD | L15: moderate | M15: medium | N15: FALSE | O15: TRUE | P15: Double | Q15: Public | R15: FALSE | S15: Running | T15: Comfortable | U15: TRUE | V15: 79 | AD15: Accountant; age 30; PR; 1 dep; rent; smoker
A16: P14 | B16: Priya Goh | C16: 44 | D16: Male | E16: Citizen | F16: Singapore | G16: Marketing Manager | H16: 4 | J16: 4775 | K16: SGD | L16: aggressive | M16: high | N16: TRUE | O16: TRUE | P16: Single | Q16: Private | R16: TRUE | S16: Golf | T16: Luxurious | U16: FALSE | V16: 84 | AD16: Marketing Manager; age 44; Citizen; 4 dep; home; non-smoker
A17: P15 | B17: Marcus Teo | C17: 57 | D17: Female | E17: Citizen | F17: Singapore | G17: Software Engineer | H17: 2 | J17: 5750 | K17: SGD | L17: conservative | M17: high | N17: TRUE | O17: TRUE | P17: B | Q17: Private | R17: FALSE | S17: Life style activities | T17: stress-free | U17: FALSE | V17: 92 | AD17: Software Engineer; age 57; Citizen; 2 dep; home; non-smoker
... A52: P50 | B52: Siti Lim | C52: 47 | D52: Female | E52: Foreigner | F52: Singapore | G52: Driver | H52: 2 | J52: 5000 | K52: SGD | L52: aggressive | M52: high | N52: TRUE | O52: FALSE | P52: A | Q52: Private | R52: TRUE | S52: Adventurous Sports | T52: only the best | U52: FALSE | V52: 90 | AD52: Driver; age 47; Foreigner; 2 dep; home; non-smoker

Sheet CPF
A1: CPF — social-security plug-in. In: gross, age, residency, country. Out: employee contribution, take-home. Runs in user currency.
A2: Selected persona | B2: =SelectedPersona | C2: =IFERROR(INDEX(Personas!B$3:B$52,MATCH($B$2,Personas!$A$3:$A$52,0)),"") | D2: Follows the dropdown on the Selected persona tab. | F2: A · INPUT DATA
A3: Attribute | B3: Value | C3: Kind | D3: Source / formula | F3: B · LLM PREDICTED DATA
A4: A · INPUT DATA — from the selected Personas row | F4: C · DETERMINISTICALLY CALCULATED | I4: D · MODULE PER COUNTRY — TRUE = SG-CPF module; FALSE = default module (no contribution)
A5: country | B5: =IFERROR(INDEX(Personas!F$3:F$52,MATCH($B$2,Personas!$A$3:$A$52,0)),"") | C5: A · input | D5: Personas F. Looks up the country switch. | F5: D · ASSUMPTIONS / SHARED DATA | I5: country | J5: CPF on? | K5: note
A6: residency | B6: =IFERROR(INDEX(Personas!E$3:E$52,MATCH($B$2,Personas!$A$3:$A$52,0)),"") | C6: A · input | D6: Personas E. When CPF is on, Foreigner → rate 0. | F6: E · USER / FRONTEND OVERRIDE | I6: Singapore | J6: TRUE | K6: src/cpf.py applies. Citizen / PR contribute; Foreigner rate 0.
A7: age | B7: =IFERROR(INDEX(Personas!C$3:C$52,MATCH($B$2,Personas!$A$3:$A$52,0)),"") | C7: A · input | D7: Personas C. Age-band rate when CPF is on. | I7: Vietnam | J7: FALSE | K7: No CPF. Take-home = gross.
A8: incomeMonthly | B8: =IFERROR(INDEX(Personas!J$3:J$52,MATCH($B$2,Personas!$A$3:$A$52,0)),"") | C8: A · input | D8: Personas J (LLM or user overwrite). | I8: Malaysia | J8: FALSE | K8: No CPF. Take-home = gross.
I9: Thailand | J9: FALSE | K9: No CPF. Take-home = gross.
A10: D · ASSUMPTIONS — src/cpf.py (used only when CPF is on) | I10: Philippines | J10: FALSE | K10: No CPF. Take-home = gross.
A11: OW_CEILING | B11: 8000 | C11: D · assumption / shared | D11: Ordinary-wage ceiling. Employee CPF is on min(gross, this). | I11: Australia | J11: FALSE | K11: No CPF. Take-home = gross.
A12: cpfRate_to55 | B12: 0.2 | C12: D · assumption / shared | D12: Employee rate age ≤ 55. | I12: Germany | J12: FALSE | K12: No CPF. Take-home = gross.
A13: cpfRate_to60 | B13: 0.18 | C13: D · assumption / shared | D13: Age 56–60. | I13: Hong Kong | J13: FALSE | K13: No CPF. Take-home = gross.
A14: cpfRate_to65 | B14: 0.125 | C14: D · assumption / shared | D14: Age 61–65. | I14: United States | J14: FALSE | K14: No CPF. Take-home = gross.
A15: cpfRate_to70 | B15: 0.075 | C15: D · assumption / shared | D15: Age 66–70.
A16: cpfRate_over70 | B16: 0.05 | C16: D · assumption / shared | D16: Age > 70.
A18: E · OVERRIDE — blank = country switch. TRUE / FALSE forces CPF on or off
A19: CPF on? (override) | C19: E · user / frontend override | D19: TRUE / FALSE / blank. Blank uses the country table.
A21: C · DETERMINISTICALLY CALCULATED — src/cpf.py when on; identity when off
A22: CPF on (effective) | B22: =IF(B19="",IFERROR(VLOOKUP(B5,CpfCountrySwitch,2,FALSE),FALSE),B19) | C22: C · calculated | D22: Country table, unless the orange override is set.
A23: module used | B23: =IF(B22=TRUE,"SG-CPF (src/cpf.py)","default: no contribution, take-home = gross") | C23: C · calculated | D23: Plug-in interface. Other countries get their own module later; the rest of the model does not change.
A24: Singapore age-band rate | B24: =IF(LOWER(B6)="foreigner",0,IF(B7<=55,cpfRate_to55,IF(B7<=60,cpfRate_to60,IF(B7<=65,cpfRate_to65,IF(B7<=70,cpfRate_to70,cpfRate_over70))))) | C24: C · calculated | D24: employee_cpf_rate. Ignored when CPF is off.
A25: CPF rate used | B25: =IF(B22=TRUE,B24,0) | C25: C · calculated | D25: 0 when CPF is off for this country.
A26: employee CPF | B26: =IF(OR(B22<>TRUE,B8<=0,B25<=0),0,FLOOR(MIN(B8,OW_CEILING)*B25,1)) | C26: C · calculated | D26: floor(min(gross, ceiling) × rate). 0 if CPF off.
A27: take-home | B27: =IF(B8<=0,0,ROUND(MAX(0,B8-B26),2)) | C27: C · calculated | D27: Gross minus employee CPF. Equals income when CPF is off.

Sheet People Like You
A1: People Like You — selected persona. Spend, assets, home, life cover. Take-home comes from the CPF tab.
A2: Selected persona | B2: =SelectedPersona | C2: =IFERROR(INDEX(Personas!B$3:B$52,MATCH($B$2,Personas!$A$3:$A$52,0)),"") | D2: Follows the dropdown on the Selected persona tab. | F2: A · INPUT DATA
A3: Attribute | B3: Value | C3: Kind | D3: Source / formula | F3: B · LLM PREDICTED DATA
A4: A · INPUT DATA — About you from the selected Personas row | F4: C · DETERMINISTICALLY CALCULATED
A5: age | B5: =IFERROR(INDEX(Personas!C$3:C$52,MATCH($B$2,Personas!$A$3:$A$52,0)),"") | C5: A · input | D5: Personas C. Working years = age − 21. | F5: D · ASSUMPTIONS / SHARED DATA
A6: gender | B6: =IFERROR(INDEX(Personas!D$3:D$52,MATCH($B$2,Personas!$A$3:$A$52,0)),"") | C6: A · input | D6: Personas D. Not used by this component. | F6: E · USER / FRONTEND OVERRIDE
A7: residency | B7: =IFERROR(INDEX(Personas!E$3:E$52,MATCH($B$2,Personas!$A$3:$A$52,0)),"") | C7: A · input | D7: Personas E. Passed to the CPF tab (Foreigner → 0 when CPF is on).
A8: country | B8: =IFERROR(INDEX(Personas!F$3:F$52,MATCH($B$2,Personas!$A$3:$A$52,0)),"") | C8: A · input | D8: Personas F. CPF on/off is decided on the CPF tab.
A9: occupation | B9: =IFERROR(INDEX(Personas!G$3:G$52,MATCH($B$2,Personas!$A$3:$A$52,0)),"") | C9: A · input | D9: Personas G. Looks up income_anchors.json Singapore band.
A10: dependents | B10: =IFERROR(INDEX(Personas!H$3:H$52,MATCH($B$2,Personas!$A$3:$A$52,0)),"") | C10: A · input | D10: Personas H. Spend-share +5 pp each; 5× income life cover if > 0.
A11: maritalStatus (typed) | B11: =IFERROR(INDEX(Personas!I$3:I$52,MATCH($B$2,Personas!$A$3:$A$52,0)),"") | C11: A · input | D11: Personas I. Blank → infer below.
A13: B · LLM PREDICTED DATA — fields this component reads from Personas
A14: income (LLM gross monthly) | B14: =IFERROR(INDEX(Personas!J$3:J$52,MATCH($B$2,Personas!$A$3:$A$52,0)),"") | C14: B · LLM predicted | D14: Personas J. people_like_you_all_fields.json income.
A15: currency | B15: =IFERROR(INDEX(Personas!K$3:K$52,MATCH($B$2,Personas!$A$3:$A$52,0)),"") | C15: B · LLM predicted | D15: Personas K. SGD in this workbook.
A16: property (owns home) | B16: =IFERROR(INDEX(Personas!N$3:N$52,MATCH($B$2,Personas!$A$3:$A$52,0)),"") | C16: B · LLM predicted | D16: Personas N. seed_property_value if TRUE.
A17: life_expectancy (raw) | B17: =IFERROR(INDEX(Personas!V$3:V$52,MATCH($B$2,Personas!$A$3:$A$52,0)),"") | C17: B · LLM predicted | D17: Personas V. Capped at 99. Missing or ≤ 0 → 85.
A19: D · ASSUMPTIONS / SHARED DATA — named cells on Assumptions (CPF is on the CPF tab)
A20: spendShareBase | B20: =spendShareBase | C20: D · assumption / shared | D20: 67.5% of take-home.
A21: spendSharePerDependant | B21: =spendSharePerDependant | C21: D · assumption / shared | D21: +5 pp per dependant.
A22: spendShareCap | B22: =spendShareCap | C22: D · assumption / shared | D22: 90% cap.
A23: assetsSaveShare | B23: =assetsSaveShare | C23: D · assumption / shared | D23: 50% of annual surplus saved.
A24: workStartAge | B24: =workStartAge | C24: D · assumption / shared | D24: 21. Working years = max(0, age − 21).
A25: CASH_SAVINGS_SHARE | B25: =CASH_SAVINGS_SHARE | C25: D · assumption / shared | D25: src/predict.py 15% cash.
A26: INVESTMENTS_SHARE | B26: =INVESTMENTS_SHARE | C26: D · assumption / shared | D26: src/predict.py 85%.
A27: liabilityRatio | B27: =liabilityRatio | C27: D · assumption / shared | D27: PLU liabilities = liquid assets × 0.7 (not the mortgage).
A28: propertyLow (USD) | B28: =propertyLow | C28: D · assumption / shared | D28: income < propertyIncomeLow (USD).
A29: propertyMid (USD) | B29: =propertyMid | C29: D · assumption / shared | D29: income between the two USD bands.
A30: propertyHigh (USD) | B30: =propertyHigh | C30: D · assumption / shared | D30: income > propertyIncomeHigh (USD).
A31: propertyIncomeLow (USD) | B31: =propertyIncomeLow | C31: D · assumption / shared | D31: Monthly gross income in USD.
A32: propertyIncomeHigh (USD) | B32: =propertyIncomeHigh | C32: D · assumption / shared | D32: Monthly gross income in USD.
A33: PROPERTY_LTV | B33: =PROPERTY_LTV | C33: D · assumption / shared | D33: Mortgage = round(property × 55%).
A34: lifePremiumRate | B34: =lifePremiumRate | C34: D · assumption / shared | D34: 0.31% of sum assured.
A35: life cover step (user currency) | B35: =FX_lifeRound | C35: D · assumption / shared | D35: lifeRoundUnit (USD) as a nice step in user currency (FX tab).
A36: lifeExpectancyDefault | B36: =lifeExpectancyDefault | C36: D · assumption / shared | D36: Used when raw LE is missing or ≤ 0.
A38: C · DETERMINISTICALLY CALCULATED — _apply_plu. Take-home is read from the CPF tab.
A39: band min | B39: =IFERROR(INDEX(Assumptions!$K$6:$K$13,MATCH(B9,Assumptions!$J$6:$J$13,0)),"") | C39: C · calculated | D39: income_anchors.json Singapore min for occupation.
A40: band max | B40: =IFERROR(INDEX(Assumptions!$L$6:$L$13,MATCH(B9,Assumptions!$J$6:$J$13,0)),"") | C40: C · calculated | D40: income_anchors.json Singapore max.
A41: incomeMonthly (clamped) | B41: =IF(OR(B39="",B14=0),B14,MIN(MAX(B14,B39),B40)) | C41: C · calculated | D41: Clamp LLM income into the occupation band. 0 stays 0.
A42: CPF on (from CPF tab) | B42: =CPF_on | C42: A · input | D42: Country switch or orange override on the CPF tab.
A43: CPF rate | B43: =CPF_rate | C43: C · calculated | D43: 0 when CPF is off for this country.
A44: employee CPF | B44: =CPF_employee | C44: C · calculated | D44: 0 when CPF is off.
A45: take-home | B45: =CPF_takeHome | C45: C · calculated | D45: Gross minus employee CPF. Equals income when CPF is off.
A46: spend share | B46: =MIN(spendShareBase+spendSharePerDependant*MAX(0,B10),spendShareCap) | C46: C · calculated | D46: min(67.5% + 5pp × dependents, 90%).
A47: expenseMonthly | B47: =IF(B45<=0,0,ROUND(B45*B46,2)) | C47: C · calculated | D47: expenses_from_gross / spend of take-home.
A48: surplus / mo | B48: =B45-B47 | C48: C · calculated | D48: take-home − expense.
A49: working years | B49: =MAX(0,B5-workStartAge) | C49: C · calculated | D49: max(0, age − 21).
A50: liquid assets | B50: =IF(AND(B14>0,B47>0,B5>workStartAge),MAX(0,B48*12*assetsSaveShare*B49),0) | C50: C · calculated | D50: surplus × 12 × 0.5 × working years.
A51: PLU liabilities | B51: =B50*liabilityRatio | C51: C · calculated | D51: liquid × 0.7. Not the mortgage.
A52: cash (15%) | B52: =IF(MOD(B50*CASH_SAVINGS_SHARE,1)=0.5,2*ROUND((B50*CASH_SAVINGS_SHARE)/2,0),ROUND(B50*CASH_SAVINGS_SHARE,0)) | C52: C · calculated | D52: CASH_SAVINGS_SHARE. Python round (half to even).
A53: investments (85%) | B53: =IF(MOD(B50*INVESTMENTS_SHARE,1)=0.5,2*ROUND((B50*INVESTMENTS_SHARE)/2,0),ROUND(B50*INVESTMENTS_SHARE,0)) | C53: C · calculated | D53: INVESTMENTS_SHARE. Python round (half to even).
A54: income USD (home seed) | B54: =B14*FX_usdPerLocal | C54: C · calculated | D54: System currency: user currency × USD per 1.
A55: property USD | B55: =IF(B16=FALSE,0,IF(B54<propertyIncomeLow*FX_priceLevel,propertyLow,IF(B54<=propertyIncomeHigh*FX_priceLevel,propertyMid,propertyHigh))*FX_priceLevel) | C55: C · calculated | D55: seed_property_value on USD bands.
A56: property | B56: =ROUND(B55/FX_usdPerLocal,0) | C56: C · calculated | D56: Back to user currency.
A57: mortgage | B57: =IF(B56=0,0,IF(MOD(B56*PROPERTY_LTV,1)=0.5,2*ROUND((B56*PROPERTY_LTV)/2,0),ROUND(B56*PROPERTY_LTV,0))) | C57: C · calculated | D57: round(property × 55%).
A58: life sum assured | B58: =MAX(IF(B56>0,INT((B57+FX_lifeRound/2)/FX_lifeRound)*FX_lifeRound,0),IF(B10>0,IF(MOD(B14*12*5,1)=0.5,2*ROUND((B14*12*5)/2,0),ROUND(B14*12*5,0)),0)) | C58: C · calculated | D58: _assumed_life_policy: max(mortgage rounded to the life cover step, 5 × annual income if dependents).
A59: life premium | B59: =IF(B58<=0,0,IF(MOD(B58*lifePremiumRate,1)=0.5,2*ROUND((B58*lifePremiumRate)/2,0),ROUND(B58*lifePremiumRate,0))) | C59: C · calculated | D59: round(sum × 0.31%), half to even like Python (790.5 → 790).
A60: lifeExpectancy used | B60: =MIN(LON_AGE,IF(B17>0,B17,lifeExpectancyDefault)) | C60: C · calculated | D60: min(raw, 99). Missing or ≤ 0 → 85.
A61: marital (inferred) | B61: =IF(IFERROR(INDEX(Personas!I$3:I$52,MATCH($B$2,Personas!$A$3:$A$52,0)),"")<>"",LOWER(IFERROR(INDEX(Personas!I$3:I$52,MATCH($B$2,Personas!$A$3:$A$52,0)),"")),IF(B5<30,"single","married")) | C61: C · calculated | D61: Typed maritalStatus, else age < 30 → single.
A63: E · USER / FRONTEND OVERRIDE — Personas W–AC (Money page). Blank keeps the green calculated value.
A64: override expenseMonthly | B64: =IFERROR(INDEX(Personas!W$3:W$52,MATCH($B$2,Personas!$A$3:$A$52,0)),"") | C64: E · user / frontend override | D64: Money page spend. Frontend MIN_EXPENSE_MONTHLY = 100 SGD.
A65: override cash | B65: =IFERROR(INDEX(Personas!X$3:X$52,MATCH($B$2,Personas!$A$3:$A$52,0)),"") | C65: E · user / frontend override | D65: Cash & Savings. Provenance key cash / savings.
A66: override investments | B66: =IFERROR(INDEX(Personas!Y$3:Y$52,MATCH($B$2,Personas!$A$3:$A$52,0)),"") | C66: E · user / frontend override | D66: Investments.
A67: override property value | B67: =IFERROR(INDEX(Personas!Z$3:Z$52,MATCH($B$2,Personas!$A$3:$A$52,0)),"") | C67: E · user / frontend override | D67: Home value. Distinct from owns-home flag N.
A68: override mortgage | B68: =IFERROR(INDEX(Personas!AA$3:AA$52,MATCH($B$2,Personas!$A$3:$A$52,0)),"") | C68: E · user / frontend override | D68: Money page loans.
A69: override PLU liabilities | B69: =IFERROR(INDEX(Personas!AB$3:AB$52,MATCH($B$2,Personas!$A$3:$A$52,0)),"") | C69: E · user / frontend override | D69: Need Profiler TotalLiabilities. Not the mortgage.
A70: override life sum assured | B70: =IFERROR(INDEX(Personas!AC$3:AC$52,MATCH($B$2,Personas!$A$3:$A$52,0)),"") | C70: E · user / frontend override | D70: Existing Life Protection cover.
A72: C · EFFECTIVE SESSION — override if set, else calculated. Downstream and Validation read these.
A73: incomeMonthly | B73: =B14 | C73: C · calculated | D73: Personas J (LLM or user). The clamp row above is what /predict would force.
A74: expenseMonthly | B74: =MAX(ROUND(MIN_EXPENSE_MONTHLY/FX_usdPerLocal,2),IF(IFERROR(INDEX(Personas!W$3:W$52,MATCH($B$2,Personas!$A$3:$A$52,0)),"")="",B47,IFERROR(INDEX(Personas!W$3:W$52,MATCH($B$2,Personas!$A$3:$A$52,0)),""))) | C74: C · calculated | D74: Floor: MIN_EXPENSE_MONTHLY (USD 100) in user currency.
A75: take-home | B75: =B45 | C75: C · calculated | D75: From Personas J and CPF.
A76: surplus / mo | B76: =B75-B74 | C76: C · calculated
A77: cash | B77: =IF(IFERROR(INDEX(Personas!X$3:X$52,MATCH($B$2,Personas!$A$3:$A$52,0)),"")="",B52,IFERROR(INDEX(Personas!X$3:X$52,MATCH($B$2,Personas!$A$3:$A$52,0)),"")) | C77: C · calculated
A78: investments | B78: =IF(IFERROR(INDEX(Personas!Y$3:Y$52,MATCH($B$2,Personas!$A$3:$A$52,0)),"")="",B53,IFERROR(INDEX(Personas!Y$3:Y$52,MATCH($B$2,Personas!$A$3:$A$52,0)),"")) | C78: C · calculated
A79: liquid assets | B79: =B77+B78 | C79: C · calculated | D79: cash + investments.
A80: property | B80: =IF(IFERROR(INDEX(Personas!Z$3:Z$52,MATCH($B$2,Personas!$A$3:$A$52,0)),"")="",B56,IFERROR(INDEX(Personas!Z$3:Z$52,MATCH($B$2,Personas!$A$3:$A$52,0)),"")) | C80: C · calculated
A81: mortgage | B81: =IF(IFERROR(INDEX(Personas!AA$3:AA$52,MATCH($B$2,Personas!$A$3:$A$52,0)),"")="",B57,IFERROR(INDEX(Personas!AA$3:AA$52,MATCH($B$2,Personas!$A$3:$A$52,0)),"")) | C81: C · calculated
A82: PLU liabilities | B82: =IF(IFERROR(INDEX(Personas!AB$3:AB$52,MATCH($B$2,Personas!$A$3:$A$52,0)),"")="",B51,IFERROR(INDEX(Personas!AB$3:AB$52,MATCH($B$2,Personas!$A$3:$A$52,0)),"")) | C82: C · calculated
A83: life sum assured | B83: =IF(IFERROR(INDEX(Personas!AC$3:AC$52,MATCH($B$2,Personas!$A$3:$A$52,0)),"")="",B58,IFERROR(INDEX(Personas!AC$3:AC$52,MATCH($B$2,Personas!$A$3:$A$52,0)),"")) | C83: C · calculated
A84: life premium | B84: =IF(B83<=0,0,IF(MOD(B83*lifePremiumRate,1)=0.5,2*ROUND((B83*lifePremiumRate)/2,0),ROUND(B83*lifePremiumRate,0))) | C84: C · calculated | D84: Recomputed from effective sum.
A85: currency | B85: =IFERROR(INDEX(Personas!K$3:K$52,MATCH($B$2,Personas!$A$3:$A$52,0)),"") | C85: B · LLM predicted | D85: Personas K. FX converts with this ISO code.

Sheet Need Profiler
A1: Need Profiler — selected persona. Weighted scores → two protection + N_RET + one growth. Parked coverage needs are scored only.
A2: Selected persona | B2: =SelectedPersona | C2: =IFERROR(INDEX(Personas!B$3:B$52,MATCH($B$2,Personas!$A$3:$A$52,0)),"") | D2: Follows the dropdown on the Selected persona tab. | F2: A · INPUT DATA
A3: Attribute | B3: Value | C3: Kind | D3: Source / formula | F3: B · LLM PREDICTED DATA
A4: A · INPUT DATA — from selected Personas + People Like You results | F4: C · DETERMINISTICALLY CALCULATED
A5: age | B5: =IFERROR(INDEX(Personas!C$3:C$52,MATCH($B$2,Personas!$A$3:$A$52,0)),"") | C5: A · input | D5: Personas C. Bucket <21 / ≤30 / ≤40 / else. | F5: D · ASSUMPTIONS / SHARED DATA
A6: gender | B6: =IFERROR(INDEX(Personas!D$3:D$52,MATCH($B$2,Personas!$A$3:$A$52,0)),"") | C6: A · input | D6: Personas D. male=3, female=2. | F6: E · USER / FRONTEND OVERRIDE
A7: dependents | B7: =IFERROR(INDEX(Personas!H$3:H$52,MATCH($B$2,Personas!$A$3:$A$52,0)),"") | C7: A · input | D7: Personas H. 0 / 1 / ≥2 → 0 / 2 / 4.
A8: occupation | B8: =IFERROR(INDEX(Personas!G$3:G$52,MATCH($B$2,Personas!$A$3:$A$52,0)),"") | C8: A · input | D8: Personas G. Self-employed tokens → 2, else 1.
A9: incomeMonthly (from PLU) | B9: =PLU_incomeMonthly | C9: A · input | D9: People Like You calculated income, used as profiler Income.
A10: expenseMonthly (from PLU) | B10: =PLU_expenseMonthly | C10: A · input | D10: People Like You calculated spend.
A11: liquid assets (from PLU) | B11: =PLU_cash+PLU_investments | C11: A · input | D11: cash + investments.
A12: PLU liabilities (from PLU) | B12: =PLU_liabilities | C12: A · input | D12: Not the mortgage.
A14: B · LLM PREDICTED DATA — lifestyle flags this component reads
A15: is_smoker | B15: =IFERROR(INDEX(Personas!U$3:U$52,MATCH($B$2,Personas!$A$3:$A$52,0)),"") | C15: B · LLM predicted | D15: Personas U. TRUE→3, else 1 (JSON has no Smoking options).
A16: hospitalization_type | B16: =IFERROR(INDEX(Personas!Q$3:Q$52,MATCH($B$2,Personas!$A$3:$A$52,0)),"") | C16: B · LLM predicted | D16: Personas Q. private=4, public=2.
A17: ward_type | B17: =IFERROR(INDEX(Personas!P$3:P$52,MATCH($B$2,Personas!$A$3:$A$52,0)),"") | C17: B · LLM predicted | D17: Personas P. A=3, B=2. Single/Double/Ward score 0.
A18: retirement_lifestyle | B18: =IFERROR(INDEX(Personas!T$3:T$52,MATCH($B$2,Personas!$A$3:$A$52,0)),"") | C18: B · LLM predicted | D18: Personas T. frugal / stress-free / only the best.
A19: sports | B19: =IFERROR(INDEX(Personas!S$3:S$52,MATCH($B$2,Personas!$A$3:$A$52,0)),"") | C19: B · LLM predicted | D19: Personas S. Adventurous / I dont do sports / Life style.
A20: property (owns home) | B20: =IFERROR(INDEX(Personas!N$3:N$52,MATCH($B$2,Personas!$A$3:$A$52,0)),"") | C20: B · LLM predicted | D20: Personas N. V0-16: no longer swaps N_SAV / N_PRP (not used for selection).
A22: D · ASSUMPTIONS / SHARED DATA — used by this component
A23: Existing hospital cover | B23: 0 | C23: D · assumption / shared | D23: build_profiler_profile hard-codes Existing*Coverage = False → option weight 1.
A24: Existing disability cover | B24: 0 | C24: D · assumption / shared | D24: Same. Stored as 0 here; option weight of False is 1.
A25: PPP-USD per 1 local (market ÷ price level) | B25: =FX_pppUsdPerLocal | C25: D · assumption / shared | D25: From the FX tab. Income / expense / assets / liabilities convert local × this rate (equals the market rate for the base country).
A26: Selection rule | B26: 2 prot + N_RET + 1 growth | C26: D · assumption / shared | D26: V0-16: protection from N_INC/N_CRI/N_TPD/N_HOS/N_PAC; growth N_EDU vs N_SAV. N_PRP is never auto-picked (no profiler label).
A27: Profiler weight matrix | B27: Assumptions!B90:L104 | C27: D · assumption / shared | D27: Need_profiler.json needs_factor_weights. SUMPRODUCT with option weights.
A29: C · DETERMINISTICALLY CALCULATED — local × FX → USD, then 15 option weights
A30: usd Income | B30: =IF(FX_usdPerLocal="","",PLU_incomeMonthly*FX_pppUsdPerLocal) | C30: C · calculated | D30: local income × PPP-USD rate (market USD ÷ price level, V0-22). Singapore = market USD.
A31: usd Expense | B31: =IF(FX_usdPerLocal="","",PLU_expenseMonthly*FX_pppUsdPerLocal) | C31: C · calculated | D31: local expense × FX.
A32: usd Assets | B32: =IF(FX_usdPerLocal="","",(PLU_cash+PLU_investments)*FX_pppUsdPerLocal) | C32: C · calculated | D32: cash + investments × FX.
A33: usd Liab | B33: =IF(FX_usdPerLocal="","",PLU_liabilities*FX_pppUsdPerLocal) | C33: C · calculated | D33: PLU liabilities × FX.
A34: ow Age | B34: =IF(B5<21,1,IF(B5<=30,2,IF(B5<=40,3,4))) | C34: C · calculated | D34: _get_option_weight Date of Birth.
A35: ow Gender | B35: =IF(LOWER(B6)="male",3,IF(LOWER(B6)="female",2,0)) | C35: C · calculated | D35: male=3, female=2.
A36: ow Deps | B36: =IF(B7=0,0,IF(B7=1,2,4)) | C36: C · calculated | D36: 0 / 1 / else.
A37: ow Occ | B37: =IF(OR(ISNUMBER(SEARCH("self",B8)),ISNUMBER(SEARCH("entrepreneur",B8)),ISNUMBER(SEARCH("own business",B8)),ISNUMBER(SEARCH("freelance",B8))),2,1) | C37: C · calculated | D37: Self-employed tokens.
A38: ow Smoke | B38: =IF(B15=TRUE,3,1) | C38: C · calculated | D38: No Smoking options in JSON.
A39: ow Income | B39: =IF(B30<1000,4,IF(B30<2500,3,IF(B30<5000,2,IF(B30<10000,1,0)))) | C39: C · calculated | D39: Need_profiler.json Income lt bands (USD after FX).
A40: ow Expense | B40: =IF(B31<600,4,IF(B31<1500,3,IF(B31<3000,2,IF(B31<6000,1,0)))) | C40: C · calculated | D40: Expense USD bands (~0.6× income).
A41: ow Assets | B41: =IF(B32<10000,4,IF(B32<50000,3,IF(B32<150000,2,IF(B32<500000,1,0)))) | C41: C · calculated | D41: Assets USD bands (stock).
A42: ow Liab | B42: =IF(B33<5000,4,IF(B33<25000,3,IF(B33<100000,2,IF(B33<250000,1,0)))) | C42: C · calculated | D42: Liabilities USD bands (stock).
A43: ow HospExist | B43: 1 | C43: C · calculated | D43: Existing hospital coverage always False → 1.
A44: ow DisExist | B44: 1 | C44: C · calculated | D44: Existing disability coverage always False → 1.
A45: ow HospType | B45: =IF(LOWER(B16)="private",4,IF(LOWER(B16)="public",2,0)) | C45: C · calculated | D45: Hospital Type.
A46: ow Ward | B46: =IF(OR(UPPER(B17)="A",UPPER(B17)="SINGLE"),3,IF(OR(UPPER(B17)="B",UPPER(B17)="DOUBLE",UPPER(B17)="WARD"),2,0)) | C46: C · calculated | D46: V0-24 map: Single → A (3); Double / Ward → B (2, shared room).
A47: ow Lifestyle | B47: =IF(OR(LOWER(B18)="frugal",LOWER(B18)="basic"),1,IF(OR(LOWER(B18)="stress-free",LOWER(B18)="stress free",LOWER(B18)="comfortable"),2,IF(OR(LOWER(B18)="only the best",LOWER(B18)="luxurious"),4,0))) | C47: C · calculated | D47: V0-24 map: Basic → frugal (1), Comfortable → stress-free (2), Luxurious → only the best (4).
A48: ow Sports | B48: =IF(OR(ISNUMBER(SEARCH("adventur",B19)),ISNUMBER(SEARCH("diving",B19)),ISNUMBER(SEARCH("climb",B19)),ISNUMBER(SEARCH("ski",B19)),ISNUMBER(SEARCH("surf",B19)),ISNUMBER(SEARCH("martial",B19)),ISNUMBER(SEARCH("rugby",B19)),ISNUMBER(SEARCH("motor",B19)),ISNUMBER(SEARCH("extreme",B19)),ISNUMBER(SEARCH("parachut",B19)),ISNUMBER(SEARCH("boxing",B19))),4,IF(OR(TRIM(B19)="",ISNUMBER(SEARCH("dont",B19)),ISNUMBER(SEARCH("no sport",B19)),LOWER(TRIM(B19))="none"),0,1)) | C48: C · calculated | D48: V0-24 map: adventurous / high-risk sports → Adventurous (4); none → 0; any other sport (running, yoga, golf, …) → Life style (1).
A50: C · RESULTS — raw Σ (factor × option), then min–max scale 0–10
A51: raw Life Protection | B51: =ROUND(SUMPRODUCT($B$34:$B$48,Assumptions!B$90:B$104),2) | C51: C · calculated | D51: Need_profiler.json column Life Protection.
A52: raw Critical Illness | B52: =ROUND(SUMPRODUCT($B$34:$B$48,Assumptions!C$90:C$104),2) | C52: C · calculated | D52: Need_profiler.json column Critical Illness.
A53: raw TPD | B53: =ROUND(SUMPRODUCT($B$34:$B$48,Assumptions!D$90:D$104),2) | C53: C · calculated | D53: Need_profiler.json column Disability. Shown as TPD.
A54: raw Retirement | B54: =ROUND(SUMPRODUCT($B$34:$B$48,Assumptions!E$90:E$104),2) | C54: C · calculated | D54: Need_profiler.json column Retirement.
A55: raw Education | B55: =ROUND(SUMPRODUCT($B$34:$B$48,Assumptions!F$90:F$104),2) | C55: C · calculated | D55: Need_profiler.json column Education.
A56: raw Hospitalization | B56: =ROUND(SUMPRODUCT($B$34:$B$48,Assumptions!G$90:G$104),2) | C56: C · calculated | D56: Need_profiler.json column Hospitalization.
A57: raw General Savings | B57: =ROUND(SUMPRODUCT($B$34:$B$48,Assumptions!H$90:H$104),2) | C57: C · calculated | D57: Need_profiler.json column General Savings.
A58: raw Personal Accident | B58: =ROUND(SUMPRODUCT($B$34:$B$48,Assumptions!I$90:I$104),2) | C58: C · calculated | D58: Need_profiler.json column Personal Accident.
A59: raw Car Protection | B59: =ROUND(SUMPRODUCT($B$34:$B$48,Assumptions!J$90:J$104),2) | C59: C · calculated | D59: Need_profiler.json column Car Protection.
A60: raw Home Protection | B60: =ROUND(SUMPRODUCT($B$34:$B$48,Assumptions!K$90:K$104),2) | C60: C · calculated | D60: Need_profiler.json column Home Protection.
A61: raw Travel Protection | B61: =ROUND(SUMPRODUCT($B$34:$B$48,Assumptions!L$90:L$104),2) | C61: C · calculated | D61: Need_profiler.json column Travel Protection.
A62: min raw | B62: =MIN(B51:B61) | C62: C · calculated | D62: scale_scores min.
A63: max raw | B63: =MAX(B51:B61) | C63: C · calculated | D63: If max=min, divisor is forced to 1 so every scaled value is 0.
A64: scaled Life Protection | B64: =ROUND(((B51-B62)/IF(B63>B62,B63-B62,1))*10,1) | C64: C · calculated | D64: 0–10, 1 decimal.
A65: scaled Critical Illness | B65: =ROUND(((B52-B62)/IF(B63>B62,B63-B62,1))*10,1) | C65: C · calculated | D65: 0–10, 1 decimal.
A66: scaled TPD | B66: =ROUND(((B53-B62)/IF(B63>B62,B63-B62,1))*10,1) | C66: C · calculated | D66: 0–10, 1 decimal.
A67: scaled Retirement | B67: =ROUND(((B54-B62)/IF(B63>B62,B63-B62,1))*10,1) | C67: C · calculated | D67: 0–10, 1 decimal.
A68: scaled Education | B68: =ROUND(((B55-B62)/IF(B63>B62,B63-B62,1))*10,1) | C68: C · calculated | D68: 0–10, 1 decimal.
A69: scaled Hospitalization | B69: =ROUND(((B56-B62)/IF(B63>B62,B63-B62,1))*10,1) | C69: C · calculated | D69: 0–10, 1 decimal.
A70: scaled General Savings | B70: =ROUND(((B57-B62)/IF(B63>B62,B63-B62,1))*10,1) | C70: C · calculated | D70: 0–10, 1 decimal.
A71: scaled Personal Accident | B71: =ROUND(((B58-B62)/IF(B63>B62,B63-B62,1))*10,1) | C71: C · calculated | D71: 0–10, 1 decimal.
A72: scaled Car Protection | B72: =ROUND(((B59-B62)/IF(B63>B62,B63-B62,1))*10,1) | C72: C · calculated | D72: 0–10, 1 decimal.
A73: scaled Home Protection | B73: =ROUND(((B60-B62)/IF(B63>B62,B63-B62,1))*10,1) | C73: C · calculated | D73: 0–10, 1 decimal.
A74: scaled Travel Protection | B74: =ROUND(((B61-B62)/IF(B63>B62,B63-B62,1))*10,1) | C74: C · calculated | D74: 0–10, 1 decimal.
A76: tb N_INC | B76: =B64+0.005 | C76: C · calculated | D76: Tie-break bonus. Life Protection first in label order.
A77: tb N_CRI | B77: =B65+0.004 | C77: C · calculated | D77: Tie-break bonus. Critical Illness second.
A78: tb N_TPD | B78: =B66+0.003 | C78: C · calculated | D78: Tie-break bonus. TPD third.
A79: tb N_HOS | B79: =B69+0.002 | C79: C · calculated | D79: Tie-break bonus. Hospitalization fourth.
A80: tb N_PAC | B80: =B71+0.001 | C80: C · calculated | D80: Tie-break bonus. Personal Accident last (V0-16).
A81: prot1 | B81: =IF(B76=MAX(B76,B77,B78,B79,B80),"N_INC",IF(B77=MAX(B76,B77,B78,B79,B80),"N_CRI",IF(B78=MAX(B76,B77,B78,B79,B80),"N_TPD",IF(B79=MAX(B76,B77,B78,B79,B80),"N_HOS","N_PAC")))) | C81: C · calculated | D81: Highest protection score after the order bonus.
A82: tb2 N_INC | B82: =IF(B81="N_INC",-1,B64+0.005) | C82: C · calculated | D82: Winner of prot1 is excluded.
A83: tb2 N_CRI | B83: =IF(B81="N_CRI",-1,B65+0.004) | C83: C · calculated | D83: Winner of prot1 is excluded.
A84: tb2 N_TPD | B84: =IF(B81="N_TPD",-1,B66+0.003) | C84: C · calculated | D84: Winner of prot1 is excluded.
A85: tb2 N_HOS | B85: =IF(B81="N_HOS",-1,B69+0.002) | C85: C · calculated | D85: Winner of prot1 is excluded.
A86: tb2 N_PAC | B86: =IF(B81="N_PAC",-1,B71+0.001) | C86: C · calculated | D86: Winner of prot1 is excluded.
A87: prot2 | B87: =IF(B82=MAX(B82,B83,B84,B85,B86),"N_INC",IF(B83=MAX(B82,B83,B84,B85,B86),"N_CRI",IF(B84=MAX(B82,B83,B84,B85,B86),"N_TPD",IF(B85=MAX(B82,B83,B84,B85,B86),"N_HOS","N_PAC")))) | C87: C · calculated | D87: Second protection.
A88: tb N_EDU | B88: =B68+0.002 | C88: C · calculated | D88: Education first on a tie.
A89: tb N_SAV | B89: =B70+0.001 | C89: C · calculated | D89: General Savings second.
A90: grow2 | B90: =IF(B88>=B89,"N_EDU","N_SAV") | C90: C · calculated | D90: Second growth after forced N_RET. V0-16: N_EDU vs N_SAV only; no home-ownership swap; N_PRP never auto-picked.
A92: C · RESULTS — nine calculator needs, then three parked coverage needs (scored, no calculator)
A93: type | B93: calc on | C93: Enable? | D93: on (effective) | E93: priority | F93: scaled score
A94: N_INC | B94: =OR($B$81="N_INC",$B$87="N_INC") | D94: =IF(C94="",B94,C94) | E94: =IF(B64>7,5,3) | F94: =B64
A95: N_CRI | B95: =OR($B$81="N_CRI",$B$87="N_CRI") | D95: =IF(C95="",B95,C95) | E95: =IF(B65>7,5,3) | F95: =B65
A96: N_TPD | B96: =OR($B$81="N_TPD",$B$87="N_TPD") | D96: =IF(C96="",B96,C96) | E96: =IF(B66>7,5,3) | F96: =B66
A97: N_HOS | B97: =OR($B$81="N_HOS",$B$87="N_HOS") | D97: =IF(C97="",B97,C97) | E97: =IF(B69>7,5,3) | F97: =B69
A98: N_PAC | B98: =OR($B$81="N_PAC",$B$87="N_PAC") | D98: =IF(C98="",B98,C98) | E98: =IF(B71>7,5,3) | F98: =B71
A99: N_LTC | B99: =FALSE() | D99: =IF(C99="",B99,C99) | E99: 3 | F99: no label
A100: N_RET | B100: =TRUE() | D100: =IF(C100="",B100,C100) | E100: =IF(B67>7,5,3) | F100: =B67
A101: N_EDU | B101: =$B$90="N_EDU" | D101: =IF(C101="",B101,C101) | E101: =IF(B68>7,5,3) | F101: =B68
A102: N_SAV | B102: =$B$90="N_SAV" | D102: =IF(C102="",B102,C102) | E102: =IF(B70>7,5,3) | F102: =B70
A103: N_PRP | B103: =FALSE() | D103: =IF(C103="",B103,C103) | E103: 3 | F103: no label
A104: N_HOM | B104: parked | D104: coverage need | E104: =IF(B73>7,5,3) | F104: =B73
A105: N_CAR | B105: parked | D105: coverage need | E105: =IF(B72>7,5,3) | F105: =B72
A106: N_TRV | B106: parked | D106: coverage need | E106: =IF(B74>7,5,3) | F106: =B74
...

Sheet Need Calculator
A1: Need Calculator — selected persona. Runs in USD (S-block), results back in user currency. Orange cells are goal-card sliders (user currency).
A2: Selected persona | B2: =SelectedPersona | C2: =IFERROR(INDEX(Personas!B$3:B$52,MATCH($B$2,Personas!$A$3:$A$52,0)),"") | D2: Follows the dropdown on the Selected persona tab. | F2: A · INPUT DATA
A3: Attribute | B3: Value | C3: Kind | D3: Source / formula | F3: B · LLM PREDICTED DATA
A4: A · INPUT DATA — from Personas, People Like You, and Need Profiler | F4: C · DETERMINISTICALLY CALCULATED
A5: age | B5: =IFERROR(INDEX(Personas!C$3:C$52,MATCH($B$2,Personas!$A$3:$A$52,0)),"") | C5: A · input | D5: Personas C. | F5: D · ASSUMPTIONS / SHARED DATA
A6: incomeMonthly (from PLU) | B6: =PLU_incomeMonthly | C6: A · input | D6: Clamped gross monthly. | F6: E · USER / FRONTEND OVERRIDE
A7: expenseMonthly (from PLU) | B7: =PLU_expenseMonthly | C7: A · input | D7: Annual spend = this × 12.
A8: mortgage (from PLU) | B8: =PLU_mortgage | C8: A · input | D8: Added to N_INC amount.
A9: life sum (from PLU) | B9: =PLU_lifeSum | C9: A · input | D9: N_INC have.
A10: investments (from PLU) | B10: =PLU_investments | C10: A · input | D10: Tagged wealth pot only. Cash is never allocated.
A11: lifeExpectancy used (from PLU) | B11: =PLU_leUsed | C11: A · input | D11: yearsInRet = max(0, LE − retAge).
A13: O · GOAL-CARD SLIDERS / OVERRIDES — orange. Blank years keep the age rule
A14: lifestyle (1/2/3) | B14: 2 | C14: E · user / frontend override | D14: 1=frugal, 2=stress-free, 3=only the best. Default 2.
A15: retAge | B15: =ageOfRetirement | C15: E · user / frontend override | D15: Default from Assumptions (65).
A16: targetYear N_EDU | B16: =currentYear+MAX(1,EDU_TARGET_AGE-B5) | C16: E · user / frontend override | D16: Default: the year the customer turns EDU_TARGET_AGE (50); next year if older.
A17: targetYear N_SAV | B17: =currentYear+MAX(1,SAV_TARGET_AGE-B5) | C17: E · user / frontend override | D17: Default: the year the customer turns SAV_TARGET_AGE (40); next year if older.
A18: targetYear N_PRP | B18: =currentYear+MAX(1,PRP_TARGET_AGE-B5) | C18: E · user / frontend override | D18: Default: the year the customer turns PRP_TARGET_AGE (33); next year if older.
A19: bequest | B19: 0 | C19: E · user / frontend override | D19: Added to N_INC amount.
A20: dependYears (blank = age rule) | C20: E · user / frontend override | D20: Blank or ≤0 → supportYears.
A21: incomeReplace (blank = income) | C21: E · user / frontend override | D21: Blank → incomeMonthly for CI / TPD.
A22: N_SAV stored | B22: 0 | C22: E · user / frontend override | D22: If > 0, this is N_SAV amount; else 1× annual income.
A23: N_PRP stored | B23: 0 | C23: E · user / frontend override | D23: If > 0, this is N_PRP amount; else 5× annual income.
A24: tag N_RET | B24: 0 | C24: E · user / frontend override | D24: Investments tagged to retirement, then grown at realReturn.
A25: tag N_EDU | B25: 0 | C25: E · user / frontend override | D25: apply_investment_pot walk order: RET, EDU, SAV, PRP.
A26: tag N_SAV | B26: 0 | C26: E · user / frontend override | D26: Takes from remaining investments after RET and EDU.
A27: tag N_PRP | B27: 0 | C27: E · user / frontend override | D27: Last in the walk.
A28: LTC start age | B28: =LTC_START_AGE | C28: E · user / frontend override | D28: N_LTC front-end input. Default LTC_START_AGE (80).
A30: S · SYSTEM CURRENCY (USD) — user-currency inputs × USD per 1. The calculator below runs on these
A31: USD per 1 user-currency unit | B31: =FX_usdPerLocal | C31: D · assumption / shared | D31: FX tab. #N/A if the currency is unknown.
A32: price level (option B) | B32: =FX_priceLevel | C32: D · assumption / shared | D32: 1 under option A. Scales the USD fixed amounts.
A33: incomeMonthly USD | B33: =PLU_incomeMonthly*B31 | C33: C · calculated
A34: expenseMonthly USD | B34: =PLU_expenseMonthly*B31 | C34: C · calculated
A35: mortgage USD | B35: =PLU_mortgage*B31 | C35: C · calculated
A36: life sum USD | B36: =PLU_lifeSum*B31 | C36: C · calculated
A37: investments USD | B37: =PLU_investments*B31 | C37: C · calculated
A38: bequest USD | B38: =B19*B31 | C38: C · calculated
A39: N_SAV stored USD | B39: =B22*B31 | C39: C · calculated
A40: N_PRP stored USD | B40: =B23*B31 | C40: C · calculated
A41: tag N_RET USD | B41: =B24*B31 | C41: C · calculated
A42: tag N_EDU USD | B42: =B25*B31 | C42: C · calculated
A43: tag N_SAV USD | B43: =B26*B31 | C43: C · calculated
A44: tag N_PRP USD | B44: =B27*B31 | C44: C · calculated
A45: incomeReplace USD | B45: =IF(B21="","",B21*B31) | C45: C · calculated | D45: Blank → income.
A46: CRI_COST USD (× price level) | B46: =CRI_COST*B32 | C46: C · calculated | D46: Fixed amount, USD.
A47: TPD_COST USD (× price level) | B47: =TPD_COST*B32 | C47: C · calculated | D47: Fixed amount, USD.
A48: EDU_COST USD (× price level) | B48: =EDU_COST*B32 | C48: C · calculated | D48: Fixed amount, USD.
A49: PAC_COST USD (× price level) | B49: =PAC_COST*B32 | C49: C · calculated | D49: Fixed amount, USD.
A50: LTC_COST USD / year (× price level) | B50: =LTC_COST*B32 | C50: C · calculated | D50: Fixed amount, USD a year.
A52: D · ASSUMPTIONS / SHARED DATA — rates and need parameters
A53: inflationRate | B53: =inflationRate | C53: D · assumption / shared | D53: Grows EDU cost. N_RET grows at realReturn, not inflation.
A54: investmentReturn | B54: =investmentReturn | C54: D · assumption / shared | D54: Used to form realReturn.
A55: realReturn | B55: =realReturn | C55: D · assumption / shared | D55: max(0, (1+i)/(1+π) − 1). Discount rate.
A56: RET_LIFESTYLE_FRUGAL | B56: =RET_LIFESTYLE_FRUGAL | C56: D · assumption / shared | D56: N_RET spend multiple when lifestyle=1.
A57: RET_LIFESTYLE_STRESSFREE | B57: =RET_LIFESTYLE_STRESSFREE | C57: D · assumption / shared | D57: Default lifestyle=2.
A58: RET_LIFESTYLE_ONLYTHEBEST | B58: =RET_LIFESTYLE_ONLYTHEBEST | C58: D · assumption / shared | D58: lifestyle=3.
A59: INC_SUPPORT_MIN / Max / Pivot | B59: =INC_SUPPORT_MIN | C59: D · assumption / shared | D59: supportYears = min(max(10, 50 − age), 25).
A60: CRI_YEARS / CRI_COST | B60: =CRI_YEARS | C60: D · assumption / shared | D60: 3 years annuity-due + CRI_COST (USD, S-block).
A61: TPD_YEARS / TPD_COST | B61: =TPD_YEARS | C61: D · assumption / shared | D61: 5 years annuity-due + TPD_COST (USD, S-block).
A62: PAC_YEARS / PAC_COST | B62: =PAC_YEARS | C62: D · assumption / shared | D62: 1 year annuity-due + PAC_COST (USD, S-block). Agreed V0-18.
A63: HOS_MONTHS | B63: =HOS_MONTHS | C63: D · assumption / shared | D63: N_HOS = income × 6.
A64: EDU_COST (USD) | B64: =EDU_COST | C64: D · assumption / shared | D64: USD course cost, grown at inflation.
A65: SAV_INCOME_MULT | B65: =SAV_INCOME_MULT | C65: D · assumption / shared | D65: 1 × annual income if stored is 0.
A66: PRP_INCOME_MULT | B66: =PRP_INCOME_MULT | C66: D · assumption / shared | D66: 5 × annual income if stored is 0.
A67: currentYear / ageOfRetirement | B67: =currentYear | C67: D · assumption / shared | D67: 2026 / 65 in this workbook.
A69: C · DETERMINISTICALLY CALCULATED — horizons
A70: supportYears | B70: =MIN(MAX(INC_SUPPORT_MIN,INC_SUPPORT_PIVOT_AGE-B5),INC_SUPPORT_MAX) | C70: C · calculated | D70: life_support_years(age).
A71: yearsToRet | B71: =MAX(0,B15-B5) | C71: C · calculated | D71: years_to_retirement.
A72: yearsInRet | B72: =MAX(0,PLU_leUsed-B15) | C72: C · calculated | D72: years_in_retirement(retAge, session LE).
A73: eduYears | B73: =MAX(0,B16-currentYear) | C73: C · calculated | D73: max(0, targetYear N_EDU − thisYear).
A74: savYears | B74: =MAX(0,B17-currentYear) | C74: C · calculated | D74: max(0, targetYear N_SAV − thisYear).
A75: prpYears | B75: =MAX(0,B18-currentYear) | C75: C · calculated | D75: max(0, targetYear N_PRP − thisYear).
A76: careYears (N_LTC) | B76: =MAX(0,PLU_leUsed-B28) | C76: C · calculated | D76: lifeExpectancy − LTC start age.
A78: C · RESULTS — amount / have / gap for every UNIFIED type (even when off)
A79: type | B79: needAmount | C79: have | D79: gap | E79: Enable? | F79: on (effective) | H79: needAmount USD | I79: have USD | J79: gap USD
A80: N_INC | B80: =ROUND(H80/$B$31,0) | C80: =ROUND(I80/$B$31,0) | D80: =MAX(0,B80-C80) | F80: =IF(E80="",NP_on_N_INC,E80) | G80: bequest + mortgage + PV of annual spend over dependYears. | H80: =MAX(0,B38+B35+IF(OR((IF(OR(B20="",B20<=0),B70,B20))<=0,(B34*12)<=0),0,IF(ABS(realReturn)<1E-12,(B34*12)*(IF(OR(B20="",B20<=0),B70,B20)),(B34*12)*(1-(1+realReturn)^(-(IF(OR(B20="",B20<=0),B70,B20))))/(realReturn)))) | I80: =B36 | J80: =MAX(0,H80-I80)
A81: N_CRI | B81: =ROUND(H81/$B$31,0) | C81: =ROUND(I81/$B$31,0) | D81: =MAX(0,B81-C81) | F81: =IF(E81="",NP_on_N_CRI,E81) | G81: Annuity-due of replacement income for CRI_YEARS + CRI_COST. | H81: =MAX(0,IF(OR((CRI_YEARS)<=0,((IF(B45="",B33,B45))*12)<=0),0,IF(ABS(realReturn)<1E-12,((IF(B45="",B33,B45))*12)*(CRI_YEARS),((IF(B45="",B33,B45))*12)*(1-(1/((1+realReturn)))^(CRI_YEARS))/(1-(1/((1+realReturn))))))+B46) | I81: =0 | J81: =MAX(0,H81-I81)
A82: N_TPD | B82: =ROUND(H82/$B$31,0) | C82: =ROUND(I82/$B$31,0) | D82: =MAX(0,B82-C82) | F82: =IF(E82="",NP_on_N_TPD,E82) | G82: Annuity-due of replacement income for TPD_YEARS + TPD_COST. | H82: =MAX(0,IF(OR((TPD_YEARS)<=0,((IF(B45="",B33,B45))*12)<=0),0,IF(ABS(realReturn)<1E-12,((IF(B45="",B33,B45))*12)*(TPD_YEARS),((IF(B45="",B33,B45))*12)*(1-(1/((1+realReturn)))^(TPD_YEARS))/(1-(1/((1+realReturn))))))+B47) | I82: =0 | J82: =MAX(0,H82-I82)
A83: N_HOS | B83: =ROUND(H83/$B$31,0) | C83: =ROUND(I83/$B$31,0) | D83: =MAX(0,B83-C83) | F83: =IF(E83="",NP_on_N_HOS,E83) | G83: incomeMonthly × HOS_MONTHS. | H83: =MAX(0,B33*HOS_MONTHS) | I83: =0 | J83: =MAX(0,H83-I83)
A84: N_PAC | B84: =ROUND(H84/$B$31,0) | C84: =ROUND(I84/$B$31,0) | D84: =MAX(0,B84-C84) | F84: =IF(E84="",NP_on_N_PAC,E84) | G84: Annuity-due of replacement income for PAC_YEARS + PAC_COST. | H84: =MAX(0,IF(OR((PAC_YEARS)<=0,((IF(B45="",B33,B45))*12)<=0),0,IF(ABS(realReturn)<1E-12,((IF(B45="",B33,B45))*12)*(PAC_YEARS),((IF(B45="",B33,B45))*12)*(1-(1/((1+realReturn)))^(PAC_YEARS))/(1-(1/((1+realReturn))))))+B49) | I84: =0 | J84: =MAX(0,H84-I84)
A85: N_LTC | B85: =ROUND(H85/$B$31,0) | C85: =ROUND(I85/$B$31,0) | D85: =MAX(0,B85-C85) | F85: =IF(E85="",NP_on_N_LTC,E85) | G85: Annuity-due of LTC_COST over careYears (LTC start age → life expectancy), today's money. | H85: =MAX(0,IF(OR((B76)<=0,(B50)<=0),0,IF(ABS(realReturn)<1E-12,(B50)*(B76),(B50)*(1-(1/((1+realReturn)))^(B76))/(1-(1/((1+realReturn))))))) | I85: =0 | J85: =MAX(0,H85-I85)
A86: N_RET | B86: =ROUND(H86/$B$31,0) | C86: =ROUND(I86/$B$31,0) | D86: =MAX(0,B86-C86) | F86: =IF(E86="",NP_on_N_RET,E86) | G86: annualSpend × (1+realReturn)^T × a(realReturn, yearsInRet). | H86: =MAX(0,IF(OR((B72)<=0,(IF((B71)<=0,MAX(0,B34*12*(IF(B14=1,RET_LIFESTYLE_FRUGAL,IF(B14=3,RET_LIFESTYLE_ONLYTHEBEST,RET_LIFESTYLE_STRESSFREE)))),(B34*12*(IF(B14=1,RET_LIFESTYLE_FRUGAL,IF(B14=3,RET_LIFESTYLE_ONLYTHEBEST,RET_LIFESTYLE_STRESSFREE))))*(1+realReturn)^(B71)))<=0),0,IF(ABS(realReturn)<1E-12,(IF((B71)<=0,MAX(0,B34*12*(IF(B14=1,RET_LIFESTYLE_FRUGAL,IF(B14=3,RET_LIFESTYLE_ONLYTHEBEST,RET_LIFESTYLE_STRESSFREE)))),(B34*12*(IF(B14=1,RET_LIFESTYLE_FRUGAL,IF(B14=3,RET_LIFESTYLE_ONLYTHEBEST,RET_LIFESTYLE_STRESSFREE))))*(1+realReturn)^(B71)))*(B72),(IF((B71)<=0,MAX(0,B34*12*(IF(B14=1,RET_LIFESTYLE_FRUGAL,IF(B14=3,RET_LIFESTYLE_ONLYTHEBEST,RET_LIFESTYLE_STRESSFREE)))),(B34*12*(IF(B14=1,RET_LIFESTYLE_FRUGAL,IF(B14=3,RET_LIFESTYLE_ONLYTHEBEST,RET_LIFESTYLE_STRESSFREE))))*(1+realReturn)^(B71)))*(1-(1+realReturn)^(-(B72)))/(realReturn)))) | I86: =IF((B71)<=0,MAX(0,MIN(MAX(0,B41),MAX(0,B37))),(MIN(MAX(0,B41),MAX(0,B37)))*(1+realReturn)^(B71)) | J86: =MAX(0,H86-I86)
A87: N_EDU | B87: =ROUND(H87/$B$31,0) | C87: =ROUND(I87/$B$31,0) | D87: =MAX(0,B87-C87) | F87: =IF(E87="",NP_on_N_EDU,E87) | G87: EDU_COST (USD) × (1+inflation)^eduYears. | H87: =MAX(0,B48*(1+inflationRate)^B73) | I87: =IF((B73)<=0,MAX(0,MIN(MAX(0,B42),MAX(0,B37-MIN(MAX(0,B41),MAX(0,B37))))),(MIN(MAX(0,B42),MAX(0,B37-MIN(MAX(0,B41),MAX(0,B37)))))*(1+realReturn)^(B73)) | J87: =MAX(0,H87-I87)
A88: N_SAV | B88: =ROUND(H88/$B$31,0) | C88: =ROUND(I88/$B$31,0) | D88: =MAX(0,B88-C88) | F88: =IF(E88="",NP_on_N_SAV,E88) | G88: Stored or 1× annual income. | H88: =IF(B22>0,B39,B33*12*SAV_INCOME_MULT) | I88: =IF((B74)<=0,MAX(0,MIN(MAX(0,B43),MAX(0,MAX(0,B37-MIN(MAX(0,B41),MAX(0,B37)))-MIN(MAX(0,B42),MAX(0,B37-MIN(MAX(0,B41),MAX(0,B37))))))),(MIN(MAX(0,B43),MAX(0,MAX(0,B37-MIN(MAX(0,B41),MAX(0,B37)))-MIN(MAX(0,B42),MAX(0,B37-MIN(MAX(0,B41),MAX(0,B37)))))))*(1+realReturn)^(B74)) | J88: =MAX(0,H88-I88)
A89: N_PRP | B89: =ROUND(H89/$B$31,0) | C89: =ROUND(I89/$B$31,0) | D89: =MAX(0,B89-C89) | F89: =IF(E89="",NP_on_N_PRP,E89) | G89: Stored or 5× annual income. | H89: =IF(B23>0,B40,B33*12*PRP_INCOME_MULT) | I89: =IF((B75)<=0,MAX(0,MIN(MAX(0,B44),MAX(0,MAX(0,MAX(0,B37-MIN(MAX(0,B41),MAX(0,B37)))-MIN(MAX(0,B42),MAX(0,B37-MIN(MAX(0,B41),MAX(0,B37)))))-MIN(MAX(0,B43),MAX(0,MAX(0,B37-MIN(MAX(0,B41),MAX(0,B37)))-MIN(MAX(0,B42),MAX(0,B37-MIN(MAX(0,B41),MAX(0,B37))))))))),(MIN(MAX(0,B44),MAX(0,MAX(0,MAX(0,B37-MIN(MAX(0,B41),MAX(0,B37)))-MIN(MAX(0,B42),MAX(0,B37-MIN(MAX(0,B41),MAX(0,B37)))))-MIN(MAX(0,B43),MAX(0,MAX(0,B37-MIN(MAX(0,B41),MAX(0,B37)))-MIN(MAX(0,B42),MAX(0,B37-MIN(MAX(0,B41),MAX(0,B37)))))))))*(1+realReturn)^(B75)) | J89: =MAX(0,H89-I89)
A91: C · STRESS R_LON — longevity: N_RET and N_LTC if the customer lives until LON_AGE (99). Does not change the plan
A92: LON_AGE | B92: =LON_AGE | C92: D · assumption / shared | D92: Assumptions. Life expectancy under R_LON.
A93: yearsInRet at LON_AGE | B93: =MAX(0,LON_AGE-B15) | C93: C · calculated | D93: LON_AGE − retAge.
A94: N_RET need at LON_AGE USD | B94: =MAX(0,IF(OR((B93)<=0,(IF((B71)<=0,MAX(0,B34*12*(IF(B14=1,RET_LIFESTYLE_FRUGAL,IF(B14=3,RET_LIFESTYLE_ONLYTHEBEST,RET_LIFESTYLE_STRESSFREE)))),(B34*12*(IF(B14=1,RET_LIFESTYLE_FRUGAL,IF(B14=3,RET_LIFESTYLE_ONLYTHEBEST,RET_LIFESTYLE_STRESSFREE))))*(1+realReturn)^(B71)))<=0),0,IF(ABS(realReturn)<1E-12,(IF((B71)<=0,MAX(0,B34*12*(IF(B14=1,RET_LIFESTYLE_FRUGAL,IF(B14=3,RET_LIFESTYLE_ONLYTHEBEST,RET_LIFESTYLE_STRESSFREE)))),(B34*12*(IF(B14=1,RET_LIFESTYLE_FRUGAL,IF(B14=3,RET_LIFESTYLE_ONLYTHEBEST,RET_LIFESTYLE_STRESSFREE))))*(1+realReturn)^(B71)))*(B93),(IF((B71)<=0,MAX(0,B34*12*(IF(B14=1,RET_LIFESTYLE_FRUGAL,IF(B14=3,RET_LIFESTYLE_ONLYTHEBEST,RET_LIFESTYLE_STRESSFREE)))),(B34*12*(IF(B14=1,RET_LIFESTYLE_FRUGAL,IF(B14=3,RET_LIFESTYLE_ONLYTHEBEST,RET_LIFESTYLE_STRESSFREE))))*(1+realReturn)^(B71)))*(1-(1+realReturn)^(-(B93)))/(realReturn)))) | C94: C · calculated | D94: Same formula as N_RET, years to LON_AGE.
A95: N_RET need at LON_AGE | B95: =ROUND(B94/$B$31,0) | C95: C · calculated | D95: User currency.
A96: N_RET gap at LON_AGE | B96: =MAX(0,B95-C86) | C96: C · calculated | D96: Need at 99 − have.
A97: extra need from longevity | B97: =MAX(0,B95-B86) | C97: C · calculated | D97: Need at 99 − base need.
A98: careYears at LON_AGE | B98: =MAX(0,LON_AGE-B28) | C98: C · calculated | D98: LON_AGE − LTC start age.
A99: N_LTC need at LON_AGE | B99: =ROUND(MAX(0,IF(OR((B98)<=0,(B50)<=0),0,IF(ABS(realReturn)<1E-12,(B50)*(B98),(B50)*(1-(1/((1+realReturn)))^(B98))/(1-(1/((1+realReturn)))))))/$B$31,0) | C99: C · calculated | D99: Same formula as N_LTC, care until LON_AGE. User currency.

Sheet Plan Calculator
A1: Plan Calculator — selected persona. seedProducts / planProducts.ts. Suggested = enabled AND gap > 0.
A2: Selected persona | B2: =SelectedPersona | C2: =IFERROR(INDEX(Personas!B$3:B$52,MATCH($B$2,Personas!$A$3:$A$52,0)),"") | D2: Follows the dropdown on the Selected persona tab. | F2: A · INPUT DATA
A3: Attribute | B3: Value | C3: Kind | D3: Source / formula | F3: B · LLM PREDICTED DATA
A4: A · INPUT DATA — from People Like You and Need Calculator | F4: C · DETERMINISTICALLY CALCULATED
A5: take-home (from PLU) | B5: =PLU_takeHome | C5: A · input | D5: Surplus uses take-home, not gross income. | F5: D · ASSUMPTIONS / SHARED DATA
A6: expenseMonthly (from PLU) | B6: =PLU_expenseMonthly | C6: A · input | D6: types.ts availableBudget. | F6: E · USER / FRONTEND OVERRIDE
A7: N_INC on (from Need Calculator) | B7: =NC_on_N_INC | C7: A · input | D7: Effective enable after Need Calculator override.
A8: N_INC gap (from Need Calculator) | B8: =NC_gap_N_INC | C8: A · input | D8: remaining_gap.
A9: N_CRI on (from Need Calculator) | B9: =NC_on_N_CRI | C9: A · input | D9: Effective enable after Need Calculator override.
A10: N_CRI gap (from Need Calculator) | B10: =NC_gap_N_CRI | C10: A · input | D10: remaining_gap.
A11: N_TPD on (from Need Calculator) | B11: =NC_on_N_TPD | C11: A · input | D11: Effective enable after Need Calculator override.
A12: N_TPD gap (from Need Calculator) | B12: =NC_gap_N_TPD | C12: A · input | D12: remaining_gap.
A13: N_HOS on (from Need Calculator) | B13: =NC_on_N_HOS | C13: A · input | D13: Effective enable after Need Calculator override.
A14: N_HOS gap (from Need Calculator) | B14: =NC_gap_N_HOS | C14: A · input | D14: remaining_gap.
A15: N_PAC on (from Need Calculator) | B15: =NC_on_N_PAC | C15: A · input | D15: Effective enable after Need Calculator override.
A16: N_PAC gap (from Need Calculator) | B16: =NC_gap_N_PAC | C16: A · input | D16: remaining_gap.
A17: N_LTC on (from Need Calculator) | B17: =NC_on_N_LTC | C17: A · input | D17: Effective enable after Need Calculator override.
A18: N_LTC gap (from Need Calculator) | B18: =NC_gap_N_LTC | C18: A · input | D18: remaining_gap.
A19: N_RET on (from Need Calculator) | B19: =NC_on_N_RET | C19: A · input | D19: Effective enable after Need Calculator override.
A20: N_RET gap (from Need Calculator) | B20: =NC_gap_N_RET | C20: A · input | D20: remaining_gap.
A21: N_EDU on (from Need Calculator) | B21: =NC_on_N_EDU | C21: A · input | D21: Effective enable after Need Calculator override.
A22: N_EDU gap (from Need Calculator) | B22: =NC_gap_N_EDU | C22: A · input | D22: remaining_gap.
A23: N_SAV on (from Need Calculator) | B23: =NC_on_N_SAV | C23: A · input | D23: Effective enable after Need Calculator override.
A24: N_SAV gap (from Need Calculator) | B24: =NC_gap_N_SAV | C24: A · input | D24: remaining_gap.
A25: N_PRP on (from Need Calculator) | B25: =NC_on_N_PRP | C25: A · input | D25: Effective enable after Need Calculator override.
A26: N_PRP gap (from Need Calculator) | B26: =NC_gap_N_PRP | C26: A · input | D26: remaining_gap.
A27: yearsToRet (from Need Calculator) | B27: =NC_yearsToRet | C27: A · input | D27: Retirement contribution horizon.
A28: eduYears (from Need Calculator) | B28: =NC_eduYears | C28: A · input | D28: N_EDU contribution horizon.
A29: savYears (from Need Calculator) | B29: =NC_savYears | C29: A · input | D29: N_SAV contribution horizon.
A30: prpYears (from Need Calculator) | B30: =NC_prpYears | C30: A · input | D30: N_PRP contribution horizon.
A32: D · ASSUMPTIONS / SHARED DATA
A33: protectionPremiumRate | B33: =protectionPremiumRate | C33: D · assumption / shared | D33: Dummy 0.00078. Future: premium-quote calculator API.
A34: FREE_BUDGET_SHARE | B34: =FREE_BUDGET_SHARE | C34: D · assumption / shared | D34: Half of leftover surplus split across wealth needs.
A35: monthly step (user currency) | B35: =FX_monthlyStep | C35: D · assumption / shared | D35: monthlyRoundStep (USD) as a nice step in user currency. SGD: 50.
A36: premium step (user currency) | B36: =FX_coverPremStep | C36: D · assumption / shared | D36: coverPremRoundStep (USD) as a nice step in user currency. SGD: 10.
A37: realReturn | B37: =realReturn | C37: D · assumption / shared | D37: annualPmtToHitFv for the wealth cap.
A39: C · DETERMINISTICALLY CALCULATED — suggested flags and protection sizing
A40: sug N_INC | B40: =AND(NC_on_N_INC,NC_gap_N_INC>0) | C40: C · calculated | D40: enabled AND gap > 0.
A41: sug N_CRI | B41: =AND(NC_on_N_CRI,NC_gap_N_CRI>0) | C41: C · calculated | D41: enabled AND gap > 0.
A42: sug N_TPD | B42: =AND(NC_on_N_TPD,NC_gap_N_TPD>0) | C42: C · calculated | D42: enabled AND gap > 0.
A43: sug N_HOS | B43: =AND(NC_on_N_HOS,NC_gap_N_HOS>0) | C43: C · calculated | D43: enabled AND gap > 0.
A44: sug N_PAC | B44: =AND(NC_on_N_PAC,NC_gap_N_PAC>0) | C44: C · calculated | D44: enabled AND gap > 0.
A45: sug N_LTC | B45: =AND(NC_on_N_LTC,NC_gap_N_LTC>0) | C45: C · calculated | D45: enabled AND gap > 0.
A46: sug N_RET | B46: =AND(NC_on_N_RET,NC_gap_N_RET>0) | C46: C · calculated | D46: enabled AND gap > 0.
A47: sug N_EDU | B47: =AND(NC_on_N_EDU,NC_gap_N_EDU>0) | C47: C · calculated | D47: enabled AND gap > 0.
A48: sug N_SAV | B48: =AND(NC_on_N_SAV,NC_gap_N_SAV>0) | C48: C · calculated | D48: enabled AND gap > 0.
A49: sug N_PRP | B49: =AND(NC_on_N_PRP,NC_gap_N_PRP>0) | C49: C · calculated | D49: enabled AND gap > 0.
A50: n wealth suggested | B50: =(B46*1)+(B47*1)+(B48*1)+(B49*1) | C50: C · calculated | D50: Count of suggested wealth needs.
A51: planSum N_INC | B51: =IF(B40,MAX(0,ROUND(NC_gap_N_INC,0)),0) | C51: C · calculated | D51: Suggested protection sum = gap.
A52: planPrem N_INC | B52: =IF(B51<=0,0,MAX(0,ROUND((B51*protectionPremiumRate)/FX_coverPremStep,0)*FX_coverPremStep)) | C52: C · calculated | D52: coverPremiumFor(sum). Indicative, not half of slider max.
A53: planSum N_CRI | B53: =IF(B41,MAX(0,ROUND(NC_gap_N_CRI,0)),0) | C53: C · calculated | D53: Suggested protection sum = gap.
A54: planPrem N_CRI | B54: =IF(B53<=0,0,MAX(0,ROUND((B53*protectionPremiumRate)/FX_coverPremStep,0)*FX_coverPremStep)) | C54: C · calculated | D54: coverPremiumFor(sum). Indicative, not half of slider max.
A55: planSum N_TPD | B55: =IF(B42,MAX(0,ROUND(NC_gap_N_TPD,0)),0) | C55: C · calculated | D55: Suggested protection sum = gap.
A56: planPrem N_TPD | B56: =IF(B55<=0,0,MAX(0,ROUND((B55*protectionPremiumRate)/FX_coverPremStep,0)*FX_coverPremStep)) | C56: C · calculated | D56: coverPremiumFor(sum). Indicative, not half of slider max.
A57: planSum N_HOS | B57: =IF(B43,MAX(0,ROUND(NC_gap_N_HOS,0)),0) | C57: C · calculated | D57: Suggested protection sum = gap.
A58: planPrem N_HOS | B58: =IF(B57<=0,0,MAX(0,ROUND((B57*protectionPremiumRate)/FX_coverPremStep,0)*FX_coverPremStep)) | C58: C · calculated | D58: coverPremiumFor(sum). Indicative, not half of slider max.
A59: planSum N_PAC | B59: =IF(B44,MAX(0,ROUND(NC_gap_N_PAC,0)),0) | C59: C · calculated | D59: Suggested protection sum = gap.
A60: planPrem N_PAC | B60: =IF(B59<=0,0,MAX(0,ROUND((B59*protectionPremiumRate)/FX_coverPremStep,0)*FX_coverPremStep)) | C60: C · calculated | D60: coverPremiumFor(sum). Indicative, not half of slider max.
A61: planSum N_LTC | B61: =IF(B45,MAX(0,ROUND(NC_gap_N_LTC,0)),0) | C61: C · calculated | D61: Suggested protection sum = gap.
A62: planPrem N_LTC | B62: =IF(B61<=0,0,MAX(0,ROUND((B61*protectionPremiumRate)/FX_coverPremStep,0)*FX_coverPremStep)) | C62: C · calculated | D62: coverPremiumFor(sum). Indicative, not half of slider max.
A63: prot prem / yr | B63: =B52+B54+B56+B58+B60+B62 | C63: C · calculated | D63: Sum of suggested protection premiums (before Include?).
A64: default wealth mth share | B64: =IF(B50=0,0,MAX(0,ROUNDDOWN((MAX(0,PLU_takeHome-PLU_expenseMonthly)*FREE_BUDGET_SHARE-B63/12)/B50/FX_monthlyStep,0)*FX_monthlyStep)) | C64: C · calculated | D64: V0-24: (free budget − protection premiums / 12) ÷ n wealth, rounded DOWN to the monthly step. Free budget = 50% of monthly surplus, as in the Budget Calculator, so the default plan always fits.
A65: cap mth N_RET | B65: =IF((IF(OR((NC_gap_N_RET)<=0,(NC_yearsToRet)<=0),0,IF(ABS(realReturn)<1E-12,(NC_gap_N_RET)/(NC_yearsToRet),(NC_gap_N_RET)*realReturn/((1+realReturn)^(NC_yearsToRet)-1))))<=0,0,ROUNDUP((IF(OR((NC_gap_N_RET)<=0,(NC_yearsToRet)<=0),0,IF(ABS(realReturn)<1E-12,(NC_gap_N_RET)/(NC_yearsToRet),(NC_gap_N_RET)*realReturn/((1+realReturn)^(NC_yearsToRet)-1))))/12/FX_monthlyStep,0)*FX_monthlyStep) | C65: C · calculated | D65: annualPmtToHitFv / 12, rounded up to the monthly step.
A66: planMth N_RET | B66: =IF(B46,MIN(B64,B65),0) | C66: C · calculated | D66: min(default share, cap).
A67: planLump N_RET | B67: 0 | C67: C · calculated | D67: Default lump is 0.
A68: cap mth N_EDU | B68: =IF((IF(OR((NC_gap_N_EDU)<=0,(NC_eduYears)<=0),0,IF(ABS(realReturn)<1E-12,(NC_gap_N_EDU)/(NC_eduYears),(NC_gap_N_EDU)*realReturn/((1+realReturn)^(NC_eduYears)-1))))<=0,0,ROUNDUP((IF(OR((NC_gap_N_EDU)<=0,(NC_eduYears)<=0),0,IF(ABS(realReturn)<1E-12,(NC_gap_N_EDU)/(NC_eduYears),(NC_gap_N_EDU)*realReturn/((1+realReturn)^(NC_eduYears)-1))))/12/FX_monthlyStep,0)*FX_monthlyStep) | C68: C · calculated | D68: annualPmtToHitFv / 12, rounded up to the monthly step.
A69: planMth N_EDU | B69: =IF(B47,MIN(B64,B68),0) | C69: C · calculated | D69: min(default share, cap).
A70: planLump N_EDU | B70: 0 | C70: C · calculated | D70: Default lump is 0.
A71: cap mth N_SAV | B71: =IF((IF(OR((NC_gap_N_SAV)<=0,(NC_savYears)<=0),0,IF(ABS(realReturn)<1E-12,(NC_gap_N_SAV)/(NC_savYears),(NC_gap_N_SAV)*realReturn/((1+realReturn)^(NC_savYears)-1))))<=0,0,ROUNDUP((IF(OR((NC_gap_N_SAV)<=0,(NC_savYears)<=0),0,IF(ABS(realReturn)<1E-12,(NC_gap_N_SAV)/(NC_savYears),(NC_gap_N_SAV)*realReturn/((1+realReturn)^(NC_savYears)-1))))/12/FX_monthlyStep,0)*FX_monthlyStep) | C71: C · calculated | D71: annualPmtToHitFv / 12, rounded up to the monthly step.
A72: planMth N_SAV | B72: =IF(B48,MIN(B64,B71),0) | C72: C · calculated | D72: min(default share, cap).
A73: planLump N_SAV | B73: 0 | C73: C · calculated | D73: Default lump is 0.
A74: cap mth N_PRP | B74: =IF((IF(OR((NC_gap_N_PRP)<=0,(NC_prpYears)<=0),0,IF(ABS(realReturn)<1E-12,(NC_gap_N_PRP)/(NC_prpYears),(NC_gap_N_PRP)*realReturn/((1+realReturn)^(NC_prpYears)-1))))<=0,0,ROUNDUP((IF(OR((NC_gap_N_PRP)<=0,(NC_prpYears)<=0),0,IF(ABS(realReturn)<1E-12,(NC_gap_N_PRP)/(NC_prpYears),(NC_gap_N_PRP)*realReturn/((1+realReturn)^(NC_prpYears)-1))))/12/FX_monthlyStep,0)*FX_monthlyStep) | C74: C · calculated | D74: annualPmtToHitFv / 12, rounded up to the monthly step.
A75: planMth N_PRP | B75: =IF(B49,MIN(B64,B74),0) | C75: C · calculated | D75: min(default share, cap).
A76: planLump N_PRP | B76: 0 | C76: C · calculated | D76: Default lump is 0.
A78: C · RESULTS — Include? blank keeps the suggested product
A79: type | B79: suggested | C79: Include? | D79: included
A80: N_INC | B80: =B40 | D80: =AND(B80,IF(C80="",TRUE,C80))
A81: N_CRI | B81: =B41 | D81: =AND(B81,IF(C81="",TRUE,C81))
A82: N_TPD | B82: =B42 | D82: =AND(B82,IF(C82="",TRUE,C82))
A83: N_HOS | B83: =B43 | D83: =AND(B83,IF(C83="",TRUE,C83))
A84: N_PAC | B84: =B44 | D84: =AND(B84,IF(C84="",TRUE,C84))
A85: N_LTC | B85: =B45 | D85: =AND(B85,IF(C85="",TRUE,C85))
A86: N_RET | B86: =B46 | D86: =AND(B86,IF(C86="",TRUE,C86))
A87: N_EDU | B87: =B47 | D87: =AND(B87,IF(C87="",TRUE,C87))
A88: N_SAV | B88: =B48 | D88: =AND(B88,IF(C88="",TRUE,C88))
A89: N_PRP | B89: =B49 | D89: =AND(B89,IF(C89="",TRUE,C89))
A91: investMth | B91: =(D86*B66)+(D87*B69)+(D88*B72)+(D89*B75) | C91: C · calculated | D91: Sum of included wealth monthly contributions.
A92: investLump | B92: =(D86*B67)+(D87*B70)+(D88*B73)+(D89*B76) | C92: C · calculated | D92: Sum of included wealth lumps (default 0).

Sheet Budget Calculator
A1: Budget Calculator — selected persona. planAfford. Surplus is take-home minus expense.
A2: Selected persona | B2: =SelectedPersona | C2: =IFERROR(INDEX(Personas!B$3:B$52,MATCH($B$2,Personas!$A$3:$A$52,0)),"") | D2: Follows the dropdown on the Selected persona tab. | F2: A · INPUT DATA
A3: Attribute | B3: Value | C3: Kind | D3: Source / formula | F3: B · LLM PREDICTED DATA
A4: A · INPUT DATA — from People Like You and Plan Calculator | F4: C · DETERMINISTICALLY CALCULATED
A5: take-home (from PLU) | B5: =PLU_takeHome | C5: A · input | D5: types.ts availableBudget uses take-home. | F5: D · ASSUMPTIONS / SHARED DATA
A6: expenseMonthly (from PLU) | B6: =PLU_expenseMonthly | C6: A · input | D6: Not gross income. | F6: E · USER / FRONTEND OVERRIDE
A7: investments (from PLU) | B7: =PLU_investments | C7: A · input | D7: Cap for lumps.
A8: included N_INC premium | B8: =IF(PLAN_included_N_INC,PLAN_prem_N_INC,0) | C8: A · input | D8: Only included protection.
A9: included N_CRI premium | B9: =IF(PLAN_included_N_CRI,PLAN_prem_N_CRI,0) | C9: A · input
A10: included N_TPD premium | B10: =IF(PLAN_included_N_TPD,PLAN_prem_N_TPD,0) | C10: A · input
A11: included N_HOS premium | B11: =IF(PLAN_included_N_HOS,PLAN_prem_N_HOS,0) | C11: A · input
A12: included N_PAC premium | B12: =IF(PLAN_included_N_PAC,PLAN_prem_N_PAC,0) | C12: A · input | D12: V0-16.
A13: included N_LTC premium | B13: =IF(PLAN_included_N_LTC,PLAN_prem_N_LTC,0) | C13: A · input | D13: V0-19.
A14: investMth (from Plan) | B14: =PLAN_investMth | C14: A · input | D14: Included wealth contributions.
A15: investLump (from Plan) | B15: =PLAN_investLump | C15: A · input | D15: Included wealth lumps.
A17: D · ASSUMPTIONS / SHARED DATA
A18: FREE_BUDGET_SHARE | B18: =FREE_BUDGET_SHARE | C18: D · assumption / shared | D18: Half of monthly surplus is the free budget.
A20: C · DETERMINISTICALLY CALCULATED — planAfford
A21: available | B21: =MAX(0,PLU_takeHome-PLU_expenseMonthly) | C21: C · calculated | D21: max(0, take-home − expense).
A22: free (50%) | B22: =ROUND(B21*FREE_BUDGET_SHARE,0) | C22: C · calculated | D22: available × 50%, rounded.
A23: included prot prem / yr | B23: =IF(PLAN_included_N_INC,PLAN_prem_N_INC,0)+IF(PLAN_included_N_CRI,PLAN_prem_N_CRI,0)+IF(PLAN_included_N_TPD,PLAN_prem_N_TPD,0)+IF(PLAN_included_N_HOS,PLAN_prem_N_HOS,0)+IF(PLAN_included_N_PAC,PLAN_prem_N_PAC,0)+IF(PLAN_included_N_LTC,PLAN_prem_N_LTC,0) | C23: C · calculated | D23: Sum of included protection premiums.
A24: premMth (display) | B24: =ROUND(B23/12,0) | C24: C · calculated | D24: Annual premiums / 12.
A25: contribMth | B25: =PLAN_investMth | C25: C · calculated | D25: Same as investMth.
A26: monthly | B26: =ROUND(PLAN_investMth+B23/12,0) | C26: C · calculated | D26: contrib + prem/12.
A27: monthlyOver | B27: =B26-B22 | C27: C · calculated | D27: > 0 means the plan exceeds the free budget.
A28: lumps | B28: =PLAN_investLump | C28: C · calculated | D28: Included lumps.
A29: lumpOver | B29: =B28-PLU_investments | C29: C · calculated | D29: > 0 means lumps exceed current investments.

Sheet Scenario Visualizer
A1: Scenario Visualizer — selected persona. One deterministic path of SV CashFlowGeneratorV2 on GP's payload.
A2: Selected persona | B2: =SelectedPersona | C2: =IFERROR(INDEX(Personas!B$3:B$52,MATCH($B$2,Personas!$A$3:$A$52,0)),"") | D2: Follows the dropdown on the Selected persona tab. | F2: A · INPUT DATA
A3: Attribute | B3: Value | C3: Kind | D3: Source / formula | F3: B · LLM PREDICTED DATA
A4: A · INPUT DATA — effective session (People Like You, Need Calculator, Plan Calculator) | F4: C · DETERMINISTICALLY CALCULATED | H4: D · SV CPF TABLES — SocialSecurityR_SGP (by age at contribution)
A5: age | B5: =IFERROR(INDEX(Personas!C$3:C$52,MATCH($B$2,Personas!$A$3:$A$52,0)),"") | C5: A · input | D5: Personas C. | F5: D · ASSUMPTIONS / SHARED DATA | H5: from age | I5: to age | J5: total rate | K5: employee rate | L5: OA share | M5: SA share | N5: MA share
A6: residency | B6: =IFERROR(INDEX(Personas!E$3:E$52,MATCH($B$2,Personas!$A$3:$A$52,0)),"") | C6: A · input | D6: Personas E. sv_payload.py sends CPF region R_SGP unless Foreigner. | F6: E · USER / FRONTEND OVERRIDE | H6: 0 | I6: 35 | J6: 0.37 | K6: 0.2 | L6: 0.6217 | M6: 0.1621 | N6: 0.2162
A7: incomeMonthly | B7: =PLU_incomeMonthly | C7: A · input | D7: Salary I_SAL = round(× 12). | H7: 36 | I7: 45 | J7: 0.37 | K7: 0.2 | L7: 0.5677 | M7: 0.1891 | N7: 0.2432
A8: take-home | B8: =PLU_takeHome | C8: A · input | D8: Investment contribution = take-home − spend. | H8: 46 | I8: 50 | J8: 0.37 | K8: 0.2 | L8: 0.5136 | M8: 0.2162 | N8: 0.2702
A9: expenseMonthly | B9: =PLU_expenseMonthly | C9: A · input | D9: PERSONAL_EXPENSE = round(× 12). | H9: 51 | I9: 55 | J9: 0.37 | K9: 0.2 | L9: 0.4055 | M9: 0.3108 | N9: 0.2837
A10: cash | B10: =PLU_cash | C10: A · input | D10: A_SAV, grows at interestRate. | H10: 56 | I10: 60 | J10: 0.325 | K10: 0.17 | L10: 0.4069 | M10: 0.2372 | N10: 0.3559
A11: investments | B11: =PLU_investments | C11: A · input | D11: INVESTMENT_PORTFOLIO, grows at investmentReturn. | H11: 61 | I11: 65 | J11: 0.235 | K11: 0.115 | L11: 0.1709 | M11: 0.317 | N11: 0.5121
A12: property | B12: =PLU_property | C12: A · input | D12: RESIDENTIAL_PROPERTY (illiquid). | H12: 66 | I12: 70 | J12: 0.165 | K12: 0.075 | L12: 0.0646 | M12: 0.258 | N12: 0.6774
A13: mortgage | B13: =PLU_mortgage | C13: A · input | D13: Mortgage loan, 20-year annuity at loanRate. | H13: 71 | I13: 999 | J13: 0.125 | K13: 0.05 | L13: 0.08 | M13: 0.08 | N13: 0.84
A14: life sum assured | B14: =PLU_lifeSum | C14: A · input | D14: Existing life policy (only when > 0).
A15: life premium / yr | B15: =PLU_lifePrem | C15: A · input | D15: regularPremium of the existing policy. | H15: D · CPF LIFE — BRS and monthly payout by (55 − age)+ + year − 2023
H16: row | I16: BRS | J16: payout × 1 | K16: payout × 2 | L16: payout × 3
A17: D · ASSUMPTIONS — SV helium tenant conf.ini and SocialSecurityR_SGP | H17: 0 | I17: 99400 | J17: 870 | K17: 1620 | L17: 2370
A18: path end age (sent: LON_AGE) | B18: =LON_AGE | C18: D · assumption / shared | D18: V0-21: GP sends the cap (99); was SV tenant 100. | H18: 1 | I18: 102900 | J18: 900 | K18: 1640 | L18: 2350
A19: savingsRate | B19: 0.01 | C19: D · assumption / shared | D19: helium conf.ini. Savings account growth; also the premium load (× 1.01). | H19: 2 | I19: 106500 | J19: 930 | K19: 1730 | L19: 2530
A20: ageOfRetirement | B20: =ageOfRetirement | C20: D · assumption / shared | D20: Assumptions. | H20: 3 | I20: 110200 | J20: 950 | K20: 1780 | L20: 2610
A21: loan / premium term (years) | B21: 20 | C21: D · assumption / shared | D21: Mortgage remainingYears and existing policyTerm in sv_payload.py. | H21: 4 | I21: 114100 | J21: 980 | K21: 1840 | L21: 2690
A22: property rate premium | B22: 0.004 | C22: D · assumption / shared | D22: Property grows at max(0, assetReturn + 0.4%).
A23: currency shock share | B23: 0.66666667 | C23: D · assumption / shared | D23: Liquid assets fall by 2/3 of the slider.
A24: CPF ordinary-wage cap / yr | B24: 96000 | C24: D · assumption / shared | D24: SocialSecurityR_SGP.
A25: CPF MA cap | B25: 63000 | C25: D · assumption / shared | D25: Medisave excess moves to RA at payout age; MA is capped from then.
A26: CPF OA rate | B26: 0.025 | C26: D · assumption / shared
A27: CPF SA / MA rate | B27: 0.04 | C27: D · assumption / shared
A28: CPF RA / LIFE growth factor | B28: 1.04 | C28: D · assumption / shared | D28: RA and the CPF LIFE pot grow × 1.04 a year.
A29: BRS / payout growth | B29: 0.03 | C29: D · assumption / shared | D29: Past the 2027 row, and per year of payout age past 55.
A30: payout bonus per deferral year | B30: 0.07 | C30: D · assumption / shared | D30: × (1 + 7% × (payout age − 65)).
A32: C · DETERMINISTICALLY CALCULATED — sv_payload.py values as SV reads them
A33: years on the path (T) | B33: =MAX(SV_LE-SV_age,0) | C33: C · calculated | D33: SV numYears = 100 − age.
A34: array length (T + 1) | B34: =SV_T+1 | C34: C · calculated | D34: Asset / CPF columns run 0..T.
A35: years to retirement | B35: =MAX(SV_ret-SV_age,0) | C35: C · calculated
A36: salary zero from index | B36: =IF(SV_dtr>=1,SV_dtr-1,SV_T-1) | C36: C · calculated | D36: numpy arr[dtr−1:] = 0. When dtr = 0 only the last year is zeroed (SV keeps salary for retirees).
A37: salary / yr | B37: =IF(MOD(SV_income*12,1)=0.5,2*ROUND((SV_income*12)/2,0),ROUND(SV_income*12,0)) | C37: C · calculated | D37: I_SAL absoluteValue. Python round (half to even).
A38: spend / yr | B38: =IF(MOD(SV_expense*12,1)=0.5,2*ROUND((SV_expense*12)/2,0),ROUND(SV_expense*12,0)) | C38: C · calculated | D38: PERSONAL_EXPENSE absoluteValue. Python round (half to even).
A39: mortgage principal | B39: =INT(SV_mortgage) | C39: C · calculated | D39: int(mortgage).
A40: mortgage instalment / yr | B40: =IF(SV_mortgage>0,IF(MOD(IF(loanRate=0,SV_mortgage/SV_loanYears,SV_mortgage*loanRate/(1-(1+loanRate)^(-SV_loanYears))),1)=0.5,2*ROUND((IF(loanRate=0,SV_mortgage/SV_loanYears,SV_mortgage*loanRate/(1-(1+loanRate)^(-SV_loanYears))))/2,0),ROUND(IF(loanRate=0,SV_mortgage/SV_loanYears,SV_mortgage*loanRate/(1-(1+loanRate)^(-SV_loanYears))),0)),0) | C40: C · calculated | D40: Level annual annuity that clears the loan in 20 years, interest included (goal_math.annual_loan_payment). rate 0 → mortgage / 20. Paid from spend for 20 years. Python round (half to even).
A41: investment contribution / yr | B41: =IF(MOD(MAX(0,SV_takeHome-SV_expense),1)=0.5,2*ROUND((MAX(0,SV_takeHome-SV_expense))/2,0),ROUND(MAX(0,SV_takeHome-SV_expense),0)) | C41: C · calculated | D41: sv_payload.py sends the MONTHLY surplus; SV adds it once a year. Python round (half to even).
A42: existing life premium / yr | B42: =IF(SV_lifeSum>0,SV_lifePrem,0)*(1+SV_savRate) | C42: C · calculated | D42: InsuranceBaseClass premium × (1 + savingsRate), first 20 years.
A43: property growth | B43: =MAX(0,assetReturn+SV_propPremium) | C43: C · calculated
A44: N_EDU withdrawal year | B44: =IF(NC_eduYears>=1,NC_eduYears,SV_T) | C44: C · calculated | D44: fundsNeededYear − now (V0-24: own target year).
A45: N_EDU withdrawal amount | B45: =IF(NC_eduYears<=SV_T,NC_on_N_EDU*NC_amount_N_EDU,0) | C45: C · calculated | D45: capitalSumRequired, not inflated. Leaves savings in that year.
A46: N_SAV withdrawal year | B46: =IF(NC_savYears>=1,NC_savYears,SV_T) | C46: C · calculated | D46: fundsNeededYear − now (V0-24: own target year).
A47: N_SAV withdrawal amount | B47: =IF(NC_savYears<=SV_T,NC_on_N_SAV*NC_amount_N_SAV,0) | C47: C · calculated | D47: capitalSumRequired, not inflated. Leaves savings in that year.
A48: N_PRP withdrawal year | B48: =IF(NC_prpYears>=1,NC_prpYears,SV_T) | C48: C · calculated | D48: fundsNeededYear − now (V0-24: own target year).
A49: N_PRP withdrawal amount | B49: =IF(NC_prpYears<=SV_T,NC_on_N_PRP*NC_amount_N_PRP,0) | C49: C · calculated | D49: capitalSumRequired, not inflated. Leaves savings in that year.
A50: plan RET monthly | B50: =IF(PLAN_included_N_RET,PLAN_mth_N_RET,0) | C50: C · calculated | D50: plan_benefit_visualizer pot.
A51: plan RET lump | B51: =IF(PLAN_included_N_RET,PLAN_lump_N_RET,0) | C51: C · calculated
A52: plan RET pay years | B52: =MAX(1,SV_ret-SV_age) | C52: C · calculated
A53: plan N_EDU monthly | B53: =IF(PLAN_included_N_EDU,PLAN_mth_N_EDU,0) | C53: C · calculated | D53: One pot column for the three goals.
A54: plan N_EDU lump | B54: =IF(PLAN_included_N_EDU,PLAN_lump_N_EDU,0) | C54: C · calculated
A55: plan N_EDU pay years | B55: =MAX(1,NC_eduYears) | C55: C · calculated | D55: V0-24: own target year.
A56: plan N_SAV monthly | B56: =IF(PLAN_included_N_SAV,PLAN_mth_N_SAV,0) | C56: C · calculated | D56: One pot column for the three goals.
A57: plan N_SAV lump | B57: =IF(PLAN_included_N_SAV,PLAN_lump_N_SAV,0) | C57: C · calculated
A58: plan N_SAV pay years | B58: =MAX(1,NC_savYears) | C58: C · calculated | D58: V0-24: own target year.
A59: plan N_PRP monthly | B59: =IF(PLAN_included_N_PRP,PLAN_mth_N_PRP,0) | C59: C · calculated | D59: One pot column for the three goals.
A60: plan N_PRP lump | B60: =IF(PLAN_included_N_PRP,PLAN_lump_N_PRP,0) | C60: C · calculated
A61: plan N_PRP pay years | B61: =MAX(1,NC_prpYears) | C61: C · calculated | D61: V0-24: own target year.
A62: plan protection premium / yr | B62: =IF(PLAN_included_N_INC,PLAN_prem_N_INC,0)+IF(PLAN_included_N_CRI,PLAN_prem_N_CRI,0)+IF(PLAN_included_N_TPD,PLAN_prem_N_TPD,0)+IF(PLAN_included_N_HOS,PLAN_prem_N_HOS,0)+IF(PLAN_included_N_PAC,PLAN_prem_N_PAC,0)+IF(PLAN_included_N_LTC,PLAN_prem_N_LTC,0) | C62: C · calculated | D62: Premiums only: protection pots have no account value on SV's no-death path. Includes N_PAC and N_LTC.
A63: plan protection pay years | B63: =MAX(1,SV_ret-SV_age) | C63: C · calculated
A65: E · OVERRIDE — stress events (blank size = off). Slider years as on the SV screen
A66: R_MKT market crash: year | C66: E · user / frontend override | D66: Slider year; SV applies it at year + 1.
A67: R_MKT market crash: size | C67: E · user / frontend override | D67: e.g. 0.35. Every asset × (1 − size).
A68: R_CCY currency shock: year | C68: E · user / frontend override
A69: R_CCY currency shock: size | C69: E · user / frontend override | D69: Liquid assets × (1 − size × 2/3).
A70: R_INF inflation shock: from | C70: E · user / frontend override
A71: R_INF inflation shock: to | C71: E · user / frontend override
A72: R_INF inflation shock: extra | C72: E · user / frontend override | D72: Added to inflationRate for the window.
A73: R_ICT income impact: from | C73: E · user / frontend override
A74: R_ICT income impact: to | C74: E · user / frontend override
A75: R_ICT income impact: size | C75: E · user / frontend override | D75: −0.2 = salary × 0.8 (also the CPF wage).
A76: R_EXP expense impact: from | C76: E · user / frontend override
A77: R_EXP expense impact: to | C77: E · user / frontend override
A78: R_EXP expense impact: size | C78: E · user / frontend override | D78: Scales spend, instalment and goal withdrawals.
A79: crash on | B79: =SV_crashV<>"" | C79: C · calculated
A80: crash year (SV) | B80: =MAX(1,N(SV_crashY)+1) | C80: C · calculated
A81: crash factor | B81: =1-ABS(N(SV_crashV)) | C81: C · calculated
A82: currency on | B82: =SV_ccyV<>"" | C82: C · calculated
A83: currency year (SV) | B83: =MAX(1,N(SV_ccyY)+1) | C83: C · calculated
A84: currency factor | B84: =1-ABS(N(SV_ccyV))*SV_fxShare | C84: C · calculated
A85: inflation on | B85: =SV_inflV<>"" | C85: C · calculated
A86: inflation first year (SV) | B86: =MAX(1,N(SV_inflFrom)+1) | C86: C · calculated
A87: inflation last year (SV) | B87: =MAX(SV_inflS,N(SV_inflTo)+1) | C87: C · calculated
A88: income on | B88: =SV_incV<>"" | C88: C · calculated
A89: income first year (SV) | B89: =MAX(1,N(SV_incFrom)+1) | C89: C · calculated
A90: income last year (SV) | B90: =MAX(SV_incS,N(SV_incTo)+1) | C90: C · calculated
A91: expense on | B91: =SV_expV<>"" | C91: C · calculated
A92: expense first year (SV) | B92: =MAX(1,N(SV_expFrom)+1) | C92: C · calculated
A93: expense last year (SV) | B93: =MAX(SV_expS,N(SV_expTo)+1) | C93: C · calculated
A94: shock inflation rate | B94: =inflationRate+ABS(N(SV_inflV)) | C94: C · calculated
A95: income impact | B95: =IF(N(SV_incV)<=0,N(SV_incV),-ABS(N(SV_incV))) | C95: C · calculated
A96: expense impact | B96: =ABS(N(SV_expV)) | C96: C · calculated
A97: R_LON longevity: on (TRUE / blank) | C97: E · user / frontend override | D97: Chart horizon to LON_AGE (99). SV already runs the path to 100.
A98: R_LON on | B98: =SV_lonV=TRUE | C98: C · calculated
A99: chart horizon (age) | B99: =IF(SV_lonOn,LON_AGE,PLU_leUsed) | C99: C · calculated | D99: Session life expectancy, or LON_AGE under R_LON.
A100: R_DEA death: on (TRUE / blank) | C100: E · user / frontend override | D100: Size and timing from Assumptions (R_DEA_SIZE, R_DEA_WHEN).
A101: R_DEA on | B101: =SV_deaV=TRUE | C101: C · calculated
A102: R_DEA engine year | B102: =MAX(1,R_DEA_WHEN-SV_age) | C102: C · calculated | D102: Age-based; if already older, next year.
...

Sheet HappiU
A1: HappiU — selected persona. Deterministic HU score: expected values weighted by survival, on HU's cashflow rules.
A2: Selected persona | B2: =SelectedPersona | C2: =IFERROR(INDEX(Personas!B$3:B$52,MATCH($B$2,Personas!$A$3:$A$52,0)),"") | D2: Follows the dropdown on the Selected persona tab. | F2: A · INPUT DATA
A3: Attribute | B3: Value | C3: Kind | D3: Source / formula | F3: B · LLM PREDICTED DATA
A4: A · INPUT DATA — effective session (what hu_payload.py sends) | F4: C · DETERMINISTICALLY CALCULATED | H4: C · GOALS — enabled needs plus N_RET (GP always sends it)
A5: age | B5: =IFERROR(INDEX(Personas!C$3:C$52,MATCH($B$2,Personas!$A$3:$A$52,0)),"") | C5: A · input | D5: Personas C. HU needs 18–83. | F5: D · ASSUMPTIONS / SHARED DATA | H5: type | I5: code | J5: in list | K5: need | L5: existing | M5: in plan | N5: benefit | O5: priority | P5: duration | Q5: D | R5: path | S5: w0 | T5: whl | U5: v(0) | V5: U base | W5: U pre | X5: U rec | Y5: U full | Z5: denominator | AA5: pre | AB5: post | AC5: flag | AD5: log priority | AE5: calibration | AF5: weight
A6: gender | B6: =IFERROR(INDEX(Personas!D$3:D$52,MATCH($B$2,Personas!$A$3:$A$52,0)),"") | C6: A · input | D6: Personas D. Picks the q(age) column. | F6: E · USER / FRONTEND OVERRIDE | H6: N_INC | I6: N_INC | J6: =NC_on_N_INC | K6: =NC_amount_N_INC | L6: =HU_lifeSum | M6: =NOT(AND(PLAN_sug_N_INC,NOT(PLAN_included_N_INC))) | N6: =IF(NOT($M$6),0,IF(PLAN_sug_N_INC,MAX(0,PLAN_sum_N_INC),MAX(0,ROUND($K$6/HU_benefitRound,0)*HU_benefitRound))) | O6: =NP_priority_N_INC | P6: =IF($M$6,MIN(HU_term,HU_depYears),HU_depYears)+1 | Q6: =MIN($P$6,HU_T) | R6: W | S6: =INDEX($AD$73:$AD$155,IF(HU_T>=1,2,1))+$K$6 | T6: =HU_whl*$K$6 | U6: =IF($S$6=0,0,IF(0>$S$6/HU_alpha+$K$6,0.5*$S$6/HU_alpha,IF(0>=$K$6,(0-$K$6)-0.5*HU_alpha/$S$6*(0-$K$6)^2,IF(0>=$T$6,HU_beta*(0-$K$6),HU_beta*($T$6-$K$6))))) | V6: =$U$6*SUM($AF$73:$AF$155) | W6: =SUMPRODUCT($AF$73:$AF$155,$AG$73:$AG$155) | X6: =SUMPRODUCT($AF$73:$AF$155,$AH$73:$AH$155) | Y6: =SUMPRODUCT($AF$73:$AF$155,$AI$73:$AI$155) | Z6: =$Y$6-$V$6 | AA6: =IF(NOT($J$6),"",IF($S$6=0,1,IF($Z$6=0,1,IF(AND($Z$6=$W$6-$V$6,$W$6>0),1,MAX(0,MIN(1,($W$6-$V$6)/$Z$6)))))) | AB6: =IF(NOT($J$6),"",IF($S$6=0,1,IF($Z$6=0,1,IF(AND($Z$6=$X$6-$V$6,$X$6>0),1,MAX(0,MIN(1,($X$6-$V$6)/$Z$6)))))) | AC6: =IF(NOT($J$6),"",IF($S$6=0,"w0 = 0 (HU raises an error)",IF($Z$6=0,"denominator 0",""))) | AD6: =IF($J$6,MAX(LN($O$6+1),LN(1+1)),0) | AE6: =IF($J$6,1,0) | AF6: =IF($J$6,$AD$6*$AE$6/SUMPRODUCT($AD$6:$AD$13,$AE$6:$AE$13),0)
A7: is smoker | B7: =IFERROR(INDEX(Personas!U$3:U$52,MATCH($B$2,Personas!$A$3:$A$52,0)),"") | C7: A · input | D7: Personas U. | H7: N_CRI | I7: N_CRI | J7: =NC_on_N_CRI | K7: =NC_amount_N_CRI | L7: 0 | M7: =NOT(AND(PLAN_sug_N_CRI,NOT(PLAN_included_N_CRI))) | N7: =IF(NOT($M$7),0,IF(PLAN_sug_N_CRI,MAX(0,PLAN_sum_N_CRI),MAX(0,ROUND($K$7/HU_benefitRound,0)*HU_benefitRound))) | O7: =NP_priority_N_CRI | P7: =IF($M$7,HU_term,HU_ciMaxAge-HU_age)+1 | Q7: =MIN($P$7,HU_T) | R7: C | S7: =$K$7 | T7: =HU_whl*$K$7 | U7: =IF($S$7=0,0,IF(0>$S$7/HU_alpha+$K$7,0.5*$S$7/HU_alpha,IF(0>=$K$7,(0-$K$7)-0.5*HU_alpha/$S$7*(0-$K$7)^2,IF(0>=$T$7,HU_beta*(0-$K$7),HU_beta*($T$7-$K$7))))) | V7: =$U$7*SUM($AJ$73:$AJ$155) | W7: =SUMPRODUCT($AJ$73:$AJ$155,$AK$73:$AK$155) | X7: =SUMPRODUCT($AJ$73:$AJ$155,$AL$73:$AL$155) | Y7: =SUMPRODUCT($AJ$73:$AJ$155,$AM$73:$AM$155) | Z7: =$Y$7-$V$7 | AA7: =IF(NOT($J$7),"",IF($S$7=0,1,IF($Z$7=0,1,IF(AND($Z$7=$W$7-$V$7,$W$7>0),1,MAX(0,MIN(1,($W$7-$V$7)/$Z$7)))))) | AB7: =IF(NOT($J$7),"",IF($S$7=0,1,IF($Z$7=0,1,IF(AND($Z$7=$X$7-$V$7,$X$7>0),1,MAX(0,MIN(1,($X$7-$V$7)/$Z$7)))))) | AC7: =IF(NOT($J$7),"",IF($S$7=0,"w0 = 0 (HU raises an error)",IF($Z$7=0,"denominator 0",""))) | AD7: =IF($J$7,MAX(LN($O$7+1),LN(1+1)),0) | AE7: =IF($J$7,1/HU_nCons,0) | AF7: =IF($J$7,$AD$7*$AE$7/SUMPRODUCT($AD$6:$AD$13,$AE$6:$AE$13),0)
A8: incomeMonthly | B8: =PLU_incomeMonthly | C8: A · input | H8: N_TPD | I8: N_TPD | J8: =NC_on_N_TPD | K8: =NC_amount_N_TPD | L8: 0 | M8: =NOT(AND(PLAN_sug_N_TPD,NOT(PLAN_included_N_TPD))) | N8: =IF(NOT($M$8),0,IF(PLAN_sug_N_TPD,MAX(0,PLAN_sum_N_TPD),MAX(0,ROUND($K$8/HU_benefitRound,0)*HU_benefitRound))) | O8: =NP_priority_N_TPD | P8: =IF($M$8,HU_term,HU_ciMaxAge-HU_age)+1 | Q8: =MIN($P$8,HU_T) | R8: C | S8: =$K$8 | T8: =HU_whl*$K$8 | U8: =IF($S$8=0,0,IF(0>$S$8/HU_alpha+$K$8,0.5*$S$8/HU_alpha,IF(0>=$K$8,(0-$K$8)-0.5*HU_alpha/$S$8*(0-$K$8)^2,IF(0>=$T$8,HU_beta*(0-$K$8),HU_beta*($T$8-$K$8))))) | V8: =$U$8*SUM($AN$73:$AN$155) | W8: =SUMPRODUCT($AN$73:$AN$155,$AO$73:$AO$155) | X8: =SUMPRODUCT($AN$73:$AN$155,$AP$73:$AP$155) | Y8: =SUMPRODUCT($AN$73:$AN$155,$AQ$73:$AQ$155) | Z8: =$Y$8-$V$8 | AA8: =IF(NOT($J$8),"",IF($S$8=0,1,IF($Z$8=0,1,IF(AND($Z$8=$W$8-$V$8,$W$8>0),1,MAX(0,MIN(1,($W$8-$V$8)/$Z$8)))))) | AB8: =IF(NOT($J$8),"",IF($S$8=0,1,IF($Z$8=0,1,IF(AND($Z$8=$X$8-$V$8,$X$8>0),1,MAX(0,MIN(1,($X$8-$V$8)/$Z$8)))))) | AC8: =IF(NOT($J$8),"",IF($S$8=0,"w0 = 0 (HU raises an error)",IF($Z$8=0,"denominator 0",""))) | AD8: =IF($J$8,MAX(LN($O$8+1),LN(0+1)),0) | AE8: =IF($J$8,1/HU_nCons,0) | AF8: =IF($J$8,$AD$8*$AE$8/SUMPRODUCT($AD$6:$AD$13,$AE$6:$AE$13),0)
A9: expenseMonthly | B9: =PLU_expenseMonthly | C9: A · input | H9: N_HOS | I9: N_HSP | J9: =NC_on_N_HOS | K9: =NC_amount_N_HOS | L9: 0 | M9: =NOT(AND(PLAN_sug_N_HOS,NOT(PLAN_included_N_HOS))) | N9: =IF(NOT($M$9),0,IF(PLAN_sug_N_HOS,MAX(0,PLAN_sum_N_HOS),MAX(0,ROUND($K$9/HU_benefitRound,0)*HU_benefitRound))) | O9: =NP_priority_N_HOS | P9: =IF($M$9,HU_term,HU_ciMaxAge-HU_age)+1 | Q9: =MIN($P$9,HU_T) | R9: C | S9: =$K$9 | T9: =HU_whl*$K$9 | U9: =IF($S$9=0,0,IF(0>$S$9/HU_alpha+$K$9,0.5*$S$9/HU_alpha,IF(0>=$K$9,(0-$K$9)-0.5*HU_alpha/$S$9*(0-$K$9)^2,IF(0>=$T$9,HU_beta*(0-$K$9),HU_beta*($T$9-$K$9))))) | V9: =$U$9*SUM($AR$73:$AR$155) | W9: =SUMPRODUCT($AR$73:$AR$155,$AS$73:$AS$155) | X9: =SUMPRODUCT($AR$73:$AR$155,$AT$73:$AT$155) | Y9: =SUMPRODUCT($AR$73:$AR$155,$AU$73:$AU$155) | Z9: =$Y$9-$V$9 | AA9: =IF(NOT($J$9),"",IF($S$9=0,1,IF($Z$9=0,1,IF(AND($Z$9=$W$9-$V$9,$W$9>0),1,MAX(0,MIN(1,($W$9-$V$9)/$Z$9)))))) | AB9: =IF(NOT($J$9),"",IF($S$9=0,1,IF($Z$9=0,1,IF(AND($Z$9=$X$9-$V$9,$X$9>0),1,MAX(0,MIN(1,($X$9-$V$9)/$Z$9)))))) | AC9: =IF(NOT($J$9),"",IF($S$9=0,"w0 = 0 (HU raises an error)",IF($Z$9=0,"denominator 0",""))) | AD9: =IF($J$9,MAX(LN($O$9+1),LN(0+1)),0) | AE9: =IF($J$9,1/HU_nCons,0) | AF9: =IF($J$9,$AD$9*$AE$9/SUMPRODUCT($AD$6:$AD$13,$AE$6:$AE$13),0)
A10: cash | B10: =PLU_cash | C10: A · input | D10: A_SAV. HU starts savings at 1 when cash is 0. | H10: N_RET | I10: N_RET | J10: =TRUE | K10: =IF(NC_on_N_RET,NC_amount_N_RET,HU_expense*12*MAX(0,HU_leS-HU_ret)) | L10: 0 | M10: =NOT(AND(PLAN_sug_N_RET,NOT(PLAN_included_N_RET))) | N10: =IF(NOT($M$10),0,MAX(0,ROUND($K$10/HU_benefitRound,0)*HU_benefitRound)) | O10: =IF(NC_on_N_RET,NP_priority_N_RET,5) | P10: =MAX(0,HU_ret-HU_age) | Q10: =MIN($P$10,HU_T) | R10: W | S10: =INDEX($AD$73:$AD$155,IF(HU_T>=1,2,1))+$K$10 | T10: =HU_whl*$K$10 | U10: =IF($S$10=0,0,IF(0>$S$10/HU_alpha+$K$10,0.5*$S$10/HU_alpha,IF(0>=$K$10,(0-$K$10)-0.5*HU_alpha/$S$10*(0-$K$10)^2,IF(0>=$T$10,HU_beta*(0-$K$10),HU_beta*($T$10-$K$10))))) | V10: =$U$10*SUM($AV$73:$AV$155) | W10: =SUMPRODUCT($AV$73:$AV$155,$AW$73:$AW$155) | X10: =SUMPRODUCT($AV$73:$AV$155,$AX$73:$AX$155) | Y10: =SUMPRODUCT($AV$73:$AV$155,$AY$73:$AY$155) | Z10: =$Y$10-$V$10 | AA10: =IF(NOT($J$10),"",IF($S$10=0,1,IF($Z$10=0,1,IF(AND($Z$10=$W$10-$V$10,$W$10>0),1,MAX(0,MIN(1,($W$10-$V$10)/$Z$10)))))) | AB10: =IF(NOT($J$10),"",IF($S$10=0,1,IF($Z$10=0,1,IF(AND($Z$10=$X$10-$V$10,$X$10>0),1,MAX(0,MIN(1,($X$10-$V$10)/$Z$10)))))) | AC10: =IF(NOT($J$10),"",IF($S$10=0,"w0 = 0 (HU raises an error)",IF($Z$10=0,"denominator 0",""))) | AD10: =IF($J$10,MAX(LN($O$10+1),LN(1+1)),0) | AE10: =IF($J$10,HU_calRet,0) | AF10: =IF($J$10,$AD$10*$AE$10/SUMPRODUCT($AD$6:$AD$13,$AE$6:$AE$13),0)
A11: investments | B11: =PLU_investments | C11: A · input | D11: A_INV. Deterministic growth e^(mu·t). | H11: N_EDU | I11: N_EDU | J11: =NC_on_N_EDU | K11: =NC_amount_N_EDU | L11: 0 | M11: =NOT(AND(PLAN_sug_N_EDU,NOT(PLAN_included_N_EDU))) | N11: =IF(NOT($M$11),0,MAX(0,ROUND($K$11/HU_benefitRound,0)*HU_benefitRound)) | O11: =NP_priority_N_EDU | P11: =MAX(0,NC_eduYears) | Q11: =MIN($P$11,HU_T) | R11: C | S11: =$K$11 | T11: =HU_whl*$K$11 | U11: =IF($S$11=0,0,IF(0>$S$11/HU_alpha+$K$11,0.5*$S$11/HU_alpha,IF(0>=$K$11,(0-$K$11)-0.5*HU_alpha/$S$11*(0-$K$11)^2,IF(0>=$T$11,HU_beta*(0-$K$11),HU_beta*($T$11-$K$11))))) | V11: =$U$11*SUM($AZ$73:$AZ$155) | W11: =SUMPRODUCT($AZ$73:$AZ$155,$BA$73:$BA$155) | X11: =SUMPRODUCT($AZ$73:$AZ$155,$BB$73:$BB$155) | Y11: =SUMPRODUCT($AZ$73:$AZ$155,$BC$73:$BC$155) | Z11: =$Y$11-$V$11 | AA11: =IF(NOT($J$11),"",IF($S$11=0,1,IF($Z$11=0,1,IF(AND($Z$11=$W$11-$V$11,$W$11>0),1,MAX(0,MIN(1,($W$11-$V$11)/$Z$11)))))) | AB11: =IF(NOT($J$11),"",IF($S$11=0,1,IF($Z$11=0,1,IF(AND($Z$11=$X$11-$V$11,$X$11>0),1,MAX(0,MIN(1,($X$11-$V$11)/$Z$11)))))) | AC11: =IF(NOT($J$11),"",IF($S$11=0,"w0 = 0 (HU raises an error)",IF($Z$11=0,"denominator 0",""))) | AD11: =IF($J$11,MAX(LN($O$11+1),LN(0+1)),0) | AE11: =IF($J$11,1/HU_nCons,0) | AF11: =IF($J$11,$AD$11*$AE$11/SUMPRODUCT($AD$6:$AD$13,$AE$6:$AE$13),0)
A12: life sum assured | B12: =PLU_lifeSum | C12: A · input | D12: N_INC existing cover. | H12: N_SAV | I12: N_SAV | J12: =NC_on_N_SAV | K12: =NC_amount_N_SAV | L12: 0 | M12: =NOT(AND(PLAN_sug_N_SAV,NOT(PLAN_included_N_SAV))) | N12: =IF(NOT($M$12),0,MAX(0,ROUND($K$12/HU_benefitRound,0)*HU_benefitRound)) | O12: =NP_priority_N_SAV | P12: =MAX(0,NC_savYears) | Q12: =MIN($P$12,HU_T) | R12: C | S12: =$K$12 | T12: =HU_whl*$K$12 | U12: =IF($S$12=0,0,IF(0>$S$12/HU_alpha+$K$12,0.5*$S$12/HU_alpha,IF(0>=$K$12,(0-$K$12)-0.5*HU_alpha/$S$12*(0-$K$12)^2,IF(0>=$T$12,HU_beta*(0-$K$12),HU_beta*($T$12-$K$12))))) | V12: =$U$12*SUM($BD$73:$BD$155) | W12: =SUMPRODUCT($BD$73:$BD$155,$BE$73:$BE$155) | X12: =SUMPRODUCT($BD$73:$BD$155,$BF$73:$BF$155) | Y12: =SUMPRODUCT($BD$73:$BD$155,$BG$73:$BG$155) | Z12: =$Y$12-$V$12 | AA12: =IF(NOT($J$12),"",IF($S$12=0,1,IF($Z$12=0,1,IF(AND($Z$12=$W$12-$V$12,$W$12>0),1,MAX(0,MIN(1,($W$12-$V$12)/$Z$12)))))) | AB12: =IF(NOT($J$12),"",IF($S$12=0,1,IF($Z$12=0,1,IF(AND($Z$12=$X$12-$V$12,$X$12>0),1,MAX(0,MIN(1,($X$12-$V$12)/$Z$12)))))) | AC12: =IF(NOT($J$12),"",IF($S$12=0,"w0 = 0 (HU raises an error)",IF($Z$12=0,"denominator 0",""))) | AD12: =IF($J$12,MAX(LN($O$12+1),LN(0+1)),0) | AE12: =IF($J$12,1/HU_nCons,0) | AF12: =IF($J$12,$AD$12*$AE$12/SUMPRODUCT($AD$6:$AD$13,$AE$6:$AE$13),0)
A13: session life expectancy | B13: =MIN(PLU_leUsed,LON_AGE) | C13: A · input | D13: Sent by GP, capped at LON_AGE (99). | H13: N_PRP | I13: N_PRP | J13: =NC_on_N_PRP | K13: =NC_amount_N_PRP | L13: 0 | M13: =NOT(AND(PLAN_sug_N_PRP,NOT(PLAN_included_N_PRP))) | N13: =IF(NOT($M$13),0,MAX(0,ROUND($K$13/HU_benefitRound,0)*HU_benefitRound)) | O13: =NP_priority_N_PRP | P13: =MAX(0,NC_prpYears) | Q13: =MIN($P$13,HU_T) | R13: C | S13: =$K$13 | T13: =HU_whl*$K$13 | U13: =IF($S$13=0,0,IF(0>$S$13/HU_alpha+$K$13,0.5*$S$13/HU_alpha,IF(0>=$K$13,(0-$K$13)-0.5*HU_alpha/$S$13*(0-$K$13)^2,IF(0>=$T$13,HU_beta*(0-$K$13),HU_beta*($T$13-$K$13))))) | V13: =$U$13*SUM($BH$73:$BH$155) | W13: =SUMPRODUCT($BH$73:$BH$155,$BI$73:$BI$155) | X13: =SUMPRODUCT($BH$73:$BH$155,$BJ$73:$BJ$155) | Y13: =SUMPRODUCT($BH$73:$BH$155,$BK$73:$BK$155) | Z13: =$Y$13-$V$13 | AA13: =IF(NOT($J$13),"",IF($S$13=0,1,IF($Z$13=0,1,IF(AND($Z$13=$W$13-$V$13,$W$13>0),1,MAX(0,MIN(1,($W$13-$V$13)/$Z$13)))))) | AB13: =IF(NOT($J$13),"",IF($S$13=0,1,IF($Z$13=0,1,IF(AND($Z$13=$X$13-$V$13,$X$13>0),1,MAX(0,MIN(1,($X$13-$V$13)/$Z$13)))))) | AC13: =IF(NOT($J$13),"",IF($S$13=0,"w0 = 0 (HU raises an error)",IF($Z$13=0,"denominator 0",""))) | AD13: =IF($J$13,MAX(LN($O$13+1),LN(0+1)),0) | AE13: =IF($J$13,1/HU_nCons,0) | AF13: =IF($J$13,$AD$13*$AE$13/SUMPRODUCT($AD$6:$AD$13,$AE$6:$AE$13),0)
A15: D · ASSUMPTIONS — HU conf.json / config/default/conf.ini / hu_payload.py
A16: ageOfRetirement | B16: =ageOfRetirement | C16: D · assumption / shared
A17: default life expectancy | B17: =lifeExpectancyDefault | C17: D · assumption / shared | D17: V0-21: GP sends the one default (85); was HU 83.
A18: CI income years (N_CRI on) | B18: =CRI_YEARS | C18: D · assumption / shared | D18: numYearsIncomeNeeded from GP.
A19: CI income years (N_CRI off) | B19: 5 | C19: D · assumption / shared | D19: HU ciAssumptions default.
A20: CI medical cost (sent: CRI_COST) | B20: =CRI_COST/FX_usdPerLocal | C20: D · assumption / shared | D20: V0-21: GP sends CRI_COST in user currency; was HU 200,000.
A21: TPD medical cost (sent: TPD_COST) | B21: =TPD_COST/FX_usdPerLocal | C21: D · assumption / shared | D21: V0-21: GP sends TPD_COST in user currency; was HU 444,000.
A22: TPD income cut | B22: 0.5 | C22: D · assumption / shared
A23: dismemberment income cut | B23: 1 | C23: D · assumption / shared | D23: From the year after.
A24: cover age (off-plan CI / TPD / HSP) | B24: 75 | C24: D · assumption / shared | D24: Off-plan protection runs to age 75.
A25: dependent years (N_INC) | B25: 10 | C25: D · assumption / shared | D25: numYearDependents default.
A26: plan policy term | B26: 10 | C26: D · assumption / shared | D26: segregatedBudget policyTerm in hu_payload.py.
A27: wealth high-loss factor | B27: 0.25 | C27: D · assumption / shared | D27: conf.ini wealth_hight_loss_factor.
A28: beta | B28: 1 | C28: D · assumption / shared | D28: conf.ini beta.
A29: minimum equity drift | B29: 0.01 | C29: D · assumption / shared | D29: ProductEquity mu floor.
A30: riskProfile | B30: 4 | C30: D · assumption / shared | D30: hu_payload.py default.
A31: retirement lifestyle rate | B31: =RET_LIFESTYLE_STRESSFREE | C31: D · assumption / shared | D31: N_RET lifestyle 2.
A32: retirement spend share | B32: 0.75 | C32: D · assumption / shared | D32: expectedLivingExpenseInTheCountry = living × 0.75.
A33: benefit round (user currency) | B33: =FX_benefitRound | C33: D · assumption / shared | D33: benefitRound (USD) as a nice step in user currency. SGD: 50,000.
A34: N_RET calibration | B34: 2 | C34: D · assumption / shared | D34: N_INC 1, N_RET 2, consumption goals 1 / count.
A36: C · DETERMINISTICALLY CALCULATED — HU input mapping
A37: life expectancy (HU) | B37: =IF(HU_leS>HU_ret,HU_leS,HU_defaultLE) | C37: C · calculated | D37: durationOfRetirement + 65, or the default (85).
A38: years on the path (T) | B38: =MAX(HU_le-HU_age,0) | C38: C · calculated
A39: years to retirement | B39: =MAX(HU_ret-HU_age,0) | C39: C · calculated
A40: q(age) column | B40: =IF(HU_gender="Male",1,3)+IF(HU_smoker=TRUE,1,0) | C40: C · calculated | D40: 1 Male, 2 Male smoker, 3 Female, 4 Female smoker.
A41: income / yr (HU) | B41: =1+HU_income*12 | C41: C · calculated | D41: HU adds 1 to the salary.
A42: spend / yr | B42: =HU_expense*12 | C42: C · calculated
A43: retirement spend / yr | B43: =HU_exp0*HU_retLifestyle*HU_retShare | C43: C · calculated | D43: Replaces spend after retirement.
A44: CI income years | B44: =IF(NC_on_N_CRI,HU_ciYearsGP,HU_ciDefaultYears) | C44: C · calculated
A45: CI income share | B45: =MAX(0,MIN(1,HU_exp0/HU_inc0)) | C45: C · calculated | D45: Share of income lost while ill.
A46: savings at t = 0 | B46: =IF(N(HU_cash)=0,1,HU_cash) | C46: C · calculated
A47: equity drift | B47: =IF(HU_inv>0,MAX(HU_minMu,investmentReturn),0) | C47: C · calculated
A48: HU errors (retiree with investments) | B48: =AND(HU_inv>0,HU_dtr=0) | C48: C · calculated | D48: Live HU returns NaN here; this tab still scores (Discrepancies).
A49: alpha | B49: =1+(HU_riskProfile-1)*0.5 | C49: C · calculated | D49: Value-function curvature from riskProfile.
A50: N_EDU withdrawal on the path | B50: =AND(HU_T>0,NC_eduYears<=HU_T) | C50: C · calculated | D50: V0-24: own target year.
A51: N_EDU withdrawal year | B51: =IF(HU_T>0,MOD(NC_eduYears-1,HU_T)+1,0) | C51: C · calculated | D51: fundsNeededYear − now.
A52: N_EDU amount | B52: =NC_on_N_EDU*NC_amount_N_EDU | C52: C · calculated | D52: SAV / PRP: booked as income in the target year and spent again (net 0). EDU: spent.
A53: N_SAV withdrawal on the path | B53: =AND(HU_T>0,NC_savYears<=HU_T) | C53: C · calculated | D53: V0-24: own target year.
A54: N_SAV withdrawal year | B54: =IF(HU_T>0,MOD(NC_savYears-1,HU_T)+1,0) | C54: C · calculated | D54: fundsNeededYear − now.
A55: N_SAV amount | B55: =NC_on_N_SAV*NC_amount_N_SAV | C55: C · calculated | D55: SAV / PRP: booked as income in the target year and spent again (net 0). EDU: spent.
A56: N_PRP withdrawal on the path | B56: =AND(HU_T>0,NC_prpYears<=HU_T) | C56: C · calculated | D56: V0-24: own target year.
A57: N_PRP withdrawal year | B57: =IF(HU_T>0,MOD(NC_prpYears-1,HU_T)+1,0) | C57: C · calculated | D57: fundsNeededYear − now.
A58: N_PRP amount | B58: =NC_on_N_PRP*NC_amount_N_PRP | C58: C · calculated | D58: SAV / PRP: booked as income in the target year and spent again (net 0). EDU: spent.
A60: C · RESULTS — weights, sigmoid, HappiU (0–100)
A61: goals scored | B61: =COUNTIF($J$6:$J$13,TRUE) | C61: C · calculated
A62: consumption goals | B62: =COUNTIFS($J$6:$J$13,TRUE,$R$6:$R$13,"C") | C62: C · calculated | D62: Everything except N_INC / N_ADB / N_RET.
A63: sigmoid divisor | B63: =1+EXP(-HU_nGoals) | C63: C · calculated | D63: Weighted sum ÷ (1 + e^(−number of goals)).
A64: pre (0–1) | B64: =SUMPRODUCT($AA$6:$AA$13,$AF$6:$AF$13)/HU_sig | C64: C · calculated
A65: post (0–1) | B65: =SUMPRODUCT($AB$6:$AB$13,$AF$6:$AF$13)/HU_sig | C65: C · calculated
A66: preHappiU | B66: =ROUND(HU_preRaw*100,0) | C66: C · calculated | D66: Today's cover.
A67: postHappiU | B67: =ROUND(HU_postRaw*100,0) | C67: C · calculated | D67: With the plan's benefits.
A71: year | D71: D · q(age + year) from Assumptions | I71: C · PROBABILITIES | R71: C · EXPECTED CASH FLOWS AND PATHS (alive) | AF71: C · N_INC (W path) | AJ71: C · N_CRI (consumption path) | AN71: C · N_TPD (consumption path) | AR71: C · N_HOS (consumption path) | AV71: C · N_RET (W path) | AZ71: C · N_EDU (consumption path) | BD71: C · N_SAV (consumption path) | BH71: C · N_PRP (consumption path)
A72: year | B72: age | C72: on path | D72: q mortality | E72: q accidental death | F72: q critical illness | G72: q TPD | H72: q dismemberment | I72: alive | J72: score weight | K72: no TPD yet | L72: P(TPD so far) | M72: P(first TPD) | N72: no dismemberment | O72: P(dismembered before) | P72: no CI (running) | Q72: P(CI in window) | R72: inflation index | S72: salary | T72: ss growth index | U72: social-security lump | V72: income + lump + SAV/PRP | W72: expected income cut | X72: income after cut | Y72: spend | Z72: spend + goals | AA72: expected medical | AB72: savings | AC72: equity | AD72: WEALTH | AE72: CONSUMPTION WEALTH | AF72: N_INC weight | AG72: N_INC v pre | AH72: N_INC v rec | AI72: N_INC v full | AJ72: N_CRI weight | AK72: N_CRI v pre | AL72: N_CRI v rec | AM72: N_CRI v full | AN72: N_TPD weight | AO72: N_TPD v pre | AP72: N_TPD v rec | AQ72: N_TPD v full | AR72: N_HOS weight | AS72: N_HOS v pre | AT72: N_HOS v rec | AU72: N_HOS v full | AV72: N_RET weight | AW72: N_RET v pre | AX72: N_RET v rec | AY72: N_RET v full | AZ72: N_EDU weight | BA72: N_EDU v pre | BB72: N_EDU v rec | BC72: N_EDU v full | BD72: N_SAV weight | BE72: N_SAV v pre | BF72: N_SAV v rec | BG72: N_SAV v full | BH72: N_PRP weight | BI72: N_PRP v pre | BJ72: N_PRP v rec | BK72: N_PRP v full
A73: 0 | B73: =HU_age+A73 | C73: =A73<=HU_T | D73: =IF(OR(A73<1,A73>HU_T),0,INDEX(HU_q_mort,HU_age+A73-17,HU_col)) | E73: =IF(OR(A73<1,A73>HU_T),0,INDEX(HU_q_adb,HU_age+A73-17,HU_col)) | F73: =IF(OR(A73<1,A73>HU_T),0,INDEX(HU_q_morb,HU_age+A73-17,HU_col)) | G73: =IF(OR(A73<1,A73>HU_T),0,INDEX(HU_q_ptd,HU_age+A73-17,HU_col)) | H73: =IF(OR(A73<1,A73>HU_T),0,INDEX(HU_q_dis,HU_age+A73-17,HU_col)) | I73: 1 | J73: =IF(A73>=HU_T,0,N(I74)) | K73: 1 | L73: 0 | M73: 0 | N73: 1 | O73: 0 | P73: 1 | Q73: 0 | R73: =(1+inflationRate)^A73 | S73: 0 | T73: 1 | U73: 0 | V73: 0 | W73: 0 | X73: 0 | Y73: 0 | Z73: 0 | AA73: 0 | AB73: =HU_cash0 | AC73: =IF(A73>HU_T,0,HU_inv*EXP(HU_mu*A73)) | AD73: =IF(A73>HU_T,0,MAX(0,AC73+AB73)) | AE73: 0 | AF73: =IF(AND($J$6,A73>=1,A73<=$Q$6-1),J73,0) | AG73: =IF(OR(AF73=0,$S$6=0),0,IF((AD73+$L$6)>$S$6/HU_alpha+$K$6,0.5*$S$6/HU_alpha,IF((AD73+$L$6)>=$K$6,((AD73+$L$6)-$K$6)-0.5*HU_alpha/$S$6*((AD73+$L$6)-$K$6)^2,IF((AD73+$L$6)>=$T$6,HU_beta*((AD73+$L$6)-$K$6),HU_beta*($T$6-$K$6))))) | AH73: =IF(OR(AF73=0,$S$6=0),0,IF((AD73+$L$6+$N$6)>$S$6/HU_alpha+$K$6,0.5*$S$6/HU_alpha,IF((AD73+$L$6+$N$6)>=$K$6,((AD73+$L$6+$N$6)-$K$6)-0.5*HU_alpha/$S$6*((AD73+$L$6+$N$6)-$K$6)^2,IF((AD73+$L$6+$N$6)>=$T$6,HU_beta*((AD73+$L$6+$N$6)-$K$6),HU_beta*($T$6-$K$6))))) | AI73: =IF(OR(AF73=0,$S$6=0),0,IF((AD73+$K$6)>$S$6/HU_alpha+$K$6,0.5*$S$6/HU_alpha,IF((AD73+$K$6)>=$K$6,((AD73+$K$6)-$K$6)-0.5*HU_alpha/$S$6*((AD73+$K$6)-$K$6)^2,IF((AD73+$K$6)>=$T$6,HU_beta*((AD73+$K$6)-$K$6),HU_beta*($T$6-$K$6))))) | AJ73: =IF(AND($J$7,A73>=1,A73<=$Q$7-1),J73,0) | AK73: =IF(OR(AJ73=0,$S$7=0),0,IF((AE73+$L$7)>$S$7/HU_alpha+$K$7,0.5*$S$7/HU_alpha,IF((AE73+$L$7)>=$K$7,((AE73+$L$7)-$K$7)-0.5*HU_alpha/$S$7*((AE73+$L$7)-$K$7)^2,IF((AE73+$L$7)>=$T$7,HU_beta*((AE73+$L$7)-$K$7),HU_beta*($T$7-$K$7))))) | AL73: =IF(OR(AJ73=0,$S$7=0),0,IF((AE73+$L$7+$N$7)>$S$7/HU_alpha+$K$7,0.5*$S$7/HU_alpha,IF((AE73+$L$7+$N$7)>=$K$7,((AE73+$L$7+$N$7)-$K$7)-0.5*HU_alpha/$S$7*((AE73+$L$7+$N$7)-$K$7)^2,IF((AE73+$L$7+$N$7)>=$T$7,HU_beta*((AE73+$L$7+$N$7)-$K$7),HU_beta*($T$7-$K$7))))) | AM73: =IF(OR(AJ73=0,$S$7=0),0,IF((AE73+$K$7)>$S$7/HU_alpha+$K$7,0.5*$S$7/HU_alpha,IF((AE73+$K$7)>=$K$7,((AE73+$K$7)-$K$7)-0.5*HU_alpha/$S$7*((AE73+$K$7)-$K$7)^2,IF((AE73+$K$7)>=$T$7,HU_beta*((AE73+$K$7)-$K$7),HU_beta*($T$7-$K$7))))) | AN73: =IF(AND($J$8,A73>=1,A73<=$Q$8-1),J73,0) | AO73: =IF(OR(AN73=0,$S$8=0),0,IF((AE73+$L$8)>$S$8/HU_alpha+$K$8,0.5*$S$8/HU_alpha,IF((AE73+$L$8)>=$K$8,((AE73+$L$8)-$K$8)-0.5*HU_alpha/$S$8*((AE73+$L$8)-$K$8)^2,IF((AE73+$L$8)>=$T$8,HU_beta*((AE73+$L$8)-$K$8),HU_beta*($T$8-$K$8))))) | AP73: =IF(OR(AN73=0,$S$8=0),0,IF((AE73+$L$8+$N$8)>$S$8/HU_alpha+$K$8,0.5*$S$8/HU_alpha,IF((AE73+$L$8+$N$8)>=$K$8,((AE73+$L$8+$N$8)-$K$8)-0.5*HU_alpha/$S$8*((AE73+$L$8+$N$8)-$K$8)^2,IF((AE73+$L$8+$N$8)>=$T$8,HU_beta*((AE73+$L$8+$N$8)-$K$8),HU_beta*($T$8-$K$8))))) | AQ73: =IF(OR(AN73=0,$S$8=0),0,IF((AE73+$K$8)>$S$8/HU_alpha+$K$8,0.5*$S$8/HU_alpha,IF((AE73+$K$8)>=$K$8,((AE73+$K$8)-$K$8)-0.5*HU_alpha/$S$8*((AE73+$K$8)-$K$8)^2,IF((AE73+$K$8)>=$T$8,HU_beta*((AE73+$K$8)-$K$8),HU_beta*($T$8-$K$8))))) | AR73: =IF(AND($J$9,A73>=1,A73<=$Q$9-1),J73,0) | AS73: =IF(OR(AR73=0,$S$9=0),0,IF((AE73+$L$9)>$S$9/HU_alpha+$K$9,0.5*$S$9/HU_alpha,IF((AE73+$L$9)>=$K$9,((AE73+$L$9)-$K$9)-0.5*HU_alpha/$S$9*((AE73+$L$9)-$K$9)^2,IF((AE73+$L$9)>=$T$9,HU_beta*((AE73+$L$9)-$K$9),HU_beta*($T$9-$K$9))))) | AT73: =IF(OR(AR73=0,$S$9=0),0,IF((AE73+$L$9+$N$9)>$S$9/HU_alpha+$K$9,0.5*$S$9/HU_alpha,IF((AE73+$L$9+$N$9)>=$K$9,((AE73+$L$9+$N$9)-$K$9)-0.5*HU_alpha/$S$9*((AE73+$L$9+$N$9)-$K$9)^2,IF((AE73+$L$9+$N$9)>=$T$9,HU_beta*((AE73+$L$9+$N$9)-$K$9),HU_beta*($T$9-$K$9))))) | AU73: =IF(OR(AR73=0,$S$9=0),0,IF((AE73+$K$9)>$S$9/HU_alpha+$K$9,0.5*$S$9/HU_alpha,IF((AE73+$K$9)>=$K$9,((AE73+$K$9)-$K$9)-0.5*HU_alpha/$S$9*((AE73+$K$9)-$K$9)^2,IF((AE73+$K$9)>=$T$9,HU_beta*((AE73+$K$9)-$K$9),HU_beta*($T$9-$K$9))))) | AV73: =IF(AND($J$10,A73=$Q$10),J73,0) | AW73: =IF(OR(AV73=0,$S$10=0),0,IF((AD73+$L$10)>$S$10/HU_alpha+$K$10,0.5*$S$10/HU_alpha,IF((AD73+$L$10)>=$K$10,((AD73+$L$10)-$K$10)-0.5*HU_alpha/$S$10*((AD73+$L$10)-$K$10)^2,IF((AD73+$L$10)>=$T$10,HU_beta*((AD73+$L$10)-$K$10),HU_beta*($T$10-$K$10))))) | AX73: =IF(OR(AV73=0,$S$10=0),0,IF((AD73+$L$10+$N$10)>$S$10/HU_alpha+$K$10,0.5*$S$10/HU_alpha,IF((AD73+$L$10+$N$10)>=$K$10,((AD73+$L$10+$N$10)-$K$10)-0.5*HU_alpha/$S$10*((AD73+$L$10+$N$10)-$K$10)^2,IF((AD73+$L$10+$N$10)>=$T$10,HU_beta*((AD73+$L$10+$N$10)-$K$10),HU_beta*($T$10-$K$10))))) | AY73: =IF(OR(AV73=0,$S$10=0),0,IF((AD73+$K$10)>$S$10/HU_alpha+$K$10,0.5*$S$10/HU_alpha,IF((AD73+$K$10)>=$K$10,((AD73+$K$10)-$K$10)-0.5*HU_alpha/$S$10*((AD73+$K$10)-$K$10)^2,IF((AD73+$K$10)>=$T$10,HU_beta*((AD73+$K$10)-$K$10),HU_beta*($T$10-$K$10))))) | AZ73: =IF(AND($J$11,A73=$Q$11),J73,0) | BA73: =IF(OR(AZ73=0,$S$11=0),0,IF((AE73+$L$11)>$S$11/HU_alpha+$K$11,0.5*$S$11/HU_alpha,IF((AE73+$L$11)>=$K$11,((AE73+$L$11)-$K$11)-0.5*HU_alpha/$S$11*((AE73+$L$11)-$K$11)^2,IF((AE73+$L$11)>=$T$11,HU_beta*((AE73+$L$11)-$K$11),HU_beta*($T$11-$K$11))))) | BB73: =IF(OR(AZ73=0,$S$11=0),0,IF((AE73+$L$11+$N$11)>$S$11/HU_alpha+$K$11,0.5*$S$11/HU_alpha,IF((AE73+$L$11+$N$11)>=$K$11,((AE73+$L$11+$N$11)-$K$11)-0.5*HU_alpha/$S$11*((AE73+$L$11+$N$11)-$K$11)^2,IF((AE73+$L$11+$N$11)>=$T$11,HU_beta*((AE73+$L$11+$N$11)-$K$11),HU_beta*($T$11-$K$11))))) | BC73: =IF(OR(AZ73=0,$S$11=0),0,IF((AE73+$K$11)>$S$11/HU_alpha+$K$11,0.5*$S$11/HU_alpha,IF((AE73+$K$11)>=$K$11,((AE73+$K$11)-$K$11)-0.5*HU_alpha/$S$11*((AE73+$K$11)-$K$11)^2,IF((AE73+$K$11)>=$T$11,HU_beta*((AE73+$K$11)-$K$11),HU_beta*($T$11-$K$11))))) | BD73: =IF(AND($J$12,A73=$Q$12),J73,0) | BE73: =IF(OR(BD73=0,$S$12=0),0,IF((AE73+$L$12)>$S$12/HU_alpha+$K$12,0.5*$S$12/HU_alpha,IF((AE73+$L$12)>=$K$12,((AE73+$L$12)-$K$12)-0.5*HU_alpha/$S$12*((AE73+$L$12)-$K$12)^2,IF((AE73+$L$12)>=$T$12,HU_beta*((AE73+$L$12)-$K$12),HU_beta*($T$12-$K$12))))) | BF73: =IF(OR(BD73=0,$S$12=0),0,IF((AE73+$L$12+$N$12)>$S$12/HU_alpha+$K$12,0.5*$S$12/HU_alpha,IF((AE73+$L$12+$N$12)>=$K$12,((AE73+$L$12+$N$12)-$K$12)-0.5*HU_alpha/$S$12*((AE73+$L$12+$N$12)-$K$12)^2,IF((AE73+$L$12+$N$12)>=$T$12,HU_beta*((AE73+$L$12+$N$12)-$K$12),HU_beta*($T$12-$K$12))))) | BG73: =IF(OR(BD73=0,$S$12=0),0,IF((AE73+$K$12)>$S$12/HU_alpha+$K$12,0.5*$S$12/HU_alpha,IF((AE73+$K$12)>=$K$12,((AE73+$K$12)-$K$12)-0.5*HU_alpha/$S$12*((AE73+$K$12)-$K$12)^2,IF((AE73+$K$12)>=$T$12,HU_beta*((AE73+$K$12)-$K$12),HU_beta*($T$12-$K$12))))) | BH73: =IF(AND($J$13,A73=$Q$13),J73,0) | BI73: =IF(OR(BH73=0,$S$13=0),0,IF((AE73+$L$13)>$S$13/HU_alpha+$K$13,0.5*$S$13/HU_alpha,IF((AE73+$L$13)>=$K$13,((AE73+$L$13)-$K$13)-0.5*HU_alpha/$S$13*((AE73+$L$13)-$K$13)^2,IF((AE73+$L$13)>=$T$13,HU_beta*((AE73+$L$13)-$K$13),HU_beta*($T$13-$K$13))))) | BJ73: =IF(OR(BH73=0,$S$13=0),0,IF((AE73+$L$13+$N$13)>$S$13/HU_alpha+$K$13,0.5*$S$13/HU_alpha,IF((AE73+$L$13+$N$13)>=$K$13,((AE73+$L$13+$N$13)-$K$13)-0.5*HU_alpha/$S$13*((AE73+$L$13+$N$13)-$K$13)^2,IF((AE73+$L$13+$N$13)>=$T$13,HU_beta*((AE73+$L$13+$N$13)-$K$13),HU_beta*($T$13-$K$13))))) | BK73: =IF(OR(BH73=0,$S$13=0),0,IF((AE73+$K$13)>$S$13/HU_alpha+$K$13,0.5*$S$13/HU_alpha,IF((AE73+$K$13)>=$K$13,((AE73+$K$13)-$K$13)-0.5*HU_alpha/$S$13*((AE73+$K$13)-$K$13)^2,IF((AE73+$K$13)>=$T$13,HU_beta*((AE73+$K$13)-$K$13),HU_beta*($T$13-$K$13)))))
A74: 1 | B74: =HU_age+A74 | C74: =A74<=HU_T | D74: =IF(OR(A74<1,A74>HU_T),0,INDEX(HU_q_mort,HU_age+A74-17,HU_col)) | E74: =IF(OR(A74<1,A74>HU_T),0,INDEX(HU_q_adb,HU_age+A74-17,HU_col)) | F74: =IF(OR(A74<1,A74>HU_T),0,INDEX(HU_q_morb,HU_age+A74-17,HU_col)) | G74: =IF(OR(A74<1,A74>HU_T),0,INDEX(HU_q_ptd,HU_age+A74-17,HU_col)) | H74: =IF(OR(A74<1,A74>HU_T),0,INDEX(HU_q_dis,HU_age+A74-17,HU_col)) | I74: =IF(A74>HU_T,0,I73*(1-D74)*(1-E74)) | J74: =IF(A74>=HU_T,0,N(I75)) | K74: =K73*(1-G74) | L74: =1-K74 | M74: =K73*G74 | N74: =N73*(1-H74) | O74: =1-N73 | P74: =P73*(1-F74) | Q74: =1-P73/INDEX($P$73:$P$155,MAX(1,A74-HU_ciYears)) | R74: =(1+inflationRate)^A74 | S74: =IF(OR(OR(A74<1,A74>HU_T),A74-1>=HU_dtr),0,HU_inc0*(1+incomeGrowthRate)^A74) | T74: =IF(A74>HU_T,T73,T73*(1+INDEX(HU_ssG,HU_age+A74-17))) | U74: =IF(AND(HU_dtr>=1,A74=HU_dtr,A74<=HU_T),MIN(S74*INDEX(HU_ssC,HU_age+A74-17)/(1-INDEX(HU_ssC,HU_age+A74-17)),INDEX(HU_ssCap,HU_age+A74-17))*T74,0) | V74: =S74+U74+IF(AND(HU_wdSAVOn,A74=HU_wdSAVYear),HU_wdSAVAmt,0)+IF(AND(HU_wdPRPOn,A74=HU_wdPRPYear),HU_wdPRPAmt,0) | W74: =HU_ciProp*Q74+HU_tpdCut*L74+HU_disCut*O74 | X74: =IF(OR(A74<1,A74>HU_T),0,V74*(1-W74)) | Y74: =IF(OR(A74<1,A74>HU_T),0,IF(AND(HU_retExp>0,A74-1>=HU_dtr),HU_retExp,HU_exp0)*R74) | Z74: =-Y74-IF(AND(HU_wdEDUOn,A74=HU_wdEDUYear),HU_wdEDUAmt,0)-IF(AND(HU_wdSAVOn,A74=HU_wdSAVYear),HU_wdSAVAmt,0)-IF(AND(HU_wdPRPOn,A74=HU_wdPRPYear),HU_wdPRPAmt,0) | AA74: =IF(OR(A74<1,A74>HU_T),0,-HU_medCost*R74*F74-HU_tpdCost*R74*M74) | AB74: =IF(A74>HU_T,0,AB73*(1+interestRate)+X74+Z74+AA74) | AC74: =IF(A74>HU_T,0,HU_inv*EXP(HU_mu*A74)) | AD74: =IF(A74>HU_T,0,MAX(0,AC74+AB74)) | AE74: =IF(A74>HU_T,0,MAX(0,X74-Y74)) | AF74: =IF(AND($J$6,A74>=1,A74<=$Q$6-1),J74,0) | AG74: =IF(OR(AF74=0,$S$6=0),0,IF((AD74+$L$6)>$S$6/HU_alpha+$K$6,0.5*$S$6/HU_alpha,IF((AD74+$L$6)>=$K$6,((AD74+$L$6)-$K$6)-0.5*HU_alpha/$S$6*((AD74+$L$6)-$K$6)^2,IF((AD74+$L$6)>=$T$6,HU_beta*((AD74+$L$6)-$K$6),HU_beta*($T$6-$K$6))))) | AH74: =IF(OR(AF74=0,$S$6=0),0,IF((AD74+$L$6+$N$6)>$S$6/HU_alpha+$K$6,0.5*$S$6/HU_alpha,IF((AD74+$L$6+$N$6)>=$K$6,((AD74+$L$6+$N$6)-$K$6)-0.5*HU_alpha/$S$6*((AD74+$L$6+$N$6)-$K$6)^2,IF((AD74+$L$6+$N$6)>=$T$6,HU_beta*((AD74+$L$6+$N$6)-$K$6),HU_beta*($T$6-$K$6))))) | AI74: =IF(OR(AF74=0,$S$6=0),0,IF((AD74+$K$6)>$S$6/HU_alpha+$K$6,0.5*$S$6/HU_alpha,IF((AD74+$K$6)>=$K$6,((AD74+$K$6)-$K$6)-0.5*HU_alpha/$S$6*((AD74+$K$6)-$K$6)^2,IF((AD74+$K$6)>=$T$6,HU_beta*((AD74+$K$6)-$K$6),HU_beta*($T$6-$K$6))))) | AJ74: =IF(AND($J$7,A74>=1,A74<=$Q$7-1),J74,0) | AK74: =IF(OR(AJ74=0,$S$7=0),0,IF((AE74+$L$7)>$S$7/HU_alpha+$K$7,0.5*$S$7/HU_alpha,IF((AE74+$L$7)>=$K$7,((AE74+$L$7)-$K$7)-0.5*HU_alpha/$S$7*((AE74+$L$7)-$K$7)^2,IF((AE74+$L$7)>=$T$7,HU_beta*((AE74+$L$7)-$K$7),HU_beta*($T$7-$K$7))))) | AL74: =IF(OR(AJ74=0,$S$7=0),0,IF((AE74+$L$7+$N$7)>$S$7/HU_alpha+$K$7,0.5*$S$7/HU_alpha,IF((AE74+$L$7+$N$7)>=$K$7,((AE74+$L$7+$N$7)-$K$7)-0.5*HU_alpha/$S$7*((AE74+$L$7+$N$7)-$K$7)^2,IF((AE74+$L$7+$N$7)>=$T$7,HU_beta*((AE74+$L$7+$N$7)-$K$7),HU_beta*($T$7-$K$7))))) | AM74: =IF(OR(AJ74=0,$S$7=0),0,IF((AE74+$K$7)>$S$7/HU_alpha+$K$7,0.5*$S$7/HU_alpha,IF((AE74+$K$7)>=$K$7,((AE74+$K$7)-$K$7)-0.5*HU_alpha/$S$7*((AE74+$K$7)-$K$7)^2,IF((AE74+$K$7)>=$T$7,HU_beta*((AE74+$K$7)-$K$7),HU_beta*($T$7-$K$7))))) | AN74: =IF(AND($J$8,A74>=1,A74<=$Q$8-1),J74,0) | AO74: =IF(OR(AN74=0,$S$8=0),0,IF((AE74+$L$8)>$S$8/HU_alpha+$K$8,0.5*$S$8/HU_alpha,IF((AE74+$L$8)>=$K$8,((AE74+$L$8)-$K$8)-0.5*HU_alpha/$S$8*((AE74+$L$8)-$K$8)^2,IF((AE74+$L$8)>=$T$8,HU_beta*((AE74+$L$8)-$K$8),HU_beta*($T$8-$K$8))))) | AP74: =IF(OR(AN74=0,$S$8=0),0,IF((AE74+$L$8+$N$8)>$S$8/HU_alpha+$K$8,0.5*$S$8/HU_alpha,IF((AE74+$L$8+$N$8)>=$K$8,((AE74+$L$8+$N$8)-$K$8)-0.5*HU_alpha/$S$8*((AE74+$L$8+$N$8)-$K$8)^2,IF((AE74+$L$8+$N$8)>=$T$8,HU_beta*((AE74+$L$8+$N$8)-$K$8),HU_beta*($T$8-$K$8))))) | AQ74: =IF(OR(AN74=0,$S$8=0),0,IF((AE74+$K$8)>$S$8/HU_alpha+$K$8,0.5*$S$8/HU_alpha,IF((AE74+$K$8)>=$K$8,((AE74+$K$8)-$K$8)-0.5*HU_alpha/$S$8*((AE74+$K$8)-$K$8)^2,IF((AE74+$K$8)>=$T$8,HU_beta*((AE74+$K$8)-$K$8),HU_beta*($T$8-$K$8))))) | AR74: =IF(AND($J$9,A74>=1,A74<=$Q$9-1),J74,0) | AS74: =IF(OR(AR74=0,$S$9=0),0,IF((AE74+$L$9)>$S$9/HU_alpha+$K$9,0.5*$S$9/HU_alpha,IF((AE74+$L$9)>=$K$9,((AE74+$L$9)-$K$9)-0.5*HU_alpha/$S$9*((AE74+$L$9)-$K$9)^2,IF((AE74+$L$9)>=$T$9,HU_beta*((AE74+$L$9)-$K$9),HU_beta*($T$9-$K$9))))) | AT74: =IF(OR(AR74=0,$S$9=0),0,IF((AE74+$L$9+$N$9)>$S$9/HU_alpha+$K$9,0.5*$S$9/HU_alpha,IF((AE74+$L$9+$N$9)>=$K$9,((AE74+$L$9+$N$9)-$K$9)-0.5*HU_alpha/$S$9*((AE74+$L$9+$N$9)-$K$9)^2,IF((AE74+$L$9+$N$9)>=$T$9,HU_beta*((AE74+$L$9+$N$9)-$K$9),HU_beta*($T$9-$K$9))))) | AU74: =IF(OR(AR74=0,$S$9=0),0,IF((AE74+$K$9)>$S$9/HU_alpha+$K$9,0.5*$S$9/HU_alpha,IF((AE74+$K$9)>=$K$9,((AE74+$K$9)-$K$9)-0.5*HU_alpha/$S$9*((AE74+$K$9)-$K$9)^2,IF((AE74+$K$9)>=$T$9,HU_beta*((AE74+$K$9)-$K$9),HU_beta*($T$9-$K$9))))) | AV74: =IF(AND($J$10,A74=$Q$10),J74,0) | AW74: =IF(OR(AV74=0,$S$10=0),0,IF((AD74+$L$10)>$S$10/HU_alpha+$K$10,0.5*$S$10/HU_alpha,IF((AD74+$L$10)>=$K$10,((AD74+$L$10)-$K$10)-0.5*HU_alpha/$S$10*((AD74+$L$10)-$K$10)^2,IF((AD74+$L$10)>=$T$10,HU_beta*((AD74+$L$10)-$K$10),HU_beta*($T$10-$K$10))))) | AX74: =IF(OR(AV74=0,$S$10=0),0,IF((AD74+$L$10+$N$10)>$S$10/HU_alpha+$K$10,0.5*$S$10/HU_alpha,IF((AD74+$L$10+$N$10)>=$K$10,((AD74+$L$10+$N$10)-$K$10)-0.5*HU_alpha/$S$10*((AD74+$L$10+$N$10)-$K$10)^2,IF((AD74+$L$10+$N$10)>=$T$10,HU_beta*((AD74+$L$10+$N$10)-$K$10),HU_beta*($T$10-$K$10))))) | AY74: =IF(OR(AV74=0,$S$10=0),0,IF((AD74+$K$10)>$S$10/HU_alpha+$K$10,0.5*$S$10/HU_alpha,IF((AD74+$K$10)>=$K$10,((AD74+$K$10)-$K$10)-0.5*HU_alpha/$S$10*((AD74+$K$10)-$K$10)^2,IF((AD74+$K$10)>=$T$10,HU_beta*((AD74+$K$10)-$K$10),HU_beta*($T$10-$K$10))))) | AZ74: =IF(AND($J$11,A74=$Q$11),J74,0) | BA74: =IF(OR(AZ74=0,$S$11=0),0,IF((AE74+$L$11)>$S$11/HU_alpha+$K$11,0.5*$S$11/HU_alpha,IF((AE74+$L$11)>=$K$11,((AE74+$L$11)-$K$11)-0.5*HU_alpha/$S$11*((AE74+$L$11)-$K$11)^2,IF((AE74+$L$11)>=$T$11,HU_beta*((AE74+$L$11)-$K$11),HU_beta*($T$11-$K$11))))) | BB74: =IF(OR(AZ74=0,$S$11=0),0,IF((AE74+$L$11+$N$11)>$S$11/HU_alpha+$K$11,0.5*$S$11/HU_alpha,IF((AE74+$L$11+$N$11)>=$K$11,((AE74+$L$11+$N$11)-$K$11)-0.5*HU_alpha/$S$11*((AE74+$L$11+$N$11)-$K$11)^2,IF((AE74+$L$11+$N$11)>=$T$11,HU_beta*((AE74+$L$11+$N$11)-$K$11),HU_beta*($T$11-$K$11))))) | BC74: =IF(OR(AZ74=0,$S$11=0),0,IF((AE74+$K$11)>$S$11/HU_alpha+$K$11,0.5*$S$11/HU_alpha,IF((AE74+$K$11)>=$K$11,((AE74+$K$11)-$K$11)-0.5*HU_alpha/$S$11*((AE74+$K$11)-$K$11)^2,IF((AE74+$K$11)>=$T$11,HU_beta*((AE74+$K$11)-$K$11),HU_beta*($T$11-$K$11))))) | BD74: =IF(AND($J$12,A74=$Q$12),J74,0) | BE74: =IF(OR(BD74=0,$S$12=0),0,IF((AE74+$L$12)>$S$12/HU_alpha+$K$12,0.5*$S$12/HU_alpha,IF((AE74+$L$12)>=$K$12,((AE74+$L$12)-$K$12)-0.5*HU_alpha/$S$12*((AE74+$L$12)-$K$12)^2,IF((AE74+$L$12)>=$T$12,HU_beta*((AE74+$L$12)-$K$12),HU_beta*($T$12-$K$12))))) | BF74: =IF(OR(BD74=0,$S$12=0),0,IF((AE74+$L$12+$N$12)>$S$12/HU_alpha+$K$12,0.5*$S$12/HU_alpha,IF((AE74+$L$12+$N$12)>=$K$12,((AE74+$L$12+$N$12)-$K$12)-0.5*HU_alpha/$S$12*((AE74+$L$12+$N$12)-$K$12)^2,IF((AE74+$L$12+$N$12)>=$T$12,HU_beta*((AE74+$L$12+$N$12)-$K$12),HU_beta*($T$12-$K$12))))) | BG74: =IF(OR(BD74=0,$S$12=0),0,IF((AE74+$K$12)>$S$12/HU_alpha+$K$12,0.5*$S$12/HU_alpha,IF((AE74+$K$12)>=$K$12,((AE74+$K$12)-$K$12)-0.5*HU_alpha/$S$12*((AE74+$K$12)-$K$12)^2,IF((AE74+$K$12)>=$T$12,HU_beta*((AE74+$K$12)-$K$12),HU_beta*($T$12-$K$12))))) | BH74: =IF(AND($J$13,A74=$Q$13),J74,0) | BI74: =IF(OR(BH74=0,$S$13=0),0,IF((AE74+$L$13)>$S$13/HU_alpha+$K$13,0.5*$S$13/HU_alpha,IF((AE74+$L$13)>=$K$13,((AE74+$L$13)-$K$13)-0.5*HU_alpha/$S$13*((AE74+$L$13)-$K$13)^2,IF((AE74+$L$13)>=$T$13,HU_beta*((AE74+$L$13)-$K$13),HU_beta*($T$13-$K$13))))) | BJ74: =IF(OR(BH74=0,$S$13=0),0,IF((AE74+$L$13+$N$13)>$S$13/HU_alpha+$K$13,0.5*$S$13/HU_alpha,IF((AE74+$L$13+$N$13)>=$K$13,((AE74+$L$13+$N$13)-$K$13)-0.5*HU_alpha/$S$13*((AE74+$L$13+$N$13)-$K$13)^2,IF((AE74+$L$13+$N$13)>=$T$13,HU_beta*((AE74+$L$13+$N$13)-$K$13),HU_beta*($T$13-$K$13))))) | BK74: =IF(OR(BH74=0,$S$13=0),0,IF((AE74+$K$13)>$S$13/HU_alpha+$K$13,0.5*$S$13/HU_alpha,IF((AE74+$K$13)>=$K$13,((AE74+$K$13)-$K$13)-0.5*HU_alpha/$S$13*((AE74+$K$13)-$K$13)^2,IF((AE74+$K$13)>=$T$13,HU_beta*((AE74+$K$13)-$K$13),HU_beta*($T$13-$K$13)))))
A75: 2 | B75: =HU_age+A75 | C75: =A75<=HU_T | D75: =IF(OR(A75<1,A75>HU_T),0,INDEX(HU_q_mort,HU_age+A75-17,HU_col)) | E75: =IF(OR(A75<1,A75>HU_T),0,INDEX(HU_q_adb,HU_age+A75-17,HU_col)) | F75: =IF(OR(A75<1,A75>HU_T),0,INDEX(HU_q_morb,HU_age+A75-17,HU_col)) | G75: =IF(OR(A75<1,A75>HU_T),0,INDEX(HU_q_ptd,HU_age+A75-17,HU_col)) | H75: =IF(OR(A75<1,A75>HU_T),0,INDEX(HU_q_dis,HU_age+A75-17,HU_col)) | I75: =IF(A75>HU_T,0,I74*(1-D75)*(1-E75)) | J75: =IF(A75>=HU_T,0,N(I76)) | K75: =K74*(1-G75) | L75: =1-K75 | M75: =K74*G75 | N75: =N74*(1-H75) | O75: =1-N74 | P75: =P74*(1-F75) | Q75: =1-P74/INDEX($P$73:$P$155,MAX(1,A75-HU_ciYears)) | R75: =(1+inflationRate)^A75 | S75: =IF(OR(OR(A75<1,A75>HU_T),A75-1>=HU_dtr),0,HU_inc0*(1+incomeGrowthRate)^A75) | T75: =IF(A75>HU_T,T74,T74*(1+INDEX(HU_ssG,HU_age+A75-17))) | U75: =IF(AND(HU_dtr>=1,A75=HU_dtr,A75<=HU_T),MIN(S75*INDEX(HU_ssC,HU_age+A75-17)/(1-INDEX(HU_ssC,HU_age+A75-17)),INDEX(HU_ssCap,HU_age+A75-17))*T75,0) | V75: =S75+U75+IF(AND(HU_wdSAVOn,A75=HU_wdSAVYear),HU_wdSAVAmt,0)+IF(AND(HU_wdPRPOn,A75=HU_wdPRPYear),HU_wdPRPAmt,0) | W75: =HU_ciProp*Q75+HU_tpdCut*L75+HU_disCut*O75 | X75: =IF(OR(A75<1,A75>HU_T),0,V75*(1-W75)) | Y75: =IF(OR(A75<1,A75>HU_T),0,IF(AND(HU_retExp>0,A75-1>=HU_dtr),HU_retExp,HU_exp0)*R75) | Z75: =-Y75-IF(AND(HU_wdEDUOn,A75=HU_wdEDUYear),HU_wdEDUAmt,0)-IF(AND(HU_wdSAVOn,A75=HU_wdSAVYear),HU_wdSAVAmt,0)-IF(AND(HU_wdPRPOn,A75=HU_wdPRPYear),HU_wdPRPAmt,0) | AA75: =IF(OR(A75<1,A75>HU_T),0,-HU_medCost*R75*F75-HU_tpdCost*R75*M75) | AB75: =IF(A75>HU_T,0,AB74*(1+interestRate)+X75+Z75+AA75) | AC75: =IF(A75>HU_T,0,HU_inv*EXP(HU_mu*A75)) | AD75: =IF(A75>HU_T,0,MAX(0,AC75+AB75)) | AE75: =IF(A75>HU_T,0,MAX(0,X75-Y75)) | AF75: =IF(AND($J$6,A75>=1,A75<=$Q$6-1),J75,0) | AG75: =IF(OR(AF75=0,$S$6=0),0,IF((AD75+$L$6)>$S$6/HU_alpha+$K$6,0.5*$S$6/HU_alpha,IF((AD75+$L$6)>=$K$6,((AD75+$L$6)-$K$6)-0.5*HU_alpha/$S$6*((AD75+$L$6)-$K$6)^2,IF((AD75+$L$6)>=$T$6,HU_beta*((AD75+$L$6)-$K$6),HU_beta*($T$6-$K$6))))) | AH75: =IF(OR(AF75=0,$S$6=0),0,IF((AD75+$L$6+$N$6)>$S$6/HU_alpha+$K$6,0.5*$S$6/HU_alpha,IF((AD75+$L$6+$N$6)>=$K$6,((AD75+$L$6+$N$6)-$K$6)-0.5*HU_alpha/$S$6*((AD75+$L$6+$N$6)-$K$6)^2,IF((AD75+$L$6+$N$6)>=$T$6,HU_beta*((AD75+$L$6+$N$6)-$K$6),HU_beta*($T$6-$K$6))))) | AI75: =IF(OR(AF75=0,$S$6=0),0,IF((AD75+$K$6)>$S$6/HU_alpha+$K$6,0.5*$S$6/HU_alpha,IF((AD75+$K$6)>=$K$6,((AD75+$K$6)-$K$6)-0.5*HU_alpha/$S$6*((AD75+$K$6)-$K$6)^2,IF((AD75+$K$6)>=$T$6,HU_beta*((AD75+$K$6)-$K$6),HU_beta*($T$6-$K$6))))) | AJ75: =IF(AND($J$7,A75>=1,A75<=$Q$7-1),J75,0) | AK75: =IF(OR(AJ75=0,$S$7=0),0,IF((AE75+$L$7)>$S$7/HU_alpha+$K$7,0.5*$S$7/HU_alpha,IF((AE75+$L$7)>=$K$7,((AE75+$L$7)-$K$7)-0.5*HU_alpha/$S$7*((AE75+$L$7)-$K$7)^2,IF((AE75+$L$7)>=$T$7,HU_beta*((AE75+$L$7)-$K$7),HU_beta*($T$7-$K$7))))) | AL75: =IF(OR(AJ75=0,$S$7=0),0,IF((AE75+$L$7+$N$7)>$S$7/HU_alpha+$K$7,0.5*$S$7/HU_alpha,IF((AE75+$L$7+$N$7)>=$K$7,((AE75+$L$7+$N$7)-$K$7)-0.5*HU_alpha/$S$7*((AE75+$L$7+$N$7)-$K$7)^2,IF((AE75+$L$7+$N$7)>=$T$7,HU_beta*((AE75+$L$7+$N$7)-$K$7),HU_beta*($T$7-$K$7))))) | AM75: =IF(OR(AJ75=0,$S$7=0),0,IF((AE75+$K$7)>$S$7/HU_alpha+$K$7,0.5*$S$7/HU_alpha,IF((AE75+$K$7)>=$K$7,((AE75+$K$7)-$K$7)-0.5*HU_alpha/$S$7*((AE75+$K$7)-$K$7)^2,IF((AE75+$K$7)>=$T$7,HU_beta*((AE75+$K$7)-$K$7),HU_beta*($T$7-$K$7))))) | AN75: =IF(AND($J$8,A75>=1,A75<=$Q$8-1),J75,0) | AO75: =IF(OR(AN75=0,$S$8=0),0,IF((AE75+$L$8)>$S$8/HU_alpha+$K$8,0.5*$S$8/HU_alpha,IF((AE75+$L$8)>=$K$8,((AE75+$L$8)-$K$8)-0.5*HU_alpha/$S$8*((AE75+$L$8)-$K$8)^2,IF((AE75+$L$8)>=$T$8,HU_beta*((AE75+$L$8)-$K$8),HU_beta*($T$8-$K$8))))) | AP75: =IF(OR(AN75=0,$S$8=0),0,IF((AE75+$L$8+$N$8)>$S$8/HU_alpha+$K$8,0.5*$S$8/HU_alpha,IF((AE75+$L$8+$N$8)>=$K$8,((AE75+$L$8+$N$8)-$K$8)-0.5*HU_alpha/$S$8*((AE75+$L$8+$N$8)-$K$8)^2,IF((AE75+$L$8+$N$8)>=$T$8,HU_beta*((AE75+$L$8+$N$8)-$K$8),HU_beta*($T$8-$K$8))))) | AQ75: =IF(OR(AN75=0,$S$8=0),0,IF((AE75+$K$8)>$S$8/HU_alpha+$K$8,0.5*$S$8/HU_alpha,IF((AE75+$K$8)>=$K$8,((AE75+$K$8)-$K$8)-0.5*HU_alpha/$S$8*((AE75+$K$8)-$K$8)^2,IF((AE75+$K$8)>=$T$8,HU_beta*((AE75+$K$8)-$K$8),HU_beta*($T$8-$K$8))))) | AR75: =IF(AND($J$9,A75>=1,A75<=$Q$9-1),J75,0) | AS75: =IF(OR(AR75=0,$S$9=0),0,IF((AE75+$L$9)>$S$9/HU_alpha+$K$9,0.5*$S$9/HU_alpha,IF((AE75+$L$9)>=$K$9,((AE75+$L$9)-$K$9)-0.5*HU_alpha/$S$9*((AE75+$L$9)-$K$9)^2,IF((AE75+$L$9)>=$T$9,HU_beta*((AE75+$L$9)-$K$9),HU_beta*($T$9-$K$9))))) | AT75: =IF(OR(AR75=0,$S$9=0),0,IF((AE75+$L$9+$N$9)>$S$9/HU_alpha+$K$9,0.5*$S$9/HU_alpha,IF((AE75+$L$9+$N$9)>=$K$9,((AE75+$L$9+$N$9)-$K$9)-0.5*HU_alpha/$S$9*((AE75+$L$9+$N$9)-$K$9)^2,IF((AE75+$L$9+$N$9)>=$T$9,HU_beta*((AE75+$L$9+$N$9)-$K$9),HU_beta*($T$9-$K$9))))) | AU75: =IF(OR(AR75=0,$S$9=0),0,IF((AE75+$K$9)>$S$9/HU_alpha+$K$9,0.5*$S$9/HU_alpha,IF((AE75+$K$9)>=$K$9,((AE75+$K$9)-$K$9)-0.5*HU_alpha/$S$9*((AE75+$K$9)-$K$9)^2,IF((AE75+$K$9)>=$T$9,HU_beta*((AE75+$K$9)-$K$9),HU_beta*($T$9-$K$9))))) | AV75: =IF(AND($J$10,A75=$Q$10),J75,0) | AW75: =IF(OR(AV75=0,$S$10=0),0,IF((AD75+$L$10)>$S$10/HU_alpha+$K$10,0.5*$S$10/HU_alpha,IF((AD75+$L$10)>=$K$10,((AD75+$L$10)-$K$10)-0.5*HU_alpha/$S$10*((AD75+$L$10)-$K$10)^2,IF((AD75+$L$10)>=$T$10,HU_beta*((AD75+$L$10)-$K$10),HU_beta*($T$10-$K$10))))) | AX75: =IF(OR(AV75=0,$S$10=0),0,IF((AD75+$L$10+$N$10)>$S$10/HU_alpha+$K$10,0.5*$S$10/HU_alpha,IF((AD75+$L$10+$N$10)>=$K$10,((AD75+$L$10+$N$10)-$K$10)-0.5*HU_alpha/$S$10*((AD75+$L$10+$N$10)-$K$10)^2,IF((AD75+$L$10+$N$10)>=$T$10,HU_beta*((AD75+$L$10+$N$10)-$K$10),HU_beta*($T$10-$K$10))))) | AY75: =IF(OR(AV75=0,$S$10=0),0,IF((AD75+$K$10)>$S$10/HU_alpha+$K$10,0.5*$S$10/HU_alpha,IF((AD75+$K$10)>=$K$10,((AD75+$K$10)-$K$10)-0.5*HU_alpha/$S$10*((AD75+$K$10)-$K$10)^2,IF((AD75+$K$10)>=$T$10,HU_beta*((AD75+$K$10)-$K$10),HU_beta*($T$10-$K$10))))) | AZ75: =IF(AND($J$11,A75=$Q$11),J75,0) | BA75: =IF(OR(AZ75=0,$S$11=0),0,IF((AE75+$L$11)>$S$11/HU_alpha+$K$11,0.5*$S$11/HU_alpha,IF((AE75+$L$11)>=$K$11,((AE75+$L$11)-$K$11)-0.5*HU_alpha/$S$11*((AE75+$L$11)-$K$11)^2,IF((AE75+$L$11)>=$T$11,HU_beta*((AE75+$L$11)-$K$11),HU_beta*($T$11-$K$11))))) | BB75: =IF(OR(AZ75=0,$S$11=0),0,IF((AE75+$L$11+$N$11)>$S$11/HU_alpha+$K$11,0.5*$S$11/HU_alpha,IF((AE75+$L$11+$N$11)>=$K$11,((AE75+$L$11+$N$11)-$K$11)-0.5*HU_alpha/$S$11*((AE75+$L$11+$N$11)-$K$11)^2,IF((AE75+$L$11+$N$11)>=$T$11,HU_beta*((AE75+$L$11+$N$11)-$K$11),HU_beta*($T$11-$K$11))))) | BC75: =IF(OR(AZ75=0,$S$11=0),0,IF((AE75+$K$11)>$S$11/HU_alpha+$K$11,0.5*$S$11/HU_alpha,IF((AE75+$K$11)>=$K$11,((AE75+$K$11)-$K$11)-0.5*HU_alpha/$S$11*((AE75+$K$11)-$K$11)^2,IF((AE75+$K$11)>=$T$11,HU_beta*((AE75+$K$11)-$K$11),HU_beta*($T$11-$K$11))))) | BD75: =IF(AND($J$12,A75=$Q$12),J75,0) | BE75: =IF(OR(BD75=0,$S$12=0),0,IF((AE75+$L$12)>$S$12/HU_alpha+$K$12,0.5*$S$12/HU_alpha,IF((AE75+$L$12)>=$K$12,((AE75+$L$12)-$K$12)-0.5*HU_alpha/$S$12*((AE75+$L$12)-$K$12)^2,IF((AE75+$L$12)>=$T$12,HU_beta*((AE75+$L$12)-$K$12),HU_beta*($T$12-$K$12))))) | BF75: =IF(OR(BD75=0,$S$12=0),0,IF((AE75+$L$12+$N$12)>$S$12/HU_alpha+$K$12,0.5*$S$12/HU_alpha,IF((AE75+$L$12+$N$12)>=$K$12,((AE75+$L$12+$N$12)-$K$12)-0.5*HU_alpha/$S$12*((AE75+$L$12+$N$12)-$K$12)^2,IF((AE75+$L$12+$N$12)>=$T$12,HU_beta*((AE75+$L$12+$N$12)-$K$12),HU_beta*($T$12-$K$12))))) | BG75: =IF(OR(BD75=0,$S$12=0),0,IF((AE75+$K$12)>$S$12/HU_alpha+$K$12,0.5*$S$12/HU_alpha,IF((AE75+$K$12)>=$K$12,((AE75+$K$12)-$K$12)-0.5*HU_alpha/$S$12*((AE75+$K$12)-$K$12)^2,IF((AE75+$K$12)>=$T$12,HU_beta*((AE75+$K$12)-$K$12),HU_beta*($T$12-$K$12))))) | BH75: =IF(AND($J$13,A75=$Q$13),J75,0) | BI75: =IF(OR(BH75=0,$S$13=0),0,IF((AE75+$L$13)>$S$13/HU_alpha+$K$13,0.5*$S$13/HU_alpha,IF((AE75+$L$13)>=$K$13,((AE75+$L$13)-$K$13)-0.5*HU_alpha/$S$13*((AE75+$L$13)-$K$13)^2,IF((AE75+$L$13)>=$T$13,HU_beta*((AE75+$L$13)-$K$13),HU_beta*($T$13-$K$13))))) | BJ75: =IF(OR(BH75=0,$S$13=0),0,IF((AE75+$L$13+$N$13)>$S$13/HU_alpha+$K$13,0.5*$S$13/HU_alpha,IF((AE75+$L$13+$N$13)>=$K$13,((AE75+$L$13+$N$13)-$K$13)-0.5*HU_alpha/$S$13*((AE75+$L$13+$N$13)-$K$13)^2,IF((AE75+$L$13+$N$13)>=$T$13,HU_beta*((AE75+$L$13+$N$13)-$K$13),HU_beta*($T$13-$K$13))))) | BK75: =IF(OR(BH75=0,$S$13=0),0,IF((AE75+$K$13)>$S$13/HU_alpha+$K$13,0.5*$S$13/HU_alpha,IF((AE75+$K$13)>=$K$13,((AE75+$K$13)-$K$13)-0.5*HU_alpha/$S$13*((AE75+$K$13)-$K$13)^2,IF((AE75+$K$13)>=$T$13,HU_beta*((AE75+$K$13)-$K$13),HU_beta*($T$13-$K$13)))))
A76: 3 | B76: =HU_age+A76 | C76: =A76<=HU_T | D76: =IF(OR(A76<1,A76>HU_T),0,INDEX(HU_q_mort,HU_age+A76-17,HU_col)) | E76: =IF(OR(A76<1,A76>HU_T),0,INDEX(HU_q_adb,HU_age+A76-17,HU_col)) | F76: =IF(OR(A76<1,A76>HU_T),0,INDEX(HU_q_morb,HU_age+A76-17,HU_col)) | G76: =IF(OR(A76<1,A76>HU_T),0,INDEX(HU_q_ptd,HU_age+A76-17,HU_col)) | H76: =IF(OR(A76<1,A76>HU_T),0,INDEX(HU_q_dis,HU_age+A76-17,HU_col)) | I76: =IF(A76>HU_T,0,I75*(1-D76)*(1-E76)) | J76: =IF(A76>=HU_T,0,N(I77)) | K76: =K75*(1-G76) | L76: =1-K76 | M76: =K75*G76 | N76: =N75*(1-H76) | O76: =1-N75 | P76: =P75*(1-F76) | Q76: =1-P75/INDEX($P$73:$P$155,MAX(1,A76-HU_ciYears)) | R76: =(1+inflationRate)^A76 | S76: =IF(OR(OR(A76<1,A76>HU_T),A76-1>=HU_dtr),0,HU_inc0*(1+incomeGrowthRate)^A76) | T76: =IF(A76>HU_T,T75,T75*(1+INDEX(HU_ssG,HU_age+A76-17))) | U76: =IF(AND(HU_dtr>=1,A76=HU_dtr,A76<=HU_T),MIN(S76*INDEX(HU_ssC,HU_age+A76-17)/(1-INDEX(HU_ssC,HU_age+A76-17)),INDEX(HU_ssCap,HU_age+A76-17))*T76,0) | V76: =S76+U76+IF(AND(HU_wdSAVOn,A76=HU_wdSAVYear),HU_wdSAVAmt,0)+IF(AND(HU_wdPRPOn,A76=HU_wdPRPYear),HU_wdPRPAmt,0) | W76: =HU_ciProp*Q76+HU_tpdCut*L76+HU_disCut*O76 | X76: =IF(OR(A76<1,A76>HU_T),0,V76*(1-W76)) | Y76: =IF(OR(A76<1,A76>HU_T),0,IF(AND(HU_retExp>0,A76-1>=HU_dtr),HU_retExp,HU_exp0)*R76) | Z76: =-Y76-IF(AND(HU_wdEDUOn,A76=HU_wdEDUYear),HU_wdEDUAmt,0)-IF(AND(HU_wdSAVOn,A76=HU_wdSAVYear),HU_wdSAVAmt,0)-IF(AND(HU_wdPRPOn,A76=HU_wdPRPYear),HU_wdPRPAmt,0) | AA76: =IF(OR(A76<1,A76>HU_T),0,-HU_medCost*R76*F76-HU_tpdCost*R76*M76) | AB76: =IF(A76>HU_T,0,AB75*(1+interestRate)+X76+Z76+AA76) | AC76: =IF(A76>HU_T,0,HU_inv*EXP(HU_mu*A76)) | AD76: =IF(A76>HU_T,0,MAX(0,AC76+AB76)) | AE76: =IF(A76>HU_T,0,MAX(0,X76-Y76)) | AF76: =IF(AND($J$6,A76>=1,A76<=$Q$6-1),J76,0) | AG76: =IF(OR(AF76=0,$S$6=0),0,IF((AD76+$L$6)>$S$6/HU_alpha+$K$6,0.5*$S$6/HU_alpha,IF((AD76+$L$6)>=$K$6,((AD76+$L$6)-$K$6)-0.5*HU_alpha/$S$6*((AD76+$L$6)-$K$6)^2,IF((AD76+$L$6)>=$T$6,HU_beta*((AD76+$L$6)-$K$6),HU_beta*($T$6-$K$6))))) | AH76: =IF(OR(AF76=0,$S$6=0),0,IF((AD76+$L$6+$N$6)>$S$6/HU_alpha+$K$6,0.5*$S$6/HU_alpha,IF((AD76+$L$6+$N$6)>=$K$6,((AD76+$L$6+$N$6)-$K$6)-0.5*HU_alpha/$S$6*((AD76+$L$6+$N$6)-$K$6)^2,IF((AD76+$L$6+$N$6)>=$T$6,HU_beta*((AD76+$L$6+$N$6)-$K$6),HU_beta*($T$6-$K$6))))) | AI76: =IF(OR(AF76=0,$S$6=0),0,IF((AD76+$K$6)>$S$6/HU_alpha+$K$6,0.5*$S$6/HU_alpha,IF((AD76+$K$6)>=$K$6,((AD76+$K$6)-$K$6)-0.5*HU_alpha/$S$6*((AD76+$K$6)-$K$6)^2,IF((AD76+$K$6)>=$T$6,HU_beta*((AD76+$K$6)-$K$6),HU_beta*($T$6-$K$6))))) | AJ76: =IF(AND($J$7,A76>=1,A76<=$Q$7-1),J76,0) | AK76: =IF(OR(AJ76=0,$S$7=0),0,IF((AE76+$L$7)>$S$7/HU_alpha+$K$7,0.5*$S$7/HU_alpha,IF((AE76+$L$7)>=$K$7,((AE76+$L$7)-$K$7)-0.5*HU_alpha/$S$7*((AE76+$L$7)-$K$7)^2,IF((AE76+$L$7)>=$T$7,HU_beta*((AE76+$L$7)-$K$7),HU_beta*($T$7-$K$7))))) | AL76: =IF(OR(AJ76=0,$S$7=0),0,IF((AE76+$L$7+$N$7)>$S$7/HU_alpha+$K$7,0.5*$S$7/HU_alpha,IF((AE76+$L$7+$N$7)>=$K$7,((AE76+$L$7+$N$7)-$K$7)-0.5*HU_alpha/$S$7*((AE76+$L$7+$N$7)-$K$7)^2,IF((AE76+$L$7+$N$7)>=$T$7,HU_beta*((AE76+$L$7+$N$7)-$K$7),HU_beta*($T$7-$K$7))))) | AM76: =IF(OR(AJ76=0,$S$7=0),0,IF((AE76+$K$7)>$S$7/HU_alpha+$K$7,0.5*$S$7/HU_alpha,IF((AE76+$K$7)>=$K$7,((AE76+$K$7)-$K$7)-0.5*HU_alpha/$S$7*((AE76+$K$7)-$K$7)^2,IF((AE76+$K$7)>=$T$7,HU_beta*((AE76+$K$7)-$K$7),HU_beta*($T$7-$K$7))))) | AN76: =IF(AND($J$8,A76>=1,A76<=$Q$8-1),J76,0) | AO76: =IF(OR(AN76=0,$S$8=0),0,IF((AE76+$L$8)>$S$8/HU_alpha+$K$8,0.5*$S$8/HU_alpha,IF((AE76+$L$8)>=$K$8,((AE76+$L$8)-$K$8)-0.5*HU_alpha/$S$8*((AE76+$L$8)-$K$8)^2,IF((AE76+$L$8)>=$T$8,HU_beta*((AE76+$L$8)-$K$8),HU_beta*($T$8-$K$8))))) | AP76: =IF(OR(AN76=0,$S$8=0),0,IF((AE76+$L$8+$N$8)>$S$8/HU_alpha+$K$8,0.5*$S$8/HU_alpha,IF((AE76+$L$8+$N$8)>=$K$8,((AE76+$L$8+$N$8)-$K$8)-0.5*HU_alpha/$S$8*((AE76+$L$8+$N$8)-$K$8)^2,IF((AE76+$L$8+$N$8)>=$T$8,HU_beta*((AE76+$L$8+$N$8)-$K$8),HU_beta*($T$8-$K$8))))) | AQ76: =IF(OR(AN76=0,$S$8=0),0,IF((AE76+$K$8)>$S$8/HU_alpha+$K$8,0.5*$S$8/HU_alpha,IF((AE76+$K$8)>=$K$8,((AE76+$K$8)-$K$8)-0.5*HU_alpha/$S$8*((AE76+$K$8)-$K$8)^2,IF((AE76+$K$8)>=$T$8,HU_beta*((AE76+$K$8)-$K$8),HU_beta*($T$8-$K$8))))) | AR76: =IF(AND($J$9,A76>=1,A76<=$Q$9-1),J76,0) | AS76: =IF(OR(AR76=0,$S$9=0),0,IF((AE76+$L$9)>$S$9/HU_alpha+$K$9,0.5*$S$9/HU_alpha,IF((AE76+$L$9)>=$K$9,((AE76+$L$9)-$K$9)-0.5*HU_alpha/$S$9*((AE76+$L$9)-$K$9)^2,IF((AE76+$L$9)>=$T$9,HU_beta*((AE76+$L$9)-$K$9),HU_beta*($T$9-$K$9))))) | AT76: =IF(OR(AR76=0,$S$9=0),0,IF((AE76+$L$9+$N$9)>$S$9/HU_alpha+$K$9,0.5*$S$9/HU_alpha,IF((AE76+$L$9+$N$9)>=$K$9,((AE76+$L$9+$N$9)-$K$9)-0.5*HU_alpha/$S$9*((AE76+$L$9+$N$9)-$K$9)^2,IF((AE76+$L$9+$N$9)>=$T$9,HU_beta*((AE76+$L$9+$N$9)-$K$9),HU_beta*($T$9-$K$9))))) | AU76: =IF(OR(AR76=0,$S$9=0),0,IF((AE76+$K$9)>$S$9/HU_alpha+$K$9,0.5*$S$9/HU_alpha,IF((AE76+$K$9)>=$K$9,((AE76+$K$9)-$K$9)-0.5*HU_alpha/$S$9*((AE76+$K$9)-$K$9)^2,IF((AE76+$K$9)>=$T$9,HU_beta*((AE76+$K$9)-$K$9),HU_beta*($T$9-$K$9))))) | AV76: =IF(AND($J$10,A76=$Q$10),J76,0) | AW76: =IF(OR(AV76=0,$S$10=0),0,IF((AD76+$L$10)>$S$10/HU_alpha+$K$10,0.5*$S$10/HU_alpha,IF((AD76+$L$10)>=$K$10,((AD76+$L$10)-$K$10)-0.5*HU_alpha/$S$10*((AD76+$L$10)-$K$10)^2,IF((AD76+$L$10)>=$T$10,HU_beta*((AD76+$L$10)-$K$10),HU_beta*($T$10-$K$10))))) | AX76: =IF(OR(AV76=0,$S$10=0),0,IF((AD76+$L$10+$N$10)>$S$10/HU_alpha+$K$10,0.5*$S$10/HU_alpha,IF((AD76+$L$10+$N$10)>=$K$10,((AD76+$L$10+$N$10)-$K$10)-0.5*HU_alpha/$S$10*((AD76+$L$10+$N$10)-$K$10)^2,IF((AD76+$L$10+$N$10)>=$T$10,HU_beta*((AD76+$L$10+$N$10)-$K$10),HU_beta*($T$10-$K$10))))) | AY76: =IF(OR(AV76=0,$S$10=0),0,IF((AD76+$K$10)>$S$10/HU_alpha+$K$10,0.5*$S$10/HU_alpha,IF((AD76+$K$10)>=$K$10,((AD76+$K$10)-$K$10)-0.5*HU_alpha/$S$10*((AD76+$K$10)-$K$10)^2,IF((AD76+$K$10)>=$T$10,HU_beta*((AD76+$K$10)-$K$10),HU_beta*($T$10-$K$10))))) | AZ76: =IF(AND($J$11,A76=$Q$11),J76,0) | BA76: =IF(OR(AZ76=0,$S$11=0),0,IF((AE76+$L$11)>$S$11/HU_alpha+$K$11,0.5*$S$11/HU_alpha,IF((AE76+$L$11)>=$K$11,((AE76+$L$11)-$K$11)-0.5*HU_alpha/$S$11*((AE76+$L$11)-$K$11)^2,IF((AE76+$L$11)>=$T$11,HU_beta*((AE76+$L$11)-$K$11),HU_beta*($T$11-$K$11))))) | BB76: =IF(OR(AZ76=0,$S$11=0),0,IF((AE76+$L$11+$N$11)>$S$11/HU_alpha+$K$11,0.5*$S$11/HU_alpha,IF((AE76+$L$11+$N$11)>=$K$11,((AE76+$L$11+$N$11)-$K$11)-0.5*HU_alpha/$S$11*((AE76+$L$11+$N$11)-$K$11)^2,IF((AE76+$L$11+$N$11)>=$T$11,HU_beta*((AE76+$L$11+$N$11)-$K$11),HU_beta*($T$11-$K$11))))) | BC76: =IF(OR(AZ76=0,$S$11=0),0,IF((AE76+$K$11)>$S$11/HU_alpha+$K$11,0.5*$S$11/HU_alpha,IF((AE76+$K$11)>=$K$11,((AE76+$K$11)-$K$11)-0.5*HU_alpha/$S$11*((AE76+$K$11)-$K$11)^2,IF((AE76+$K$11)>=$T$11,HU_beta*((AE76+$K$11)-$K$11),HU_beta*($T$11-$K$11))))) | BD76: =IF(AND($J$12,A76=$Q$12),J76,0) | BE76: =IF(OR(BD76=0,$S$12=0),0,IF((AE76+$L$12)>$S$12/HU_alpha+$K$12,0.5*$S$12/HU_alpha,IF((AE76+$L$12)>=$K$12,((AE76+$L$12)-$K$12)-0.5*HU_alpha/$S$12*((AE76+$L$12)-$K$12)^2,IF((AE76+$L$12)>=$T$12,HU_beta*((AE76+$L$12)-$K$12),HU_beta*($T$12-$K$12))))) | BF76: =IF(OR(BD76=0,$S$12=0),0,IF((AE76+$L$12+$N$12)>$S$12/HU_alpha+$K$12,0.5*$S$12/HU_alpha,IF((AE76+$L$12+$N$12)>=$K$12,((AE76+$L$12+$N$12)-$K$12)-0.5*HU_alpha/$S$12*((AE76+$L$12+$N$12)-$K$12)^2,IF((AE76+$L$12+$N$12)>=$T$12,HU_beta*((AE76+$L$12+$N$12)-$K$12),HU_beta*($T$12-$K$12))))) | BG76: =IF(OR(BD76=0,$S$12=0),0,IF((AE76+$K$12)>$S$12/HU_alpha+$K$12,0.5*$S$12/HU_alpha,IF((AE76+$K$12)>=$K$12,((AE76+$K$12)-$K$12)-0.5*HU_alpha/$S$12*((AE76+$K$12)-$K$12)^2,IF((AE76+$K$12)>=$T$12,HU_beta*((AE76+$K$12)-$K$12),HU_beta*($T$12-$K$12))))) | BH76: =IF(AND($J$13,A76=$Q$13),J76,0) | BI76: =IF(OR(BH76=0,$S$13=0),0,IF((AE76+$L$13)>$S$13/HU_alpha+$K$13,0.5*$S$13/HU_alpha,IF((AE76+$L$13)>=$K$13,((AE76+$L$13)-$K$13)-0.5*HU_alpha/$S$13*((AE76+$L$13)-$K$13)^2,IF((AE76+$L$13)>=$T$13,HU_beta*((AE76+$L$13)-$K$13),HU_beta*($T$13-$K$13))))) | BJ76: =IF(OR(BH76=0,$S$13=0),0,IF((AE76+$L$13+$N$13)>$S$13/HU_alpha+$K$13,0.5*$S$13/HU_alpha,IF((AE76+$L$13+$N$13)>=$K$13,((AE76+$L$13+$N$13)-$K$13)-0.5*HU_alpha/$S$13*((AE76+$L$13+$N$13)-$K$13)^2,IF((AE76+$L$13+$N$13)>=$T$13,HU_beta*((AE76+$L$13+$N$13)-$K$13),HU_beta*($T$13-$K$13))))) | BK76: =IF(OR(BH76=0,$S$13=0),0,IF((AE76+$K$13)>$S$13/HU_alpha+$K$13,0.5*$S$13/HU_alpha,IF((AE76+$K$13)>=$K$13,((AE76+$K$13)-$K$13)-0.5*HU_alpha/$S$13*((AE76+$K$13)-$K$13)^2,IF((AE76+$K$13)>=$T$13,HU_beta*((AE76+$K$13)-$K$13),HU_beta*($T$13-$K$13)))))
A77: 4 | B77: =HU_age+A77 | C77: =A77<=HU_T | D77: =IF(OR(A77<1,A77>HU_T),0,INDEX(HU_q_mort,HU_age+A77-17,HU_col)) | E77: =IF(OR(A77<1,A77>HU_T),0,INDEX(HU_q_adb,HU_age+A77-17,HU_col)) | F77: =IF(OR(A77<1,A77>HU_T),0,INDEX(HU_q_morb,HU_age+A77-17,HU_col)) | G77: =IF(OR(A77<1,A77>HU_T),0,INDEX(HU_q_ptd,HU_age+A77-17,HU_col)) | H77: =IF(OR(A77<1,A77>HU_T),0,INDEX(HU_q_dis,HU_age+A77-17,HU_col)) | I77: =IF(A77>HU_T,0,I76*(1-D77)*(1-E77)) | J77: =IF(A77>=HU_T,0,N(I78)) | K77: =K76*(1-G77) | L77: =1-K77 | M77: =K76*G77 | N77: =N76*(1-H77) | O77: =1-N76 | P77: =P76*(1-F77) | Q77: =1-P76/INDEX($P$73:$P$155,MAX(1,A77-HU_ciYears)) | R77: =(1+inflationRate)^A77 | S77: =IF(OR(OR(A77<1,A77>HU_T),A77-1>=HU_dtr),0,HU_inc0*(1+incomeGrowthRate)^A77) | T77: =IF(A77>HU_T,T76,T76*(1+INDEX(HU_ssG,HU_age+A77-17))) | U77: =IF(AND(HU_dtr>=1,A77=HU_dtr,A77<=HU_T),MIN(S77*INDEX(HU_ssC,HU_age+A77-17)/(1-INDEX(HU_ssC,HU_age+A77-17)),INDEX(HU_ssCap,HU_age+A77-17))*T77,0) | V77: =S77+U77+IF(AND(HU_wdSAVOn,A77=HU_wdSAVYear),HU_wdSAVAmt,0)+IF(AND(HU_wdPRPOn,A77=HU_wdPRPYear),HU_wdPRPAmt,0) | W77: =HU_ciProp*Q77+HU_tpdCut*L77+HU_disCut*O77 | X77: =IF(OR(A77<1,A77>HU_T),0,V77*(1-W77)) | Y77: =IF(OR(A77<1,A77>HU_T),0,IF(AND(HU_retExp>0,A77-1>=HU_dtr),HU_retExp,HU_exp0)*R77) | Z77: =-Y77-IF(AND(HU_wdEDUOn,A77=HU_wdEDUYear),HU_wdEDUAmt,0)-IF(AND(HU_wdSAVOn,A77=HU_wdSAVYear),HU_wdSAVAmt,0)-IF(AND(HU_wdPRPOn,A77=HU_wdPRPYear),HU_wdPRPAmt,0) | AA77: =IF(OR(A77<1,A77>HU_T),0,-HU_medCost*R77*F77-HU_tpdCost*R77*M77) | AB77: =IF(A77>HU_T,0,AB76*(1+interestRate)+X77+Z77+AA77) | AC77: =IF(A77>HU_T,0,HU_inv*EXP(HU_mu*A77)) | AD77: =IF(A77>HU_T,0,MAX(0,AC77+AB77)) | AE77: =IF(A77>HU_T,0,MAX(0,X77-Y77)) | AF77: =IF(AND($J$6,A77>=1,A77<=$Q$6-1),J77,0) | AG77: =IF(OR(AF77=0,$S$6=0),0,IF((AD77+$L$6)>$S$6/HU_alpha+$K$6,0.5*$S$6/HU_alpha,IF((AD77+$L$6)>=$K$6,((AD77+$L$6)-$K$6)-0.5*HU_alpha/$S$6*((AD77+$L$6)-$K$6)^2,IF((AD77+$L$6)>=$T$6,HU_beta*((AD77+$L$6)-$K$6),HU_beta*($T$6-$K$6))))) | AH77: =IF(OR(AF77=0,$S$6=0),0,IF((AD77+$L$6+$N$6)>$S$6/HU_alpha+$K$6,0.5*$S$6/HU_alpha,IF((AD77+$L$6+$N$6)>=$K$6,((AD77+$L$6+$N$6)-$K$6)-0.5*HU_alpha/$S$6*((AD77+$L$6+$N$6)-$K$6)^2,IF((AD77+$L$6+$N$6)>=$T$6,HU_beta*((AD77+$L$6+$N$6)-$K$6),HU_beta*($T$6-$K$6))))) | AI77: =IF(OR(AF77=0,$S$6=0),0,IF((AD77+$K$6)>$S$6/HU_alpha+$K$6,0.5*$S$6/HU_alpha,IF((AD77+$K$6)>=$K$6,((AD77+$K$6)-$K$6)-0.5*HU_alpha/$S$6*((AD77+$K$6)-$K$6)^2,IF((AD77+$K$6)>=$T$6,HU_beta*((AD77+$K$6)-$K$6),HU_beta*($T$6-$K$6))))) | AJ77: =IF(AND($J$7,A77>=1,A77<=$Q$7-1),J77,0) | AK77: =IF(OR(AJ77=0,$S$7=0),0,IF((AE77+$L$7)>$S$7/HU_alpha+$K$7,0.5*$S$7/HU_alpha,IF((AE77+$L$7)>=$K$7,((AE77+$L$7)-$K$7)-0.5*HU_alpha/$S$7*((AE77+$L$7)-$K$7)^2,IF((AE77+$L$7)>=$T$7,HU_beta*((AE77+$L$7)-$K$7),HU_beta*($T$7-$K$7))))) | AL77: =IF(OR(AJ77=0,$S$7=0),0,IF((AE77+$L$7+$N$7)>$S$7/HU_alpha+$K$7,0.5*$S$7/HU_alpha,IF((AE77+$L$7+$N$7)>=$K$7,((AE77+$L$7+$N$7)-$K$7)-0.5*HU_alpha/$S$7*((AE77+$L$7+$N$7)-$K$7)^2,IF((AE77+$L$7+$N$7)>=$T$7,HU_beta*((AE77+$L$7+$N$7)-$K$7),HU_beta*($T$7-$K$7))))) | AM77: =IF(OR(AJ77=0,$S$7=0),0,IF((AE77+$K$7)>$S$7/HU_alpha+$K$7,0.5*$S$7/HU_alpha,IF((AE77+$K$7)>=$K$7,((AE77+$K$7)-$K$7)-0.5*HU_alpha/$S$7*((AE77+$K$7)-$K$7)^2,IF((AE77+$K$7)>=$T$7,HU_beta*((AE77+$K$7)-$K$7),HU_beta*($T$7-$K$7))))) | AN77: =IF(AND($J$8,A77>=1,A77<=$Q$8-1),J77,0) | AO77: =IF(OR(AN77=0,$S$8=0),0,IF((AE77+$L$8)>$S$8/HU_alpha+$K$8,0.5*$S$8/HU_alpha,IF((AE77+$L$8)>=$K$8,((AE77+$L$8)-$K$8)-0.5*HU_alpha/$S$8*((AE77+$L$8)-$K$8)^2,IF((AE77+$L$8)>=$T$8,HU_beta*((AE77+$L$8)-$K$8),HU_beta*($T$8-$K$8))))) | AP77: =IF(OR(AN77=0,$S$8=0),0,IF((AE77+$L$8+$N$8)>$S$8/HU_alpha+$K$8,0.5*$S$8/HU_alpha,IF((AE77+$L$8+$N$8)>=$K$8,((AE77+$L$8+$N$8)-$K$8)-0.5*HU_alpha/$S$8*((AE77+$L$8+$N$8)-$K$8)^2,IF((AE77+$L$8+$N$8)>=$T$8,HU_beta*((AE77+$L$8+$N$8)-$K$8),HU_beta*($T$8-$K$8))))) | AQ77: =IF(OR(AN77=0,$S$8=0),0,IF((AE77+$K$8)>$S$8/HU_alpha+$K$8,0.5*$S$8/HU_alpha,IF((AE77+$K$8)>=$K$8,((AE77+$K$8)-$K$8)-0.5*HU_alpha/$S$8*((AE77+$K$8)-$K$8)^2,IF((AE77+$K$8)>=$T$8,HU_beta*((AE77+$K$8)-$K$8),HU_beta*($T$8-$K$8))))) | AR77: =IF(AND($J$9,A77>=1,A77<=$Q$9-1),J77,0) | AS77: =IF(OR(AR77=0,$S$9=0),0,IF((AE77+$L$9)>$S$9/HU_alpha+$K$9,0.5*$S$9/HU_alpha,IF((AE77+$L$9)>=$K$9,((AE77+$L$9)-$K$9)-0.5*HU_alpha/$S$9*((AE77+$L$9)-$K$9)^2,IF((AE77+$L$9)>=$T$9,HU_beta*((AE77+$L$9)-$K$9),HU_beta*($T$9-$K$9))))) | AT77: =IF(OR(AR77=0,$S$9=0),0,IF((AE77+$L$9+$N$9)>$S$9/HU_alpha+$K$9,0.5*$S$9/HU_alpha,IF((AE77+$L$9+$N$9)>=$K$9,((AE77+$L$9+$N$9)-$K$9)-0.5*HU_alpha/$S$9*((AE77+$L$9+$N$9)-$K$9)^2,IF((AE77+$L$9+$N$9)>=$T$9,HU_beta*((AE77+$L$9+$N$9)-$K$9),HU_beta*($T$9-$K$9))))) | AU77: =IF(OR(AR77=0,$S$9=0),0,IF((AE77+$K$9)>$S$9/HU_alpha+$K$9,0.5*$S$9/HU_alpha,IF((AE77+$K$9)>=$K$9,((AE77+$K$9)-$K$9)-0.5*HU_alpha/$S$9*((AE77+$K$9)-$K$9)^2,IF((AE77+$K$9)>=$T$9,HU_beta*((AE77+$K$9)-$K$9),HU_beta*($T$9-$K$9))))) | AV77: =IF(AND($J$10,A77=$Q$10),J77,0) | AW77: =IF(OR(AV77=0,$S$10=0),0,IF((AD77+$L$10)>$S$10/HU_alpha+$K$10,0.5*$S$10/HU_alpha,IF((AD77+$L$10)>=$K$10,((AD77+$L$10)-$K$10)-0.5*HU_alpha/$S$10*((AD77+$L$10)-$K$10)^2,IF((AD77+$L$10)>=$T$10,HU_beta*((AD77+$L$10)-$K$10),HU_beta*($T$10-$K$10))))) | AX77: =IF(OR(AV77=0,$S$10=0),0,IF((AD77+$L$10+$N$10)>$S$10/HU_alpha+$K$10,0.5*$S$10/HU_alpha,IF((AD77+$L$10+$N$10)>=$K$10,((AD77+$L$10+$N$10)-$K$10)-0.5*HU_alpha/$S$10*((AD77+$L$10+$N$10)-$K$10)^2,IF((AD77+$L$10+$N$10)>=$T$10,HU_beta*((AD77+$L$10+$N$10)-$K$10),HU_beta*($T$10-$K$10))))) | AY77: =IF(OR(AV77=0,$S$10=0),0,IF((AD77+$K$10)>$S$10/HU_alpha+$K$10,0.5*$S$10/HU_alpha,IF((AD77+$K$10)>=$K$10,((AD77+$K$10)-$K$10)-0.5*HU_alpha/$S$10*((AD77+$K$10)-$K$10)^2,IF((AD77+$K$10)>=$T$10,HU_beta*((AD77+$K$10)-$K$10),HU_beta*($T$10-$K$10))))) | AZ77: =IF(AND($J$11,A77=$Q$11),J77,0) | BA77: =IF(OR(AZ77=0,$S$11=0),0,IF((AE77+$L$11)>$S$11/HU_alpha+$K$11,0.5*$S$11/HU_alpha,IF((AE77+$L$11)>=$K$11,((AE77+$L$11)-$K$11)-0.5*HU_alpha/$S$11*((AE77+$L$11)-$K$11)^2,IF((AE77+$L$11)>=$T$11,HU_beta*((AE77+$L$11)-$K$11),HU_beta*($T$11-$K$11))))) | BB77: =IF(OR(AZ77=0,$S$11=0),0,IF((AE77+$L$11+$N$11)>$S$11/HU_alpha+$K$11,0.5*$S$11/HU_alpha,IF((AE77+$L$11+$N$11)>=$K$11,((AE77+$L$11+$N$11)-$K$11)-0.5*HU_alpha/$S$11*((AE77+$L$11+$N$11)-$K$11)^2,IF((AE77+$L$11+$N$11)>=$T$11,HU_beta*((AE77+$L$11+$N$11)-$K$11),HU_beta*($T$11-$K$11))))) | BC77: =IF(OR(AZ77=0,$S$11=0),0,IF((AE77+$K$11)>$S$11/HU_alpha+$K$11,0.5*$S$11/HU_alpha,IF((AE77+$K$11)>=$K$11,((AE77+$K$11)-$K$11)-0.5*HU_alpha/$S$11*((AE77+$K$11)-$K$11)^2,IF((AE77+$K$11)>=$T$11,HU_beta*((AE77+$K$11)-$K$11),HU_beta*($T$11-$K$11))))) | BD77: =IF(AND($J$12,A77=$Q$12),J77,0) | BE77: =IF(OR(BD77=0,$S$12=0),0,IF((AE77+$L$12)>$S$12/HU_alpha+$K$12,0.5*$S$12/HU_alpha,IF((AE77+$L$12)>=$K$12,((AE77+$L$12)-$K$12)-0.5*HU_alpha/$S$12*((AE77+$L$12)-$K$12)^2,IF((AE77+$L$12)>=$T$12,HU_beta*((AE77+$L$12)-$K$12),HU_beta*($T$12-$K$12))))) | BF77: =IF(OR(BD77=0,$S$12=0),0,IF((AE77+$L$12+$N$12)>$S$12/HU_alpha+$K$12,0.5*$S$12/HU_alpha,IF((AE77+$L$12+$N$12)>=$K$12,((AE77+$L$12+$N$12)-$K$12)-0.5*HU_alpha/$S$12*((AE77+$L$12+$N$12)-$K$12)^2,IF((AE77+$L$12+$N$12)>=$T$12,HU_beta*((AE77+$L$12+$N$12)-$K$12),HU_beta*($T$12-$K$12))))) | BG77: =IF(OR(BD77=0,$S$12=0),0,IF((AE77+$K$12)>$S$12/HU_alpha+$K$12,0.5*$S$12/HU_alpha,IF((AE77+$K$12)>=$K$12,((AE77+$K$12)-$K$12)-0.5*HU_alpha/$S$12*((AE77+$K$12)-$K$12)^2,IF((AE77+$K$12)>=$T$12,HU_beta*((AE77+$K$12)-$K$12),HU_beta*($T$12-$K$12))))) | BH77: =IF(AND($J$13,A77=$Q$13),J77,0) | BI77: =IF(OR(BH77=0,$S$13=0),0,IF((AE77+$L$13)>$S$13/HU_alpha+$K$13,0.5*$S$13/HU_alpha,IF((AE77+$L$13)>=$K$13,((AE77+$L$13)-$K$13)-0.5*HU_alpha/$S$13*((AE77+$L$13)-$K$13)^2,IF((AE77+$L$13)>=$T$13,HU_beta*((AE77+$L$13)-$K$13),HU_beta*($T$13-$K$13))))) | BJ77: =IF(OR(BH77=0,$S$13=0),0,IF((AE77+$L$13+$N$13)>$S$13/HU_alpha+$K$13,0.5*$S$13/HU_alpha,IF((AE77+$L$13+$N$13)>=$K$13,((AE77+$L$13+$N$13)-$K$13)-0.5*HU_alpha/$S$13*((AE77+$L$13+$N$13)-$K$13)^2,IF((AE77+$L$13+$N$13)>=$T$13,HU_beta*((AE77+$L$13+$N$13)-$K$13),HU_beta*($T$13-$K$13))))) | BK77: =IF(OR(BH77=0,$S$13=0),0,IF((AE77+$K$13)>$S$13/HU_alpha+$K$13,0.5*$S$13/HU_alpha,IF((AE77+$K$13)>=$K$13,((AE77+$K$13)-$K$13)-0.5*HU_alpha/$S$13*((AE77+$K$13)-$K$13)^2,IF((AE77+$K$13)>=$T$13,HU_beta*((AE77+$K$13)-$K$13),HU_beta*($T$13-$K$13)))))
A78: 5 | B78: =HU_age+A78 | C78: =A78<=HU_T | D78: =IF(OR(A78<1,A78>HU_T),0,INDEX(HU_q_mort,HU_age+A78-17,HU_col)) | E78: =IF(OR(A78<1,A78>HU_T),0,INDEX(HU_q_adb,HU_age+A78-17,HU_col)) | F78: =IF(OR(A78<1,A78>HU_T),0,INDEX(HU_q_morb,HU_age+A78-17,HU_col)) | G78: =IF(OR(A78<1,A78>HU_T),0,INDEX(HU_q_ptd,HU_age+A78-17,HU_col)) | H78: =IF(OR(A78<1,A78>HU_T),0,INDEX(HU_q_dis,HU_age+A78-17,HU_col)) | I78: =IF(A78>HU_T,0,I77*(1-D78)*(1-E78)) | J78: =IF(A78>=HU_T,0,N(I79)) | K78: =K77*(1-G78) | L78: =1-K78 | M78: =K77*G78 | N78: =N77*(1-H78) | O78: =1-N77 | P78: =P77*(1-F78) | Q78: =1-P77/INDEX($P$73:$P$155,MAX(1,A78-HU_ciYears)) | R78: =(1+inflationRate)^A78 | S78: =IF(OR(OR(A78<1,A78>HU_T),A78-1>=HU_dtr),0,HU_inc0*(1+incomeGrowthRate)^A78) | T78: =IF(A78>HU_T,T77,T77*(1+INDEX(HU_ssG,HU_age+A78-17))) | U78: =IF(AND(HU_dtr>=1,A78=HU_dtr,A78<=HU_T),MIN(S78*INDEX(HU_ssC,HU_age+A78-17)/(1-INDEX(HU_ssC,HU_age+A78-17)),INDEX(HU_ssCap,HU_age+A78-17))*T78,0) | V78: =S78+U78+IF(AND(HU_wdSAVOn,A78=HU_wdSAVYear),HU_wdSAVAmt,0)+IF(AND(HU_wdPRPOn,A78=HU_wdPRPYear),HU_wdPRPAmt,0) | W78: =HU_ciProp*Q78+HU_tpdCut*L78+HU_disCut*O78 | X78: =IF(OR(A78<1,A78>HU_T),0,V78*(1-W78)) | Y78: =IF(OR(A78<1,A78>HU_T),0,IF(AND(HU_retExp>0,A78-1>=HU_dtr),HU_retExp,HU_exp0)*R78) | Z78: =-Y78-IF(AND(HU_wdEDUOn,A78=HU_wdEDUYear),HU_wdEDUAmt,0)-IF(AND(HU_wdSAVOn,A78=HU_wdSAVYear),HU_wdSAVAmt,0)-IF(AND(HU_wdPRPOn,A78=HU_wdPRPYear),HU_wdPRPAmt,0) | AA78: =IF(OR(A78<1,A78>HU_T),0,-HU_medCost*R78*F78-HU_tpdCost*R78*M78) | AB78: =IF(A78>HU_T,0,AB77*(1+interestRate)+X78+Z78+AA78) | AC78: =IF(A78>HU_T,0,HU_inv*EXP(HU_mu*A78)) | AD78: =IF(A78>HU_T,0,MAX(0,AC78+AB78)) | AE78: =IF(A78>HU_T,0,MAX(0,X78-Y78)) | AF78: =IF(AND($J$6,A78>=1,A78<=$Q$6-1),J78,0) | AG78: =IF(OR(AF78=0,$S$6=0),0,IF((AD78+$L$6)>$S$6/HU_alpha+$K$6,0.5*$S$6/HU_alpha,IF((AD78+$L$6)>=$K$6,((AD78+$L$6)-$K$6)-0.5*HU_alpha/$S$6*((AD78+$L$6)-$K$6)^2,IF((AD78+$L$6)>=$T$6,HU_beta*((AD78+$L$6)-$K$6),HU_beta*($T$6-$K$6))))) | AH78: =IF(OR(AF78=0,$S$6=0),0,IF((AD78+$L$6+$N$6)>$S$6/HU_alpha+$K$6,0.5*$S$6/HU_alpha,IF((AD78+$L$6+$N$6)>=$K$6,((AD78+$L$6+$N$6)-$K$6)-0.5*HU_alpha/$S$6*((AD78+$L$6+$N$6)-$K$6)^2,IF((AD78+$L$6+$N$6)>=$T$6,HU_beta*((AD78+$L$6+$N$6)-$K$6),HU_beta*($T$6-$K$6))))) | AI78: =IF(OR(AF78=0,$S$6=0),0,IF((AD78+$K$6)>$S$6/HU_alpha+$K$6,0.5*$S$6/HU_alpha,IF((AD78+$K$6)>=$K$6,((AD78+$K$6)-$K$6)-0.5*HU_alpha/$S$6*((AD78+$K$6)-$K$6)^2,IF((AD78+$K$6)>=$T$6,HU_beta*((AD78+$K$6)-$K$6),HU_beta*($T$6-$K$6))))) | AJ78: =IF(AND($J$7,A78>=1,A78<=$Q$7-1),J78,0) | AK78: =IF(OR(AJ78=0,$S$7=0),0,IF((AE78+$L$7)>$S$7/HU_alpha+$K$7,0.5*$S$7/HU_alpha,IF((AE78+$L$7)>=$K$7,((AE78+$L$7)-$K$7)-0.5*HU_alpha/$S$7*((AE78+$L$7)-$K$7)^2,IF((AE78+$L$7)>=$T$7,HU_beta*((AE78+$L$7)-$K$7),HU_beta*($T$7-$K$7))))) | AL78: =IF(OR(AJ78=0,$S$7=0),0,IF((AE78+$L$7+$N$7)>$S$7/HU_alpha+$K$7,0.5*$S$7/HU_alpha,IF((AE78+$L$7+$N$7)>=$K$7,((AE78+$L$7+$N$7)-$K$7)-0.5*HU_alpha/$S$7*((AE78+$L$7+$N$7)-$K$7)^2,IF((AE78+$L$7+$N$7)>=$T$7,HU_beta*((AE78+$L$7+$N$7)-$K$7),HU_beta*($T$7-$K$7))))) | AM78: =IF(OR(AJ78=0,$S$7=0),0,IF((AE78+$K$7)>$S$7/HU_alpha+$K$7,0.5*$S$7/HU_alpha,IF((AE78+$K$7)>=$K$7,((AE78+$K$7)-$K$7)-0.5*HU_alpha/$S$7*((AE78+$K$7)-$K$7)^2,IF((AE78+$K$7)>=$T$7,HU_beta*((AE78+$K$7)-$K$7),HU_beta*($T$7-$K$7))))) | AN78: =IF(AND($J$8,A78>=1,A78<=$Q$8-1),J78,0) | AO78: =IF(OR(AN78=0,$S$8=0),0,IF((AE78+$L$8)>$S$8/HU_alpha+$K$8,0.5*$S$8/HU_alpha,IF((AE78+$L$8)>=$K$8,((AE78+$L$8)-$K$8)-0.5*HU_alpha/$S$8*((AE78+$L$8)-$K$8)^2,IF((AE78+$L$8)>=$T$8,HU_beta*((AE78+$L$8)-$K$8),HU_beta*($T$8-$K$8))))) | AP78: =IF(OR(AN78=0,$S$8=0),0,IF((AE78+$L$8+$N$8)>$S$8/HU_alpha+$K$8,0.5*$S$8/HU_alpha,IF((AE78+$L$8+$N$8)>=$K$8,((AE78+$L$8+$N$8)-$K$8)-0.5*HU_alpha/$S$8*((AE78+$L$8+$N$8)-$K$8)^2,IF((AE78+$L$8+$N$8)>=$T$8,HU_beta*((AE78+$L$8+$N$8)-$K$8),HU_beta*($T$8-$K$8))))) | AQ78: =IF(OR(AN78=0,$S$8=0),0,IF((AE78+$K$8)>$S$8/HU_alpha+$K$8,0.5*$S$8/HU_alpha,IF((AE78+$K$8)>=$K$8,((AE78+$K$8)-$K$8)-0.5*HU_alpha/$S$8*((AE78+$K$8)-$K$8)^2,IF((AE78+$K$8)>=$T$8,HU_beta*((AE78+$K$8)-$K$8),HU_beta*($T$8-$K$8))))) | AR78: =IF(AND($J$9,A78>=1,A78<=$Q$9-1),J78,0) | AS78: =IF(OR(AR78=0,$S$9=0),0,IF((AE78+$L$9)>$S$9/HU_alpha+$K$9,0.5*$S$9/HU_alpha,IF((AE78+$L$9)>=$K$9,((AE78+$L$9)-$K$9)-0.5*HU_alpha/$S$9*((AE78+$L$9)-$K$9)^2,IF((AE78+$L$9)>=$T$9,HU_beta*((AE78+$L$9)-$K$9),HU_beta*($T$9-$K$9))))) | AT78: =IF(OR(AR78=0,$S$9=0),0,IF((AE78+$L$9+$N$9)>$S$9/HU_alpha+$K$9,0.5*$S$9/HU_alpha,IF((AE78+$L$9+$N$9)>=$K$9,((AE78+$L$9+$N$9)-$K$9)-0.5*HU_alpha/$S$9*((AE78+$L$9+$N$9)-$K$9)^2,IF((AE78+$L$9+$N$9)>=$T$9,HU_beta*((AE78+$L$9+$N$9)-$K$9),HU_beta*($T$9-$K$9))))) | AU78: =IF(OR(AR78=0,$S$9=0),0,IF((AE78+$K$9)>$S$9/HU_alpha+$K$9,0.5*$S$9/HU_alpha,IF((AE78+$K$9)>=$K$9,((AE78+$K$9)-$K$9)-0.5*HU_alpha/$S$9*((AE78+$K$9)-$K$9)^2,IF((AE78+$K$9)>=$T$9,HU_beta*((AE78+$K$9)-$K$9),HU_beta*($T$9-$K$9))))) | AV78: =IF(AND($J$10,A78=$Q$10),J78,0) | AW78: =IF(OR(AV78=0,$S$10=0),0,IF((AD78+$L$10)>$S$10/HU_alpha+$K$10,0.5*$S$10/HU_alpha,IF((AD78+$L$10)>=$K$10,((AD78+$L$10)-$K$10)-0.5*HU_alpha/$S$10*((AD78+$L$10)-$K$10)^2,IF((AD78+$L$10)>=$T$10,HU_beta*((AD78+$L$10)-$K$10),HU_beta*($T$10-$K$10))))) | AX78: =IF(OR(AV78=0,$S$10=0),0,IF((AD78+$L$10+$N$10)>$S$10/HU_alpha+$K$10,0.5*$S$10/HU_alpha,IF((AD78+$L$10+$N$10)>=$K$10,((AD78+$L$10+$N$10)-$K$10)-0.5*HU_alpha/$S$10*((AD78+$L$10+$N$10)-$K$10)^2,IF((AD78+$L$10+$N$10)>=$T$10,HU_beta*((AD78+$L$10+$N$10)-$K$10),HU_beta*($T$10-$K$10))))) | AY78: =IF(OR(AV78=0,$S$10=0),0,IF((AD78+$K$10)>$S$10/HU_alpha+$K$10,0.5*$S$10/HU_alpha,IF((AD78+$K$10)>=$K$10,((AD78+$K$10)-$K$10)-0.5*HU_alpha/$S$10*((AD78+$K$10)-$K$10)^2,IF((AD78+$K$10)>=$T$10,HU_beta*((AD78+$K$10)-$K$10),HU_beta*($T$10-$K$10))))) | AZ78: =IF(AND($J$11,A78=$Q$11),J78,0) | BA78: =IF(OR(AZ78=0,$S$11=0),0,IF((AE78+$L$11)>$S$11/HU_alpha+$K$11,0.5*$S$11/HU_alpha,IF((AE78+$L$11)>=$K$11,((AE78+$L$11)-$K$11)-0.5*HU_alpha/$S$11*((AE78+$L$11)-$K$11)^2,IF((AE78+$L$11)>=$T$11,HU_beta*((AE78+$L$11)-$K$11),HU_beta*($T$11-$K$11))))) | BB78: =IF(OR(AZ78=0,$S$11=0),0,IF((AE78+$L$11+$N$11)>$S$11/HU_alpha+$K$11,0.5*$S$11/HU_alpha,IF((AE78+$L$11+$N$11)>=$K$11,((AE78+$L$11+$N$11)-$K$11)-0.5*HU_alpha/$S$11*((AE78+$L$11+$N$11)-$K$11)^2,IF((AE78+$L$11+$N$11)>=$T$11,HU_beta*((AE78+$L$11+$N$11)-$K$11),HU_beta*($T$11-$K$11))))) | BC78: =IF(OR(AZ78=0,$S$11=0),0,IF((AE78+$K$11)>$S$11/HU_alpha+$K$11,0.5*$S$11/HU_alpha,IF((AE78+$K$11)>=$K$11,((AE78+$K$11)-$K$11)-0.5*HU_alpha/$S$11*((AE78+$K$11)-$K$11)^2,IF((AE78+$K$11)>=$T$11,HU_beta*((AE78+$K$11)-$K$11),HU_beta*($T$11-$K$11))))) | BD78: =IF(AND($J$12,A78=$Q$12),J78,0) | BE78: =IF(OR(BD78=0,$S$12=0),0,IF((AE78+$L$12)>$S$12/HU_alpha+$K$12,0.5*$S$12/HU_alpha,IF((AE78+$L$12)>=$K$12,((AE78+$L$12)-$K$12)-0.5*HU_alpha/$S$12*((AE78+$L$12)-$K$12)^2,IF((AE78+$L$12)>=$T$12,HU_beta*((AE78+$L$12)-$K$12),HU_beta*($T$12-$K$12))))) | BF78: =IF(OR(BD78=0,$S$12=0),0,IF((AE78+$L$12+$N$12)>$S$12/HU_alpha+$K$12,0.5*$S$12/HU_alpha,IF((AE78+$L$12+$N$12)>=$K$12,((AE78+$L$12+$N$12)-$K$12)-0.5*HU_alpha/$S$12*((AE78+$L$12+$N$12)-$K$12)^2,IF((AE78+$L$12+$N$12)>=$T$12,HU_beta*((AE78+$L$12+$N$12)-$K$12),HU_beta*($T$12-$K$12))))) | BG78: =IF(OR(BD78=0,$S$12=0),0,IF((AE78+$K$12)>$S$12/HU_alpha+$K$12,0.5*$S$12/HU_alpha,IF((AE78+$K$12)>=$K$12,((AE78+$K$12)-$K$12)-0.5*HU_alpha/$S$12*((AE78+$K$12)-$K$12)^2,IF((AE78+$K$12)>=$T$12,HU_beta*((AE78+$K$12)-$K$12),HU_beta*($T$12-$K$12))))) | BH78: =IF(AND($J$13,A78=$Q$13),J78,0) | BI78: =IF(OR(BH78=0,$S$13=0),0,IF((AE78+$L$13)>$S$13/HU_alpha+$K$13,0.5*$S$13/HU_alpha,IF((AE78+$L$13)>=$K$13,((AE78+$L$13)-$K$13)-0.5*HU_alpha/$S$13*((AE78+$L$13)-$K$13)^2,IF((AE78+$L$13)>=$T$13,HU_beta*((AE78+$L$13)-$K$13),HU_beta*($T$13-$K$13))))) | BJ78: =IF(OR(BH78=0,$S$13=0),0,IF((AE78+$L$13+$N$13)>$S$13/HU_alpha+$K$13,0.5*$S$13/HU_alpha,IF((AE78+$L$13+$N$13)>=$K$13,((AE78+$L$13+$N$13)-$K$13)-0.5*HU_alpha/$S$13*((AE78+$L$13+$N$13)-$K$13)^2,IF((AE78+$L$13+$N$13)>=$T$13,HU_beta*((AE78+$L$13+$N$13)-$K$13),HU_beta*($T$13-$K$13))))) | BK78: =IF(OR(BH78=0,$S$13=0),0,IF((AE78+$K$13)>$S$13/HU_alpha+$K$13,0.5*$S$13/HU_alpha,IF((AE78+$K$13)>=$K$13,((AE78+$K$13)-$K$13)-0.5*HU_alpha/$S$13*((AE78+$K$13)-$K$13)^2,IF((AE78+$K$13)>=$T$13,HU_beta*((AE78+$K$13)-$K$13),HU_beta*($T$13-$K$13)))))
A79: 6 | B79: =HU_age+A79 | C79: =A79<=HU_T | D79: =IF(OR(A79<1,A79>HU_T),0,INDEX(HU_q_mort,HU_age+A79-17,HU_col)) | E79: =IF(OR(A79<1,A79>HU_T),0,INDEX(HU_q_adb,HU_age+A79-17,HU_col)) | F79: =IF(OR(A79<1,A79>HU_T),0,INDEX(HU_q_morb,HU_age+A79-17,HU_col)) | G79: =IF(OR(A79<1,A79>HU_T),0,INDEX(HU_q_ptd,HU_age+A79-17,HU_col)) | H79: =IF(OR(A79<1,A79>HU_T),0,INDEX(HU_q_dis,HU_age+A79-17,HU_col)) | I79: =IF(A79>HU_T,0,I78*(1-D79)*(1-E79)) | J79: =IF(A79>=HU_T,0,N(I80)) | K79: =K78*(1-G79) | L79: =1-K79 | M79: =K78*G79 | N79: =N78*(1-H79) | O79: =1-N78 | P79: =P78*(1-F79) | Q79: =1-P78/INDEX($P$73:$P$155,MAX(1,A79-HU_ciYears)) | R79: =(1+inflationRate)^A79 | S79: =IF(OR(OR(A79<1,A79>HU_T),A79-1>=HU_dtr),0,HU_inc0*(1+incomeGrowthRate)^A79) | T79: =IF(A79>HU_T,T78,T78*(1+INDEX(HU_ssG,HU_age+A79-17))) | U79: =IF(AND(HU_dtr>=1,A79=HU_dtr,A79<=HU_T),MIN(S79*INDEX(HU_ssC,HU_age+A79-17)/(1-INDEX(HU_ssC,HU_age+A79-17)),INDEX(HU_ssCap,HU_age+A79-17))*T79,0) | V79: =S79+U79+IF(AND(HU_wdSAVOn,A79=HU_wdSAVYear),HU_wdSAVAmt,0)+IF(AND(HU_wdPRPOn,A79=HU_wdPRPYear),HU_wdPRPAmt,0) | W79: =HU_ciProp*Q79+HU_tpdCut*L79+HU_disCut*O79 | X79: =IF(OR(A79<1,A79>HU_T),0,V79*(1-W79)) | Y79: =IF(OR(A79<1,A79>HU_T),0,IF(AND(HU_retExp>0,A79-1>=HU_dtr),HU_retExp,HU_exp0)*R79) | Z79: =-Y79-IF(AND(HU_wdEDUOn,A79=HU_wdEDUYear),HU_wdEDUAmt,0)-IF(AND(HU_wdSAVOn,A79=HU_wdSAVYear),HU_wdSAVAmt,0)-IF(AND(HU_wdPRPOn,A79=HU_wdPRPYear),HU_wdPRPAmt,0) | AA79: =IF(OR(A79<1,A79>HU_T),0,-HU_medCost*R79*F79-HU_tpdCost*R79*M79) | AB79: =IF(A79>HU_T,0,AB78*(1+interestRate)+X79+Z79+AA79) | AC79: =IF(A79>HU_T,0,HU_inv*EXP(HU_mu*A79)) | AD79: =IF(A79>HU_T,0,MAX(0,AC79+AB79)) | AE79: =IF(A79>HU_T,0,MAX(0,X79-Y79)) | AF79: =IF(AND($J$6,A79>=1,A79<=$Q$6-1),J79,0) | AG79: =IF(OR(AF79=0,$S$6=0),0,IF((AD79+$L$6)>$S$6/HU_alpha+$K$6,0.5*$S$6/HU_alpha,IF((AD79+$L$6)>=$K$6,((AD79+$L$6)-$K$6)-0.5*HU_alpha/$S$6*((AD79+$L$6)-$K$6)^2,IF((AD79+$L$6)>=$T$6,HU_beta*((AD79+$L$6)-$K$6),HU_beta*($T$6-$K$6))))) | AH79: =IF(OR(AF79=0,$S$6=0),0,IF((AD79+$L$6+$N$6)>$S$6/HU_alpha+$K$6,0.5*$S$6/HU_alpha,IF((AD79+$L$6+$N$6)>=$K$6,((AD79+$L$6+$N$6)-$K$6)-0.5*HU_alpha/$S$6*((AD79+$L$6+$N$6)-$K$6)^2,IF((AD79+$L$6+$N$6)>=$T$6,HU_beta*((AD79+$L$6+$N$6)-$K$6),HU_beta*($T$6-$K$6))))) | AI79: =IF(OR(AF79=0,$S$6=0),0,IF((AD79+$K$6)>$S$6/HU_alpha+$K$6,0.5*$S$6/HU_alpha,IF((AD79+$K$6)>=$K$6,((AD79+$K$6)-$K$6)-0.5*HU_alpha/$S$6*((AD79+$K$6)-$K$6)^2,IF((AD79+$K$6)>=$T$6,HU_beta*((AD79+$K$6)-$K$6),HU_beta*($T$6-$K$6))))) | AJ79: =IF(AND($J$7,A79>=1,A79<=$Q$7-1),J79,0) | AK79: =IF(OR(AJ79=0,$S$7=0),0,IF((AE79+$L$7)>$S$7/HU_alpha+$K$7,0.5*$S$7/HU_alpha,IF((AE79+$L$7)>=$K$7,((AE79+$L$7)-$K$7)-0.5*HU_alpha/$S$7*((AE79+$L$7)-$K$7)^2,IF((AE79+$L$7)>=$T$7,HU_beta*((AE79+$L$7)-$K$7),HU_beta*($T$7-$K$7))))) | AL79: =IF(OR(AJ79=0,$S$7=0),0,IF((AE79+$L$7+$N$7)>$S$7/HU_alpha+$K$7,0.5*$S$7/HU_alpha,IF((AE79+$L$7+$N$7)>=$K$7,((AE79+$L$7+$N$7)-$K$7)-0.5*HU_alpha/$S$7*((AE79+$L$7+$N$7)-$K$7)^2,IF((AE79+$L$7+$N$7)>=$T$7,HU_beta*((AE79+$L$7+$N$7)-$K$7),HU_beta*($T$7-$K$7))))) | AM79: =IF(OR(AJ79=0,$S$7=0),0,IF((AE79+$K$7)>$S$7/HU_alpha+$K$7,0.5*$S$7/HU_alpha,IF((AE79+$K$7)>=$K$7,((AE79+$K$7)-$K$7)-0.5*HU_alpha/$S$7*((AE79+$K$7)-$K$7)^2,IF((AE79+$K$7)>=$T$7,HU_beta*((AE79+$K$7)-$K$7),HU_beta*($T$7-$K$7))))) | AN79: =IF(AND($J$8,A79>=1,A79<=$Q$8-1),J79,0) | AO79: =IF(OR(AN79=0,$S$8=0),0,IF((AE79+$L$8)>$S$8/HU_alpha+$K$8,0.5*$S$8/HU_alpha,IF((AE79+$L$8)>=$K$8,((AE79+$L$8)-$K$8)-0.5*HU_alpha/$S$8*((AE79+$L$8)-$K$8)^2,IF((AE79+$L$8)>=$T$8,HU_beta*((AE79+$L$8)-$K$8),HU_beta*($T$8-$K$8))))) | AP79: =IF(OR(AN79=0,$S$8=0),0,IF((AE79+$L$8+$N$8)>$S$8/HU_alpha+$K$8,0.5*$S$8/HU_alpha,IF((AE79+$L$8+$N$8)>=$K$8,((AE79+$L$8+$N$8)-$K$8)-0.5*HU_alpha/$S$8*((AE79+$L$8+$N$8)-$K$8)^2,IF((AE79+$L$8+$N$8)>=$T$8,HU_beta*((AE79+$L$8+$N$8)-$K$8),HU_beta*($T$8-$K$8))))) | AQ79: =IF(OR(AN79=0,$S$8=0),0,IF((AE79+$K$8)>$S$8/HU_alpha+$K$8,0.5*$S$8/HU_alpha,IF((AE79+$K$8)>=$K$8,((AE79+$K$8)-$K$8)-0.5*HU_alpha/$S$8*((AE79+$K$8)-$K$8)^2,IF((AE79+$K$8)>=$T$8,HU_beta*((AE79+$K$8)-$K$8),HU_beta*($T$8-$K$8))))) | AR79: =IF(AND($J$9,A79>=1,A79<=$Q$9-1),J79,0) | AS79: =IF(OR(AR79=0,$S$9=0),0,IF((AE79+$L$9)>$S$9/HU_alpha+$K$9,0.5*$S$9/HU_alpha,IF((AE79+$L$9)>=$K$9,((AE79+$L$9)-$K$9)-0.5*HU_alpha/$S$9*((AE79+$L$9)-$K$9)^2,IF((AE79+$L$9)>=$T$9,HU_beta*((AE79+$L$9)-$K$9),HU_beta*($T$9-$K$9))))) | AT79: =IF(OR(AR79=0,$S$9=0),0,IF((AE79+$L$9+$N$9)>$S$9/HU_alpha+$K$9,0.5*$S$9/HU_alpha,IF((AE79+$L$9+$N$9)>=$K$9,((AE79+$L$9+$N$9)-$K$9)-0.5*HU_alpha/$S$9*((AE79+$L$9+$N$9)-$K$9)^2,IF((AE79+$L$9+$N$9)>=$T$9,HU_beta*((AE79+$L$9+$N$9)-$K$9),HU_beta*($T$9-$K$9))))) | AU79: =IF(OR(AR79=0,$S$9=0),0,IF((AE79+$K$9)>$S$9/HU_alpha+$K$9,0.5*$S$9/HU_alpha,IF((AE79+$K$9)>=$K$9,((AE79+$K$9)-$K$9)-0.5*HU_alpha/$S$9*((AE79+$K$9)-$K$9)^2,IF((AE79+$K$9)>=$T$9,HU_beta*((AE79+$K$9)-$K$9),HU_beta*($T$9-$K$9))))) | AV79: =IF(AND($J$10,A79=$Q$10),J79,0) | AW79: =IF(OR(AV79=0,$S$10=0),0,IF((AD79+$L$10)>$S$10/HU_alpha+$K$10,0.5*$S$10/HU_alpha,IF((AD79+$L$10)>=$K$10,((AD79+$L$10)-$K$10)-0.5*HU_alpha/$S$10*((AD79+$L$10)-$K$10)^2,IF((AD79+$L$10)>=$T$10,HU_beta*((AD79+$L$10)-$K$10),HU_beta*($T$10-$K$10))))) | AX79: =IF(OR(AV79=0,$S$10=0),0,IF((AD79+$L$10+$N$10)>$S$10/HU_alpha+$K$10,0.5*$S$10/HU_alpha,IF((AD79+$L$10+$N$10)>=$K$10,((AD79+$L$10+$N$10)-$K$10)-0.5*HU_alpha/$S$10*((AD79+$L$10+$N$10)-$K$10)^2,IF((AD79+$L$10+$N$10)>=$T$10,HU_beta*((AD79+$L$10+$N$10)-$K$10),HU_beta*($T$10-$K$10))))) | AY79: =IF(OR(AV79=0,$S$10=0),0,IF((AD79+$K$10)>$S$10/HU_alpha+$K$10,0.5*$S$10/HU_alpha,IF((AD79+$K$10)>=$K$10,((AD79+$K$10)-$K$10)-0.5*HU_alpha/$S$10*((AD79+$K$10)-$K$10)^2,IF((AD79+$K$10)>=$T$10,HU_beta*((AD79+$K$10)-$K$10),HU_beta*($T$10-$K$10))))) | AZ79: =IF(AND($J$11,A79=$Q$11),J79,0) | BA79: =IF(OR(AZ79=0,$S$11=0),0,IF((AE79+$L$11)>$S$11/HU_alpha+$K$11,0.5*$S$11/HU_alpha,IF((AE79+$L$11)>=$K$11,((AE79+$L$11)-$K$11)-0.5*HU_alpha/$S$11*((AE79+$L$11)-$K$11)^2,IF((AE79+$L$11)>=$T$11,HU_beta*((AE79+$L$11)-$K$11),HU_beta*($T$11-$K$11))))) | BB79: =IF(OR(AZ79=0,$S$11=0),0,IF((AE79+$L$11+$N$11)>$S$11/HU_alpha+$K$11,0.5*$S$11/HU_alpha,IF((AE79+$L$11+$N$11)>=$K$11,((AE79+$L$11+$N$11)-$K$11)-0.5*HU_alpha/$S$11*((AE79+$L$11+$N$11)-$K$11)^2,IF((AE79+$L$11+$N$11)>=$T$11,HU_beta*((AE79+$L$11+$N$11)-$K$11),HU_beta*($T$11-$K$11))))) | BC79: =IF(OR(AZ79=0,$S$11=0),0,IF((AE79+$K$11)>$S$11/HU_alpha+$K$11,0.5*$S$11/HU_alpha,IF((AE79+$K$11)>=$K$11,((AE79+$K$11)-$K$11)-0.5*HU_alpha/$S$11*((AE79+$K$11)-$K$11)^2,IF((AE79+$K$11)>=$T$11,HU_beta*((AE79+$K$11)-$K$11),HU_beta*($T$11-$K$11))))) | BD79: =IF(AND($J$12,A79=$Q$12),J79,0) | BE79: =IF(OR(BD79=0,$S$12=0),0,IF((AE79+$L$12)>$S$12/HU_alpha+$K$12,0.5*$S$12/HU_alpha,IF((AE79+$L$12)>=$K$12,((AE79+$L$12)-$K$12)-0.5*HU_alpha/$S$12*((AE79+$L$12)-$K$12)^2,IF((AE79+$L$12)>=$T$12,HU_beta*((AE79+$L$12)-$K$12),HU_beta*($T$12-$K$12))))) | BF79: =IF(OR(BD79=0,$S$12=0),0,IF((AE79+$L$12+$N$12)>$S$12/HU_alpha+$K$12,0.5*$S$12/HU_alpha,IF((AE79+$L$12+$N$12)>=$K$12,((AE79+$L$12+$N$12)-$K$12)-0.5*HU_alpha/$S$12*((AE79+$L$12+$N$12)-$K$12)^2,IF((AE79+$L$12+$N$12)>=$T$12,HU_beta*((AE79+$L$12+$N$12)-$K$12),HU_beta*($T$12-$K$12))))) | BG79: =IF(OR(BD79=0,$S$12=0),0,IF((AE79+$K$12)>$S$12/HU_alpha+$K$12,0.5*$S$12/HU_alpha,IF((AE79+$K$12)>=$K$12,((AE79+$K$12)-$K$12)-0.5*HU_alpha/$S$12*((AE79+$K$12)-$K$12)^2,IF((AE79+$K$12)>=$T$12,HU_beta*((AE79+$K$12)-$K$12),HU_beta*($T$12-$K$12))))) | BH79: =IF(AND($J$13,A79=$Q$13),J79,0) | BI79: =IF(OR(BH79=0,$S$13=0),0,IF((AE79+$L$13)>$S$13/HU_alpha+$K$13,0.5*$S$13/HU_alpha,IF((AE79+$L$13)>=$K$13,((AE79+$L$13)-$K$13)-0.5*HU_alpha/$S$13*((AE79+$L$13)-$K$13)^2,IF((AE79+$L$13)>=$T$13,HU_beta*((AE79+$L$13)-$K$13),HU_beta*($T$13-$K$13))))) | BJ79: =IF(OR(BH79=0,$S$13=0),0,IF((AE79+$L$13+$N$13)>$S$13/HU_alpha+$K$13,0.5*$S$13/HU_alpha,IF((AE79+$L$13+$N$13)>=$K$13,((AE79+$L$13+$N$13)-$K$13)-0.5*HU_alpha/$S$13*((AE79+$L$13+$N$13)-$K$13)^2,IF((AE79+$L$13+$N$13)>=$T$13,HU_beta*((AE79+$L$13+$N$13)-$K$13),HU_beta*($T$13-$K$13))))) | BK79: =IF(OR(BH79=0,$S$13=0),0,IF((AE79+$K$13)>$S$13/HU_alpha+$K$13,0.5*$S$13/HU_alpha,IF((AE79+$K$13)>=$K$13,((AE79+$K$13)-$K$13)-0.5*HU_alpha/$S$13*((AE79+$K$13)-$K$13)^2,IF((AE79+$K$13)>=$T$13,HU_beta*((AE79+$K$13)-$K$13),HU_beta*($T$13-$K$13)))))
A80: 7 | B80: =HU_age+A80 | C80: =A80<=HU_T | D80: =IF(OR(A80<1,A80>HU_T),0,INDEX(HU_q_mort,HU_age+A80-17,HU_col)) | E80: =IF(OR(A80<1,A80>HU_T),0,INDEX(HU_q_adb,HU_age+A80-17,HU_col)) | F80: =IF(OR(A80<1,A80>HU_T),0,INDEX(HU_q_morb,HU_age+A80-17,HU_col)) | G80: =IF(OR(A80<1,A80>HU_T),0,INDEX(HU_q_ptd,HU_age+A80-17,HU_col)) | H80: =IF(OR(A80<1,A80>HU_T),0,INDEX(HU_q_dis,HU_age+A80-17,HU_col)) | I80: =IF(A80>HU_T,0,I79*(1-D80)*(1-E80)) | J80: =IF(A80>=HU_T,0,N(I81)) | K80: =K79*(1-G80) | L80: =1-K80 | M80: =K79*G80 | N80: =N79*(1-H80) | O80: =1-N79 | P80: =P79*(1-F80) | Q80: =1-P79/INDEX($P$73:$P$155,MAX(1,A80-HU_ciYears)) | R80: =(1+inflationRate)^A80 | S80: =IF(OR(OR(A80<1,A80>HU_T),A80-1>=HU_dtr),0,HU_inc0*(1+incomeGrowthRate)^A80) | T80: =IF(A80>HU_T,T79,T79*(1+INDEX(HU_ssG,HU_age+A80-17))) | U80: =IF(AND(HU_dtr>=1,A80=HU_dtr,A80<=HU_T),MIN(S80*INDEX(HU_ssC,HU_age+A80-17)/(1-INDEX(HU_ssC,HU_age+A80-17)),INDEX(HU_ssCap,HU_age+A80-17))*T80,0) | V80: =S80+U80+IF(AND(HU_wdSAVOn,A80=HU_wdSAVYear),HU_wdSAVAmt,0)+IF(AND(HU_wdPRPOn,A80=HU_wdPRPYear),HU_wdPRPAmt,0) | W80: =HU_ciProp*Q80+HU_tpdCut*L80+HU_disCut*O80 | X80: =IF(OR(A80<1,A80>HU_T),0,V80*(1-W80)) | Y80: =IF(OR(A80<1,A80>HU_T),0,IF(AND(HU_retExp>0,A80-1>=HU_dtr),HU_retExp,HU_exp0)*R80) | Z80: =-Y80-IF(AND(HU_wdEDUOn,A80=HU_wdEDUYear),HU_wdEDUAmt,0)-IF(AND(HU_wdSAVOn,A80=HU_wdSAVYear),HU_wdSAVAmt,0)-IF(AND(HU_wdPRPOn,A80=HU_wdPRPYear),HU_wdPRPAmt,0) | AA80: =IF(OR(A80<1,A80>HU_T),0,-HU_medCost*R80*F80-HU_tpdCost*R80*M80) | AB80: =IF(A80>HU_T,0,AB79*(1+interestRate)+X80+Z80+AA80) | AC80: =IF(A80>HU_T,0,HU_inv*EXP(HU_mu*A80)) | AD80: =IF(A80>HU_T,0,MAX(0,AC80+AB80)) | AE80: =IF(A80>HU_T,0,MAX(0,X80-Y80)) | AF80: =IF(AND($J$6,A80>=1,A80<=$Q$6-1),J80,0) | AG80: =IF(OR(AF80=0,$S$6=0),0,IF((AD80+$L$6)>$S$6/HU_alpha+$K$6,0.5*$S$6/HU_alpha,IF((AD80+$L$6)>=$K$6,((AD80+$L$6)-$K$6)-0.5*HU_alpha/$S$6*((AD80+$L$6)-$K$6)^2,IF((AD80+$L$6)>=$T$6,HU_beta*((AD80+$L$6)-$K$6),HU_beta*($T$6-$K$6))))) | AH80: =IF(OR(AF80=0,$S$6=0),0,IF((AD80+$L$6+$N$6)>$S$6/HU_alpha+$K$6,0.5*$S$6/HU_alpha,IF((AD80+$L$6+$N$6)>=$K$6,((AD80+$L$6+$N$6)-$K$6)-0.5*HU_alpha/$S$6*((AD80+$L$6+$N$6)-$K$6)^2,IF((AD80+$L$6+$N$6)>=$T$6,HU_beta*((AD80+$L$6+$N$6)-$K$6),HU_beta*($T$6-$K$6))))) | AI80: =IF(OR(AF80=0,$S$6=0),0,IF((AD80+$K$6)>$S$6/HU_alpha+$K$6,0.5*$S$6/HU_alpha,IF((AD80+$K$6)>=$K$6,((AD80+$K$6)-$K$6)-0.5*HU_alpha/$S$6*((AD80+$K$6)-$K$6)^2,IF((AD80+$K$6)>=$T$6,HU_beta*((AD80+$K$6)-$K$6),HU_beta*($T$6-$K$6))))) | AJ80: =IF(AND($J$7,A80>=1,A80<=$Q$7-1),J80,0) | AK80: =IF(OR(AJ80=0,$S$7=0),0,IF((AE80+$L$7)>$S$7/HU_alpha+$K$7,0.5*$S$7/HU_alpha,IF((AE80+$L$7)>=$K$7,((AE80+$L$7)-$K$7)-0.5*HU_alpha/$S$7*((AE80+$L$7)-$K$7)^2,IF((AE80+$L$7)>=$T$7,HU_beta*((AE80+$L$7)-$K$7),HU_beta*($T$7-$K$7))))) | AL80: =IF(OR(AJ80=0,$S$7=0),0,IF((AE80+$L$7+$N$7)>$S$7/HU_alpha+$K$7,0.5*$S$7/HU_alpha,IF((AE80+$L$7+$N$7)>=$K$7,((AE80+$L$7+$N$7)-$K$7)-0.5*HU_alpha/$S$7*((AE80+$L$7+$N$7)-$K$7)^2,IF((AE80+$L$7+$N$7)>=$T$7,HU_beta*((AE80+$L$7+$N$7)-$K$7),HU_beta*($T$7-$K$7))))) | AM80: =IF(OR(AJ80=0,$S$7=0),0,IF((AE80+$K$7)>$S$7/HU_alpha+$K$7,0.5*$S$7/HU_alpha,IF((AE80+$K$7)>=$K$7,((AE80+$K$7)-$K$7)-0.5*HU_alpha/$S$7*((AE80+$K$7)-$K$7)^2,IF((AE80+$K$7)>=$T$7,HU_beta*((AE80+$K$7)-$K$7),HU_beta*($T$7-$K$7))))) | AN80: =IF(AND($J$8,A80>=1,A80<=$Q$8-1),J80,0) | AO80: =IF(OR(AN80=0,$S$8=0),0,IF((AE80+$L$8)>$S$8/HU_alpha+$K$8,0.5*$S$8/HU_alpha,IF((AE80+$L$8)>=$K$8,((AE80+$L$8)-$K$8)-0.5*HU_alpha/$S$8*((AE80+$L$8)-$K$8)^2,IF((AE80+$L$8)>=$T$8,HU_beta*((AE80+$L$8)-$K$8),HU_beta*($T$8-$K$8))))) | AP80: =IF(OR(AN80=0,$S$8=0),0,IF((AE80+$L$8+$N$8)>$S$8/HU_alpha+$K$8,0.5*$S$8/HU_alpha,IF((AE80+$L$8+$N$8)>=$K$8,((AE80+$L$8+$N$8)-$K$8)-0.5*HU_alpha/$S$8*((AE80+$L$8+$N$8)-$K$8)^2,IF((AE80+$L$8+$N$8)>=$T$8,HU_beta*((AE80+$L$8+$N$8)-$K$8),HU_beta*($T$8-$K$8))))) | AQ80: =IF(OR(AN80=0,$S$8=0),0,IF((AE80+$K$8)>$S$8/HU_alpha+$K$8,0.5*$S$8/HU_alpha,IF((AE80+$K$8)>=$K$8,((AE80+$K$8)-$K$8)-0.5*HU_alpha/$S$8*((AE80+$K$8)-$K$8)^2,IF((AE80+$K$8)>=$T$8,HU_beta*((AE80+$K$8)-$K$8),HU_beta*($T$8-$K$8))))) | AR80: =IF(AND($J$9,A80>=1,A80<=$Q$9-1),J80,0) | AS80: =IF(OR(AR80=0,$S$9=0),0,IF((AE80+$L$9)>$S$9/HU_alpha+$K$9,0.5*$S$9/HU_alpha,IF((AE80+$L$9)>=$K$9,((AE80+$L$9)-$K$9)-0.5*HU_alpha/$S$9*((AE80+$L$9)-$K$9)^2,IF((AE80+$L$9)>=$T$9,HU_beta*((AE80+$L$9)-$K$9),HU_beta*($T$9-$K$9))))) | AT80: =IF(OR(AR80=0,$S$9=0),0,IF((AE80+$L$9+$N$9)>$S$9/HU_alpha+$K$9,0.5*$S$9/HU_alpha,IF((AE80+$L$9+$N$9)>=$K$9,((AE80+$L$9+$N$9)-$K$9)-0.5*HU_alpha/$S$9*((AE80+$L$9+$N$9)-$K$9)^2,IF((AE80+$L$9+$N$9)>=$T$9,HU_beta*((AE80+$L$9+$N$9)-$K$9),HU_beta*($T$9-$K$9))))) | AU80: =IF(OR(AR80=0,$S$9=0),0,IF((AE80+$K$9)>$S$9/HU_alpha+$K$9,0.5*$S$9/HU_alpha,IF((AE80+$K$9)>=$K$9,((AE80+$K$9)-$K$9)-0.5*HU_alpha/$S$9*((AE80+$K$9)-$K$9)^2,IF((AE80+$K$9)>=$T$9,HU_beta*((AE80+$K$9)-$K$9),HU_beta*($T$9-$K$9))))) | AV80: =IF(AND($J$10,A80=$Q$10),J80,0) | AW80: =IF(OR(AV80=0,$S$10=0),0,IF((AD80+$L$10)>$S$10/HU_alpha+$K$10,0.5*$S$10/HU_alpha,IF((AD80+$L$10)>=$K$10,((AD80+$L$10)-$K$10)-0.5*HU_alpha/$S$10*((AD80+$L$10)-$K$10)^2,IF((AD80+$L$10)>=$T$10,HU_beta*((AD80+$L$10)-$K$10),HU_beta*($T$10-$K$10))))) | AX80: =IF(OR(AV80=0,$S$10=0),0,IF((AD80+$L$10+$N$10)>$S$10/HU_alpha+$K$10,0.5*$S$10/HU_alpha,IF((AD80+$L$10+$N$10)>=$K$10,((AD80+$L$10+$N$10)-$K$10)-0.5*HU_alpha/$S$10*((AD80+$L$10+$N$10)-$K$10)^2,IF((AD80+$L$10+$N$10)>=$T$10,HU_beta*((AD80+$L$10+$N$10)-$K$10),HU_beta*($T$10-$K$10))))) | AY80: =IF(OR(AV80=0,$S$10=0),0,IF((AD80+$K$10)>$S$10/HU_alpha+$K$10,0.5*$S$10/HU_alpha,IF((AD80+$K$10)>=$K$10,((AD80+$K$10)-$K$10)-0.5*HU_alpha/$S$10*((AD80+$K$10)-$K$10)^2,IF((AD80+$K$10)>=$T$10,HU_beta*((AD80+$K$10)-$K$10),HU_beta*($T$10-$K$10))))) | AZ80: =IF(AND($J$11,A80=$Q$11),J80,0) | BA80: =IF(OR(AZ80=0,$S$11=0),0,IF((AE80+$L$11)>$S$11/HU_alpha+$K$11,0.5*$S$11/HU_alpha,IF((AE80+$L$11)>=$K$11,((AE80+$L$11)-$K$11)-0.5*HU_alpha/$S$11*((AE80+$L$11)-$K$11)^2,IF((AE80+$L$11)>=$T$11,HU_beta*((AE80+$L$11)-$K$11),HU_beta*($T$11-$K$11))))) | BB80: =IF(OR(AZ80=0,$S$11=0),0,IF((AE80+$L$11+$N$11)>$S$11/HU_alpha+$K$11,0.5*$S$11/HU_alpha,IF((AE80+$L$11+$N$11)>=$K$11,((AE80+$L$11+$N$11)-$K$11)-0.5*HU_alpha/$S$11*((AE80+$L$11+$N$11)-$K$11)^2,IF((AE80+$L$11+$N$11)>=$T$11,HU_beta*((AE80+$L$11+$N$11)-$K$11),HU_beta*($T$11-$K$11))))) | BC80: =IF(OR(AZ80=0,$S$11=0),0,IF((AE80+$K$11)>$S$11/HU_alpha+$K$11,0.5*$S$11/HU_alpha,IF((AE80+$K$11)>=$K$11,((AE80+$K$11)-$K$11)-0.5*HU_alpha/$S$11*((AE80+$K$11)-$K$11)^2,IF((AE80+$K$11)>=$T$11,HU_beta*((AE80+$K$11)-$K$11),HU_beta*($T$11-$K$11))))) | BD80: =IF(AND($J$12,A80=$Q$12),J80,0) | BE80: =IF(OR(BD80=0,$S$12=0),0,IF((AE80+$L$12)>$S$12/HU_alpha+$K$12,0.5*$S$12/HU_alpha,IF((AE80+$L$12)>=$K$12,((AE80+$L$12)-$K$12)-0.5*HU_alpha/$S$12*((AE80+$L$12)-$K$12)^2,IF((AE80+$L$12)>=$T$12,HU_beta*((AE80+$L$12)-$K$12),HU_beta*($T$12-$K$12))))) | BF80: =IF(OR(BD80=0,$S$12=0),0,IF((AE80+$L$12+$N$12)>$S$12/HU_alpha+$K$12,0.5*$S$12/HU_alpha,IF((AE80+$L$12+$N$12)>=$K$12,((AE80+$L$12+$N$12)-$K$12)-0.5*HU_alpha/$S$12*((AE80+$L$12+$N$12)-$K$12)^2,IF((AE80+$L$12+$N$12)>=$T$12,HU_beta*((AE80+$L$12+$N$12)-$K$12),HU_beta*($T$12-$K$12))))) | BG80: =IF(OR(BD80=0,$S$12=0),0,IF((AE80+$K$12)>$S$12/HU_alpha+$K$12,0.5*$S$12/HU_alpha,IF((AE80+$K$12)>=$K$12,((AE80+$K$12)-$K$12)-0.5*HU_alpha/$S$12*((AE80+$K$12)-$K$12)^2,IF((AE80+$K$12)>=$T$12,HU_beta*((AE80+$K$12)-$K$12),HU_beta*($T$12-$K$12))))) | BH80: =IF(AND($J$13,A80=$Q$13),J80,0) | BI80: =IF(OR(BH80=0,$S$13=0),0,IF((AE80+$L$13)>$S$13/HU_alpha+$K$13,0.5*$S$13/HU_alpha,IF((AE80+$L$13)>=$K$13,((AE80+$L$13)-$K$13)-0.5*HU_alpha/$S$13*((AE80+$L$13)-$K$13)^2,IF((AE80+$L$13)>=$T$13,HU_beta*((AE80+$L$13)-$K$13),HU_beta*($T$13-$K$13))))) | BJ80: =IF(OR(BH80=0,$S$13=0),0,IF((AE80+$L$13+$N$13)>$S$13/HU_alpha+$K$13,0.5*$S$13/HU_alpha,IF((AE80+$L$13+$N$13)>=$K$13,((AE80+$L$13+$N$13)-$K$13)-0.5*HU_alpha/$S$13*((AE80+$L$13+$N$13)-$K$13)^2,IF((AE80+$L$13+$N$13)>=$T$13,HU_beta*((AE80+$L$13+$N$13)-$K$13),HU_beta*($T$13-$K$13))))) | BK80: =IF(OR(BH80=0,$S$13=0),0,IF((AE80+$K$13)>$S$13/HU_alpha+$K$13,0.5*$S$13/HU_alpha,IF((AE80+$K$13)>=$K$13,((AE80+$K$13)-$K$13)-0.5*HU_alpha/$S$13*((AE80+$K$13)-$K$13)^2,IF((AE80+$K$13)>=$T$13,HU_beta*((AE80+$K$13)-$K$13),HU_beta*($T$13-$K$13)))))
A81: 8 | B81: =HU_age+A81 | C81: =A81<=HU_T | D81: =IF(OR(A81<1,A81>HU_T),0,INDEX(HU_q_mort,HU_age+A81-17,HU_col)) | E81: =IF(OR(A81<1,A81>HU_T),0,INDEX(HU_q_adb,HU_age+A81-17,HU_col)) | F81: =IF(OR(A81<1,A81>HU_T),0,INDEX(HU_q_morb,HU_age+A81-17,HU_col)) | G81: =IF(OR(A81<1,A81>HU_T),0,INDEX(HU_q_ptd,HU_age+A81-17,HU_col)) | H81: =IF(OR(A81<1,A81>HU_T),0,INDEX(HU_q_dis,HU_age+A81-17,HU_col)) | I81: =IF(A81>HU_T,0,I80*(1-D81)*(1-E81)) | J81: =IF(A81>=HU_T,0,N(I82)) | K81: =K80*(1-G81) | L81: =1-K81 | M81: =K80*G81 | N81: =N80*(1-H81) | O81: =1-N80 | P81: =P80*(1-F81) | Q81: =1-P80/INDEX($P$73:$P$155,MAX(1,A81-HU_ciYears)) | R81: =(1+inflationRate)^A81 | S81: =IF(OR(OR(A81<1,A81>HU_T),A81-1>=HU_dtr),0,HU_inc0*(1+incomeGrowthRate)^A81) | T81: =IF(A81>HU_T,T80,T80*(1+INDEX(HU_ssG,HU_age+A81-17))) | U81: =IF(AND(HU_dtr>=1,A81=HU_dtr,A81<=HU_T),MIN(S81*INDEX(HU_ssC,HU_age+A81-17)/(1-INDEX(HU_ssC,HU_age+A81-17)),INDEX(HU_ssCap,HU_age+A81-17))*T81,0) | V81: =S81+U81+IF(AND(HU_wdSAVOn,A81=HU_wdSAVYear),HU_wdSAVAmt,0)+IF(AND(HU_wdPRPOn,A81=HU_wdPRPYear),HU_wdPRPAmt,0) | W81: =HU_ciProp*Q81+HU_tpdCut*L81+HU_disCut*O81 | X81: =IF(OR(A81<1,A81>HU_T),0,V81*(1-W81)) | Y81: =IF(OR(A81<1,A81>HU_T),0,IF(AND(HU_retExp>0,A81-1>=HU_dtr),HU_retExp,HU_exp0)*R81) | Z81: =-Y81-IF(AND(HU_wdEDUOn,A81=HU_wdEDUYear),HU_wdEDUAmt,0)-IF(AND(HU_wdSAVOn,A81=HU_wdSAVYear),HU_wdSAVAmt,0)-IF(AND(HU_wdPRPOn,A81=HU_wdPRPYear),HU_wdPRPAmt,0) | AA81: =IF(OR(A81<1,A81>HU_T),0,-HU_medCost*R81*F81-HU_tpdCost*R81*M81) | AB81: =IF(A81>HU_T,0,AB80*(1+interestRate)+X81+Z81+AA81) | AC81: =IF(A81>HU_T,0,HU_inv*EXP(HU_mu*A81)) | AD81: =IF(A81>HU_T,0,MAX(0,AC81+AB81)) | AE81: =IF(A81>HU_T,0,MAX(0,X81-Y81)) | AF81: =IF(AND($J$6,A81>=1,A81<=$Q$6-1),J81,0) | AG81: =IF(OR(AF81=0,$S$6=0),0,IF((AD81+$L$6)>$S$6/HU_alpha+$K$6,0.5*$S$6/HU_alpha,IF((AD81+$L$6)>=$K$6,((AD81+$L$6)-$K$6)-0.5*HU_alpha/$S$6*((AD81+$L$6)-$K$6)^2,IF((AD81+$L$6)>=$T$6,HU_beta*((AD81+$L$6)-$K$6),HU_beta*($T$6-$K$6))))) | AH81: =IF(OR(AF81=0,$S$6=0),0,IF((AD81+$L$6+$N$6)>$S$6/HU_alpha+$K$6,0.5*$S$6/HU_alpha,IF((AD81+$L$6+$N$6)>=$K$6,((AD81+$L$6+$N$6)-$K$6)-0.5*HU_alpha/$S$6*((AD81+$L$6+$N$6)-$K$6)^2,IF((AD81+$L$6+$N$6)>=$T$6,HU_beta*((AD81+$L$6+$N$6)-$K$6),HU_beta*($T$6-$K$6))))) | AI81: =IF(OR(AF81=0,$S$6=0),0,IF((AD81+$K$6)>$S$6/HU_alpha+$K$6,0.5*$S$6/HU_alpha,IF((AD81+$K$6)>=$K$6,((AD81+$K$6)-$K$6)-0.5*HU_alpha/$S$6*((AD81+$K$6)-$K$6)^2,IF((AD81+$K$6)>=$T$6,HU_beta*((AD81+$K$6)-$K$6),HU_beta*($T$6-$K$6))))) | AJ81: =IF(AND($J$7,A81>=1,A81<=$Q$7-1),J81,0) | AK81: =IF(OR(AJ81=0,$S$7=0),0,IF((AE81+$L$7)>$S$7/HU_alpha+$K$7,0.5*$S$7/HU_alpha,IF((AE81+$L$7)>=$K$7,((AE81+$L$7)-$K$7)-0.5*HU_alpha/$S$7*((AE81+$L$7)-$K$7)^2,IF((AE81+$L$7)>=$T$7,HU_beta*((AE81+$L$7)-$K$7),HU_beta*($T$7-$K$7))))) | AL81: =IF(OR(AJ81=0,$S$7=0),0,IF((AE81+$L$7+$N$7)>$S$7/HU_alpha+$K$7,0.5*$S$7/HU_alpha,IF((AE81+$L$7+$N$7)>=$K$7,((AE81+$L$7+$N$7)-$K$7)-0.5*HU_alpha/$S$7*((AE81+$L$7+$N$7)-$K$7)^2,IF((AE81+$L$7+$N$7)>=$T$7,HU_beta*((AE81+$L$7+$N$7)-$K$7),HU_beta*($T$7-$K$7))))) | AM81: =IF(OR(AJ81=0,$S$7=0),0,IF((AE81+$K$7)>$S$7/HU_alpha+$K$7,0.5*$S$7/HU_alpha,IF((AE81+$K$7)>=$K$7,((AE81+$K$7)-$K$7)-0.5*HU_alpha/$S$7*((AE81+$K$7)-$K$7)^2,IF((AE81+$K$7)>=$T$7,HU_beta*((AE81+$K$7)-$K$7),HU_beta*($T$7-$K$7))))) | AN81: =IF(AND($J$8,A81>=1,A81<=$Q$8-1),J81,0) | AO81: =IF(OR(AN81=0,$S$8=0),0,IF((AE81+$L$8)>$S$8/HU_alpha+$K$8,0.5*$S$8/HU_alpha,IF((AE81+$L$8)>=$K$8,((AE81+$L$8)-$K$8)-0.5*HU_alpha/$S$8*((AE81+$L$8)-$K$8)^2,IF((AE81+$L$8)>=$T$8,HU_beta*((AE81+$L$8)-$K$8),HU_beta*($T$8-$K$8))))) | AP81: =IF(OR(AN81=0,$S$8=0),0,IF((AE81+$L$8+$N$8)>$S$8/HU_alpha+$K$8,0.5*$S$8/HU_alpha,IF((AE81+$L$8+$N$8)>=$K$8,((AE81+$L$8+$N$8)-$K$8)-0.5*HU_alpha/$S$8*((AE81+$L$8+$N$8)-$K$8)^2,IF((AE81+$L$8+$N$8)>=$T$8,HU_beta*((AE81+$L$8+$N$8)-$K$8),HU_beta*($T$8-$K$8))))) | AQ81: =IF(OR(AN81=0,$S$8=0),0,IF((AE81+$K$8)>$S$8/HU_alpha+$K$8,0.5*$S$8/HU_alpha,IF((AE81+$K$8)>=$K$8,((AE81+$K$8)-$K$8)-0.5*HU_alpha/$S$8*((AE81+$K$8)-$K$8)^2,IF((AE81+$K$8)>=$T$8,HU_beta*((AE81+$K$8)-$K$8),HU_beta*($T$8-$K$8))))) | AR81: =IF(AND($J$9,A81>=1,A81<=$Q$9-1),J81,0) | AS81: =IF(OR(AR81=0,$S$9=0),0,IF((AE81+$L$9)>$S$9/HU_alpha+$K$9,0.5*$S$9/HU_alpha,IF((AE81+$L$9)>=$K$9,((AE81+$L$9)-$K$9)-0.5*HU_alpha/$S$9*((AE81+$L$9)-$K$9)^2,IF((AE81+$L$9)>=$T$9,HU_beta*((AE81+$L$9)-$K$9),HU_beta*($T$9-$K$9))))) | AT81: =IF(OR(AR81=0,$S$9=0),0,IF((AE81+$L$9+$N$9)>$S$9/HU_alpha+$K$9,0.5*$S$9/HU_alpha,IF((AE81+$L$9+$N$9)>=$K$9,((AE81+$L$9+$N$9)-$K$9)-0.5*HU_alpha/$S$9*((AE81+$L$9+$N$9)-$K$9)^2,IF((AE81+$L$9+$N$9)>=$T$9,HU_beta*((AE81+$L$9+$N$9)-$K$9),HU_beta*($T$9-$K$9))))) | AU81: =IF(OR(AR81=0,$S$9=0),0,IF((AE81+$K$9)>$S$9/HU_alpha+$K$9,0.5*$S$9/HU_alpha,IF((AE81+$K$9)>=$K$9,((AE81+$K$9)-$K$9)-0.5*HU_alpha/$S$9*((AE81+$K$9)-$K$9)^2,IF((AE81+$K$9)>=$T$9,HU_beta*((AE81+$K$9)-$K$9),HU_beta*($T$9-$K$9))))) | AV81: =IF(AND($J$10,A81=$Q$10),J81,0) | AW81: =IF(OR(AV81=0,$S$10=0),0,IF((AD81+$L$10)>$S$10/HU_alpha+$K$10,0.5*$S$10/HU_alpha,IF((AD81+$L$10)>=$K$10,((AD81+$L$10)-$K$10)-0.5*HU_alpha/$S$10*((AD81+$L$10)-$K$10)^2,IF((AD81+$L$10)>=$T$10,HU_beta*((AD81+$L$10)-$K$10),HU_beta*($T$10-$K$10))))) | AX81: =IF(OR(AV81=0,$S$10=0),0,IF((AD81+$L$10+$N$10)>$S$10/HU_alpha+$K$10,0.5*$S$10/HU_alpha,IF((AD81+$L$10+$N$10)>=$K$10,((AD81+$L$10+$N$10)-$K$10)-0.5*HU_alpha/$S$10*((AD81+$L$10+$N$10)-$K$10)^2,IF((AD81+$L$10+$N$10)>=$T$10,HU_beta*((AD81+$L$10+$N$10)-$K$10),HU_beta*($T$10-$K$10))))) | AY81: =IF(OR(AV81=0,$S$10=0),0,IF((AD81+$K$10)>$S$10/HU_alpha+$K$10,0.5*$S$10/HU_alpha,IF((AD81+$K$10)>=$K$10,((AD81+$K$10)-$K$10)-0.5*HU_alpha/$S$10*((AD81+$K$10)-$K$10)^2,IF((AD81+$K$10)>=$T$10,HU_beta*((AD81+$K$10)-$K$10),HU_beta*($T$10-$K$10))))) | AZ81: =IF(AND($J$11,A81=$Q$11),J81,0) | BA81: =IF(OR(AZ81=0,$S$11=0),0,IF((AE81+$L$11)>$S$11/HU_alpha+$K$11,0.5*$S$11/HU_alpha,IF((AE81+$L$11)>=$K$11,((AE81+$L$11)-$K$11)-0.5*HU_alpha/$S$11*((AE81+$L$11)-$K$11)^2,IF((AE81+$L$11)>=$T$11,HU_beta*((AE81+$L$11)-$K$11),HU_beta*($T$11-$K$11))))) | BB81: =IF(OR(AZ81=0,$S$11=0),0,IF((AE81+$L$11+$N$11)>$S$11/HU_alpha+$K$11,0.5*$S$11/HU_alpha,IF((AE81+$L$11+$N$11)>=$K$11,((AE81+$L$11+$N$11)-$K$11)-0.5*HU_alpha/$S$11*((AE81+$L$11+$N$11)-$K$11)^2,IF((AE81+$L$11+$N$11)>=$T$11,HU_beta*((AE81+$L$11+$N$11)-$K$11),HU_beta*($T$11-$K$11))))) | BC81: =IF(OR(AZ81=0,$S$11=0),0,IF((AE81+$K$11)>$S$11/HU_alpha+$K$11,0.5*$S$11/HU_alpha,IF((AE81+$K$11)>=$K$11,((AE81+$K$11)-$K$11)-0.5*HU_alpha/$S$11*((AE81+$K$11)-$K$11)^2,IF((AE81+$K$11)>=$T$11,HU_beta*((AE81+$K$11)-$K$11),HU_beta*($T$11-$K$11))))) | BD81: =IF(AND($J$12,A81=$Q$12),J81,0) | BE81: =IF(OR(BD81=0,$S$12=0),0,IF((AE81+$L$12)>$S$12/HU_alpha+$K$12,0.5*$S$12/HU_alpha,IF((AE81+$L$12)>=$K$12,((AE81+$L$12)-$K$12)-0.5*HU_alpha/$S$12*((AE81+$L$12)-$K$12)^2,IF((AE81+$L$12)>=$T$12,HU_beta*((AE81+$L$12)-$K$12),HU_beta*($T$12-$K$12))))) | BF81: =IF(OR(BD81=0,$S$12=0),0,IF((AE81+$L$12+$N$12)>$S$12/HU_alpha+$K$12,0.5*$S$12/HU_alpha,IF((AE81+$L$12+$N$12)>=$K$12,((AE81+$L$12+$N$12)-$K$12)-0.5*HU_alpha/$S$12*((AE81+$L$12+$N$12)-$K$12)^2,IF((AE81+$L$12+$N$12)>=$T$12,HU_beta*((AE81+$L$12+$N$12)-$K$12),HU_beta*($T$12-$K$12))))) | BG81: =IF(OR(BD81=0,$S$12=0),0,IF((AE81+$K$12)>$S$12/HU_alpha+$K$12,0.5*$S$12/HU_alpha,IF((AE81+$K$12)>=$K$12,((AE81+$K$12)-$K$12)-0.5*HU_alpha/$S$12*((AE81+$K$12)-$K$12)^2,IF((AE81+$K$12)>=$T$12,HU_beta*((AE81+$K$12)-$K$12),HU_beta*($T$12-$K$12))))) | BH81: =IF(AND($J$13,A81=$Q$13),J81,0) | BI81: =IF(OR(BH81=0,$S$13=0),0,IF((AE81+$L$13)>$S$13/HU_alpha+$K$13,0.5*$S$13/HU_alpha,IF((AE81+$L$13)>=$K$13,((AE81+$L$13)-$K$13)-0.5*HU_alpha/$S$13*((AE81+$L$13)-$K$13)^2,IF((AE81+$L$13)>=$T$13,HU_beta*((AE81+$L$13)-$K$13),HU_beta*($T$13-$K$13))))) | BJ81: =IF(OR(BH81=0,$S$13=0),0,IF((AE81+$L$13+$N$13)>$S$13/HU_alpha+$K$13,0.5*$S$13/HU_alpha,IF((AE81+$L$13+$N$13)>=$K$13,((AE81+$L$13+$N$13)-$K$13)-0.5*HU_alpha/$S$13*((AE81+$L$13+$N$13)-$K$13)^2,IF((AE81+$L$13+$N$13)>=$T$13,HU_beta*((AE81+$L$13+$N$13)-$K$13),HU_beta*($T$13-$K$13))))) | BK81: =IF(OR(BH81=0,$S$13=0),0,IF((AE81+$K$13)>$S$13/HU_alpha+$K$13,0.5*$S$13/HU_alpha,IF((AE81+$K$13)>=$K$13,((AE81+$K$13)-$K$13)-0.5*HU_alpha/$S$13*((AE81+$K$13)-$K$13)^2,IF((AE81+$K$13)>=$T$13,HU_beta*((AE81+$K$13)-$K$13),HU_beta*($T$13-$K$13)))))
