Workbook

Sheet How to use
B2: GP journey feedback tracker
B3: Structured from two emails dated 11 Sep 2026. Nothing in this workbook has been implemented — Decision is Pending 1:1 on every row.
B5: Purpose | D5: Use this file in the 1:1 to accept, defer, or drop each request, then track delivery.
B6: Do not treat Severity as a decision | D6: Severity is only a discussion aid from the email tone (Blocker / High / Medium / Low). You set Decision.
B7: Phone-only items | D7: Gp.msg says some observations were phone-only and can be ignored if mobile is out of scope. Those rows are tagged Device = Mobile only.
B8: Where to work | D8: Primary sheet: Tracker (filters on). Dashboard counts update from Decision and Status. Screenshots holds the full-size clippings.
B9: How to update | D9: On Tracker set Decision, then Status / Owner / 1:1 outcome. Do not change ID. Original wording stays verbatim.
B10: Images | D10: Saksham’s 12 screenshots are embedded on Tracker and Screenshots. Full-resolution PNGs also sit in GP/docs/feedback-screenshots/.
B11: Positive comments kept | D11: Saksham: report looks good. Gp.msg: overall flow interesting; voice explainer, page-real-estate explainer, and video summary are superb.
B13: Source emails
B14: Email file | C14: Subject | D14: From | E14: To / Cc | F14: Date | G14: Items in tracker
B15: C:\Users\micha\Downloads\D2C Feedback.msg | C15: D2C Feedback | D15: Saksham Bhardwaj <saksham.bhardwaj@360f.com> | E15: To: Michael Gerber; Cc: Misook Hong, Vamshi Prasad | F15: 2026-09-11 15:31 +02:00 | G15: FB-01 … FB-12 (12 items, 12 screenshots)
B16: C:\Users\micha\Downloads\Gp.msg | C16: Gp | D16: Michael Gerber <michael.gerber@360f.com> (sent to self) | E16: To: Michael Gerber | F16: 2026-09-11 20:05 +02:00 | G16: FB-13 … FB-30 (18 items, no screenshots)
B18: Suggested 1:1 order (not a decision)
B19: 1. Blockers / bugs first: FB-09 SV 500, FB-24 cover vs gap, FB-17 voice cannot proceed (if mobile in scope), FB-04 OCR mock.
B20: 2. Product shape: FB-01 split savings/investments, FB-03 too many goals, FB-21 rank by relevance, FB-10 affordability.
B21: 3. Explainer UX: FB-02 animation, FB-06 overlapping CTAs, FB-05 stepper vs assumptions, FB-19 pause, FB-18 lag, FB-07 audio.
B22: 4. Report / video: FB-11 table polish, FB-12 / FB-29 share placement, FB-30 jump links, FB-28 video report section.
B23: 5. Explicit next-phase / mobile-skip candidates: FB-27 graph highlight; FB-14 / FB-15 / FB-17 if phone is out of scope.

Sheet Dashboard
B2: Status board — updates when you change Decision / Status on Tracker
B3: All counts are Excel formulas against Tracker. Blank until you open the file in Excel.
B5: Total items | D5: Still pending 1:1 | F5: Decided Do now | H5: Done
B6: =COUNTA(Tracker!A4:A33) -> 30 | D6: =COUNTIF(Tracker!B4:B33,"Pending 1:1") -> 16 | F6: =COUNTIF(Tracker!B4:B33,"Do now") -> 14 | H6: =COUNTIF(Tracker!C4:C33,"Done") -> 14
B8: By Decision | E8: By Status | H8: By source
B9: Decision | C9: Count | E9: Status | F9: Count | H9: Source | I9: Count
B10: Pending 1:1 | C10: =COUNTIF(Tracker!B4:B33,"Pending 1:1") -> 16 | E10: Not started | F10: =COUNTIF(Tracker!C4:C33,"Not started") -> 16 | H10: Saksham (desktop D2C) | I10: =COUNTIF(Tracker!Q4:Q33,"Saksham*") -> 12
B11: Do now | C11: =COUNTIF(Tracker!B4:B33,"Do now") -> 14 | E11: In progress | F11: =COUNTIF(Tracker!C4:C33,"In progress") -> 0 | H11: GP notes / mobile email | I11: =COUNTIF(Tracker!Q4:Q33,"GP notes*") -> 18
B12: Do later | C12: =COUNTIF(Tracker!B4:B33,"Do later") -> 0 | E12: Blocked | F12: =COUNTIF(Tracker!C4:C33,"Blocked") -> 0
B13: Won't do | C13: =COUNTIF(Tracker!B4:B33,"Won't do") -> 0 | E13: Done | F13: =COUNTIF(Tracker!C4:C33,"Done") -> 14
B14: Needs more info | C14: =COUNTIF(Tracker!B4:B33,"Needs more info") -> 0 | E14: Won't do | F14: =COUNTIF(Tracker!C4:C33,"Won't do") -> 0
B17: By journey step | E17: By severity (discussion aid) | H17: Flags
B18: Step | C18: Count | E18: Severity | F18: Count | H18: Flag | I18: Count
B19: Start | C19: =COUNTIF(Tracker!H4:H33,"Start") -> 1 | E19: Blocker | F19: =COUNTIF(Tracker!E4:E33,"Blocker") -> 1 | H19: Bugs | I19: =COUNTIF(Tracker!F4:F33,"Bug*") -> 6
B20: About you | C20: =COUNTIF(Tracker!H4:H33,"About you") -> 5 | E20: High | F20: =COUNTIF(Tracker!E4:E33,"High") -> 7 | H20: Mobile only | I20: =COUNTIF(Tracker!J4:J33,"Mobile only") -> 3
B21: Your money | C21: =COUNTIF(Tracker!H4:H33,"Your money") -> 1 | E21: Medium | F21: =COUNTIF(Tracker!E4:E33,"Medium") -> 15 | H21: Reviewer said next phase | I21: =COUNTIF(Tracker!K4:K33,"Next phase*") -> 1
B22: Your score | C22: =COUNTIF(Tracker!H4:H33,"Your score") -> 7 | E22: Low | F22: =COUNTIF(Tracker!E4:E33,"Low") -> 7 | H22: Has screenshot | I22: =COUNTIF(Tracker!P4:P33,"<>—") -> 11
B23: Your plan | C23: =COUNTIF(Tracker!H4:H33,"Your plan") -> 5
B24: Report | C24: =COUNTIF(Tracker!H4:H33,"Report") -> 5
B25: Global chrome | C25: =COUNTIF(Tracker!H4:H33,"Global chrome") -> 6

Sheet Tracker
A1: GP journey — requested changes (30). Decision = Pending 1:1 on every row. Filter, then fill Decision / Status / Owner / 1:1 outcome during the review.
A2: Sources: D2C Feedback.msg (Saksham, 12 items + screenshots) and Gp.msg (18 items, several mobile-only). Severity is a discussion aid only. Phone-only rows can be parked if mobile is out of scope.
A3: ID | B3: Decision (1:1) | C3: Status | D3: Owner | E3: Severity (discussion only) | F3: Kind | G3: Category | H3: Journey step | I3: Screen / component | J3: Device | K3: Phase hint | L3: Requested change | M3: Original wording | N3: Context / notes | O3: Screenshot | P3: Screenshot file(s) | Q3: Source | R3: Reviewer | S3: Email date | T3: Original # | U3: 1:1 outcome / notes | V3: GP action
A4: FB-01 | B4: Do now | C4: Done | D4: Michael | E4: High | F4: Change request | G4: UX / data model | H4: Your money | I4: Savings & investments field | J4: Desktop | K4: TBD in 1:1 | L4: Split savings and investments (do not combine) | M4: The savings and investment grow at different rates so they shouldn’t be combined together. | N4: Screenshot shows a single 'Savings & investments' line (S$80,000) with a 'YOU CHANGED THIS' chip. | P4: S01_savings_investment_combined.png | Q4: Saksham Bhardwaj — D2C Feedback | R4: Saksham Bhardwaj | S4: 2026-09-11 | T4: 1 | U4: By definition we should segregate consistently cash (short-term liquidity), savings (mid-term, fixed deposits, endowments), and investments (long-term, over 5 years, mutual funds, ETFs). However, in SV we only have two categories: cash/savings and investments. I suggest we stick with this logic. In GP we will rename accordingly. | V4: We will add a new asset class "Cash & Savings" with a related tooltip and rename the existing asset class from "Savings and Investments" to "Investments". People Like You will apply this approach, splitting Savings & investments into 15% Cash & Savings and 85% Investments.
A5: FB-02 | B5: Do now | C5: Done | D5: Michael | E5: Medium | F5: Change request | G5: UX / animation | H5: Global chrome | I5: Explain / Hear CTA buttons | J5: Desktop | K5: TBD in 1:1 | L5: Stop CTA pulse animation after 3–5 seconds | M5: The animation on these buttons is very distracting. The animations should stop 3-5 seconds. | N5: Two examples: 'Explain these figures' and landing 'Hear what you get'. | P5: S02a_button_animation.png, S02b_button_animation.png | Q5: Saksham Bhardwaj — D2C Feedback | R5: Saksham Bhardwaj | S5: 2026-09-11 | T5: 2 | U5: Accepted | V5: To be implemented in GP.
A6: FB-03 | B6: Do now | C6: Done | D6: Michael | E6: High | F6: Change request | G6: UX / content | H6: Your score | I6: Goals & needs shortfall list | J6: Desktop | K6: TBD in 1:1 | L6: Too many goals recommended — overwhelming | M6: Too Many goals recommended - very overwhelming | N6: Screenshot lists 5 shortfalls at once (Retirement S$3.9m through Savings S$22k). | P6: S03_too_many_goals.png | Q6: Saksham Bhardwaj — D2C Feedback | R6: Saksham Bhardwaj | S6: 2026-09-11 | T6: 3 | U6: Accepted | V6: To be limited to a maximum of 3 goals and needs.
A7: FB-04 | B7: Pending 1:1 | C7: Not started | D7: Unassigned | E7: High | F7: Gap vs live | G7: Integration | H7: About you | I7: Insurance policy upload / OCR | J7: Desktop | K7: TBD in 1:1 | L7: OCR / document parse is mock — needs to actually work | M7: The OCR API does work - mock currently | N7: Reading as: OCR should work; it is mock today. Dialog shows 'Simulated for this prototype' with truncated values (Life Protectio / Great Easterr). | P7: S04_ocr_api_mock.png | Q7: Saksham Bhardwaj — D2C Feedback | R7: Saksham Bhardwaj | S7: 2026-09-11 | T7: 4a | U7: Accepted | V7: This will be implemented by Luca & Luis next week.
A8: FB-05 | B8: Do now | C8: Done | D8: Michael | E8: Medium | F8: Change request | G8: UX / layout | H8: Global chrome | I8: Header: Assumptions + Tool tips + 5-step stepper | J8: Desktop | K8: TBD in 1:1 | L8: Assumptions / tooltips should not compete with the 5 steps | M8: The Assumption and tooltip should not take same space/ size as the 5 steps, which makes it difficult to interpret the 5 steps for new user | N8: Email numbered this as a second '4'. Header shows Assumptions + Tool tips toggle at same visual weight as Start → Your plan. | P8: S05_assumptions_tooltip_stepper.png | Q8: Saksham Bhardwaj — D2C Feedback | R8: Saksham Bhardwaj | S8: 2026-09-11 | T8: 4b | U8: Accepted | V8: The menu for all pages should be moved to the left side of the top bar; the tooltip switch toggle and the Assumptions control to the right side of the menu bar.
A9: FB-06 | B9: Do now | C9: Done | D9: Michael | E9: Medium | F9: Change request | G9: UX / layout | H9: Your score | I9: Dual explainer CTAs | J9: Desktop | K9: TBD in 1:1 | L9: Overlapping / duplicate explainer buttons — rethink positioning | M9: Same button - need to think about positioning | N9: 'Explain your HappiU score' and 'Explain your goals and needs' overlap. | P9: S06_duplicate_button_position.png | Q9: Saksham Bhardwaj — D2C Feedback | R9: Saksham Bhardwaj | S9: 2026-09-11 | T9: 5 | U9: Accepted | V9: The "Explain your goals and needs" button should be left-aligned, vertically aligned with the goals.
A10: FB-07 | B10: Pending 1:1 | C10: Not started | D10: Unassigned | E10: Medium | F10: Bug / investigation | G10: Voice | H10: Global chrome | I10: Voice / system audio explainer | J10: Desktop | K10: TBD in 1:1 | L10: System audio explainer does not play (reviewer laptop?) | M10: When I use system audio to understand explanation- it doesn’t work for me. Maybe it’s just my laptop | N10: No screenshot. Confirm whether this is device-specific or a product bug before treating as a change. | O10: (no screenshot in email) | P10: — | Q10: Saksham Bhardwaj — D2C Feedback | R10: Saksham Bhardwaj | S10: 2026-09-11 | T10: 6 | U10: Please retry. Wait 5 seconds for latency.
A11: FB-08 | B11: Do now | C11: Done | D11: Michael | E11: Low | F11: Change request | G11: UX / layout | H11: Your plan | I11: HappiU uplift / gauge card | J11: Desktop | K11: TBD in 1:1 | L11: Alignment on HappiU uplift card | M11: Some alignment required | N11: Gauge (99) vs '+38 HappiU uplift' copy; needle at 100 while score is 99. | P11: S07_alignment.png | Q11: Saksham Bhardwaj — D2C Feedback | R11: Saksham Bhardwaj | S11: 2026-09-11 | T11: 7 | U11: Accepted | V11: Over the gauge show the title "Your new HappiU Score". On the right side, left-align and show without a title "+38 uplift. Through a smart …". The +38 should be in a much bigger font.
A12: FB-09 | B12: Pending 1:1 | C12: Not started | D12: Unassigned | E12: Blocker | F12: Bug | G12: Bug | H12: Your plan | I12: Scenario Visualizer — Cash inflow & outflow | J12: Desktop | K12: TBD in 1:1 | L12: Scenario Visualizer Internal Server Error — SV testing blocked | M12: The scenario visualiser throwing an error so couldn’t proceed with SV Testing | N12: Chart body shows {"detail":"Internal Server Error"}. Covering note: 'Couldn’t test SV as I was getting internal server error.' | P12: S08_sv_error.png | Q12: Saksham Bhardwaj — D2C Feedback | R12: Saksham Bhardwaj | S12: 2026-09-11 | T12: 8 | U12: Checking and testing.
A13: FB-10 | B13: Do now | C13: Done | D13: Michael | E13: High | F13: Change request | G13: Feature | H13: Your plan | I13: Protection / investment plan detail modal | J13: Desktop | K13: TBD in 1:1 | L13: Add affordability indicator for protection and investment plans | M13: I dont have a view whether I am able to afford these protection and investment plans. A indicator somewhere would help. | N13: Critical illness cover modal shows sum assured / premium sliders and funded status, but no affordability vs income/cashflow. | P13: S09_affordability_indicator.png | Q13: Saksham Bhardwaj — D2C Feedback | R13: Saksham Bhardwaj | S13: 2026-09-11 | T13: 9 | U13: Accepted | V13: The budget calculator is not on the modal. The modal should also show — in a simplified way — a warning if the monthly budget or the investment (not the Cash & Savings) is exceeded. For the budget calculator, do not consume the Cash & Savings pot.
A14: FB-11 | B14: Do now | C14: Done | D14: Michael | E14: Medium | F14: Change request | G14: UX / report | H14: Report | I14: HTML report — goals and gaps | J14: Desktop | K14: TBD in 1:1 | L14: Report: reduce scrolling; keep goals/gaps in a well-formatted table | M14: Report looks good but some lots of scrolling is required. Can keep the goals and gaps in a table format for simplicity but my need to format the table to look good. | N14: Positive: report looks good. Ask is compactness + table polish (screenshot already shows a table). | P14: S10_report_scrolling.png | Q14: Saksham Bhardwaj — D2C Feedback | R14: Saksham Bhardwaj | S14: 2026-09-11 | T14: 10 | U14: Accepted | V14: The report should have expandable and collapsible containers.
A15: FB-12 | B15: Do now | C15: Done | D15: Michael | E15: Low | F15: Change request | G15: UX / layout | H15: Report | I15: Report header Close / Share | J15: Desktop | K15: TBD in 1:1 | L15: Move Close / Share report buttons to top right | M15: Can move these button to top right - which is more natural than top left | N15: Screenshot: Close + Share report clustered top-left. | P15: S11_buttons_top_left.png | Q15: Saksham Bhardwaj — D2C Feedback | R15: Saksham Bhardwaj | S15: 2026-09-11 | T15: 11 | U15: Accepted | V15: Move the close button, labelled "X Close", to the far right, and place the share button to the left of Close.
A16: FB-13 | B16: Do now | C16: Done | D16: Michael | E16: Medium | F16: Change request | G16: UX / content | H16: Start | I16: Landing / audio explainer | J16: Both | K16: TBD in 1:1 | L16: Highlight '3-minute planning' as a D2C wow factor | M16: 3min planning is at end in page as well as audio explainer, for D2C customer it could be a wow factor so if it could be highlighted | N16: Positive context from same email: voice explainer, page-real-estate explainer, and video summary are 'superb'. | O16: (no screenshot in email) | P16: — | Q16: GP notes (mobile) — Gp.msg | R16: Captured in Gp.msg (Michael Gerber mailbox) | S16: 2026-09-11 | T16: 1 | U16: Accepted | V16: Make it more dominant.
A17: FB-14 | B17: Pending 1:1 | C17: Not started | D17: Unassigned | E17: Medium | F17: Bug | G17: Voice | H17: About you | I17: Speak-button transcript | J17: Mobile only | K17: TBD in 1:1 | L17: Transcript repeats words (not as spoken) — mobile only | M17: The transcript shown on UI from the speak button has repeated words not as spoken - *only on mobile* | N17: Email preface: ignore phone-only items if we are not optimizing for phone now. | O17: (no screenshot in email) | P17: — | Q17: GP notes (mobile) — Gp.msg | R17: Captured in Gp.msg (Michael Gerber mailbox) | S17: 2026-09-11 | T17: 2 | U17: Accepted | V17: Further testing required.
A18: FB-15 | B18: Pending 1:1 | C18: Not started | D18: Unassigned | E18: Medium | F18: Change request | G18: Voice | H18: About you | I18: Voice-to-text intake | J18: Mobile only | K18: TBD in 1:1 | L18: Voice-to-text misses residency / dependents unless keywords are said | M18: observed *only on Mobile* -voice to text needs a bit of improvement as it picks some keyword I guess like citizen for residency, dependent are not picked till I say relationship | N18: Phone-only. Mapping seems keyword-triggered rather than natural speech. | O18: (no screenshot in email) | P18: — | Q18: GP notes (mobile) — Gp.msg | R18: Captured in Gp.msg (Michael Gerber mailbox) | S18: 2026-09-11 | T18: 3 | U18: Accepted | V18: Further testing required.
A19: FB-16 | B19: Pending 1:1 | C19: Not started | D19: Unassigned | E19: Low | F19: Enhancement | G19: Voice / feature | H19: About you | I19: Mira voice intake | J19: Both | K19: TBD in 1:1 | L19: Two-way voice: Mira asks for missing details | M19: if we can two way the voice would become more interesting ( Mira asks for details - please share residency status) | N19: Enhancement, not a defect. | O19: (no screenshot in email) | P19: — | Q19: GP notes (mobile) — Gp.msg | R19: Captured in Gp.msg (Michael Gerber mailbox) | S19: 2026-09-11 | T19: 4 | U19: Accepted | V19: This will be implemented by Luca & Luis next week.
A20: FB-17 | B20: Pending 1:1 | C20: Not started | D20: Unassigned | E20: High | F20: Bug | G20: Voice | H20: About you | I20: Voice intake → Next | J20: Mobile only | K20: TBD in 1:1 | L20: Cannot proceed after voice fill until classic data-entry is toggled | M20: Observed *only on phone* - even all details picked from voice - it didn't allow me to proceed to next steps(shows we fill once u pause) ( when triggered on and off classic data entry it picked) | N20: Phone-only blocker for a voice-first path. Workaround: toggle classic data entry. | O20: (no screenshot in email) | P20: — | Q20: GP notes (mobile) — Gp.msg | R20: Captured in Gp.msg (Michael Gerber mailbox) | S20: 2026-09-11 | T20: 5 | U20: Accepted | V20: Further testing required.
A21: FB-18 | B21: Pending 1:1 | C21: Not started | D21: Unassigned | E21: Medium | F21: Bug / performance | G21: Voice | H21: Global chrome | I21: Voice explainer | J21: Both | K21: TBD in 1:1 | L21: Lag on the voice explainer | M21: observed a bit of lag on the voice explainer | O21: (no screenshot in email) | P21: — | Q21: GP notes (mobile) — Gp.msg | R21: Captured in Gp.msg (Michael Gerber mailbox) | S21: 2026-09-11 | T21: 6 | U21: Accepted | V21: No action needed. This is due to the current low-cost infra.
A22: FB-19 | B22: Do now | C22: Done | D22: Michael | E22: Medium | F22: Change request | G22: Voice | H22: Global chrome | I22: Voice explainer | J22: Both | K22: TBD in 1:1 | L22: Add pause on voice explainer | M22: can add a pause button on voice explainer as people would.like to grasp what is getting told while explaining needs and goals | O22: (no screenshot in email) | P22: — | Q22: GP notes (mobile) — Gp.msg | R22: Captured in Gp.msg (Michael Gerber mailbox) | S22: 2026-09-11 | T22: 7 | U22: Accepted | V22: A pause icon like "||" or a stop square can be embedded in the button once it starts playing.
A23: FB-20 | B23: Pending 1:1 | C23: Not started | D23: Unassigned | E23: Medium | F23: Change request | G23: Content / voice | H23: Your score | I23: Goals / needs audio explainer | J23: Both | K23: TBD in 1:1 | L23: Start goal explainer with why people like you prioritise these needs | M23: I feel if we start audio goal explainer with why these needs not just people like u but why people like u prioritise these things - could be confidence building | O23: (no screenshot in email) | P23: — | Q23: GP notes (mobile) — Gp.msg | R23: Captured in Gp.msg (Michael Gerber mailbox) | S23: 2026-09-11 | T23: 8 | U23: TBD. Not clear what is meant. | V23: None.
A24: FB-21 | B24: Pending 1:1 | C24: Not started | D24: Unassigned | E24: High | F24: Change request | G24: UX / ranking | H24: Your score | I24: Need listing / ranking | J24: Both | K24: TBD in 1:1 | L24: Rank needs by relevance, not gap amount alone | M24: currently the need listing seems be on gap amount - the priority could be changed with relevance rather than amount alone - ex critical illness could eat current savings hence should be top priority | N24: Related to FB-03 (too many goals). Ranking vs quantity are separate 1:1 decisions. | O24: (no screenshot in email) | P24: — | Q24: GP notes (mobile) — Gp.msg | R24: Captured in Gp.msg (Michael Gerber mailbox) | S24: 2026-09-11 | T24: 9 | U24: Not accepted. By reducing to a maximum of 3 needs/goals, further prioritisation is not needed. | V24: None.
A25: FB-22 | B25: Do now | C25: Done | D25: Michael | E25: Low | F25: Change request | G25: Content | H25: Your score | I25: Financial ratios | J25: Both | K25: TBD in 1:1 | L25: Explain how financial ratios are arrived at (or a separate explainer) | M25: should we add how we have arrived at the financial ratio? Or A seperate explainer for ratio? | O25: (no screenshot in email) | P25: — | Q25: GP notes (mobile) — Gp.msg | R25: Captured in Gp.msg (Michael Gerber mailbox) | S25: 2026-09-11 | T25: 10 | U25: Accepted | V25: A tooltip with an "i" should be added for each of the ratios.
A26: FB-23 | B26: Pending 1:1 | C26: Not started | D26: Unassigned | E26: Medium | F26: Change request | G26: UX | H26: Global chrome | I26: Inline figure edit | J26: Both | K26: TBD in 1:1 | L26: Save to persist edits; X / close = discard | M26: while editing any figure can we add a save button to Persist changes , cross can be taken as discard | O26: (no screenshot in email) | P26: — | Q26: GP notes (mobile) — Gp.msg | R26: Captured in Gp.msg (Michael Gerber mailbox) | S26: 2026-09-11 | T26: 11 | U26: Not accepted. The idea is not to capture the details until you want to get the report. Then persistence will be given. | V26: Integration with Prototype planned for this weekend.
A27: FB-24 | B27: Pending 1:1 | C27: Not started | D27: Unassigned | E27: High | F27: Bug | G27: Bug / calc | H27: Your score | I27: Insurance cover vs gap calculation | J27: Both | K27: TBD in 1:1 | L27: Changing insurance cover amount is not reflected in the gap | M27: changing insurance cover amount is not getting accounted for gap amount calculation | N27: Looks like a calculation / mapping bug, not cosmetic. | O27: (no screenshot in email) | P27: — | Q27: GP notes (mobile) — Gp.msg | R27: Captured in Gp.msg (Michael Gerber mailbox) | S27: 2026-09-11 | T27: 12 | U27: Accepted | V27: Further testing required.
A28: FB-25 | B28: Pending 1:1 | C28: Not started | D28: Unassigned | E28: Medium | F28: Enhancement | G28: Voice / UX | H28: Your score | I28: Goals audio explainer | J28: Both | K28: TBD in 1:1 | L28: Auto open / close / highlight the goal being discussed in audio | M28: while audio explains goals would becomes nicer if system auto opens/close or highligh the goal getting discussed | O28: (no screenshot in email) | P28: — | Q28: GP notes (mobile) — Gp.msg | R28: Captured in Gp.msg (Michael Gerber mailbox) | S28: 2026-09-11 | T28: 13 | U28: Accepted | V28: This will be implemented by Luca & Luis next week.
A29: FB-26 | B29: Do now | C29: Done | D29: Michael | E29: Low | F29: Change request | G29: UX / layout | H29: Your plan | I29: Scenario Visualizer page explainer tooltip | J29: Both | K29: TBD in 1:1 | L29: Adjust Scenario Visualizer page-explainer tooltip (cosmetic) | M29: cosmetic - scenario visualizer page explainer(tooltip) need to be adjusted | N29: Blocked in practice until FB-09 (SV 500) is resolved; Saksham could not test SV. | O29: (no screenshot in email) | P29: — | Q29: GP notes (mobile) — Gp.msg | R29: Captured in Gp.msg (Michael Gerber mailbox) | S29: 2026-09-11 | T29: 14 | U29: Accepted | V29: Will be fixed.
A30: FB-27 | B30: Pending 1:1 | C30: Not started | D30: Unassigned | E30: Low | F30: Enhancement | G30: Voice / SV | H30: Your plan | I30: SV graph + explainer | J30: Both | K30: Next phase (reviewer) | L30: Next phase: SV explainer auto-adjusts / highlights the graph | M30: not sure how complex this could be - in next phase if we make sv explainer with auto adjusting/highlighting the graph | N30: Reviewer already tagged this as next phase. | O30: (no screenshot in email) | P30: — | Q30: GP notes (mobile) — Gp.msg | R30: Captured in Gp.msg (Michael Gerber mailbox) | S30: 2026-09-11 | T30: 15 | U30: TBD. Not clear what is meant.
A31: FB-28 | B31: Pending 1:1 | C31: Not started | D31: Unassigned | E31: Medium | F31: Enhancement | G31: Feature / video | H31: Report | I31: Video explainer | J31: Both | K31: TBD in 1:1 | L31: Add a report section on the video explainer | M31: is it possible to add a report section on the video explainer will make the explainer out of world | N31: Positive: video summary called superb in the same email. | O31: (no screenshot in email) | P31: — | Q31: GP notes (mobile) — Gp.msg | R31: Captured in Gp.msg (Michael Gerber mailbox) | S31: 2026-09-11 | T31: 16 | U31: Accepted | V31: This will be implemented by Luca & Luis next week.
A32: FB-29 | B32: Pending 1:1 | C32: Not started | D32: Unassigned | E32: Low | F32: Change request | G32: UX / layout | H32: Report | I32: Share button vs video | J32: Both | K32: TBD in 1:1 | L32: Move Share button to just below the video | M32: share button can be moved just below video | N32: Related to FB-12 (Share currently top-left on report). | O32: (no screenshot in email) | P32: — | Q32: GP notes (mobile) — Gp.msg | R32: Captured in Gp.msg (Michael Gerber mailbox) | S32: 2026-09-11 | T32: 17 | U32: Not accepted. Moved in accordance with Saksham: the share button to the right side.
A33: FB-30 | B33: Do now | C33: Done | D33: Michael | E33: Medium | F33: Change request | G33: UX / report | H33: Report | I33: HTML report | J33: Both | K33: TBD in 1:1 | L33: Add a report header / jump links to sections | M33: since the report is in HTML - can we add a header to jump on relevant sections | N33: Pairs with FB-11 (too much scrolling). | O33: (no screenshot in email) | P33: — | Q33: GP notes (mobile) — Gp.msg | R33: Captured in Gp.msg (Michael Gerber mailbox) | S33: 2026-09-11 | T33: 18 | U33: Accepted | V33: Will be fixed.

Sheet Screenshots
B2: Screenshots from Saksham’s D2C Feedback email (12 images across 11 items)
B3: Gp.msg had no attachments. Full-resolution files: GP/docs/feedback-screenshots/
B5: ID / item | C5: Screenshot | D5: Requested change + original wording
B6: FB-01 email #1 Your money | D6: Split savings and investments (do not combine) Original: The savings and investment grow at different rates so they shouldn’t be combined together. Screenshot shows a single 'Savings & investments' line (S$80,000) with a 'YOU CHANGED THIS' chip. File: S01_savings_investment_combined.png
B7: FB-02 (1/2) email #2 Global chrome | D7: Stop CTA pulse animation after 3–5 seconds Original: The animation on these buttons is very distracting. The animations should stop 3-5 seconds. Two examples: 'Explain these figures' and landing 'Hear what you get'. File: S02a_button_animation.png
B8: FB-02 (2/2) email #2 Global chrome | D8: Stop CTA pulse animation after 3–5 seconds Original: The animation on these buttons is very distracting. The animations should stop 3-5 seconds. Two examples: 'Explain these figures' and landing 'Hear what you get'. File: S02b_button_animation.png
B9: FB-03 email #3 Your score | D9: Too many goals recommended — overwhelming Original: Too Many goals recommended - very overwhelming Screenshot lists 5 shortfalls at once (Retirement S$3.9m through Savings S$22k). File: S03_too_many_goals.png
B10: FB-04 email #4a About you | D10: OCR / document parse is mock — needs to actually work Original: The OCR API does work - mock currently Reading as: OCR should work; it is mock today. Dialog shows 'Simulated for this prototype' with truncated values (Life Protectio / Great Easterr). File: S04_ocr_api_mock.png
B11: FB-05 email #4b Global chrome | D11: Assumptions / tooltips should not compete with the 5 steps Original: The Assumption and tooltip should not take same space/ size as the 5 steps, which makes it difficult to interpret the 5 steps for new user Email numbered this as a second '4'. Header shows Assumptions + Tool tips toggle at same visual weight as Start → Your plan. File: S05_assumptions_tooltip_stepper.png
B12: FB-06 email #5 Your score | D12: Overlapping / duplicate explainer buttons — rethink positioning Original: Same button - need to think about positioning 'Explain your HappiU score' and 'Explain your goals and needs' overlap. File: S06_duplicate_button_position.png
B13: FB-08 email #7 Your plan | D13: Alignment on HappiU uplift card Original: Some alignment required Gauge (99) vs '+38 HappiU uplift' copy; needle at 100 while score is 99. File: S07_alignment.png
B14: FB-09 email #8 Your plan | D14: Scenario Visualizer Internal Server Error — SV testing blocked Original: The scenario visualiser throwing an error so couldn’t proceed with SV Testing Chart body shows {"detail":"Internal Server Error"}. Covering note: 'Couldn’t test SV as I was getting internal server error.' File: S08_sv_error.png
B15: FB-10 email #9 Your plan | D15: Add affordability indicator for protection and investment plans Original: I dont have a view whether I am able to afford these protection and investment plans. A indicator somewhere would help. Critical illness cover modal shows sum assured / premium sliders and funded status, but no affordability vs income/cashflow. File: S09_affordability_indicator.png
B16: FB-11 email #10 Report | D16: Report: reduce scrolling; keep goals/gaps in a well-formatted table Original: Report looks good but some lots of scrolling is required. Can keep the goals and gaps in a table format for simplicity but my need to format the table to look good. Positive: report looks good. Ask is compactness + table polish (screenshot already shows a table). File: S10_report_scrolling.png
B17: FB-12 email #11 Report | D17: Move Close / Share report buttons to top right Original: Can move these button to top right - which is more natural than top left Screenshot: Close + Share report clustered top-left. File: S11_buttons_top_left.png

Sheet Original emails
B2: Verbatim notes from the two emails (encoding cleaned)
B4: D2C Feedback — Saksham Bhardwaj
B5: Hi Michael, I did some testing for D2C so sharing some feedback. Couldn’t test SV as I was getting internal server error. 1. The savings and investment grow at different rates so they shouldn’t be combined together. 2. The animation on these buttons is very distracting. The animations should stop 3-5 seconds. 3. Too Many goals recommended - very overwhelming 4a. The OCR API does work - mock currently 4b. The Assumption and tooltip should not take same space/ size as the 5 steps, which makes it difficult to interpret the 5 steps for new user 5. Same button - need to think about positioning 6. When I use system audio to understand explanation- it doesn’t work for me. Maybe it’s just my laptop 7. Some alignment required 8. The scenario visualiser throwing an error so couldn’t proceed with SV Testing 9. I dont have a view whether I am able to afford these protection and investment plans. A indicator somewhere would help. 10. Report looks good but some lots of scrolling is required. Can keep the goals and gaps in a table format for simplicity but my need to format the table to look good. 11. Can move these button to top right - which is more natural than top left
B7: Gp — captured 2026-09-11 20:05 (Michael Gerber mailbox)
B8: Overall flow is interesting specially the voice explainer, page real estate explainer and video summary is superb Some quick suggestions , somewhere observed on phone inly so please ignore if we need not optimize for phone now 1) 3min planning is at end in page as well as audio explainer, for D2C customer it could be a wow factor so if it could be highlighted 2) The transcript shown on UI from the speak button has repeated words not as spoken - *only on mobile* 3) observed *only on Mobile* -voice to text needs a bit of improvement as it picks some keyword I guess like citizen for residency, dependent are not picked till I say relationship 4) if we can two way the voice would become more interesting ( Mira asks for details - please share residency status) 5) Observed *only on phone* - even all details picked from voice - it didn't allow me to proceed to next steps(shows we fill once u pause) ( when triggered on and off classic data entry it picked) 6) observed a bit of lag on the voice explainer 7) can add a pause button on voice explainer as people would.like to grasp what is getting told while explaining needs and goals 8) I feel if we start audio goal explainer with why these needs not just people like u but why people like u prioritise these things - could be confidence building 9) currently the need listing seems be on gap amount - the priority could be changed with relevance rather than amount alone - ex critical illness could eat current savings hence should be top priority 10) should we add how we have arrived at the financial ratio? Or A seperate explainer for ratio? 11) while editing any figure can we add a save button to Persist changes , cross can be taken as discard 12) changing insurance cover amount is not getting accounted for gap amount calculation 13) while audio explains goals would becomes nicer if system auto opens/close or highligh the goal getting discussed 14) cosmetic - scenario visualizer page explainer(tooltip) need to be adjusted 15) not sure how complex this could be - in next phase if we make sv explainer with auto adjusting/highlighting the graph 16) is it possible to add a report section on the video explainer will make the explainer out of world 17) share button can be moved just below video 18) since the report is in HTML - can we add a header to jump on relevant sections

Sheet Lists
A1: Pending 1:1 | B1: Not started | C1: Michael
A2: Do now | B2: In progress | C2: Unassigned
A3: Do later | B3: Blocked
A4: Won't do | B4: Done
A5: Needs more info | B5: Won't do
